Workbook
Name L_business_model: Lookups!$A$2:$A$6
Name L_site_status: Lookups!$B$2:$B$5
Name L_tier: Lookups!$C$2:$C$4
Name L_site_category: Lookups!$D$2:$D$4
Name L_redundancy: Lookups!$E$2:$E$4
Name L_room_type: Lookups!$F$2:$F$9
Name L_containment: Lookups!$G$2:$G$4
Name L_cooling_method: Lookups!$H$2:$H$4
Name L_rack_role: Lookups!$I$2:$I$10
Name L_owner: Lookups!$J$2:$J$3
Name L_density: Lookups!$K$2:$K$3
Name L_yes_no: Lookups!$L$2:$L$3
Name L_feed_type: Lookups!$M$2:$M$3
Name L_feed_role: Lookups!$N$2:$N$3
Name L_plant_kind: Lookups!$O$2:$O$3
Name L_test_result: Lookups!$P$2:$P$3
Name L_cooling_type: Lookups!$Q$2:$Q$4
Name L_sensor_kind: Lookups!$R$2:$R$4
Name L_device_role: Lookups!$S$2:$S$10
Name L_layer: Lookups!$T$2:$T$5
Name L_lifecycle: Lookups!$U$2:$U$5
Name L_if_admin: Lookups!$V$2:$V$4
Name L_link_role: Lookups!$W$2:$W$6
Name L_protocol: Lookups!$X$2:$X$6
Name L_gpu_model: Lookups!$Y$2:$Y$9
Name L_gpu_vendor: Lookups!$Z$2:$Z$3
Name L_scheduler: Lookups!$AA$2:$AA$3
Name L_air_liquid: Lookups!$AB$2:$AB$3
Name L_service_type: Lookups!$AC$2:$AC$24
Name L_service_unit: Lookups!$AD$2:$AD$9
Name L_collector_protocol: Lookups!$AE$2:$AE$8
Name L_collector_domain: Lookups!$AF$2:$AF$5
Name L_pdu_side: Lookups!$AG$2:$AG$3
Name L_pdu_kind: Lookups!$AH$2:$AH$3
Name L_panel_kind: Lookups!$AI$2:$AI$4
Name L_panel_role: Lookups!$AJ$2:$AJ$3
Name L_link_end: Lookups!$AK$2:$AK$3
Name L_tray_route: Lookups!$AL$2:$AL$3
Name L_detection: Lookups!$AM$2:$AM$3
Name L_suppression: Lookups!$AN$2:$AN$4
Name L_release_mode: Lookups!$AO$2:$AO$4
Name L_door_kind: Lookups!$AP$2:$AP$6
Name L_reader: Lookups!$AQ$2:$AQ$4
Name L_support_level: Lookups!$AR$2:$AR$5
Name L_pm_kind: Lookups!$AS$2:$AS$8
Name L_oncall_role: Lookups!$AT$2:$AT$7

Sheet README
A1: SynapseDC · Sample data for two datacenters · Cloud · India · MH-DC-001, MH-DC-002
A2: A complete, end-to-end export of MH-DC-001, MH-DC-002 as the platform holds them (data clock 2026-10-01 07:50 UTC): the two sites, their floors, rooms, racks, power and cooling plant, every device with its ports, the cables between them, GPU clusters, the customers served there and their services, plus the physical, safety, lifecycle and maintenance records. Only links whose two ends are in these sites and only customers who buy something there are included. Use it as the worked example for the import template: every sheet is filled exactly the way the customer should fill it for their own datacenters, the Summary sheet shows what the platform will then display. Snapshot_* sheets keep the alarms, incidents and changes of that moment for the record; they are not imported.
A3: Version 1.0 · 12-Oct-2026 · matches the DCO data model (app/src/api/types.ts)
A5: What this workbook is for
A6: Use it to collect everything the DCO platform needs to know about a customer's datacenters BEFORE monitoring is switched on: sites, floors, rooms, racks, power and cooling plant, sensors, every racked device, its ports and cables, GPU clusters, customers and the services they buy, and the monitoring sources.
A8: How to fill it
A9: 1. Fill the sheets in tab order. A sheet can only point at IDs that exist in the sheets before it (Sites → Floors → Rooms → Racks → … → Services).
A10: 2. Row 1 holds the import keys. Don't rename, reorder or delete columns. Hover over a header for its meaning; the Field_Dictionary sheet lists every field.
A11: 3. Header colours: dark blue = required · amber = required in some cases (see the note) · grey = optional · green = calculated by a formula (don't type it).
A12: 4. Columns with a fixed set of values have a dropdown (from the Lookups sheet). Dates use YYYY-MM-DD. Numbers are plain, with no units in the cell. Lists inside a cell use ";".
A13: 5. IDs must be unique and stable: the system keys every alarm, incident and revenue figure on them. Recommended: site XX-DC-NNN, then <site>-<object> (MP-DC-001-A01).
A14: 6. Check the Summary sheet when you finish. Every count must match what the customer expects, and the checks column must say OK.
... A24: Sheet order and the system object each one fills
A25: Sheet | B25: System object | C25: What goes in it | D25: Example rows
A26: Sites | B26: Datacenter + Location | C26: One row per datacenter. | D26: 2
A27: Floors | B27: Datacenter.floors[] | C27: One row per floor. | D27: 4
A28: Rooms | B28: Datacenter.floors[].rooms[] | C28: One row per room / hall. | D28: 8
A29: Racks | B29: Rack | C29: One row per cabinet, including tenant cabinets and AI cages. | D29: 68
A30: Power_Feeds | B30: Datacenter.power.feeds[] (PowerFeed) | C30: Utility, DG and DC-plant feeds. | D30: 6
A31: UPS | B31: Datacenter.power.ups[] (UpsUnit) | C31: One row per UPS module or system. | D31: 8
A32: Generators | B32: Datacenter.power.dg | C32: Diesel generator sets. | D32: 2
A33: DC_Plant | B33: Datacenter.power.battery + rectifier | C33: 48 V DC plant: rectifiers and battery banks. | D33: 4
A34: Cooling_Units | B34: Datacenter.cooling.units[] (CoolingUnit) | C34: CRAH, CRAC and CDU units. | D34: 16
A35: CDUs | B35: Cdu | C35: Liquid-cooling loops (only for liquid-cooled racks). | D35: 0
A36: Sensors | B36: Datacenter.cooling.sensors[] (EnvSensor) | C36: Environment sensors. | D36: 8
A37: Devices | B37: NetworkElement | C37: Every racked device: network, servers, storage, GPU nodes, and opaque tenant gear blocks. | D37: 673
... A66: Snapshot_Orders | B66: CrossConnectOrder + RemoteHandsTicket (snapshot) | C66: Colocation cross-connect orders and remote-hands tickets. | D66: 0
A67: Summary | B67: — | C67: Counts per site and the reconciliation checks (formulas).
A68: Field_Dictionary | B68: — | C68: Every column: required, type, allowed values, the system field it maps to.
A69: Lookups | B69: — | C69: Allowed values behind the dropdowns.

Sheet Summary
A1: Summary and reconciliation checks
A2: Every figure is a formula over the data sheets. Check it with the customer: these are the numbers the platform will show.
A4: Measure | B4: =IF('Sites'!A2="","(site 1)",'Sites'!A2) | C4: =IF('Sites'!A3="","(site 2)",'Sites'!A3) | D4: =IF('Sites'!A4="","(site 3)",'Sites'!A4) | E4: =IF('Sites'!A5="","(site 4)",'Sites'!A5) | F4: =IF('Sites'!A6="","(site 5)",'Sites'!A6) | G4: =IF('Sites'!A7="","(site 6)",'Sites'!A7) | H4: Total
A5: Floors | B5: =IF('Sites'!$A$2="","",COUNTIF('Floors'!$A$2:$A$4690,B$4)) | C5: =IF('Sites'!$A$3="","",COUNTIF('Floors'!$A$2:$A$4690,C$4)) | D5: =IF('Sites'!$A$4="","",COUNTIF('Floors'!$A$2:$A$4690,D$4)) | E5: =IF('Sites'!$A$5="","",COUNTIF('Floors'!$A$2:$A$4690,E$4)) | F5: =IF('Sites'!$A$6="","",COUNTIF('Floors'!$A$2:$A$4690,F$4)) | G5: =IF('Sites'!$A$7="","",COUNTIF('Floors'!$A$2:$A$4690,G$4)) | H5: =SUM(B5:G5)
A6: Rooms | B6: =IF('Sites'!$A$2="","",COUNTIF('Rooms'!$A$2:$A$4690,B$4)) | C6: =IF('Sites'!$A$3="","",COUNTIF('Rooms'!$A$2:$A$4690,C$4)) | D6: =IF('Sites'!$A$4="","",COUNTIF('Rooms'!$A$2:$A$4690,D$4)) | E6: =IF('Sites'!$A$5="","",COUNTIF('Rooms'!$A$2:$A$4690,E$4)) | F6: =IF('Sites'!$A$6="","",COUNTIF('Rooms'!$A$2:$A$4690,F$4)) | G6: =IF('Sites'!$A$7="","",COUNTIF('Rooms'!$A$2:$A$4690,G$4)) | H6: =SUM(B6:G6)
A7: Racks | B7: =IF('Sites'!$A$2="","",COUNTIF('Racks'!$B$2:$B$4690,B$4)) | C7: =IF('Sites'!$A$3="","",COUNTIF('Racks'!$B$2:$B$4690,C$4)) | D7: =IF('Sites'!$A$4="","",COUNTIF('Racks'!$B$2:$B$4690,D$4)) | E7: =IF('Sites'!$A$5="","",COUNTIF('Racks'!$B$2:$B$4690,E$4)) | F7: =IF('Sites'!$A$6="","",COUNTIF('Racks'!$B$2:$B$4690,F$4)) | G7: =IF('Sites'!$A$7="","",COUNTIF('Racks'!$B$2:$B$4690,G$4)) | H7: =SUM(B7:G7)
A8: of which tenant cabinets | B8: =IF('Sites'!$A$2="","",COUNTIFS('Racks'!$B$2:$B$4690,B$4,'Racks'!$J$2:$J$4690,"tenant")) | C8: =IF('Sites'!$A$3="","",COUNTIFS('Racks'!$B$2:$B$4690,C$4,'Racks'!$J$2:$J$4690,"tenant")) | D8: =IF('Sites'!$A$4="","",COUNTIFS('Racks'!$B$2:$B$4690,D$4,'Racks'!$J$2:$J$4690,"tenant")) | E8: =IF('Sites'!$A$5="","",COUNTIFS('Racks'!$B$2:$B$4690,E$4,'Racks'!$J$2:$J$4690,"tenant")) | F8: =IF('Sites'!$A$6="","",COUNTIFS('Racks'!$B$2:$B$4690,F$4,'Racks'!$J$2:$J$4690,"tenant")) | G8: =IF('Sites'!$A$7="","",COUNTIFS('Racks'!$B$2:$B$4690,G$4,'Racks'!$J$2:$J$4690,"tenant")) | H8: =SUM(B8:G8)
A9: of which AI / high-density | B9: =IF('Sites'!$A$2="","",COUNTIFS('Racks'!$B$2:$B$4690,B$4,'Racks'!$M$2:$M$4690,"ai")) | C9: =IF('Sites'!$A$3="","",COUNTIFS('Racks'!$B$2:$B$4690,C$4,'Racks'!$M$2:$M$4690,"ai")) | D9: =IF('Sites'!$A$4="","",COUNTIFS('Racks'!$B$2:$B$4690,D$4,'Racks'!$M$2:$M$4690,"ai")) | E9: =IF('Sites'!$A$5="","",COUNTIFS('Racks'!$B$2:$B$4690,E$4,'Racks'!$M$2:$M$4690,"ai")) | F9: =IF('Sites'!$A$6="","",COUNTIFS('Racks'!$B$2:$B$4690,F$4,'Racks'!$M$2:$M$4690,"ai")) | G9: =IF('Sites'!$A$7="","",COUNTIFS('Racks'!$B$2:$B$4690,G$4,'Racks'!$M$2:$M$4690,"ai")) | H9: =SUM(B9:G9)
A10: Rack power budget (kW) | B10: =IF('Sites'!$A$2="","",SUMIF('Racks'!$B$2:$B$4690,B$4,'Racks'!$I$2:$I$4690)) | C10: =IF('Sites'!$A$3="","",SUMIF('Racks'!$B$2:$B$4690,C$4,'Racks'!$I$2:$I$4690)) | D10: =IF('Sites'!$A$4="","",SUMIF('Racks'!$B$2:$B$4690,D$4,'Racks'!$I$2:$I$4690)) | E10: =IF('Sites'!$A$5="","",SUMIF('Racks'!$B$2:$B$4690,E$4,'Racks'!$I$2:$I$4690)) | F10: =IF('Sites'!$A$6="","",SUMIF('Racks'!$B$2:$B$4690,F$4,'Racks'!$I$2:$I$4690)) | G10: =IF('Sites'!$A$7="","",SUMIF('Racks'!$B$2:$B$4690,G$4,'Racks'!$I$2:$I$4690)) | H10: =SUM(B10:G10)
A11: Site IT capacity (kW) | B11: =IF('Sites'!$A$2="","",SUMIF('Sites'!$A$2:$A$4690,B$4,'Sites'!$O$2:$O$4690)) | C11: =IF('Sites'!$A$3="","",SUMIF('Sites'!$A$2:$A$4690,C$4,'Sites'!$O$2:$O$4690)) | D11: =IF('Sites'!$A$4="","",SUMIF('Sites'!$A$2:$A$4690,D$4,'Sites'!$O$2:$O$4690)) | E11: =IF('Sites'!$A$5="","",SUMIF('Sites'!$A$2:$A$4690,E$4,'Sites'!$O$2:$O$4690)) | F11: =IF('Sites'!$A$6="","",SUMIF('Sites'!$A$2:$A$4690,F$4,'Sites'!$O$2:$O$4690)) | G11: =IF('Sites'!$A$7="","",SUMIF('Sites'!$A$2:$A$4690,G$4,'Sites'!$O$2:$O$4690)) | H11: =SUM(B11:G11)
A12: Devices (all) | B12: =IF('Sites'!$A$2="","",COUNTIFS('Devices'!$B$2:$B$4690,B$4)) | C12: =IF('Sites'!$A$3="","",COUNTIFS('Devices'!$B$2:$B$4690,C$4)) | D12: =IF('Sites'!$A$4="","",COUNTIFS('Devices'!$B$2:$B$4690,D$4)) | E12: =IF('Sites'!$A$5="","",COUNTIFS('Devices'!$B$2:$B$4690,E$4)) | F12: =IF('Sites'!$A$6="","",COUNTIFS('Devices'!$B$2:$B$4690,F$4)) | G12: =IF('Sites'!$A$7="","",COUNTIFS('Devices'!$B$2:$B$4690,G$4)) | H12: =SUM(B12:G12)
A13: operator devices | B13: =IF('Sites'!$A$2="","",COUNTIFS('Devices'!$B$2:$B$4690,B$4,'Devices'!$P$2:$P$4690,"operator")) | C13: =IF('Sites'!$A$3="","",COUNTIFS('Devices'!$B$2:$B$4690,C$4,'Devices'!$P$2:$P$4690,"operator")) | D13: =IF('Sites'!$A$4="","",COUNTIFS('Devices'!$B$2:$B$4690,D$4,'Devices'!$P$2:$P$4690,"operator")) | E13: =IF('Sites'!$A$5="","",COUNTIFS('Devices'!$B$2:$B$4690,E$4,'Devices'!$P$2:$P$4690,"operator")) | F13: =IF('Sites'!$A$6="","",COUNTIFS('Devices'!$B$2:$B$4690,F$4,'Devices'!$P$2:$P$4690,"operator")) | G13: =IF('Sites'!$A$7="","",COUNTIFS('Devices'!$B$2:$B$4690,G$4,'Devices'!$P$2:$P$4690,"operator")) | H13: =SUM(B13:G13)
A14: tenant gear blocks | B14: =IF('Sites'!$A$2="","",COUNTIFS('Devices'!$B$2:$B$4690,B$4,'Devices'!$P$2:$P$4690,"tenant")) | C14: =IF('Sites'!$A$3="","",COUNTIFS('Devices'!$B$2:$B$4690,C$4,'Devices'!$P$2:$P$4690,"tenant")) | D14: =IF('Sites'!$A$4="","",COUNTIFS('Devices'!$B$2:$B$4690,D$4,'Devices'!$P$2:$P$4690,"tenant")) | E14: =IF('Sites'!$A$5="","",COUNTIFS('Devices'!$B$2:$B$4690,E$4,'Devices'!$P$2:$P$4690,"tenant")) | F14: =IF('Sites'!$A$6="","",COUNTIFS('Devices'!$B$2:$B$4690,F$4,'Devices'!$P$2:$P$4690,"tenant")) | G14: =IF('Sites'!$A$7="","",COUNTIFS('Devices'!$B$2:$B$4690,G$4,'Devices'!$P$2:$P$4690,"tenant")) | H14: =SUM(B14:G14)
A15: GPU nodes | B15: =IF('Sites'!$A$2="","",COUNTIFS('Devices'!$B$2:$B$4690,B$4,'Devices'!$D$2:$D$4690,"GPU")) | C15: =IF('Sites'!$A$3="","",COUNTIFS('Devices'!$B$2:$B$4690,C$4,'Devices'!$D$2:$D$4690,"GPU")) | D15: =IF('Sites'!$A$4="","",COUNTIFS('Devices'!$B$2:$B$4690,D$4,'Devices'!$D$2:$D$4690,"GPU")) | E15: =IF('Sites'!$A$5="","",COUNTIFS('Devices'!$B$2:$B$4690,E$4,'Devices'!$D$2:$D$4690,"GPU")) | F15: =IF('Sites'!$A$6="","",COUNTIFS('Devices'!$B$2:$B$4690,F$4,'Devices'!$D$2:$D$4690,"GPU")) | G15: =IF('Sites'!$A$7="","",COUNTIFS('Devices'!$B$2:$B$4690,G$4,'Devices'!$D$2:$D$4690,"GPU")) | H15: =SUM(B15:G15)
A16: network (routers, firewalls, switches) | B16: =IF('Sites'!$A$2="","",COUNTIFS('Devices'!$B$2:$B$4690,B$4,'Devices'!$D$2:$D$4690,"Router")+COUNTIFS('Devices'!$B$2:$B$4690,B$4,'Devices'!$D$2:$D$4690,"Firewall")+COUNTIFS('Devices'!$B$2:$B$4690,B$4,'Devices'!$D$2:$D$4690,"Switch")) | C16: =IF('Sites'!$A$3="","",COUNTIFS('Devices'!$B$2:$B$4690,C$4,'Devices'!$D$2:$D$4690,"Router")+COUNTIFS('Devices'!$B$2:$B$4690,C$4,'Devices'!$D$2:$D$4690,"Firewall")+COUNTIFS('Devices'!$B$2:$B$4690,C$4,'Devices'!$D$2:$D$4690,"Switch")) | D16: =IF('Sites'!$A$4="","",COUNTIFS('Devices'!$B$2:$B$4690,D$4,'Devices'!$D$2:$D$4690,"Router")+COUNTIFS('Devices'!$B$2:$B$4690,D$4,'Devices'!$D$2:$D$4690,"Firewall")+COUNTIFS('Devices'!$B$2:$B$4690,D$4,'Devices'!$D$2:$D$4690,"Switch")) | E16: =IF('Sites'!$A$5="","",COUNTIFS('Devices'!$B$2:$B$4690,E$4,'Devices'!$D$2:$D$4690,"Router")+COUNTIFS('Devices'!$B$2:$B$4690,E$4,'Devices'!$D$2:$D$4690,"Firewall")+COUNTIFS('Devices'!$B$2:$B$4690,E$4,'Devices'!$D$2:$D$4690,"Switch")) | F16: =IF('Sites'!$A$6="","",COUNTIFS('Devices'!$B$2:$B$4690,F$4,'Devices'!$D$2:$D$4690,"Router")+COUNTIFS('Devices'!$B$2:$B$4690,F$4,'Devices'!$D$2:$D$4690,"Firewall")+COUNTIFS('Devices'!$B$2:$B$4690,F$4,'Devices'!$D$2:$D$4690,"Switch")) | G16: =IF('Sites'!$A$7="","",COUNTIFS('Devices'!$B$2:$B$4690,G$4,'Devices'!$D$2:$D$4690,"Router")+COUNTIFS('Devices'!$B$2:$B$4690,G$4,'Devices'!$D$2:$D$4690,"Firewall")+COUNTIFS('Devices'!$B$2:$B$4690,G$4,'Devices'!$D$2:$D$4690,"Switch")) | H16: =SUM(B16:G16)
A17: UPS units | B17: =IF('Sites'!$A$2="","",COUNTIF('UPS'!$B$2:$B$4690,B$4)) | C17: =IF('Sites'!$A$3="","",COUNTIF('UPS'!$B$2:$B$4690,C$4)) | D17: =IF('Sites'!$A$4="","",COUNTIF('UPS'!$B$2:$B$4690,D$4)) | E17: =IF('Sites'!$A$5="","",COUNTIF('UPS'!$B$2:$B$4690,E$4)) | F17: =IF('Sites'!$A$6="","",COUNTIF('UPS'!$B$2:$B$4690,F$4)) | G17: =IF('Sites'!$A$7="","",COUNTIF('UPS'!$B$2:$B$4690,G$4)) | H17: =SUM(B17:G17)
A18: UPS capacity (kW) | B18: =IF('Sites'!$A$2="","",SUMIF('UPS'!$B$2:$B$4690,B$4,'UPS'!$H$2:$H$4690)) | C18: =IF('Sites'!$A$3="","",SUMIF('UPS'!$B$2:$B$4690,C$4,'UPS'!$H$2:$H$4690)) | D18: =IF('Sites'!$A$4="","",SUMIF('UPS'!$B$2:$B$4690,D$4,'UPS'!$H$2:$H$4690)) | E18: =IF('Sites'!$A$5="","",SUMIF('UPS'!$B$2:$B$4690,E$4,'UPS'!$H$2:$H$4690)) | F18: =IF('Sites'!$A$6="","",SUMIF('UPS'!$B$2:$B$4690,F$4,'UPS'!$H$2:$H$4690)) | G18: =IF('Sites'!$A$7="","",SUMIF('UPS'!$B$2:$B$4690,G$4,'UPS'!$H$2:$H$4690)) | H18: =SUM(B18:G18)
A19: Generators | B19: =IF('Sites'!$A$2="","",COUNTIF('Generators'!$B$2:$B$4690,B$4)) | C19: =IF('Sites'!$A$3="","",COUNTIF('Generators'!$B$2:$B$4690,C$4)) | D19: =IF('Sites'!$A$4="","",COUNTIF('Generators'!$B$2:$B$4690,D$4)) | E19: =IF('Sites'!$A$5="","",COUNTIF('Generators'!$B$2:$B$4690,E$4)) | F19: =IF('Sites'!$A$6="","",COUNTIF('Generators'!$B$2:$B$4690,F$4)) | G19: =IF('Sites'!$A$7="","",COUNTIF('Generators'!$B$2:$B$4690,G$4)) | H19: =SUM(B19:G19)
A20: Cooling units | B20: =IF('Sites'!$A$2="","",COUNTIF('Cooling_Units'!$B$2:$B$4690,B$4)) | C20: =IF('Sites'!$A$3="","",COUNTIF('Cooling_Units'!$B$2:$B$4690,C$4)) | D20: =IF('Sites'!$A$4="","",COUNTIF('Cooling_Units'!$B$2:$B$4690,D$4)) | E20: =IF('Sites'!$A$5="","",COUNTIF('Cooling_Units'!$B$2:$B$4690,E$4)) | F20: =IF('Sites'!$A$6="","",COUNTIF('Cooling_Units'!$B$2:$B$4690,F$4)) | G20: =IF('Sites'!$A$7="","",COUNTIF('Cooling_Units'!$B$2:$B$4690,G$4)) | H20: =SUM(B20:G20)
A21: Cooling unit capacity (kW) | B21: =IF('Sites'!$A$2="","",SUMIF('Cooling_Units'!$B$2:$B$4690,B$4,'Cooling_Units'!$H$2:$H$4690)) | C21: =IF('Sites'!$A$3="","",SUMIF('Cooling_Units'!$B$2:$B$4690,C$4,'Cooling_Units'!$H$2:$H$4690)) | D21: =IF('Sites'!$A$4="","",SUMIF('Cooling_Units'!$B$2:$B$4690,D$4,'Cooling_Units'!$H$2:$H$4690)) | E21: =IF('Sites'!$A$5="","",SUMIF('Cooling_Units'!$B$2:$B$4690,E$4,'Cooling_Units'!$H$2:$H$4690)) | F21: =IF('Sites'!$A$6="","",SUMIF('Cooling_Units'!$B$2:$B$4690,F$4,'Cooling_Units'!$H$2:$H$4690)) | G21: =IF('Sites'!$A$7="","",SUMIF('Cooling_Units'!$B$2:$B$4690,G$4,'Cooling_Units'!$H$2:$H$4690)) | H21: =SUM(B21:G21)
A22: Sensors | B22: =IF('Sites'!$A$2="","",COUNTIF('Sensors'!$B$2:$B$4690,B$4)) | C22: =IF('Sites'!$A$3="","",COUNTIF('Sensors'!$B$2:$B$4690,C$4)) | D22: =IF('Sites'!$A$4="","",COUNTIF('Sensors'!$B$2:$B$4690,D$4)) | E22: =IF('Sites'!$A$5="","",COUNTIF('Sensors'!$B$2:$B$4690,E$4)) | F22: =IF('Sites'!$A$6="","",COUNTIF('Sensors'!$B$2:$B$4690,F$4)) | G22: =IF('Sites'!$A$7="","",COUNTIF('Sensors'!$B$2:$B$4690,G$4)) | H22: =SUM(B22:G22)
A23: Collectors | B23: =IF('Sites'!$A$2="","",COUNTIF('Collectors'!$B$2:$B$4690,B$4)) | C23: =IF('Sites'!$A$3="","",COUNTIF('Collectors'!$B$2:$B$4690,C$4)) | D23: =IF('Sites'!$A$4="","",COUNTIF('Collectors'!$B$2:$B$4690,D$4)) | E23: =IF('Sites'!$A$5="","",COUNTIF('Collectors'!$B$2:$B$4690,E$4)) | F23: =IF('Sites'!$A$6="","",COUNTIF('Collectors'!$B$2:$B$4690,F$4)) | G23: =IF('Sites'!$A$7="","",COUNTIF('Collectors'!$B$2:$B$4690,G$4)) | H23: =SUM(B23:G23)
A24: Services | B24: =IF('Sites'!$A$2="","",COUNTIF('Services'!$D$2:$D$4690,B$4)) | C24: =IF('Sites'!$A$3="","",COUNTIF('Services'!$D$2:$D$4690,C$4)) | D24: =IF('Sites'!$A$4="","",COUNTIF('Services'!$D$2:$D$4690,D$4)) | E24: =IF('Sites'!$A$5="","",COUNTIF('Services'!$D$2:$D$4690,E$4)) | F24: =IF('Sites'!$A$6="","",COUNTIF('Services'!$D$2:$D$4690,F$4)) | G24: =IF('Sites'!$A$7="","",COUNTIF('Services'!$D$2:$D$4690,G$4)) | H24: =SUM(B24:G24)
A25: Services monthly revenue (₹) | B25: =IF('Sites'!$A$2="","",SUMIF('Services'!$D$2:$D$4690,B$4,'Services'!$M$2:$M$4690)) | C25: =IF('Sites'!$A$3="","",SUMIF('Services'!$D$2:$D$4690,C$4,'Services'!$M$2:$M$4690)) | D25: =IF('Sites'!$A$4="","",SUMIF('Services'!$D$2:$D$4690,D$4,'Services'!$M$2:$M$4690)) | E25: =IF('Sites'!$A$5="","",SUMIF('Services'!$D$2:$D$4690,E$4,'Services'!$M$2:$M$4690)) | F25: =IF('Sites'!$A$6="","",SUMIF('Services'!$D$2:$D$4690,F$4,'Services'!$M$2:$M$4690)) | G25: =IF('Sites'!$A$7="","",SUMIF('Services'!$D$2:$D$4690,G$4,'Services'!$M$2:$M$4690)) | H25: =SUM(B25:G25)
A28: Checks
A29: Check | B29: Result | C29: Why it matters
A30: Every device sits in a rack that exists | B30: =IF(SUMPRODUCT(--(COUNTIF('Racks'!$A$2:$A$4690,'Devices'!$L$2:$L$674)=0))=0,"OK","FIX: unknown rack_id") | C30: The twin and rack views place devices by rack_id.
A31: No rack is over-filled (used U ≤ height U) | B31: =IF(SUMPRODUCT(--('Racks'!$R$2:$R$69>'Racks'!$H$2:$H$69))=0,"OK","FIX: rack over capacity") | C31: used_u is calculated from Devices.
A32: Device IDs are unique | B32: =IF(SUMPRODUCT(--(COUNTIF('Devices'!$A$2:$A$674,'Devices'!$A$2:$A$674)>1))=0,"OK","FIX: duplicate device_id") | C32: Alarms and incidents key on the device ID.
A33: Operator serial numbers are unique | B33: =IF(SUMPRODUCT(('Devices'!$I$2:$I$674<>"")*(COUNTIF('Devices'!$I$2:$I$674,'Devices'!$I$2:$I$674)>1))=0,"OK","FIX: duplicate serial") | C33: Discovery matches the polled serial against this one.
A34: Tenant racks name a tenant and contracted kW | B34: =IF(COUNTIFS('Racks'!$J$2:$J$69,"tenant",'Racks'!$K$2:$K$69,"")+COUNTIFS('Racks'!$J$2:$J$69,"tenant",'Racks'!$L$2:$L$69,"")=0,"OK","FIX: tenant rack missing data") | C34: Colocation power-over-contract is measured against it.
A35: Liquid racks name a CDU | B35: =IF(COUNTIFS('Racks'!$N$2:$N$69,"Y",'Racks'!$O$2:$O$69,"")=0,"OK","FIX: liquid rack without CDU") | C35: A CDU fault is traced to the racks it feeds.
A36: Rack budget fits site IT capacity | B36: =IF(SUMPRODUCT(--(B10:G10>B11:G11))=0,"OK","CHECK: racks exceed IT capacity") | C36: Power and space views compare the two.
A37: GPU nodes = GPU devices in service | B37: =IF(COUNTA('GPU_Nodes'!$A$2:$A$4690)=COUNTIFS('Devices'!$D$2:$D$4690,"GPU",'Devices'!$R$2:$R$4690,"Y"),"OK","FIX: GPU_Nodes and Devices differ") | C37: Each GPU node in service needs a rack position and a telemetry record; hosts not yet commissioned into a cluster have none.
A38: Every installed device has a power connection | B38: =IF(SUMPRODUCT(('Devices'!$O$2:$O$674<>"Planned")*('Devices'!$A$2:$A$674<>"")*(COUNTIF('Power_Connections'!$A$2:$A$4690,'Devices'!$A$2:$A$674)=0))=0,"OK","FIX: device without a power cord") | C38: Without it the power path, single-fed devices and UPS / PDU what-ifs cannot be traced.
A39: Power cords point at a known PDU | B39: =IF(SUMPRODUCT(('Power_Connections'!$C$2:$C$4690<>"")*(COUNTIF('Rack_PDUs'!$A$2:$A$4690,'Power_Connections'!$C$2:$C$4690)=0))=0,"OK","FIX: unknown pdu_id") | C39: The outlet map and failover check group cords by PDU.
A40: Every rack has an A and a B PDU | B40: =IF(SUMPRODUCT(('Racks'!$A$2:$A$69<>"")*((COUNTIFS('Rack_PDUs'!$C$2:$C$4690,'Racks'!$A$2:$A$69,'Rack_PDUs'!$D$2:$D$4690,"A")=0)+(COUNTIFS('Rack_PDUs'!$C$2:$C$4690,'Racks'!$A$2:$A$69,'Rack_PDUs'!$D$2:$D$4690,"B")=0)))=0,"OK","CHECK: rack with one power side") | C40: A cabinet with one side is a single point of failure for everything in it.
A41: Cable paths name a known link | B41: =IF(SUMPRODUCT(('Cable_Paths'!$A$2:$A$4690<>"")*(COUNTIF('Links'!$A$2:$A$4690,'Cable_Paths'!$A$2:$A$4690)=0))=0,"OK","FIX: unknown link_id") | C41: Each cable path belongs to one link end.
A42: Every operator device has warranty / support data | B42: =IF(SUMPRODUCT(('Devices'!$P$2:$P$674="operator")*('Devices'!$O$2:$O$674<>"Planned")*(COUNTIF('Asset_Lifecycle'!$A$2:$A$4690,'Devices'!$A$2:$A$674)=0))=0,"OK","CHECK: device without lifecycle row") | C42: Warranty, contract and end-of-support flags need it.
A43: Every room has a fire system | B43: =IF(SUMPRODUCT(('Rooms'!$C$2:$C$9<>"")*(COUNTIF('Fire_Systems'!$C$2:$C$4690,'Rooms'!$C$2:$C$9)=0))=0,"OK","CHECK: room without fire protection") | C43: Fire detection / suppression and its inspection plan are tracked per room.
A44: Customer revenue = sum of services | B44: =IF(ROUND(SUM('Customers'!$I$2:$I$4690)-SUM('Services'!$M$2:$M$4690),0)=0,"OK","FIX: a service names an unknown customer") | C44: Revenue impact adds up only if every service has a customer.

Sheet Sites
A1: site_id * | B1: site_name * | C1: operator | D1: business_model * | E1: status * | F1: tier * | G1: category * | H1: region * | I1: state * | J1: city * | K1: address * | L1: latitude * | M1: longitude * | N1: commissioned_on | O1: it_capacity_kw * | P1: design_pue | Q1: cooling_capacity_kw * | R1: cooling_redundancy * | S1: timezone
A2: MH-DC-001 | B2: MH-DC-001 | D2: cloud | E2: in-progress | F2: Tier III | G2: Central | H2: West | I2: Maharashtra | J2: Pune | K2: Pune Data Park | L2: 18.593 | M2: 73.789 | O2: 1260 | P2: 1.52 | Q2: 990 | R2: N+1 | S2: Asia/Kolkata
A3: MH-DC-002 | B3: MH-DC-002 | D3: cloud | E3: on-air | F3: Tier III | G3: Central | H3: West | I3: Maharashtra | J3: Pune | K3: Pune Data Park | L3: 18.601 | M3: 73.762 | N3: 45790 | O3: 1160 | P3: 1.43 | Q3: 780 | R3: N+1 | S3: Asia/Kolkata

Sheet Floors
A1: site_id * | B1: floor_id * | C1: floor_name * | D1: level *
A2: MH-DC-001 | B2: MH-DC-001-F0 | C2: Ground | D2: 0
A3: MH-DC-001 | B3: MH-DC-001-F1 | C3: 1st floor | D3: 1
A4: MH-DC-002 | B4: MH-DC-002-F0 | C4: Ground | D4: 0
A5: MH-DC-002 | B5: MH-DC-002-F1 | C5: 1st floor | D5: 1

Sheet Rooms
A1: site_id * | B1: floor_id * | C1: room_id * | D1: room_name * | E1: room_type * | F1: area_sqm | G1: rack_rows | H1: containment | I1: cooling_method
A2: MH-DC-001 | B2: MH-DC-001-F0 | C2: MH-DC-001-F0-R1 | D2: Data hall 1 | E2: Data hall | G2: 2 | I2: Air
A3: MH-DC-001 | B3: MH-DC-001-F0 | C3: MH-DC-001-F0-R2 | D3: Data hall 2 | E3: Data hall | G3: 2 | I3: Air
A4: MH-DC-001 | B4: MH-DC-001-F1 | C4: MH-DC-001-F1-R1 | D4: Data hall 3 | E4: Data hall | G4: 2 | I4: Air
A5: MH-DC-001 | B5: MH-DC-001-F1 | C5: MH-DC-001-F1-R2 | D5: GPU hall | E5: AI hall | G5: 2 | I5: Air
A6: MH-DC-002 | B6: MH-DC-002-F0 | C6: MH-DC-002-F0-R1 | D6: Data hall 1 | E6: Data hall | G6: 1 | I6: Air
A7: MH-DC-002 | B7: MH-DC-002-F0 | C7: MH-DC-002-F0-R2 | D7: Data hall 2 | E7: Data hall | G7: 1 | I7: Air
A8: MH-DC-002 | B8: MH-DC-002-F1 | C8: MH-DC-002-F1-R1 | D8: Data hall 3 | E8: Data hall | G8: 1 | I8: Air
A9: MH-DC-002 | B9: MH-DC-002-F1 | C9: MH-DC-002-F1-R2 | D9: GPU hall | E9: AI hall | G9: 1 | I9: Air

Sheet Racks
A1: rack_id * | B1: site_id * | C1: room_id * | D1: rack_name * | E1: row | F1: position | G1: role * | H1: height_u * | I1: power_budget_kw * | J1: owner * | K1: tenant_customer_id | L1: contracted_kw | M1: density | N1: liquid_cooled | O1: cdu_id | P1: pdu_feed_a | Q1: pdu_feed_b | R1: used_u (calc)
A2: MH-DC-001-RACK-A | B2: MH-DC-001 | C2: MH-DC-001-F0-R1 | D2: RACK-A | G2: Core | H2: 45 | I2: 16 | J2: operator | M2: standard | N2: N | P2: MH-DC-001-AC-1 | Q2: MH-DC-001-AC-2 | R2: =SUMIF('Devices'!$L$2:$L$4690,A2,'Devices'!$N$2:$N$4690)
A3: MH-DC-001-RACK-B | B3: MH-DC-001 | C3: MH-DC-001-F0-R1 | D3: RACK-B | G3: Network | H3: 42 | I3: 16 | J3: operator | M3: standard | N3: N | P3: MH-DC-001-AC-1 | Q3: MH-DC-001-AC-2 | R3: =SUMIF('Devices'!$L$2:$L$4690,A3,'Devices'!$N$2:$N$4690)
A4: MH-DC-001-RACK-C | B4: MH-DC-001 | C4: MH-DC-001-F0-R1 | D4: RACK-C | G4: Compute | H4: 45 | I4: 23 | J4: operator | M4: standard | N4: N | P4: MH-DC-001-AC-1 | Q4: MH-DC-001-AC-2 | R4: =SUMIF('Devices'!$L$2:$L$4690,A4,'Devices'!$N$2:$N$4690)
A5: MH-DC-001-RACK-D | B5: MH-DC-001 | C5: MH-DC-001-F0-R1 | D5: RACK-D | G5: Compute | H5: 45 | I5: 23 | J5: operator | M5: standard | N5: N | P5: MH-DC-001-AC-1 | Q5: MH-DC-001-AC-2 | R5: =SUMIF('Devices'!$L$2:$L$4690,A5,'Devices'!$N$2:$N$4690)
A6: MH-DC-001-RACK-E | B6: MH-DC-001 | C6: MH-DC-001-F0-R1 | D6: RACK-E | G6: Compute | H6: 42 | I6: 17 | J6: operator | M6: standard | N6: N | P6: MH-DC-001-AC-1 | Q6: MH-DC-001-AC-2 | R6: =SUMIF('Devices'!$L$2:$L$4690,A6,'Devices'!$N$2:$N$4690)
A7: MH-DC-001-RACK-F | B7: MH-DC-001 | C7: MH-DC-001-F0-R1 | D7: RACK-F | G7: Compute | H7: 45 | I7: 23 | J7: operator | M7: standard | N7: N | P7: MH-DC-001-AC-1 | Q7: MH-DC-001-AC-2 | R7: =SUMIF('Devices'!$L$2:$L$4690,A7,'Devices'!$N$2:$N$4690)
A8: MH-DC-001-RACK-G | B8: MH-DC-001 | C8: MH-DC-001-F0-R1 | D8: RACK-G | G8: Compute | H8: 45 | I8: 20 | J8: operator | M8: standard | N8: N | P8: MH-DC-001-AC-1 | Q8: MH-DC-001-AC-2 | R8: =SUMIF('Devices'!$L$2:$L$4690,A8,'Devices'!$N$2:$N$4690)
A9: MH-DC-001-RACK-H | B9: MH-DC-001 | C9: MH-DC-001-F0-R1 | D9: RACK-H | G9: Compute | H9: 42 | I9: 17 | J9: operator | M9: standard | N9: N | P9: MH-DC-001-AC-1 | Q9: MH-DC-001-AC-2 | R9: =SUMIF('Devices'!$L$2:$L$4690,A9,'Devices'!$N$2:$N$4690)
A10: MH-DC-001-RACK-I | B10: MH-DC-001 | C10: MH-DC-001-F0-R1 | D10: RACK-I | G10: Compute | H10: 45 | I10: 18 | J10: operator | M10: standard | N10: N | P10: MH-DC-001-AC-1 | Q10: MH-DC-001-AC-2 | R10: =SUMIF('Devices'!$L$2:$L$4690,A10,'Devices'!$N$2:$N$4690)
A11: MH-DC-001-RACK-J | B11: MH-DC-001 | C11: MH-DC-001-F0-R1 | D11: RACK-J | G11: Compute | H11: 45 | I11: 20 | J11: operator | M11: standard | N11: N | P11: MH-DC-001-AC-1 | Q11: MH-DC-001-AC-2 | R11: =SUMIF('Devices'!$L$2:$L$4690,A11,'Devices'!$N$2:$N$4690)
A12: MH-DC-001-RACK-K | B12: MH-DC-001 | C12: MH-DC-001-F0-R1 | D12: RACK-K | G12: Compute | H12: 42 | I12: 18 | J12: operator | M12: standard | N12: N | P12: MH-DC-001-AC-1 | Q12: MH-DC-001-AC-2 | R12: =SUMIF('Devices'!$L$2:$L$4690,A12,'Devices'!$N$2:$N$4690)
A13: MH-DC-001-RACK-L | B13: MH-DC-001 | C13: MH-DC-001-F0-R1 | D13: RACK-L | G13: Compute | H13: 45 | I13: 9 | J13: operator | M13: standard | N13: N | P13: MH-DC-001-AC-1 | Q13: MH-DC-001-AC-2 | R13: =SUMIF('Devices'!$L$2:$L$4690,A13,'Devices'!$N$2:$N$4690)
... A69: MH-DC-002-RACK-W | B69: MH-DC-002 | C69: MH-DC-002-F1-R2 | D69: RACK-W | G69: ODF / patching | H69: 42 | I69: 8 | J69: operator | M69: standard | N69: N | P69: MH-DC-002-AC-1 | Q69: MH-DC-002-AC-2 | R69: =SUMIF('Devices'!$L$2:$L$4690,A69,'Devices'!$N$2:$N$4690)

Sheet Power_Feeds
A1: feed_id * | B1: site_id * | C1: type * | D1: source * | E1: rating * | F1: capacity_kw * | G1: normal_role | H1: utility_account
A2: MH-DC-001-AC-1 | B2: MH-DC-001 | C2: AC | D2: Utility feed A | E2: 1227 A · 415 V | F2: 882 | G2: Active
A3: MH-DC-001-AC-2 | B3: MH-DC-001 | C3: AC | D3: Utility feed B | E3: 1227 A · 415 V | F3: 882 | G3: Standby
A4: MH-DC-001-DC-1 | B4: MH-DC-001 | C4: DC | D4: Rectifier RECT-01 | E4: 48 V · 7880 A | F4: 378 | G4: Active
A5: MH-DC-002-AC-1 | B5: MH-DC-002 | C5: AC | D5: Utility feed A | E5: 1130 A · 415 V | F5: 812 | G5: Active
A6: MH-DC-002-AC-2 | B6: MH-DC-002 | C6: AC | D6: Utility feed B | E6: 1130 A · 415 V | F6: 812 | G6: Standby
A7: MH-DC-002-DC-1 | B7: MH-DC-002 | C7: DC | D7: Rectifier RECT-01 | E7: 48 V · 7250 A | F7: 348 | G7: Active

Sheet UPS
A1: ups_id * | B1: site_id * | C1: room_id | D1: name * | E1: vendor | F1: model | G1: serial | H1: capacity_kw * | I1: redundancy * | J1: battery_autonomy_min *
A2: MH-DC-001-UPS-1 | B2: MH-DC-001 | D2: UPS-1 | H2: 420 | I2: N+1 | J2: 13
A3: MH-DC-001-UPS-2 | B3: MH-DC-001 | D3: UPS-2 | H3: 420 | I3: N+1 | J3: 26
A4: MH-DC-001-UPS-3 | B4: MH-DC-001 | D4: UPS-3 | H4: 420 | I4: N+1 | J4: 25
A5: MH-DC-001-UPS-4 | B5: MH-DC-001 | D5: UPS-4 | H5: 420 | I5: N+1 | J5: 17
A6: MH-DC-002-UPS-1 | B6: MH-DC-002 | D6: UPS-1 | H6: 390 | I6: N+1 | J6: 26
A7: MH-DC-002-UPS-2 | B7: MH-DC-002 | D7: UPS-2 | H7: 390 | I7: N+1 | J7: 21
A8: MH-DC-002-UPS-3 | B8: MH-DC-002 | D8: UPS-3 | H8: 390 | I8: N+1 | J8: 15
A9: MH-DC-002-UPS-4 | B9: MH-DC-002 | D9: UPS-4 | H9: 390 | I9: N+1 | J9: 19

Sheet Generators
A1: dg_id * | B1: site_id * | C1: name * | D1: kva * | E1: fuel_tank_litres | F1: runtime_h_full_load * | G1: last_test_date | H1: last_test_result
A2: MH-DC-001-DG-1 | B2: MH-DC-001 | C2: DG-1 | D2: 1575 | F2: 11 | G2: 46257 | H2: Pass
A3: MH-DC-002-DG-1 | B3: MH-DC-002 | C3: DG-1 | D3: 1450 | F3: 10 | G3: 46260 | H3: Pass

Sheet DC_Plant
A1: plant_id * | B1: site_id * | C1: room_id | D1: kind * | E1: name * | F1: volts | G1: ah | H1: rated_output | I1: capacity_kw | J1: autonomy_h | K1: last_test_date
A2: MH-DC-001-RECT-01 | B2: MH-DC-001 | D2: Rectifier | E2: RECT-01 | H2: 48 V · 7880 A | I2: 378
A3: MH-DC-001-BATT-01 | B3: MH-DC-001 | D3: Battery bank | E3: BATT-01 | F3: 48 | G3: 7600 | J3: 2.9 | K3: 46211
A4: MH-DC-002-RECT-01 | B4: MH-DC-002 | D4: Rectifier | E4: RECT-01 | H4: 48 V · 7250 A | I4: 348
A5: MH-DC-002-BATT-01 | B5: MH-DC-002 | D5: Battery bank | E5: BATT-01 | F5: 48 | G5: 7000 | J5: 3.5 | K5: 46221

Sheet Cooling_Units
A1: unit_id * | B1: site_id * | C1: room_id * | D1: name * | E1: type * | F1: vendor | G1: model | H1: capacity_kw * | I1: design_supply_c
A2: MH-DC-001-CRAH-11 | B2: MH-DC-001 | C2: MH-DC-001-F0-R1 | D2: CRAH-11 | E2: CRAH | H2: 124 | I2: 19
A3: MH-DC-001-CRAH-12 | B3: MH-DC-001 | C3: MH-DC-001-F0-R2 | D3: CRAH-12 | E3: CRAH | H3: 124 | I3: 17
A4: MH-DC-001-CRAH-13 | B4: MH-DC-001 | C4: MH-DC-001-F1-R1 | D4: CRAH-13 | E4: CRAH | H4: 124 | I4: 18
A5: MH-DC-001-CRAH-14 | B5: MH-DC-001 | C5: MH-DC-001-F1-R2 | D5: CRAH-14 | E5: CRAH | H5: 124 | I5: 17
A6: MH-DC-001-CRAH-15 | B6: MH-DC-001 | C6: MH-DC-001-F0-R1 | D6: CRAH-15 | E6: CRAC | H6: 124 | I6: 20
A7: MH-DC-001-CRAH-16 | B7: MH-DC-001 | C7: MH-DC-001-F0-R2 | D7: CRAH-16 | E7: CRAH | H7: 124 | I7: 20
A8: MH-DC-001-CRAH-17 | B8: MH-DC-001 | C8: MH-DC-001-F1-R1 | D8: CRAH-17 | E8: CRAH | H8: 124 | I8: 17
A9: MH-DC-001-CRAH-18 | B9: MH-DC-001 | C9: MH-DC-001-F1-R2 | D9: CRAH-18 | E9: CRAH | H9: 124 | I9: 18
A10: MH-DC-002-CRAH-11 | B10: MH-DC-002 | C10: MH-DC-002-F0-R1 | D10: CRAH-11 | E10: CRAH | H10: 98 | I10: 18
A11: MH-DC-002-CRAH-12 | B11: MH-DC-002 | C11: MH-DC-002-F0-R2 | D11: CRAH-12 | E11: CRAH | H11: 98 | I11: 19
A12: MH-DC-002-CRAH-13 | B12: MH-DC-002 | C12: MH-DC-002-F1-R1 | D12: CRAH-13 | E12: CRAH | H12: 98 | I12: 18
A13: MH-DC-002-CRAH-14 | B13: MH-DC-002 | C13: MH-DC-002-F1-R2 | D13: CRAH-14 | E13: CRAH | H13: 98 | I13: 18
... A17: MH-DC-002-CRAH-18 | B17: MH-DC-002 | C17: MH-DC-002-F1-R2 | D17: CRAH-18 | E17: CRAH | H17: 98 | I17: 19

Sheet CDUs
A1: cdu_id * | B1: site_id * | C1: room_id * | D1: name * | E1: capacity_kw * | F1: nominal_flow_lpm * | G1: design_supply_c | H1: racks_served (calc)

Sheet Sensors
A1: sensor_id * | B1: site_id * | C1: room_id * | D1: kind * | E1: position | F1: bms_point
A2: MH-DC-001-ENV-1 | B2: MH-DC-001 | C2: MH-DC-001-F0-R1 | D2: Temperature + humidity
A3: MH-DC-001-ENV-2 | B3: MH-DC-001 | C3: MH-DC-001-F0-R2 | D3: Temperature + humidity
A4: MH-DC-001-ENV-3 | B4: MH-DC-001 | C4: MH-DC-001-F1-R1 | D4: Temperature + humidity
A5: MH-DC-001-ENV-4 | B5: MH-DC-001 | C5: MH-DC-001-F1-R2 | D5: Temperature + humidity
A6: MH-DC-002-ENV-1 | B6: MH-DC-002 | C6: MH-DC-002-F0-R1 | D6: Temperature + humidity
A7: MH-DC-002-ENV-2 | B7: MH-DC-002 | C7: MH-DC-002-F0-R2 | D7: Temperature + humidity
A8: MH-DC-002-ENV-3 | B8: MH-DC-002 | C8: MH-DC-002-F1-R1 | D8: Temperature + humidity
A9: MH-DC-002-ENV-4 | B9: MH-DC-002 | C9: MH-DC-002-F1-R2 | D9: Temperature + humidity

Sheet Devices
A1: device_id * | B1: site_id * | C1: hostname * | D1: role * | E1: layer * | F1: vendor * | G1: model * | H1: os_version | I1: serial | J1: mgmt_ip | K1: mac | L1: rack_id * | M1: u_position * | N1: u_size * | O1: lifecycle * | P1: owner * | Q1: tenant_customer_id | R1: monitored * | S1: collector_id | T1: wan_edge
A2: MH-DC-001-PE-T4-01 | B2: MH-DC-001 | C2: MH-DC-001-PE-T4-01 | D2: Router | E2: core | F2: JUNIPER | G2: MX204 | H2: 21.4R3-S5.5 | I2: JU0011000 | J2: 172.31.40.20 | K2: A4:5E:60:16:8F:48 | L2: MH-DC-001-RACK-A | M2: 2 | N2: 1 | O2: Ready | P2: operator | R2: Y | S2: COL-MH-DC-001-2 | T2: Y
A3: MH-DC-001-PE-T4-02 | B3: MH-DC-001 | C3: MH-DC-001-PE-T4-02 | D3: Router | E3: core | F3: JUNIPER | G3: MX204 | H3: 21.4R3-S5.5 | I3: JU0011012 | J3: 172.16.40.21 | K3: A4:5E:60:E4:96:7C | L3: MH-DC-001-RACK-A | M3: 3 | N3: 1 | O3: Ready | P3: operator | R3: Y | S3: COL-MH-DC-001-1 | T3: Y
A4: MH-DC-001-PE-T4-03 | B4: MH-DC-001 | C4: MH-DC-001-PE-T4-03 | D4: Router | E4: core | F4: CISCO | G4: ASR 9006 | H4: IOS XR 7.9.2 | I4: CS0011018 | J4: 172.16.40.22 | K4: A4:5E:60:03:E2:69 | L4: MH-DC-001-RACK-A | M4: 4 | N4: 1 | O4: Ready | P4: operator | R4: Y | S4: COL-MH-DC-001-2 | T4: Y
A5: MH-DC-001-PE-T4-04 | B5: MH-DC-001 | C5: MH-DC-001-PE-T4-04 | D5: Router | E5: core | F5: CISCO | G5: ASR 9006 | H5: IOS XR 7.9.2 | I5: CS0011027 | J5: 172.16.40.23 | K5: A4:5E:60:71:F5:F9 | L5: MH-DC-001-RACK-A | M5: 5 | N5: 1 | O5: Ready | P5: operator | R5: Y | S5: COL-MH-DC-001-1 | T5: Y
A6: MH-DC-001-FW-01 | B6: MH-DC-001 | C6: MH-DC-001-FW-01 | D6: Firewall | E6: core | F6: FORTINET | G6: FortiGate 3700F | H6: FortiOS 7.4.3 | I6: FG0011031 | J6: 172.16.40.24 | K6: A4:5E:60:B1:E8:37 | L6: MH-DC-001-RACK-A | M6: 6 | N6: 3 | O6: Ready | P6: operator | R6: Y | S6: COL-MH-DC-001-1 | T6: N
A7: MH-DC-001-FW-02 | B7: MH-DC-001 | C7: MH-DC-001-FW-02 | D7: Firewall | E7: core | F7: FORTINET | G7: FortiGate 3700F | H7: FortiOS 7.4.3 | I7: FG0011035 | J7: 172.16.40.25 | K7: A4:5E:60:FA:5F:B0 | L7: MH-DC-001-RACK-A | M7: 9 | N7: 3 | O7: Ready | P7: operator | R7: Y | S7: COL-MH-DC-001-2 | T7: N
A8: MH-DC-001-OLA-01 | B8: MH-DC-001 | C8: MH-DC-001-OLA-01 | D8: DWDM | E8: core | F8: NOKIA | G8: 1830 PSS-16II | H8: R23.6 | I8: NK0011042 | J8: 172.16.40.26 | K8: A4:5E:60:95:3C:15 | L8: MH-DC-001-RACK-A | M8: 12 | N8: 6 | O8: Ready | P8: operator | R8: Y | S8: COL-MH-DC-001-2 | T8: N
A9: MH-DC-001-OLA-02 | B9: MH-DC-001 | C9: MH-DC-001-OLA-02 | D9: DWDM | E9: core | F9: NOKIA | G9: 1830 PSS-16II | H9: R23.6 | I9: NK0011055 | J9: 172.16.40.27 | K9: A4:5E:60:B4:0B:73 | L9: MH-DC-001-RACK-A | M9: 18 | N9: 6 | O9: Ready | P9: operator | R9: Y | S9: COL-MH-DC-001-1 | T9: N
A10: MH-DC-001-SPINE-01 | B10: MH-DC-001 | C10: MH-DC-001-SPINE-01 | D10: Switch | E10: spine | F10: CISCO | G10: Nexus 9364D | H10: NX-OS 10.3(4a) | I10: CS0011057 | J10: 172.16.40.28 | K10: A4:5E:60:FB:48:6C | L10: MH-DC-001-RACK-A | M10: 24 | N10: 4 | O10: Ready | P10: operator | R10: Y | S10: COL-MH-DC-001-1 | T10: N
A11: MH-DC-001-SPINE-02 | B11: MH-DC-001 | C11: MH-DC-001-SPINE-02 | D11: Switch | E11: spine | F11: CISCO | G11: Nexus 9364D | H11: NX-OS 10.3(4a) | I11: CS0011064 | J11: 172.16.40.29 | K11: A4:5E:60:3B:44:EF | L11: MH-DC-001-RACK-A | M11: 28 | N11: 4 | O11: Ready | P11: operator | R11: Y | S11: COL-MH-DC-001-2 | T11: N
A12: MH-DC-001-SPINE-03 | B12: MH-DC-001 | C12: MH-DC-001-SPINE-03 | D12: Switch | E12: spine | F12: CISCO | G12: Nexus 9364D | H12: NX-OS 10.3(4a) | I12: CS0011074 | J12: 172.16.40.30 | K12: A4:5E:60:EC:7F:C0 | L12: MH-DC-001-RACK-A | M12: 32 | N12: 4 | O12: Ready | P12: operator | R12: Y | S12: COL-MH-DC-001-1 | T12: N
A13: MH-DC-001-SPINE-04 | B13: MH-DC-001 | C13: MH-DC-001-SPINE-04 | D13: Switch | E13: spine | F13: CISCO | G13: Nexus 9364D | H13: NX-OS 10.3(4a) | I13: CS0011083 | J13: 172.16.40.31 | K13: A4:5E:60:29:C4:8A | L13: MH-DC-001-RACK-B | M13: 2 | N13: 4 | O13: Ready | P13: operator | R13: Y | S13: COL-MH-DC-001-2 | T13: N
... A259: MH-DC-001-CMP-0224 | B259: MH-DC-001 | C259: MH-DC-001-CMP-0224 | D259: Server | E259: access | F259: HPE | G259: ProLiant DL380 Gen11 | H259: RHEL 9.3 | I259: HP0012805 | J259: 172.16.41.77 | K259: A4:5E:60:0C:E7:50 | L259: MH-DC-001-RACK-K | M259: 25 | N259: 1 | O259: Ready | P259: operator | R259: Y | S259: COL-MH-DC-001-1 | T259: N
A260: MH-DC-001-CMP-0225 | B260: MH-DC-001 | C260: MH-DC-001-CMP-0225 | D260: Server | E260: access | F260: HPE | G260: ProLiant DL380 Gen11 | H260: RHEL 9.3 | I260: HP0012810 | J260: 172.16.41.78 | K260: A4:5E:60:73:37:90 | L260: MH-DC-001-RACK-K | M260: 26 | N260: 2 | O260: Planned | P260: operator | R260: N | T260: N
A261: MH-DC-001-CMP-0226 | B261: MH-DC-001 | C261: MH-DC-001-CMP-0226 | D261: Server | E261: access | F261: HPE | G261: ProLiant DL380 Gen11 | H261: RHEL 9.3 | I261: HP0012813 | J261: 172.16.41.79 | K261: A4:5E:60:A5:08:EB | L261: MH-DC-001-RACK-K | M261: 28 | N261: 1 | O261: Planned | P261: operator | R261: N | T261: N
A262: MH-DC-001-CMP-0227 | B262: MH-DC-001 | C262: MH-DC-001-CMP-0227 | D262: Server | E262: access | F262: SUPERMICRO | G262: SYS-121H | H262: Ubuntu 22.04 | I262: SM0012820 | J262: 172.16.41.80 | K262: A4:5E:60:59:84:C8 | L262: MH-DC-001-RACK-K | M262: 29 | N262: 1 | O262: Planned | P262: operator | R262: N | T262: N
A263: MH-DC-001-CMP-0228 | B263: MH-DC-001 | C263: MH-DC-001-CMP-0228 | D263: Server | E263: access | F263: SUPERMICRO | G263: SYS-121H | H263: Ubuntu 22.04 | I263: SM0012827 | J263: 172.16.41.81 | K263: A4:5E:60:C4:48:B8 | L263: MH-DC-001-RACK-K | M263: 30 | N263: 2 | O263: Ready | P263: operator | R263: N | T263: N
A264: MH-DC-001-CMP-0229 | B264: MH-DC-001 | C264: MH-DC-001-CMP-0229 | D264: Server | E264: access | F264: HPE | G264: ProLiant DL380 Gen11 | H264: RHEL 9.3 | I264: HP0012837 | J264: 172.16.41.82 | K264: A4:5E:60:F8:E1:B5 | L264: MH-DC-001-RACK-K | M264: 32 | N264: 1 | O264: Ready | P264: operator | R264: N | T264: N
A265: MH-DC-001-CMP-0230 | B265: MH-DC-001 | C265: MH-DC-001-CMP-0230 | D265: Server | E265: access | F265: HPE | G265: ProLiant DL380 Gen11 | H265: RHEL 9.3 | I265: HP0012844 | J265: 172.16.41.83 | K265: A4:5E:60:A4:BE:4F | L265: MH-DC-001-RACK-K | M265: 33 | N265: 1 | O265: Planned | P265: operator | R265: N | T265: N
A266: MH-DC-001-CMP-0231 | B266: MH-DC-001 | C266: MH-DC-001-CMP-0231 | D266: Server | E266: access | F266: DELL | G266: PowerEdge R760 | H266: ESXi 8.0u2 | I266: DL0012854 | J266: 172.16.41.84 | K266: A4:5E:60:A7:0D:1D | L266: MH-DC-001-RACK-L | M266: 2 | N266: 2 | O266: Ready | P266: operator | R266: N | T266: N
A267: MH-DC-001-CMP-0232 | B267: MH-DC-001 | C267: MH-DC-001-CMP-0232 | D267: Server | E267: access | F267: HPE | G267: ProLiant DL380 Gen11 | H267: RHEL 9.3 | I267: HP0012855 | J267: 172.16.41.85 | K267: A4:5E:60:B0:68:81 | L267: MH-DC-001-RACK-L | M267: 4 | N267: 1 | O267: Ready | P267: operator | R267: N | T267: N
A268: MH-DC-001-CMP-0233 | B268: MH-DC-001 | C268: MH-DC-001-CMP-0233 | D268: Server | E268: access | F268: SUPERMICRO | G268: SYS-121H | H268: Ubuntu 22.04 | I268: SM0012868 | J268: 172.16.41.86 | K268: A4:5E:60:2D:BD:9E | L268: MH-DC-001-RACK-L | M268: 5 | N268: 1 | O268: Ready | P268: operator | R268: N | T268: N
A269: MH-DC-001-CMP-0234 | B269: MH-DC-001 | C269: MH-DC-001-CMP-0234 | D269: Server | E269: access | F269: SUPERMICRO | G269: SYS-121H | H269: Ubuntu 22.04 | I269: SM0012875 | J269: 172.16.41.87 | K269: A4:5E:60:7E:EB:EA | L269: MH-DC-001-RACK-L | M269: 6 | N269: 2 | O269: Planned | P269: operator | R269: N | T269: N
A270: MH-DC-001-CMP-0235 | B270: MH-DC-001 | C270: MH-DC-001-CMP-0235 | D270: Server | E270: access | F270: SUPERMICRO | G270: SYS-121H | H270: Ubuntu 22.04 | I270: SM0012878 | J270: 172.16.41.88 | K270: A4:5E:60:9C:6F:B3 | L270: MH-DC-001-RACK-L | M270: 8 | N270: 1 | O270: Planned | P270: operator | R270: N | T270: N
A271: MH-DC-001-CMP-0236 | B271: MH-DC-001 | C271: MH-DC-001-CMP-0236 | D271: Server | E271: access | F271: SUPERMICRO | G271: SYS-121H | H271: Ubuntu 22.04 | I271: SM0012884 | J271: 172.16.41.89 | K271: A4:5E:60:EB:1B:F7 | L271: MH-DC-001-RACK-L | M271: 9 | N271: 1 | O271: Planned | P271: operator | R271: N | T271: N
... A449: MH-DC-001-GPU-050 | B449: MH-DC-001 | C449: MH-DC-001-GPU-050 | D449: GPU | E449: access | F449: SUPERMICRO | G449: SYS-821GE (8×H100) | H449: Ubuntu 22.04 | I449: SM0014133 | J449: 172.16.42.67 | K449: A4:5E:60:2F:31:9B | L449: MH-DC-001-RACK-J1 | M449: 2 | N449: 8 | O449: Planned | P449: operator | R449: N | T449: N
A450: MH-DC-002-PE-T4-01 | B450: MH-DC-002 | C450: MH-DC-002-PE-T4-01 | D450: Router | E450: core | F450: JUNIPER | G450: MX204 | H450: 21.4R3-S5.5 | I450: JU0011001 | J450: 172.25.40.20 | K450: A4:5E:60:D1:8C:60 | L450: MH-DC-002-RACK-A | M450: 2 | N450: 1 | O450: Ready | P450: operator | R450: Y | S450: COL-MH-DC-002-1 | T450: Y
A451: MH-DC-002-PE-T4-02 | B451: MH-DC-002 | C451: MH-DC-002-PE-T4-02 | D451: Router | E451: core | F451: JUNIPER | G451: MX204 | H451: 21.4R3-S5.5 | I451: JU0011008 | J451: 172.25.40.21 | K451: A4:5E:60:58:5F:94 | L451: MH-DC-002-RACK-A | M451: 3 | N451: 1 | O451: Ready | P451: operator | R451: Y | S451: COL-MH-DC-002-2 | T451: Y
A452: MH-DC-002-PE-T4-03 | B452: MH-DC-002 | C452: MH-DC-002-PE-T4-03 | D452: Router | E452: core | F452: CISCO | G452: ASR 9006 | H452: IOS XR 7.9.2 | I452: CS0011017 | J452: 172.25.40.22 | K452: A4:5E:60:CC:DF:44 | L452: MH-DC-002-RACK-A | M452: 4 | N452: 1 | O452: Ready | P452: operator | R452: Y | S452: COL-MH-DC-002-1 | T452: Y
A453: MH-DC-002-PE-T4-04 | B453: MH-DC-002 | C453: MH-DC-002-PE-T4-04 | D453: Router | E453: core | F453: CISCO | G453: ASR 9006 | H453: IOS XR 7.9.2 | I453: CS0011023 | J453: 172.25.40.23 | K453: A4:5E:60:15:F0:8B | L453: MH-DC-002-RACK-A | M453: 5 | N453: 1 | O453: Ready | P453: operator | R453: Y | S453: COL-MH-DC-002-2 | T453: Y
A454: MH-DC-002-FW-01 | B454: MH-DC-002 | C454: MH-DC-002-FW-01 | D454: Firewall | E454: core | F454: FORTINET | G454: FortiGate 3700F | H454: FortiOS 7.4.3 | I454: FG0011028 | J454: 172.25.40.24 | K454: A4:5E:60:A2:17:62 | L454: MH-DC-002-RACK-A | M454: 6 | N454: 3 | O454: Ready | P454: operator | R454: Y | S454: COL-MH-DC-002-2 | T454: N
A455: MH-DC-002-OLA-01 | B455: MH-DC-002 | C455: MH-DC-002-OLA-01 | D455: DWDM | E455: core | F455: NOKIA | G455: 1830 PSS-16II | H455: R23.6 | I455: NK0011036 | J455: 172.25.40.25 | K455: A4:5E:60:3D:D8:21 | L455: MH-DC-002-RACK-A | M455: 9 | N455: 6 | O455: Ready | P455: operator | R455: Y | S455: COL-MH-DC-002-1 | T455: N
A456: MH-DC-002-OLA-02 | B456: MH-DC-002 | C456: MH-DC-002-OLA-02 | D456: DWDM | E456: core | F456: CIENA | G456: 6500 D7 | H456: R16.2 | I456: CI0011048 | J456: 172.25.40.26 | K456: A4:5E:60:9D:73:7F | L456: MH-DC-002-RACK-A | M456: 15 | N456: 6 | O456: Ready | P456: operator | R456: Y | S456: COL-MH-DC-002-2 | T456: N
A457: MH-DC-002-SPINE-01 | B457: MH-DC-002 | C457: MH-DC-002-SPINE-01 | D457: Switch | E457: spine | F457: ARISTA | G457: 7800R3-36P | H457: EOS 4.31.1F | I457: AR0011051 | J457: 172.25.40.27 | K457: A4:5E:60:60:8E:C0 | L457: MH-DC-002-RACK-A | M457: 21 | N457: 4 | O457: Ready | P457: operator | R457: Y | S457: COL-MH-DC-002-2 | T457: N
A458: MH-DC-002-SPINE-02 | B458: MH-DC-002 | C458: MH-DC-002-SPINE-02 | D458: Switch | E458: spine | F458: ARISTA | G458: 7800R3-36P | H458: EOS 4.31.1F | I458: AR0011057 | J458: 172.25.40.28 | K458: A4:5E:60:A2:DA:88 | L458: MH-DC-002-RACK-A | M458: 25 | N458: 4 | O458: Ready | P458: operator | R458: Y | S458: COL-MH-DC-002-1 | T458: N
A459: MH-DC-002-SPINE-03 | B459: MH-DC-002 | C459: MH-DC-002-SPINE-03 | D459: Switch | E459: spine | F459: ARISTA | G459: 7800R3-36P | H459: EOS 4.31.1F | I459: AR0011068 | J459: 172.25.40.29 | K459: A4:5E:60:D1:29:0B | L459: MH-DC-002-RACK-A | M459: 29 | N459: 4 | O459: Ready | P459: operator | R459: Y | S459: COL-MH-DC-002-2 | T459: N
A460: MH-DC-002-SPINE-04 | B460: MH-DC-002 | C460: MH-DC-002-SPINE-04 | D460: Switch | E460: spine | F460: ARISTA | G460: 7800R3-36P | H460: EOS 4.31.1F | I460: AR0011071 | J460: 172.25.40.30 | K460: A4:5E:60:6F:24:64 | L460: MH-DC-002-RACK-A | M460: 33 | N460: 4 | O460: Ready | P460: operator | R460: Y | S460: COL-MH-DC-002-1 | T460: N
A461: MH-DC-002-LEAF-01 | B461: MH-DC-002 | C461: MH-DC-002-LEAF-01 | D461: Switch | E461: leaf | F461: CISCO | G461: Nexus 9372PX | H461: NX-OS 9.3(12) | I461: CS0011079 | J461: 172.25.40.31 | K461: A4:5E:60:AA:F7:2C | L461: MH-DC-002-RACK-B | M461: 2 | N461: 2 | O461: Ready | P461: operator | R461: Y | S461: COL-MH-DC-002-1 | T461: N
... A674: MH-DC-002-GPU-024 | B674: MH-DC-002 | C674: MH-DC-002-GPU-024 | D674: GPU | E674: access | F674: NVIDIA | G674: DGX H100 | H674: DGX OS 6 | I674: NV0012572 | J674: 172.25.41.44 | K674: A4:5E:60:96:0E:90 | L674: MH-DC-002-RACK-R | M674: 18 | N674: 8 | O674: Ready | P674: operator | R674: Y | S674: COL-MH-DC-002-2 | T674: N

Sheet Modules
A1: device_id * | B1: slot * | C1: name * | D1: serial
A2: MH-DC-001-PE-T4-01 | B2: RE0 | C2: Routing Engine | D2: JU0011000-RE0
A3: MH-DC-001-PE-T4-01 | B3: FPC0 | C3: MPC (fixed) | D3: JU0011000-F0
A4: MH-DC-001-PE-T4-01 | B4: PEM0 | C4: Power supply AC | D4: JU0011000-P0
A5: MH-DC-001-PE-T4-01 | B5: PEM1 | C5: Power supply AC | D5: JU0011000-P1
A6: MH-DC-001-PE-T4-01 | B6: FAN0 | C6: Fan tray | D6: JU0011000-FT
A7: MH-DC-001-PE-T4-02 | B7: RE0 | C7: Routing Engine | D7: JU0011012-RE0
A8: MH-DC-001-PE-T4-02 | B8: FPC0 | C8: MPC (fixed) | D8: JU0011012-F0
A9: MH-DC-001-PE-T4-02 | B9: PEM0 | C9: Power supply AC | D9: JU0011012-P0
A10: MH-DC-001-PE-T4-02 | B10: PEM1 | C10: Power supply AC | D10: JU0011012-P1
A11: MH-DC-001-PE-T4-02 | B11: FAN0 | C11: Fan tray | D11: JU0011012-FT
A12: MH-DC-001-PE-T4-03 | B12: RE0 | C12: Routing Engine | D12: CS0011018-RE0
... A3276: MH-DC-002-GPU-024 | B3276: GPU7 | C3276: H100 SXM 80 GB | D3276: NV0012572-G7

Sheet Interfaces
A1: device_id * | B1: if_name * | C1: type * | D1: speed_mbps * | E1: admin_state * | F1: description | G1: optic_model
A2: MH-DC-001-PE-T4-01 | B2: xe-0/0/0 | C2: 10G SFP+ | D2: 10000 | E2: admin-down
A3: MH-DC-001-PE-T4-01 | B3: xe-0/0/1 | C3: 10G SFP+ | D3: 10000 | E3: up | F3: Backhaul to UP-DC-006 | G3: SFP-10G-LR
A4: MH-DC-001-PE-T4-01 | B4: xe-0/0/2 | C4: 10G SFP+ | D4: 10000 | E4: up | F4: Backhaul to KA-DC-021 | G4: SFP-10G-LR
A5: MH-DC-001-PE-T4-01 | B5: xe-0/0/3 | C5: 10G SFP+ | D5: 10000 | E5: up | F5: Backhaul to TS-DC-023 | G5: SFP-10G-LR
A6: MH-DC-001-PE-T4-01 | B6: xe-0/0/4 | C6: 10G SFP+ | D6: 10000 | E6: up | F6: Backhaul to BR-DC-019 | G6: SFP-10G-LR
A7: MH-DC-001-PE-T4-01 | B7: xe-0/0/5 | C7: 10G SFP+ | D7: 10000 | E7: up | F7: Backhaul to PB-DC-012 | G7: SFP-10G-LR
A8: MH-DC-001-PE-T4-01 | B8: xe-0/0/6 | C8: 10G SFP+ | D8: 10000 | E8: up | F8: Uplink to MH-DC-001-SPINE-01 | G8: SFP-10G-LR
A9: MH-DC-001-PE-T4-01 | B9: xe-0/0/7 | C9: 10G SFP+ | D9: 10000 | E9: up | F9: Uplink to MH-DC-001-SPINE-04 | G9: SFP-10G-LR
A10: MH-DC-001-PE-T4-01 | B10: xe-0/0/8 | C10: 10G SFP+ | D10: 10000 | E10: admin-down
A11: MH-DC-001-PE-T4-01 | B11: xe-0/0/9 | C11: 10G SFP+ | D11: 10000 | E11: admin-down
A12: MH-DC-001-PE-T4-01 | B12: xe-0/0/10 | C12: 10G SFP+ | D12: 10000 | E12: admin-down
A13: MH-DC-001-PE-T4-01 | B13: xe-0/0/11 | C13: 10G SFP+ | D13: 10000 | E13: admin-down
A14: MH-DC-001-PE-T4-01 | B14: et-0/1/0 | C14: 100G QSFP28 | D14: 100000 | E14: up | F14: Fabric to MH-DC-001-PE-T4-02 | G14: QSFP28-100G-LR4
A15: MH-DC-001-PE-T4-01 | B15: et-0/1/1 | C15: 100G QSFP28 | D15: 100000 | E15: up | F15: Fabric to MH-DC-001-PE-T4-03 | G15: QSFP28-100G-LR4
A16: MH-DC-001-PE-T4-01 | B16: et-0/1/2 | C16: 100G QSFP28 | D16: 100000 | E16: up | F16: Fabric to MH-DC-001-PE-T4-04 | G16: QSFP28-100G-LR4
A17: MH-DC-001-PE-T4-01 | B17: et-0/1/3 | C17: 100G QSFP28 | D17: 100000 | E17: reserved
A18: MH-DC-001-PE-T4-01 | B18: ge-0/2/0 | C18: 1G copper | D18: 1000 | E18: reserved
A19: MH-DC-001-PE-T4-01 | B19: ge-0/2/1 | C19: 1G copper | D19: 1000 | E19: admin-down
A20: MH-DC-001-PE-T4-01 | B20: ge-0/2/2 | C20: 1G copper | D20: 1000 | E20: admin-down
A21: MH-DC-001-PE-T4-01 | B21: ge-0/2/3 | C21: 1G copper | D21: 1000 | E21: admin-down
A22: MH-DC-001-PE-T4-01 | B22: ge-0/2/4 | C22: 1G copper | D22: 1000 | E22: admin-down
A23: MH-DC-001-PE-T4-01 | B23: ge-0/2/5 | C23: 1G copper | D23: 1000 | E23: admin-down
A24: MH-DC-001-PE-T4-01 | B24: ge-0/2/6 | C24: 1G copper | D24: 1000 | E24: admin-down
A25: MH-DC-001-PE-T4-01 | B25: ge-0/2/7 | C25: 1G copper | D25: 1000 | E25: admin-down
A26: MH-DC-001-PE-T4-01 | B26: ge-0/2/8 | C26: 1G copper | D26: 1000 | E26: admin-down
A27: MH-DC-001-PE-T4-01 | B27: ge-0/2/9 | C27: 1G copper | D27: 1000 | E27: admin-down
A28: MH-DC-001-PE-T4-01 | B28: ge-0/2/10 | C28: 1G copper | D28: 1000 | E28: admin-down
... A34: MH-DC-001-PE-T4-02 | B34: xe-0/0/0 | C34: 10G SFP+ | D34: 10000 | E34: admin-down
A35: MH-DC-001-PE-T4-02 | B35: xe-0/0/1 | C35: 10G SFP+ | D35: 10000 | E35: up | F35: Backhaul to HR-DC-011 | G35: SFP-10G-LR
A36: MH-DC-001-PE-T4-02 | B36: xe-0/0/2 | C36: 10G SFP+ | D36: 10000 | E36: up | F36: Backhaul to DL-DC-009 | G36: SFP-10G-LR
A37: MH-DC-001-PE-T4-02 | B37: xe-0/0/3 | C37: 10G SFP+ | D37: 10000 | E37: up | F37: Backhaul to UP-DC-006 | G37: SFP-10G-LR
A38: MH-DC-001-PE-T4-02 | B38: xe-0/0/4 | C38: 10G SFP+ | D38: 10000 | E38: up | F38: Backhaul to BR-DC-019 | G38: SFP-10G-LR
A39: MH-DC-001-PE-T4-02 | B39: xe-0/0/5 | C39: 10G SFP+ | D39: 10000 | E39: up | F39: Backhaul to TS-DC-023 | G39: SFP-10G-LR
A40: MH-DC-001-PE-T4-02 | B40: xe-0/0/6 | C40: 10G SFP+ | D40: 10000 | E40: up | F40: Uplink to MH-DC-001-SPINE-01 | G40: SFP-10G-LR
A41: MH-DC-001-PE-T4-02 | B41: xe-0/0/7 | C41: 10G SFP+ | D41: 10000 | E41: up | F41: Uplink to MH-DC-001-SPINE-02 | G41: SFP-10G-LR
A42: MH-DC-001-PE-T4-02 | B42: xe-0/0/8 | C42: 10G SFP+ | D42: 10000 | E42: admin-down
A43: MH-DC-001-PE-T4-02 | B43: xe-0/0/9 | C43: 10G SFP+ | D43: 10000 | E43: admin-down
A44: MH-DC-001-PE-T4-02 | B44: xe-0/0/10 | C44: 10G SFP+ | D44: 10000 | E44: admin-down
A45: MH-DC-001-PE-T4-02 | B45: xe-0/0/11 | C45: 10G SFP+ | D45: 10000 | E45: admin-down
A46: MH-DC-001-PE-T4-02 | B46: et-0/1/0 | C46: 100G QSFP28 | D46: 100000 | E46: up | F46: Fabric to MH-DC-001-PE-T4-01 | G46: QSFP28-100G-LR4
A47: MH-DC-001-PE-T4-02 | B47: et-0/1/1 | C47: 100G QSFP28 | D47: 100000 | E47: up | F47: Fabric to MH-DC-001-PE-T4-03 | G47: QSFP28-100G-LR4
A48: MH-DC-001-PE-T4-02 | B48: et-0/1/2 | C48: 100G QSFP28 | D48: 100000 | E48: up | F48: Fabric to MH-DC-001-PE-T4-04 | G48: QSFP28-100G-LR4
A49: MH-DC-001-PE-T4-02 | B49: et-0/1/3 | C49: 100G QSFP28 | D49: 100000 | E49: admin-down
A50: MH-DC-001-PE-T4-02 | B50: ge-0/2/0 | C50: 1G copper | D50: 1000 | E50: admin-down
A51: MH-DC-001-PE-T4-02 | B51: ge-0/2/1 | C51: 1G copper | D51: 1000 | E51: admin-down
A52: MH-DC-001-PE-T4-02 | B52: ge-0/2/2 | C52: 1G copper | D52: 1000 | E52: admin-down
A53: MH-DC-001-PE-T4-02 | B53: ge-0/2/3 | C53: 1G copper | D53: 1000 | E53: reserved
A54: MH-DC-001-PE-T4-02 | B54: ge-0/2/4 | C54: 1G copper | D54: 1000 | E54: admin-down
A55: MH-DC-001-PE-T4-02 | B55: ge-0/2/5 | C55: 1G copper | D55: 1000 | E55: admin-down
A56: MH-DC-001-PE-T4-02 | B56: ge-0/2/6 | C56: 1G copper | D56: 1000 | E56: admin-down
A57: MH-DC-001-PE-T4-02 | B57: ge-0/2/7 | C57: 1G copper | D57: 1000 | E57: admin-down
A58: MH-DC-001-PE-T4-02 | B58: ge-0/2/8 | C58: 1G copper | D58: 1000 | E58: admin-down
A59: MH-DC-001-PE-T4-02 | B59: ge-0/2/9 | C59: 1G copper | D59: 1000 | E59: admin-down
A60: MH-DC-001-PE-T4-02 | B60: ge-0/2/10 | C60: 1G copper | D60: 1000 | E60: admin-down
... A66: MH-DC-001-PE-T4-03 | B66: Te0/0/0/0 | C66: 10G SFP+ | D66: 10000 | E66: admin-down
A67: MH-DC-001-PE-T4-03 | B67: Te0/0/0/1 | C67: 10G SFP+ | D67: 10000 | E67: up | F67: Backhaul to BR-DC-019 | G67: SFP-10G-LR
A68: MH-DC-001-PE-T4-03 | B68: Te0/0/0/2 | C68: 10G SFP+ | D68: 10000 | E68: up | F68: Backhaul to WB-DC-016 | G68: SFP-10G-LR
A69: MH-DC-001-PE-T4-03 | B69: Te0/0/0/3 | C69: 10G SFP+ | D69: 10000 | E69: up | F69: Backhaul to TN-DC-022 | G69: SFP-10G-LR
A70: MH-DC-001-PE-T4-03 | B70: Te0/0/0/4 | C70: 10G SFP+ | D70: 10000 | E70: up | F70: Backhaul to RJ-DC-015 | G70: SFP-10G-LR
A71: MH-DC-001-PE-T4-03 | B71: Te0/0/0/5 | C71: 10G SFP+ | D71: 10000 | E71: up | F71: Backhaul to HR-DC-011 | G71: SFP-10G-LR
A72: MH-DC-001-PE-T4-03 | B72: Te0/0/0/6 | C72: 10G SFP+ | D72: 10000 | E72: up | F72: Uplink to MH-DC-001-SPINE-02 | G72: SFP-10G-LR
A73: MH-DC-001-PE-T4-03 | B73: Te0/0/0/7 | C73: 10G SFP+ | D73: 10000 | E73: up | F73: Uplink to MH-DC-001-SPINE-03 | G73: SFP-10G-LR
A74: MH-DC-001-PE-T4-03 | B74: Te0/0/0/8 | C74: 10G SFP+ | D74: 10000 | E74: admin-down
A75: MH-DC-001-PE-T4-03 | B75: Te0/0/0/9 | C75: 10G SFP+ | D75: 10000 | E75: admin-down
A76: MH-DC-001-PE-T4-03 | B76: Te0/0/0/10 | C76: 10G SFP+ | D76: 10000 | E76: admin-down
A77: MH-DC-001-PE-T4-03 | B77: Te0/0/0/11 | C77: 10G SFP+ | D77: 10000 | E77: admin-down
A78: MH-DC-001-PE-T4-03 | B78: Hu0/0/1/0 | C78: 100G QSFP28 | D78: 100000 | E78: up | F78: Fabric to MH-DC-001-PE-T4-01 | G78: QSFP28-100G-LR4
A79: MH-DC-001-PE-T4-03 | B79: Hu0/0/1/1 | C79: 100G QSFP28 | D79: 100000 | E79: up | F79: Fabric to MH-DC-001-PE-T4-02 | G79: QSFP28-100G-LR4
A80: MH-DC-001-PE-T4-03 | B80: Hu0/0/1/2 | C80: 100G QSFP28 | D80: 100000 | E80: up | F80: Fabric to MH-DC-001-PE-T4-04 | G80: QSFP28-100G-LR4
A81: MH-DC-001-PE-T4-03 | B81: Hu0/0/1/3 | C81: 100G QSFP28 | D81: 100000 | E81: reserved
A82: MH-DC-001-PE-T4-03 | B82: Gi0/0/2/0 | C82: 1G copper | D82: 1000 | E82: admin-down
A83: MH-DC-001-PE-T4-03 | B83: Gi0/0/2/1 | C83: 1G copper | D83: 1000 | E83: admin-down
A84: MH-DC-001-PE-T4-03 | B84: Gi0/0/2/2 | C84: 1G copper | D84: 1000 | E84: admin-down
A85: MH-DC-001-PE-T4-03 | B85: Gi0/0/2/3 | C85: 1G copper | D85: 1000 | E85: admin-down
A86: MH-DC-001-PE-T4-03 | B86: Gi0/0/2/4 | C86: 1G copper | D86: 1000 | E86: admin-down
A87: MH-DC-001-PE-T4-03 | B87: Gi0/0/2/5 | C87: 1G copper | D87: 1000 | E87: admin-down
A88: MH-DC-001-PE-T4-03 | B88: Gi0/0/2/6 | C88: 1G copper | D88: 1000 | E88: admin-down
A89: MH-DC-001-PE-T4-03 | B89: Gi0/0/2/7 | C89: 1G copper | D89: 1000 | E89: admin-down
A90: MH-DC-001-PE-T4-03 | B90: Gi0/0/2/8 | C90: 1G copper | D90: 1000 | E90: admin-down
A91: MH-DC-001-PE-T4-03 | B91: Gi0/0/2/9 | C91: 1G copper | D91: 1000 | E91: admin-down
A92: MH-DC-001-PE-T4-03 | B92: Gi0/0/2/10 | C92: 1G copper | D92: 1000 | E92: admin-down
... A98: MH-DC-001-PE-T4-04 | B98: Te0/0/0/0 | C98: 10G SFP+ | D98: 10000 | E98: admin-down
A99: MH-DC-001-PE-T4-04 | B99: Te0/0/0/1 | C99: 10G SFP+ | D99: 10000 | E99: up | F99: Backhaul to MP-DC-014 | G99: SFP-10G-LR
A100: MH-DC-001-PE-T4-04 | B100: Te0/0/0/2 | C100: 10G SFP+ | D100: 10000 | E100: up | F100: Backhaul to MH-DC-004 | G100: SFP-10G-LR
A101: MH-DC-001-PE-T4-04 | B101: Te0/0/0/3 | C101: 10G SFP+ | D101: 10000 | E101: up | F101: Backhaul to KL-DC-024 | G101: SFP-10G-LR
A102: MH-DC-001-PE-T4-04 | B102: Te0/0/0/4 | C102: 10G SFP+ | D102: 10000 | E102: up | F102: Backhaul to KA-DC-021 | G102: SFP-10G-LR
A103: MH-DC-001-PE-T4-04 | B103: Te0/0/0/5 | C103: 10G SFP+ | D103: 10000 | E103: up | F103: Backhaul to TS-DC-023 | G103: SFP-10G-LR
A104: MH-DC-001-PE-T4-04 | B104: Te0/0/0/6 | C104: 10G SFP+ | D104: 10000 | E104: up | F104: Uplink to MH-DC-001-SPINE-03 | G104: SFP-10G-LR
A105: MH-DC-001-PE-T4-04 | B105: Te0/0/0/7 | C105: 10G SFP+ | D105: 10000 | E105: up | F105: Uplink to MH-DC-001-SPINE-04 | G105: SFP-10G-LR
A106: MH-DC-001-PE-T4-04 | B106: Te0/0/0/8 | C106: 10G SFP+ | D106: 10000 | E106: admin-down
A107: MH-DC-001-PE-T4-04 | B107: Te0/0/0/9 | C107: 10G SFP+ | D107: 10000 | E107: admin-down
A108: MH-DC-001-PE-T4-04 | B108: Te0/0/0/10 | C108: 10G SFP+ | D108: 10000 | E108: admin-down
A109: MH-DC-001-PE-T4-04 | B109: Te0/0/0/11 | C109: 10G SFP+ | D109: 10000 | E109: admin-down
A110: MH-DC-001-PE-T4-04 | B110: Hu0/0/1/0 | C110: 100G QSFP28 | D110: 100000 | E110: up | F110: Fabric to MH-DC-001-PE-T4-01 | G110: QSFP28-100G-LR4
A111: MH-DC-001-PE-T4-04 | B111: Hu0/0/1/1 | C111: 100G QSFP28 | D111: 100000 | E111: up | F111: Fabric to MH-DC-001-PE-T4-02 | G111: QSFP28-100G-LR4
A112: MH-DC-001-PE-T4-04 | B112: Hu0/0/1/2 | C112: 100G QSFP28 | D112: 100000 | E112: up | F112: Fabric to MH-DC-001-PE-T4-03 | G112: QSFP28-100G-LR4
A113: MH-DC-001-PE-T4-04 | B113: Hu0/0/1/3 | C113: 100G QSFP28 | D113: 100000 | E113: admin-down
A114: MH-DC-001-PE-T4-04 | B114: Gi0/0/2/0 | C114: 1G copper | D114: 1000 | E114: admin-down
A115: MH-DC-001-PE-T4-04 | B115: Gi0/0/2/1 | C115: 1G copper | D115: 1000 | E115: admin-down
...

Sheet Links
A1: link_id * | B1: a_device_id * | C1: a_if_name * | D1: z_device_id * | E1: z_if_name * | F1: role * | G1: protocol | H1: capacity_mbps * | I1: cable_id | J1: strand | K1: a_patch_port | L1: z_patch_port | M1: carrier_circuit_id
A2: LNK-00001 | B2: MH-DC-001-PE-T4-01 | C2: et-0/1/0 | D2: MH-DC-001-PE-T4-02 | E2: et-0/1/0 | F2: Fabric | G2: LLDP | H2: 100000 | I2: MH-DC-001-CBL-0001 | J2: Red | K2: ODF-2/P24 | L2: ODF-2/P15
A3: LNK-00002 | B3: MH-DC-001-PE-T4-01 | C3: et-0/1/0 | D3: MH-DC-001-PE-T4-02 | E3: et-0/1/0 | F3: Fabric | G3: OSPF | H3: 100000
A4: LNK-00003 | B4: MH-DC-001-PE-T4-01 | C4: et-0/1/0 | D4: MH-DC-001-PE-T4-02 | E4: et-0/1/0 | F4: Fabric | G4: ISIS | H4: 100000
A5: LNK-00004 | B5: MH-DC-001-PE-T4-01 | C5: et-0/1/0 | D5: MH-DC-001-PE-T4-02 | E5: et-0/1/0 | F5: Fabric | G5: BGP | H5: 100000
A6: LNK-00005 | B6: MH-DC-001-PE-T4-01 | C6: et-0/1/0 | D6: MH-DC-001-PE-T4-02 | E6: et-0/1/0 | F6: Fabric | G6: LSP | H6: 100000
A7: LNK-00006 | B7: MH-DC-001-PE-T4-01 | C7: et-0/1/1 | D7: MH-DC-001-PE-T4-03 | E7: Hu0/0/1/0 | F7: Fabric | G7: LLDP | H7: 100000 | I7: MH-DC-001-CBL-0002 | J7: Yellow | K7: ODF-4/P13 | L7: ODF-2/P12
A8: LNK-00007 | B8: MH-DC-001-PE-T4-01 | C8: et-0/1/1 | D8: MH-DC-001-PE-T4-03 | E8: Hu0/0/1/0 | F8: Fabric | G8: OSPF | H8: 100000
A9: LNK-00008 | B9: MH-DC-001-PE-T4-01 | C9: et-0/1/1 | D9: MH-DC-001-PE-T4-03 | E9: Hu0/0/1/0 | F9: Fabric | G9: ISIS | H9: 100000
A10: LNK-00009 | B10: MH-DC-001-PE-T4-01 | C10: et-0/1/1 | D10: MH-DC-001-PE-T4-03 | E10: Hu0/0/1/0 | F10: Fabric | G10: BGP | H10: 100000
A11: LNK-00010 | B11: MH-DC-001-PE-T4-01 | C11: et-0/1/1 | D11: MH-DC-001-PE-T4-03 | E11: Hu0/0/1/0 | F11: Fabric | G11: LSP | H11: 100000
A12: LNK-00011 | B12: MH-DC-001-PE-T4-01 | C12: et-0/1/2 | D12: MH-DC-001-PE-T4-04 | E12: Hu0/0/1/0 | F12: Fabric | G12: LLDP | H12: 100000 | I12: MH-DC-001-CBL-0003 | J12: Rose | K12: ODF-2/P17 | L12: ODF-2/P19
A13: LNK-00012 | B13: MH-DC-001-PE-T4-01 | C13: et-0/1/2 | D13: MH-DC-001-PE-T4-04 | E13: Hu0/0/1/0 | F13: Fabric | G13: OSPF | H13: 100000
A14: LNK-00013 | B14: MH-DC-001-PE-T4-01 | C14: et-0/1/2 | D14: MH-DC-001-PE-T4-04 | E14: Hu0/0/1/0 | F14: Fabric | G14: ISIS | H14: 100000
A15: LNK-00014 | B15: MH-DC-001-PE-T4-01 | C15: et-0/1/2 | D15: MH-DC-001-PE-T4-04 | E15: Hu0/0/1/0 | F15: Fabric | G15: BGP | H15: 100000
A16: LNK-00015 | B16: MH-DC-001-PE-T4-01 | C16: et-0/1/2 | D16: MH-DC-001-PE-T4-04 | E16: Hu0/0/1/0 | F16: Fabric | G16: LSP | H16: 100000
A17: LNK-00016 | B17: MH-DC-001-PE-T4-02 | C17: et-0/1/1 | D17: MH-DC-001-PE-T4-03 | E17: Hu0/0/1/1 | F17: Fabric | G17: LLDP | H17: 100000 | I17: MH-DC-001-CBL-0004 | J17: Brown | K17: ODF-3/P24 | L17: ODF-2/P20
A18: LNK-00017 | B18: MH-DC-001-PE-T4-02 | C18: et-0/1/1 | D18: MH-DC-001-PE-T4-03 | E18: Hu0/0/1/1 | F18: Fabric | G18: OSPF | H18: 100000
A19: LNK-00018 | B19: MH-DC-001-PE-T4-02 | C19: et-0/1/1 | D19: MH-DC-001-PE-T4-03 | E19: Hu0/0/1/1 | F19: Fabric | G19: ISIS | H19: 100000
A20: LNK-00019 | B20: MH-DC-001-PE-T4-02 | C20: et-0/1/1 | D20: MH-DC-001-PE-T4-03 | E20: Hu0/0/1/1 | F20: Fabric | G20: BGP | H20: 100000
A21: LNK-00020 | B21: MH-DC-001-PE-T4-02 | C21: et-0/1/1 | D21: MH-DC-001-PE-T4-03 | E21: Hu0/0/1/1 | F21: Fabric | G21: LSP | H21: 100000
A22: LNK-00021 | B22: MH-DC-001-PE-T4-02 | C22: et-0/1/2 | D22: MH-DC-001-PE-T4-04 | E22: Hu0/0/1/1 | F22: Fabric | G22: LLDP | H22: 100000 | I22: MH-DC-001-CBL-0005 | J22: Black | K22: ODF-3/P2 | L22: ODF-3/P12
A23: LNK-00022 | B23: MH-DC-001-PE-T4-02 | C23: et-0/1/2 | D23: MH-DC-001-PE-T4-04 | E23: Hu0/0/1/1 | F23: Fabric | G23: OSPF | H23: 100000
A24: LNK-00023 | B24: MH-DC-001-PE-T4-02 | C24: et-0/1/2 | D24: MH-DC-001-PE-T4-04 | E24: Hu0/0/1/1 | F24: Fabric | G24: ISIS | H24: 100000
A25: LNK-00024 | B25: MH-DC-001-PE-T4-02 | C25: et-0/1/2 | D25: MH-DC-001-PE-T4-04 | E25: Hu0/0/1/1 | F25: Fabric | G25: BGP | H25: 100000
A26: LNK-00025 | B26: MH-DC-001-PE-T4-02 | C26: et-0/1/2 | D26: MH-DC-001-PE-T4-04 | E26: Hu0/0/1/1 | F26: Fabric | G26: LSP | H26: 100000
A27: LNK-00026 | B27: MH-DC-001-PE-T4-03 | C27: Hu0/0/1/2 | D27: MH-DC-001-PE-T4-04 | E27: Hu0/0/1/2 | F27: Fabric | G27: LLDP | H27: 100000 | I27: MH-DC-001-CBL-0006 | J27: Black | K27: ODF-3/P6 | L27: ODF-4/P2
A28: LNK-00027 | B28: MH-DC-001-PE-T4-03 | C28: Hu0/0/1/2 | D28: MH-DC-001-PE-T4-04 | E28: Hu0/0/1/2 | F28: Fabric | G28: OSPF | H28: 100000
A29: LNK-00028 | B29: MH-DC-001-PE-T4-03 | C29: Hu0/0/1/2 | D29: MH-DC-001-PE-T4-04 | E29: Hu0/0/1/2 | F29: Fabric | G29: ISIS | H29: 100000
A30: LNK-00029 | B30: MH-DC-001-PE-T4-03 | C30: Hu0/0/1/2 | D30: MH-DC-001-PE-T4-04 | E30: Hu0/0/1/2 | F30: Fabric | G30: BGP | H30: 100000
A31: LNK-00030 | B31: MH-DC-001-PE-T4-03 | C31: Hu0/0/1/2 | D31: MH-DC-001-PE-T4-04 | E31: Hu0/0/1/2 | F31: Fabric | G31: LSP | H31: 100000
A32: LNK-00031 | B32: MH-DC-001-SPINE-01 | C32: Hu0/0/1/0 | D32: MH-DC-001-PE-T4-01 | E32: xe-0/0/6 | F32: Uplink | G32: LLDP | H32: 10000 | I32: MH-DC-001-CBL-0007 | J32: Green | K32: ODF-3/P22 | L32: ODF-4/P23
A33: LNK-00032 | B33: MH-DC-001-SPINE-01 | C33: Hu0/0/1/0 | D33: MH-DC-001-PE-T4-01 | E33: xe-0/0/6 | F33: Uplink | G33: OSPF | H33: 10000
A34: LNK-00033 | B34: MH-DC-001-SPINE-01 | C34: Hu0/0/1/0 | D34: MH-DC-001-PE-T4-01 | E34: xe-0/0/6 | F34: Uplink | G34: ISIS | H34: 10000
A35: LNK-00034 | B35: MH-DC-001-SPINE-01 | C35: Hu0/0/1/1 | D35: MH-DC-001-PE-T4-02 | E35: xe-0/0/6 | F35: Uplink | G35: LLDP | H35: 10000 | I35: MH-DC-001-CBL-0008 | J35: Green | K35: ODF-2/P2 | L35: ODF-2/P12
A36: LNK-00035 | B36: MH-DC-001-SPINE-01 | C36: Hu0/0/1/1 | D36: MH-DC-001-PE-T4-02 | E36: xe-0/0/6 | F36: Uplink | G36: OSPF | H36: 10000
A37: LNK-00036 | B37: MH-DC-001-SPINE-01 | C37: Hu0/0/1/1 | D37: MH-DC-001-PE-T4-02 | E37: xe-0/0/6 | F37: Uplink | G37: ISIS | H37: 10000
A38: LNK-00037 | B38: MH-DC-001-SPINE-02 | C38: Hu0/0/1/0 | D38: MH-DC-001-PE-T4-02 | E38: xe-0/0/7 | F38: Uplink | G38: LLDP | H38: 10000 | I38: MH-DC-001-CBL-0009 | J38: Yellow | K38: ODF-1/P13 | L38: ODF-1/P16
A39: LNK-00038 | B39: MH-DC-001-SPINE-02 | C39: Hu0/0/1/0 | D39: MH-DC-001-PE-T4-02 | E39: xe-0/0/7 | F39: Uplink | G39: OSPF | H39: 10000
A40: LNK-00039 | B40: MH-DC-001-SPINE-02 | C40: Hu0/0/1/0 | D40: MH-DC-001-PE-T4-02 | E40: xe-0/0/7 | F40: Uplink | G40: ISIS | H40: 10000
A41: LNK-00040 | B41: MH-DC-001-SPINE-02 | C41: Hu0/0/1/1 | D41: MH-DC-001-PE-T4-03 | E41: Te0/0/0/6 | F41: Uplink | G41: LLDP | H41: 10000 | I41: MH-DC-001-CBL-0010 | J41: Yellow | K41: ODF-2/P16 | L41: ODF-1/P3
A42: LNK-00041 | B42: MH-DC-001-SPINE-02 | C42: Hu0/0/1/1 | D42: MH-DC-001-PE-T4-03 | E42: Te0/0/0/6 | F42: Uplink | G42: OSPF | H42: 10000
A43: LNK-00042 | B43: MH-DC-001-SPINE-02 | C43: Hu0/0/1/1 | D43: MH-DC-001-PE-T4-03 | E43: Te0/0/0/6 | F43: Uplink | G43: ISIS | H43: 10000
A44: LNK-00043 | B44: MH-DC-001-SPINE-03 | C44: Hu0/0/1/0 | D44: MH-DC-001-PE-T4-03 | E44: Te0/0/0/7 | F44: Uplink | G44: LLDP | H44: 10000 | I44: MH-DC-001-CBL-0011 | J44: Orange | K44: ODF-1/P24 | L44: ODF-3/P4
A45: LNK-00044 | B45: MH-DC-001-SPINE-03 | C45: Hu0/0/1/0 | D45: MH-DC-001-PE-T4-03 | E45: Te0/0/0/7 | F45: Uplink | G45: OSPF | H45: 10000
A46: LNK-00045 | B46: MH-DC-001-SPINE-03 | C46: Hu0/0/1/0 | D46: MH-DC-001-PE-T4-03 | E46: Te0/0/0/7 | F46: Uplink | G46: ISIS | H46: 10000
A47: LNK-00046 | B47: MH-DC-001-SPINE-03 | C47: Hu0/0/1/1 | D47: MH-DC-001-PE-T4-04 | E47: Te0/0/0/6 | F47: Uplink | G47: LLDP | H47: 10000 | I47: MH-DC-001-CBL-0012 | J47: Red | K47: ODF-4/P5 | L47: ODF-2/P1
A48: LNK-00047 | B48: MH-DC-001-SPINE-03 | C48: Hu0/0/1/1 | D48: MH-DC-001-PE-T4-04 | E48: Te0/0/0/6 | F48: Uplink | G48: OSPF | H48: 10000
A49: LNK-00048 | B49: MH-DC-001-SPINE-03 | C49: Hu0/0/1/1 | D49: MH-DC-001-PE-T4-04 | E49: Te0/0/0/6 | F49: Uplink | G49: ISIS | H49: 10000
A50: LNK-00049 | B50: MH-DC-001-SPINE-04 | C50: Hu0/0/1/0 | D50: MH-DC-001-PE-T4-04 | E50: Te0/0/0/7 | F50: Uplink | G50: LLDP | H50: 10000 | I50: MH-DC-001-CBL-0013 | J50: Slate | K50: ODF-2/P12 | L50: ODF-2/P11
A51: LNK-00050 | B51: MH-DC-001-SPINE-04 | C51: Hu0/0/1/0 | D51: MH-DC-001-PE-T4-04 | E51: Te0/0/0/7 | F51: Uplink | G51: OSPF | H51: 10000
A52: LNK-00051 | B52: MH-DC-001-SPINE-04 | C52: Hu0/0/1/0 | D52: MH-DC-001-PE-T4-04 | E52: Te0/0/0/7 | F52: Uplink | G52: ISIS | H52: 10000
A53: LNK-00052 | B53: MH-DC-001-SPINE-04 | C53: Hu0/0/1/1 | D53: MH-DC-001-PE-T4-01 | E53: xe-0/0/7 | F53: Uplink | G53: LLDP | H53: 10000 | I53: MH-DC-001-CBL-0014 | J53: Aqua | K53: ODF-2/P20 | L53: ODF-4/P23
A54: LNK-00053 | B54: MH-DC-001-SPINE-04 | C54: Hu0/0/1/1 | D54: MH-DC-001-PE-T4-01 | E54: xe-0/0/7 | F54: Uplink | G54: OSPF | H54: 10000
A55: LNK-00054 | B55: MH-DC-001-SPINE-04 | C55: Hu0/0/1/1 | D55: MH-DC-001-PE-T4-01 | E55: xe-0/0/7 | F55: Uplink | G55: ISIS | H55: 10000
A56: LNK-00055 | B56: MH-DC-001-OLA-01 | C56: 1/2/c1 | D56: MH-DC-001-SPINE-01 | E56: Hu0/0/1/2 | F56: Uplink | G56: LLDP | H56: 100000 | I56: MH-DC-001-CBL-0015 | J56: Green | K56: ODF-3/P2 | L56: ODF-2/P15
A57: LNK-00056 | B57: MH-DC-001-OLA-02 | C57: 1/2/c1 | D57: MH-DC-001-SPINE-02 | E57: Hu0/0/1/2 | F57: Uplink | G57: LLDP | H57: 100000 | I57: MH-DC-001-CBL-0016 | J57: Yellow | K57: ODF-4/P6 | L57: ODF-1/P13
A58: LNK-00057 | B58: MH-DC-001-FW-01 | C58: port1 | D58: MH-DC-001-SPINE-01 | E58: Te0/0/0/0 | F58: Uplink | G58: LLDP | H58: 10000 | I58: MH-DC-001-CBL-0017 | J58: Green | K58: ODF-1/P14 | L58: ODF-3/P8
A59: LNK-00058 | B59: MH-DC-001-FW-01 | C59: port2 | D59: MH-DC-001-SPINE-02 | E59: Te0/0/0/0 | F59: Uplink | G59: LLDP | H59: 10000 | I59: MH-DC-001-CBL-0018 | J59: Slate | K59: ODF-1/P16 | L59: ODF-2/P15
A60: LNK-00059 | B60: MH-DC-001-FW-02 | C60: port1 | D60: MH-DC-001-SPINE-02 | E60: Te0/0/0/1 | F60: Uplink | G60: LLDP | H60: 10000 | I60: MH-DC-001-CBL-0019 | J60: Rose | K60: ODF-2/P22 | L60: ODF-4/P7
A61: LNK-00060 | B61: MH-DC-001-FW-02 | C61: port2 | D61: MH-DC-001-SPINE-03 | E61: Te0/0/0/0 | F61: Uplink | G61: LLDP | H61: 10000 | I61: MH-DC-001-CBL-0020 | J61: Blue | K61: ODF-3/P19 | L61: ODF-4/P21
A62: LNK-00061 | B62: MH-DC-001-LEAF-01 | C62: et-0/1/0 | D62: MH-DC-001-SPINE-01 | E62: Te0/0/0/1 | F62: Uplink | G62: LLDP | H62: 10000 | I62: MH-DC-001-CBL-0021 | J62: Black | K62: ODF-3/P17 | L62: ODF-4/P13
A63: LNK-00062 | B63: MH-DC-001-LEAF-01 | C63: et-0/1/1 | D63: MH-DC-001-SPINE-04 | E63: Te0/0/0/0 | F63: Uplink | G63: LLDP | H63: 10000 | I63: MH-DC-001-CBL-0022 | J63: Violet | K63: ODF-1/P15 | L63: ODF-1/P23
A64: LNK-00063 | B64: MH-DC-001-LEAF-02 | C64: Hu0/0/1/0 | D64: MH-DC-001-SPINE-02 | E64: Te0/0/0/2 | F64: Uplink | G64: LLDP | H64: 10000 | I64: MH-DC-001-CBL-0023 | J64: Green | K64: ODF-3/P12 | L64: ODF-2/P6
A65: LNK-00064 | B65: MH-DC-001-LEAF-02 | C65: Hu0/0/1/1 | D65: MH-DC-001-SPINE-01 | E65: Te0/0/0/2 | F65: Uplink | G65: LLDP | H65: 10000 | I65: MH-DC-001-CBL-0024 | J65: White | K65: ODF-4/P4 | L65: ODF-4/P21
A66: LNK-00065 | B66: MH-DC-001-LEAF-03 | C66: Hu0/0/1/0 | D66: MH-DC-001-SPINE-03 | E66: Te0/0/0/1 | F66: Uplink | G66: LLDP | H66: 10000 | I66: MH-DC-001-CBL-0025 | J66: White | K66: ODF-1/P17 | L66: ODF-1/P21
A67: LNK-00066 | B67: MH-DC-001-LEAF-03 | C67: Hu0/0/1/1 | D67: MH-DC-001-SPINE-02 | E67: Te0/0/0/3 | F67: Uplink | G67: LLDP | H67: 10000 | I67: MH-DC-001-CBL-0026 | J67: Rose | K67: ODF-4/P8 | L67: ODF-4/P10
... A554: LNK-00553 | B554: MH-DC-002-PE-T4-01 | C554: et-0/1/0 | D554: MH-DC-002-PE-T4-02 | E554: et-0/1/0 | F554: Fabric | G554: LLDP | H554: 100000 | I554: MH-DC-002-CBL-0513 | J554: Aqua | K554: ODF-4/P10 | L554: ODF-4/P4
A555: LNK-00554 | B555: MH-DC-002-PE-T4-01 | C555: et-0/1/0 | D555: MH-DC-002-PE-T4-02 | E555: et-0/1/0 | F555: Fabric | G555: OSPF | H555: 100000
A556: LNK-00555 | B556: MH-DC-002-PE-T4-01 | C556: et-0/1/0 | D556: MH-DC-002-PE-T4-02 | E556: et-0/1/0 | F556: Fabric | G556: ISIS | H556: 100000
A557: LNK-00556 | B557: MH-DC-002-PE-T4-01 | C557: et-0/1/0 | D557: MH-DC-002-PE-T4-02 | E557: et-0/1/0 | F557: Fabric | G557: BGP | H557: 100000
A558: LNK-00557 | B558: MH-DC-002-PE-T4-01 | C558: et-0/1/0 | D558: MH-DC-002-PE-T4-02 | E558: et-0/1/0 | F558: Fabric | G558: LSP | H558: 100000
A559: LNK-00558 | B559: MH-DC-002-PE-T4-01 | C559: et-0/1/1 | D559: MH-DC-002-PE-T4-03 | E559: Hu0/0/1/0 | F559: Fabric | G559: LLDP | H559: 100000 | I559: MH-DC-002-CBL-0514 | J559: Red | K559: ODF-3/P20 | L559: ODF-3/P16
A560: LNK-00559 | B560: MH-DC-002-PE-T4-01 | C560: et-0/1/1 | D560: MH-DC-002-PE-T4-03 | E560: Hu0/0/1/0 | F560: Fabric | G560: OSPF | H560: 100000
A561: LNK-00560 | B561: MH-DC-002-PE-T4-01 | C561: et-0/1/1 | D561: MH-DC-002-PE-T4-03 | E561: Hu0/0/1/0 | F561: Fabric | G561: ISIS | H561: 100000
A562: LNK-00561 | B562: MH-DC-002-PE-T4-01 | C562: et-0/1/1 | D562: MH-DC-002-PE-T4-03 | E562: Hu0/0/1/0 | F562: Fabric | G562: BGP | H562: 100000
A563: LNK-00562 | B563: MH-DC-002-PE-T4-01 | C563: et-0/1/1 | D563: MH-DC-002-PE-T4-03 | E563: Hu0/0/1/0 | F563: Fabric | G563: LSP | H563: 100000
A564: LNK-00563 | B564: MH-DC-002-PE-T4-01 | C564: et-0/1/2 | D564: MH-DC-002-PE-T4-04 | E564: Hu0/0/1/0 | F564: Fabric | G564: LLDP | H564: 100000 | I564: MH-DC-002-CBL-0515 | J564: Yellow | K564: ODF-3/P22 | L564: ODF-3/P12
A565: LNK-00564 | B565: MH-DC-002-PE-T4-01 | C565: et-0/1/2 | D565: MH-DC-002-PE-T4-04 | E565: Hu0/0/1/0 | F565: Fabric | G565: OSPF | H565: 100000
A566: LNK-00565 | B566: MH-DC-002-PE-T4-01 | C566: et-0/1/2 | D566: MH-DC-002-PE-T4-04 | E566: Hu0/0/1/0 | F566: Fabric | G566: ISIS | H566: 100000
A567: LNK-00566 | B567: MH-DC-002-PE-T4-01 | C567: et-0/1/2 | D567: MH-DC-002-PE-T4-04 | E567: Hu0/0/1/0 | F567: Fabric | G567: BGP | H567: 100000
A568: LNK-00567 | B568: MH-DC-002-PE-T4-01 | C568: et-0/1/2 | D568: MH-DC-002-PE-T4-04 | E568: Hu0/0/1/0 | F568: Fabric | G568: LSP | H568: 100000
A569: LNK-00568 | B569: MH-DC-002-PE-T4-02 | C569: et-0/1/1 | D569: MH-DC-002-PE-T4-03 | E569: Hu0/0/1/1 | F569: Fabric | G569: LLDP | H569: 100000 | I569: MH-DC-002-CBL-0516 | J569: Brown | K569: ODF-3/P17 | L569: ODF-4/P18
A570: LNK-00569 | B570: MH-DC-002-PE-T4-02 | C570: et-0/1/1 | D570: MH-DC-002-PE-T4-03 | E570: Hu0/0/1/1 | F570: Fabric | G570: OSPF | H570: 100000
A571: LNK-00570 | B571: MH-DC-002-PE-T4-02 | C571: et-0/1/1 | D571: MH-DC-002-PE-T4-03 | E571: Hu0/0/1/1 | F571: Fabric | G571: ISIS | H571: 100000
A572: LNK-00571 | B572: MH-DC-002-PE-T4-02 | C572: et-0/1/1 | D572: MH-DC-002-PE-T4-03 | E572: Hu0/0/1/1 | F572: Fabric | G572: BGP | H572: 100000
A573: LNK-00572 | B573: MH-DC-002-PE-T4-02 | C573: et-0/1/1 | D573: MH-DC-002-PE-T4-03 | E573: Hu0/0/1/1 | F573: Fabric | G573: LSP | H573: 100000
A574: LNK-00573 | B574: MH-DC-002-PE-T4-02 | C574: et-0/1/2 | D574: MH-DC-002-PE-T4-04 | E574: Hu0/0/1/1 | F574: Fabric | G574: LLDP | H574: 100000 | I574: MH-DC-002-CBL-0517 | J574: Red | K574: ODF-4/P1 | L574: ODF-1/P10
A575: LNK-00574 | B575: MH-DC-002-PE-T4-02 | C575: et-0/1/2 | D575: MH-DC-002-PE-T4-04 | E575: Hu0/0/1/1 | F575: Fabric | G575: OSPF | H575: 100000
A576: LNK-00575 | B576: MH-DC-002-PE-T4-02 | C576: et-0/1/2 | D576: MH-DC-002-PE-T4-04 | E576: Hu0/0/1/1 | F576: Fabric | G576: ISIS | H576: 100000
A577: LNK-00576 | B577: MH-DC-002-PE-T4-02 | C577: et-0/1/2 | D577: MH-DC-002-PE-T4-04 | E577: Hu0/0/1/1 | F577: Fabric | G577: BGP | H577: 100000
A578: LNK-00577 | B578: MH-DC-002-PE-T4-02 | C578: et-0/1/2 | D578: MH-DC-002-PE-T4-04 | E578: Hu0/0/1/1 | F578: Fabric | G578: LSP | H578: 100000
A579: LNK-00578 | B579: MH-DC-002-PE-T4-03 | C579: Hu0/0/1/2 | D579: MH-DC-002-PE-T4-04 | E579: Hu0/0/1/2 | F579: Fabric | G579: LLDP | H579: 100000 | I579: MH-DC-002-CBL-0518 | J579: Yellow | K579: ODF-2/P20 | L579: ODF-2/P7
A580: LNK-00579 | B580: MH-DC-002-PE-T4-03 | C580: Hu0/0/1/2 | D580: MH-DC-002-PE-T4-04 | E580: Hu0/0/1/2 | F580: Fabric | G580: OSPF | H580: 100000
A581: LNK-00580 | B581: MH-DC-002-PE-T4-03 | C581: Hu0/0/1/2 | D581: MH-DC-002-PE-T4-04 | E581: Hu0/0/1/2 | F581: Fabric | G581: ISIS | H581: 100000
A582: LNK-00581 | B582: MH-DC-002-PE-T4-03 | C582: Hu0/0/1/2 | D582: MH-DC-002-PE-T4-04 | E582: Hu0/0/1/2 | F582: Fabric | G582: BGP | H582: 100000
A583: LNK-00582 | B583: MH-DC-002-PE-T4-03 | C583: Hu0/0/1/2 | D583: MH-DC-002-PE-T4-04 | E583: Hu0/0/1/2 | F583: Fabric | G583: LSP | H583: 100000
A584: LNK-00583 | B584: MH-DC-002-SPINE-01 | C584: Ethernet49/1 | D584: MH-DC-002-PE-T4-01 | E584: xe-0/0/6 | F584: Uplink | G584: LLDP | H584: 10000 | I584: MH-DC-002-CBL-0519 | J584: Orange | K584: ODF-1/P12 | L584: ODF-2/P15
A585: LNK-00584 | B585: MH-DC-002-SPINE-01 | C585: Ethernet49/1 | D585: MH-DC-002-PE-T4-01 | E585: xe-0/0/6 | F585: Uplink | G585: OSPF | H585: 10000
A586: LNK-00585 | B586: MH-DC-002-SPINE-01 | C586: Ethernet49/1 | D586: MH-DC-002-PE-T4-01 | E586: xe-0/0/6 | F586: Uplink | G586: ISIS | H586: 10000
...

Sheet Rack_PDUs
A1: pdu_id * | B1: site_id * | C1: rack_id * | D1: side * | E1: kind * | F1: model | G1: volts * | H1: phases * | I1: rating_a * | J1: capacity_kw * | K1: outlets * | L1: upstream_id * | M1: feed_id *
A2: MH-DC-001-RACK-A-PDU-A | B2: MH-DC-001 | C2: MH-DC-001-RACK-A | D2: A | E2: AC | F2: Switched rack PDU · 3-ph 32 A · 400 V | G2: 400 | H2: 3 | I2: 32 | J2: 16 | K2: 36 | L2: MH-DC-001-UPS-2 | M2: MH-DC-001-AC-1
A3: MH-DC-001-RACK-A-PDU-B | B3: MH-DC-001 | C3: MH-DC-001-RACK-A | D3: B | E3: AC | F3: Switched rack PDU · 3-ph 32 A · 400 V | G3: 400 | H3: 3 | I3: 32 | J3: 16 | K3: 36 | L3: MH-DC-001-UPS-1 | M3: MH-DC-001-AC-2
A4: MH-DC-001-RACK-B-PDU-A | B4: MH-DC-001 | C4: MH-DC-001-RACK-B | D4: A | E4: AC | F4: Switched rack PDU · 3-ph 32 A · 400 V | G4: 400 | H4: 3 | I4: 32 | J4: 16 | K4: 36 | L4: MH-DC-001-UPS-2 | M4: MH-DC-001-AC-1
A5: MH-DC-001-RACK-B-PDU-B | B5: MH-DC-001 | C5: MH-DC-001-RACK-B | D5: B | E5: AC | F5: Switched rack PDU · 3-ph 32 A · 400 V | G5: 400 | H5: 3 | I5: 32 | J5: 16 | K5: 36 | L5: MH-DC-001-UPS-1 | M5: MH-DC-001-AC-2
A6: MH-DC-001-RACK-C-PDU-A | B6: MH-DC-001 | C6: MH-DC-001-RACK-C | D6: A | E6: AC | F6: High-density rack PDU · 3-ph 63 A · 400 V | G6: 400 | H6: 3 | I6: 63 | J6: 23 | K6: 48 | L6: MH-DC-001-UPS-2 | M6: MH-DC-001-AC-1
A7: MH-DC-001-RACK-C-PDU-B | B7: MH-DC-001 | C7: MH-DC-001-RACK-C | D7: B | E7: AC | F7: High-density rack PDU · 3-ph 63 A · 400 V | G7: 400 | H7: 3 | I7: 63 | J7: 23 | K7: 48 | L7: MH-DC-001-UPS-1 | M7: MH-DC-001-AC-2
A8: MH-DC-001-RACK-D-PDU-A | B8: MH-DC-001 | C8: MH-DC-001-RACK-D | D8: A | E8: AC | F8: High-density rack PDU · 3-ph 63 A · 400 V | G8: 400 | H8: 3 | I8: 63 | J8: 23 | K8: 48 | L8: MH-DC-001-UPS-2 | M8: MH-DC-001-AC-1
A9: MH-DC-001-RACK-D-PDU-B | B9: MH-DC-001 | C9: MH-DC-001-RACK-D | D9: B | E9: AC | F9: High-density rack PDU · 3-ph 63 A · 400 V | G9: 400 | H9: 3 | I9: 63 | J9: 23 | K9: 48 | L9: MH-DC-001-UPS-1 | M9: MH-DC-001-AC-2
A10: MH-DC-001-RACK-E-PDU-A | B10: MH-DC-001 | C10: MH-DC-001-RACK-E | D10: A | E10: AC | F10: Switched rack PDU · 3-ph 32 A · 400 V | G10: 400 | H10: 3 | I10: 32 | J10: 17 | K10: 36 | L10: MH-DC-001-UPS-2 | M10: MH-DC-001-AC-1
A11: MH-DC-001-RACK-E-PDU-B | B11: MH-DC-001 | C11: MH-DC-001-RACK-E | D11: B | E11: AC | F11: Switched rack PDU · 3-ph 32 A · 400 V | G11: 400 | H11: 3 | I11: 32 | J11: 17 | K11: 36 | L11: MH-DC-001-UPS-1 | M11: MH-DC-001-AC-2
A12: MH-DC-001-RACK-F-PDU-A | B12: MH-DC-001 | C12: MH-DC-001-RACK-F | D12: A | E12: AC | F12: High-density rack PDU · 3-ph 63 A · 400 V | G12: 400 | H12: 3 | I12: 63 | J12: 23 | K12: 48 | L12: MH-DC-001-UPS-2 | M12: MH-DC-001-AC-1
A13: MH-DC-001-RACK-F-PDU-B | B13: MH-DC-001 | C13: MH-DC-001-RACK-F | D13: B | E13: AC | F13: High-density rack PDU · 3-ph 63 A · 400 V | G13: 400 | H13: 3 | I13: 63 | J13: 23 | K13: 48 | L13: MH-DC-001-UPS-1 | M13: MH-DC-001-AC-2
... A137: MH-DC-002-RACK-W-PDU-B | B137: MH-DC-002 | C137: MH-DC-002-RACK-W | D137: B | E137: AC | F137: Switched rack PDU · 3-ph 16 A · 400 V | G137: 400 | H137: 3 | I137: 16 | J137: 8 | K137: 24 | L137: MH-DC-002-UPS-3 | M137: MH-DC-002-AC-2

Sheet Power_Connections
A1: device_id * | B1: psu_slot * | C1: pdu_id * | D1: outlet * | E1: breaker_bank | F1: psu_rated_w
A2: MH-DC-001-PE-T4-01 | B2: PEM0 | C2: MH-DC-001-RACK-A-PDU-A | D2: 1 | E2: L1
A3: MH-DC-001-PE-T4-01 | B3: PEM1 | C3: MH-DC-001-RACK-A-PDU-B | D3: 1 | E3: L1
A4: MH-DC-001-PE-T4-02 | B4: PEM0 | C4: MH-DC-001-RACK-A-PDU-A | D4: 13 | E4: L2
A5: MH-DC-001-PE-T4-02 | B5: PEM1 | C5: MH-DC-001-RACK-A-PDU-B | D5: 13 | E5: L2
A6: MH-DC-001-PE-T4-03 | B6: PEM0 | C6: MH-DC-001-RACK-A-PDU-A | D6: 25 | E6: L3
A7: MH-DC-001-PE-T4-03 | B7: PEM1 | C7: MH-DC-001-RACK-A-PDU-B | D7: 25 | E7: L3
A8: MH-DC-001-PE-T4-04 | B8: PEM0 | C8: MH-DC-001-RACK-A-PDU-A | D8: 2 | E8: L1
A9: MH-DC-001-PE-T4-04 | B9: PEM1 | C9: MH-DC-001-RACK-A-PDU-B | D9: 2 | E9: L1
A10: MH-DC-001-FW-01 | B10: PSU1 | C10: MH-DC-001-RACK-A-PDU-A | D10: 14 | E10: L2
A11: MH-DC-001-FW-01 | B11: PSU2 | C11: MH-DC-001-RACK-A-PDU-B | D11: 14 | E11: L2
A12: MH-DC-001-FW-02 | B12: PSU1 | C12: MH-DC-001-RACK-A-PDU-A | D12: 26 | E12: L3
A13: MH-DC-001-FW-02 | B13: PSU2 | C13: MH-DC-001-RACK-A-PDU-B | D13: 26 | E13: L3
... A1201: MH-DC-002-GPU-024 | B1201: PSU4 | C1201: MH-DC-002-RACK-R-PDU-B | D1201: 34 | E1201: L3

Sheet Patch_Panels
A1: panel_id * | B1: site_id * | C1: rack_id * | D1: name * | E1: kind * | F1: role * | G1: ports *
A2: MH-DC-001-RACK-B-PP-F1 | B2: MH-DC-001 | C2: MH-DC-001-RACK-B | D2: PP-F1 | E2: LC duplex | F2: rack | G2: 24
A3: MH-DC-001-RACK-B-PP-F2 | B3: MH-DC-001 | C3: MH-DC-001-RACK-B | D3: PP-F2 | E3: LC duplex | F3: rack | G3: 24
A4: MH-DC-001-RACK-B-PP-F3 | B4: MH-DC-001 | C4: MH-DC-001-RACK-B | D4: PP-F3 | E4: LC duplex | F4: rack | G4: 24
A5: MH-DC-001-RACK-B-PP-F4 | B5: MH-DC-001 | C5: MH-DC-001-RACK-B | D5: PP-F4 | E5: LC duplex | F5: rack | G5: 24
A6: MH-DC-001-RACK-B-PP-F5 | B6: MH-DC-001 | C6: MH-DC-001-RACK-B | D6: PP-F5 | E6: LC duplex | F6: rack | G6: 24
A7: MH-DC-001-RACK-B-PP-F6 | B7: MH-DC-001 | C7: MH-DC-001-RACK-B | D7: PP-F6 | E7: LC duplex | F7: rack | G7: 24
A8: MH-DC-001-RACK-B-PP-F7 | B8: MH-DC-001 | C8: MH-DC-001-RACK-B | D8: PP-F7 | E8: LC duplex | F8: rack | G8: 24
A9: MH-DC-001-RACK-B-PP-F8 | B9: MH-DC-001 | C9: MH-DC-001-RACK-B | D9: PP-F8 | E9: LC duplex | F9: rack | G9: 24
A10: MH-DC-001-RACK-B-PP-F9 | B10: MH-DC-001 | C10: MH-DC-001-RACK-B | D10: PP-F9 | E10: LC duplex | F10: rack | G10: 24
A11: MH-DC-001-RACK-B-PP-F10 | B11: MH-DC-001 | C11: MH-DC-001-RACK-B | D11: PP-F10 | E11: LC duplex | F11: rack | G11: 24
A12: MH-DC-001-RACK-B-PP-F11 | B12: MH-DC-001 | C12: MH-DC-001-RACK-B | D12: PP-F11 | E12: LC duplex | F12: rack | G12: 24
A13: MH-DC-001-RACK-B-PP-F12 | B13: MH-DC-001 | C13: MH-DC-001-RACK-B | D13: PP-F12 | E13: LC duplex | F13: rack | G13: 24
... A163: MH-DC-002-RACK-W-ODF-34 | B163: MH-DC-002 | C163: MH-DC-002-RACK-W | D163: ODF-34 | E163: LC duplex | F163: odf | G163: 24

Sheet Trunk_Cables
A1: trunk_id * | B1: site_id * | C1: a_panel_id * | D1: z_panel_id * | E1: kind * | F1: pairs * | G1: route * | H1: length_m
A2: MH-DC-001-RACK-B-TRK-1 | B2: MH-DC-001 | C2: MH-DC-001-RACK-B-PP-F1 | D2: MH-DC-001-RACK-S1-ODF-1 | E2: MPO-24 OM4 trunk × 19 | F2: 228 | G2: Tray route 1 | H2: 50
A3: MH-DC-001-RACK-A-TRK-1 | B3: MH-DC-001 | C3: MH-DC-001-RACK-A-PP-F1 | D3: MH-DC-001-RACK-S1-ODF-1 | E3: MPO-24 OM4 trunk × 2 | F3: 24 | G3: Tray route 1 | H3: 56
A4: MH-DC-001-RACK-B-TRK-2 | B4: MH-DC-001 | C4: MH-DC-001-RACK-B-PP-F1 | D4: MH-DC-001-RACK-S1-ODF-1 | E4: MPO-24 OM4 trunk × 19 | F4: 228 | G4: Tray route 2 | H4: 58
A5: MH-DC-001-RACK-A-TRK-2 | B5: MH-DC-001 | C5: MH-DC-001-RACK-A-PP-F1 | D5: MH-DC-001-RACK-S1-ODF-1 | E5: MPO-24 OM4 trunk × 2 | F5: 24 | G5: Tray route 2 | H5: 56
A6: MH-DC-001-RACK-C-TRK-1 | B6: MH-DC-001 | C6: MH-DC-001-RACK-C-PP-F1 | D6: MH-DC-001-RACK-S1-ODF-1 | E6: MPO-24 OM4 trunk × 3 | F6: 36 | G6: Tray route 1 | H6: 86
A7: MH-DC-001-RACK-C-TRK-2 | B7: MH-DC-001 | C7: MH-DC-001-RACK-C-PP-F1 | D7: MH-DC-001-RACK-S1-ODF-1 | E7: MPO-24 OM4 trunk × 3 | F7: 36 | G7: Tray route 2 | H7: 75
A8: MH-DC-001-RACK-D-TRK-1 | B8: MH-DC-001 | C8: MH-DC-001-RACK-D-PP-F1 | D8: MH-DC-001-RACK-S1-ODF-1 | E8: MPO-24 OM4 trunk × 3 | F8: 36 | G8: Tray route 1 | H8: 73
A9: MH-DC-001-RACK-D-TRK-2 | B9: MH-DC-001 | C9: MH-DC-001-RACK-D-PP-F1 | D9: MH-DC-001-RACK-S1-ODF-1 | E9: MPO-24 OM4 trunk × 3 | F9: 36 | G9: Tray route 2 | H9: 87
A10: MH-DC-001-RACK-E-TRK-1 | B10: MH-DC-001 | C10: MH-DC-001-RACK-E-PP-F1 | D10: MH-DC-001-RACK-S1-ODF-1 | E10: MPO-24 OM4 trunk × 2 | F10: 24 | G10: Tray route 1 | H10: 66
A11: MH-DC-001-RACK-E-TRK-2 | B11: MH-DC-001 | C11: MH-DC-001-RACK-E-PP-F1 | D11: MH-DC-001-RACK-S1-ODF-1 | E11: MPO-24 OM4 trunk × 2 | F11: 24 | G11: Tray route 2 | H11: 64
A12: MH-DC-001-RACK-F-TRK-1 | B12: MH-DC-001 | C12: MH-DC-001-RACK-F-PP-F1 | D12: MH-DC-001-RACK-S1-ODF-1 | E12: MPO-24 OM4 trunk × 3 | F12: 36 | G12: Tray route 1 | H12: 64
A13: MH-DC-001-RACK-F-TRK-2 | B13: MH-DC-001 | C13: MH-DC-001-RACK-F-PP-F1 | D13: MH-DC-001-RACK-S1-ODF-1 | E13: MPO-24 OM4 trunk × 3 | F13: 36 | G13: Tray route 2 | H13: 73
... A59: MH-DC-002-RACK-R-TRK-2 | B59: MH-DC-002 | C59: MH-DC-002-RACK-R-PP-F1 | D59: MH-DC-002-RACK-W-ODF-1 | E59: MPO-24 OM4 trunk × 1 | F59: 12 | G59: Tray route 2 | H59: 79

Sheet Cable_Paths
A1: link_id * | B1: end * | C1: device_id * | D1: patch_cord_id | E1: panel_id | F1: panel_port | G1: trunk_id | H1: odf_panel_id | I1: odf_port | J1: osp_core
A2: LNK-00001 | B2: A | C2: MH-DC-001-PE-T4-01 | D2: MH-DC-001-PC-00001
A3: LNK-00001 | B3: Z | C3: MH-DC-001-PE-T4-02 | D3: MH-DC-001-PC-00002
A4: LNK-00006 | B4: A | C4: MH-DC-001-PE-T4-01 | D4: MH-DC-001-PC-00003
A5: LNK-00006 | B5: Z | C5: MH-DC-001-PE-T4-03 | D5: MH-DC-001-PC-00004
A6: LNK-00011 | B6: A | C6: MH-DC-001-PE-T4-01 | D6: MH-DC-001-PC-00005
A7: LNK-00011 | B7: Z | C7: MH-DC-001-PE-T4-04 | D7: MH-DC-001-PC-00006
A8: LNK-00016 | B8: A | C8: MH-DC-001-PE-T4-02 | D8: MH-DC-001-PC-00007
A9: LNK-00016 | B9: Z | C9: MH-DC-001-PE-T4-03 | D9: MH-DC-001-PC-00008
A10: LNK-00021 | B10: A | C10: MH-DC-001-PE-T4-02 | D10: MH-DC-001-PC-00009
A11: LNK-00021 | B11: Z | C11: MH-DC-001-PE-T4-04 | D11: MH-DC-001-PC-00010
A12: LNK-00026 | B12: A | C12: MH-DC-001-PE-T4-03 | D12: MH-DC-001-PC-00011
A13: LNK-00026 | B13: Z | C13: MH-DC-001-PE-T4-04 | D13: MH-DC-001-PC-00012
... A25: LNK-00046 | B25: Z | C25: MH-DC-001-PE-T4-04 | D25: MH-DC-001-PC-00024
A26: LNK-00049 | B26: A | C26: MH-DC-001-SPINE-04 | D26: MH-DC-001-PC-00025 | E26: MH-DC-001-RACK-B-PP-F1 | F26: 1 | G26: MH-DC-001-RACK-B-TRK-1 | H26: MH-DC-001-RACK-S1-ODF-1 | I26: 1
A27: LNK-00049 | B27: Z | C27: MH-DC-001-PE-T4-04 | D27: MH-DC-001-PC-00026 | E27: MH-DC-001-RACK-A-PP-F1 | F27: 1 | G27: MH-DC-001-RACK-A-TRK-1 | H27: MH-DC-001-RACK-S1-ODF-1 | I27: 2
A28: LNK-00052 | B28: A | C28: MH-DC-001-SPINE-04 | D28: MH-DC-001-PC-00027 | E28: MH-DC-001-RACK-B-PP-F1 | F28: 2 | G28: MH-DC-001-RACK-B-TRK-2 | H28: MH-DC-001-RACK-S1-ODF-1 | I28: 3
A29: LNK-00052 | B29: Z | C29: MH-DC-001-PE-T4-01 | D29: MH-DC-001-PC-00028 | E29: MH-DC-001-RACK-A-PP-F1 | F29: 2 | G29: MH-DC-001-RACK-A-TRK-1 | H29: MH-DC-001-RACK-S1-ODF-1 | I29: 4
A30: LNK-00055 | B30: A | C30: MH-DC-001-OLA-01 | D30: MH-DC-001-PC-00029
A31: LNK-00055 | B31: Z | C31: MH-DC-001-SPINE-01 | D31: MH-DC-001-PC-00030
A32: LNK-00056 | B32: A | C32: MH-DC-001-OLA-02 | D32: MH-DC-001-PC-00031
A33: LNK-00056 | B33: Z | C33: MH-DC-001-SPINE-02 | D33: MH-DC-001-PC-00032
A34: LNK-00057 | B34: A | C34: MH-DC-001-FW-01 | D34: MH-DC-001-PC-00033
A35: LNK-00057 | B35: Z | C35: MH-DC-001-SPINE-01 | D35: MH-DC-001-PC-00034
A36: LNK-00058 | B36: A | C36: MH-DC-001-FW-01 | D36: MH-DC-001-PC-00035
A37: LNK-00058 | B37: Z | C37: MH-DC-001-SPINE-02 | D37: MH-DC-001-PC-00036
A38: LNK-00059 | B38: A | C38: MH-DC-001-FW-02 | D38: MH-DC-001-PC-00037
A39: LNK-00059 | B39: Z | C39: MH-DC-001-SPINE-02 | D39: MH-DC-001-PC-00038
A40: LNK-00060 | B40: A | C40: MH-DC-001-FW-02 | D40: MH-DC-001-PC-00039
A41: LNK-00060 | B41: Z | C41: MH-DC-001-SPINE-03 | D41: MH-DC-001-PC-00040
A42: LNK-00061 | B42: A | C42: MH-DC-001-LEAF-01 | D42: MH-DC-001-PC-00041 | E42: MH-DC-001-RACK-B-PP-F1 | F42: 3 | G42: MH-DC-001-RACK-B-TRK-1 | H42: MH-DC-001-RACK-S1-ODF-1 | I42: 5
A43: LNK-00061 | B43: Z | C43: MH-DC-001-SPINE-01 | D43: MH-DC-001-PC-00042 | E43: MH-DC-001-RACK-A-PP-F1 | F43: 3 | G43: MH-DC-001-RACK-A-TRK-1 | H43: MH-DC-001-RACK-S1-ODF-1 | I43: 6
A44: LNK-00062 | B44: A | C44: MH-DC-001-LEAF-01 | D44: MH-DC-001-PC-00043
A45: LNK-00062 | B45: Z | C45: MH-DC-001-SPINE-04 | D45: MH-DC-001-PC-00044
A46: LNK-00063 | B46: A | C46: MH-DC-001-LEAF-02 | D46: MH-DC-001-PC-00045 | E46: MH-DC-001-RACK-B-PP-F1 | F46: 4 | G46: MH-DC-001-RACK-B-TRK-1 | H46: MH-DC-001-RACK-S1-ODF-1 | I46: 7
A47: LNK-00063 | B47: Z | C47: MH-DC-001-SPINE-02 | D47: MH-DC-001-PC-00046 | E47: MH-DC-001-RACK-A-PP-F1 | F47: 4 | G47: MH-DC-001-RACK-A-TRK-2 | H47: MH-DC-001-RACK-S1-ODF-1 | I47: 8
A48: LNK-00064 | B48: A | C48: MH-DC-001-LEAF-02 | D48: MH-DC-001-PC-00047 | E48: MH-DC-001-RACK-B-PP-F1 | F48: 5 | G48: MH-DC-001-RACK-B-TRK-2 | H48: MH-DC-001-RACK-S1-ODF-1 | I48: 9
A49: LNK-00064 | B49: Z | C49: MH-DC-001-SPINE-01 | D49: MH-DC-001-PC-00048 | E49: MH-DC-001-RACK-A-PP-F1 | F49: 5 | G49: MH-DC-001-RACK-A-TRK-2 | H49: MH-DC-001-RACK-S1-ODF-1 | I49: 10
A50: LNK-00065 | B50: A | C50: MH-DC-001-LEAF-03 | D50: MH-DC-001-PC-00049 | E50: MH-DC-001-RACK-B-PP-F1 | F50: 6 | G50: MH-DC-001-RACK-B-TRK-1 | H50: MH-DC-001-RACK-S1-ODF-1 | I50: 11
A51: LNK-00065 | B51: Z | C51: MH-DC-001-SPINE-03 | D51: MH-DC-001-PC-00050 | E51: MH-DC-001-RACK-A-PP-F1 | F51: 6 | G51: MH-DC-001-RACK-A-TRK-2 | H51: MH-DC-001-RACK-S1-ODF-1 | I51: 12
A52: LNK-00066 | B52: A | C52: MH-DC-001-LEAF-03 | D52: MH-DC-001-PC-00051 | E52: MH-DC-001-RACK-B-PP-F1 | F52: 7 | G52: MH-DC-001-RACK-B-TRK-2 | H52: MH-DC-001-RACK-S1-ODF-1 | I52: 13
A53: LNK-00066 | B53: Z | C53: MH-DC-001-SPINE-02 | D53: MH-DC-001-PC-00052 | E53: MH-DC-001-RACK-A-PP-F1 | F53: 7 | G53: MH-DC-001-RACK-A-TRK-1 | H53: MH-DC-001-RACK-S1-ODF-1 | I53: 14
A54: LNK-00067 | B54: A | C54: MH-DC-001-LEAF-04 | D54: MH-DC-001-PC-00053
A55: LNK-00067 | B55: Z | C55: MH-DC-001-SPINE-04 | D55: MH-DC-001-PC-00054
A56: LNK-00068 | B56: A | C56: MH-DC-001-LEAF-04 | D56: MH-DC-001-PC-00055 | E56: MH-DC-001-RACK-B-PP-F1 | F56: 8 | G56: MH-DC-001-RACK-B-TRK-2 | H56: MH-DC-001-RACK-S1-ODF-1 | I56: 15
A57: LNK-00068 | B57: Z | C57: MH-DC-001-SPINE-03 | D57: MH-DC-001-PC-00056 | E57: MH-DC-001-RACK-A-PP-F1 | F57: 8 | G57: MH-DC-001-RACK-A-TRK-1 | H57: MH-DC-001-RACK-S1-ODF-1 | I57: 16
A58: LNK-00069 | B58: A | C58: MH-DC-001-TOR-001 | D58: MH-DC-001-PC-00057
A59: LNK-00069 | B59: Z | C59: MH-DC-001-LEAF-01 | D59: MH-DC-001-PC-00058
A60: LNK-00070 | B60: A | C60: MH-DC-001-TOR-001 | D60: MH-DC-001-PC-00059
A61: LNK-00070 | B61: Z | C61: MH-DC-001-LEAF-02 | D61: MH-DC-001-PC-00060
A62: LNK-00071 | B62: A | C62: MH-DC-001-TOR-002 | D62: MH-DC-001-PC-00061
A63: LNK-00071 | B63: Z | C63: MH-DC-001-LEAF-02 | D63: MH-DC-001-PC-00062
A64: LNK-00072 | B64: A | C64: MH-DC-001-TOR-002 | D64: MH-DC-001-PC-00063
A65: LNK-00072 | B65: Z | C65: MH-DC-001-LEAF-03 | D65: MH-DC-001-PC-00064
A66: LNK-00073 | B66: A | C66: MH-DC-001-TOR-003 | D66: MH-DC-001-PC-00065
A67: LNK-00073 | B67: Z | C67: MH-DC-001-LEAF-03 | D67: MH-DC-001-PC-00066
A68: LNK-00074 | B68: A | C68: MH-DC-001-TOR-003 | D68: MH-DC-001-PC-00067
A69: LNK-00074 | B69: Z | C69: MH-DC-001-LEAF-04 | D69: MH-DC-001-PC-00068
... A137: LNK-00108 | B137: Z | C137: MH-DC-001-TOR-003 | D137: MH-DC-001-PC-00136
A138: LNK-00109 | B138: A | C138: MH-DC-001-CMP-0003 | D138: MH-DC-001-PC-00137 | E138: MH-DC-001-RACK-C-PP-F1 | F138: 1 | G138: MH-DC-001-RACK-C-TRK-1 | H138: MH-DC-001-RACK-S1-ODF-1 | I138: 17
A139: LNK-00109 | B139: Z | C139: MH-DC-001-TOR-003 | D139: MH-DC-001-PC-00138 | E139: MH-DC-001-RACK-B-PP-F1 | F139: 9 | G139: MH-DC-001-RACK-B-TRK-2 | H139: MH-DC-001-RACK-S1-ODF-1 | I139: 18
A140: LNK-00110 | B140: A | C140: MH-DC-001-CMP-0003 | D140: MH-DC-001-PC-00139 | E140: MH-DC-001-RACK-C-PP-F1 | F140: 2 | G140: MH-DC-001-RACK-C-TRK-2 | H140: MH-DC-001-RACK-S1-ODF-1 | I140: 19
A141: LNK-00110 | B141: Z | C141: MH-DC-001-TOR-004 | D141: MH-DC-001-PC-00140 | E141: MH-DC-001-RACK-B-PP-F1 | F141: 10 | G141: MH-DC-001-RACK-B-TRK-1 | H141: MH-DC-001-RACK-S1-ODF-1 | I141: 20
A142: LNK-00111 | B142: A | C142: MH-DC-001-CMP-0004 | D142: MH-DC-001-PC-00141 | E142: MH-DC-001-RACK-C-PP-F1 | F142: 3 | G142: MH-DC-001-RACK-C-TRK-1 | H142: MH-DC-001-RACK-S1-ODF-1 | I142: 21
A143: LNK-00111 | B143: Z | C143: MH-DC-001-TOR-004 | D143: MH-DC-001-PC-00142 | E143: MH-DC-001-RACK-B-PP-F1 | F143: 11 | G143: MH-DC-001-RACK-B-TRK-2 | H143: MH-DC-001-RACK-S1-ODF-1 | I143: 22
A144: LNK-00112 | B144: A | C144: MH-DC-001-CMP-0004 | D144: MH-DC-001-PC-00143 | E144: MH-DC-001-RACK-C-PP-F1 | F144: 4 | G144: MH-DC-001-RACK-C-TRK-2 | H144: MH-DC-001-RACK-S1-ODF-1 | I144: 23
A145: LNK-00112 | B145: Z | C145: MH-DC-001-TOR-005 | D145: MH-DC-001-PC-00144 | E145: MH-DC-001-RACK-B-PP-F1 | F145: 12 | G145: MH-DC-001-RACK-B-TRK-1 | H145: MH-DC-001-RACK-S1-ODF-1 | I145: 24
A146: LNK-00113 | B146: A | C146: MH-DC-001-CMP-0005 | D146: MH-DC-001-PC-00145 | E146: MH-DC-001-RACK-C-PP-F1 | F146: 5 | G146: MH-DC-001-RACK-C-TRK-1 | H146: MH-DC-001-RACK-S1-ODF-2 | I146: 1
A147: LNK-00113 | B147: Z | C147: MH-DC-001-TOR-005 | D147: MH-DC-001-PC-00146 | E147: MH-DC-001-RACK-B-PP-F1 | F147: 13 | G147: MH-DC-001-RACK-B-TRK-2 | H147: MH-DC-001-RACK-S1-ODF-2 | I147: 2
A148: LNK-00114 | B148: A | C148: MH-DC-001-CMP-0005 | D148: MH-DC-001-PC-00147 | E148: MH-DC-001-RACK-C-PP-F1 | F148: 6 | G148: MH-DC-001-RACK-C-TRK-2 | H148: MH-DC-001-RACK-S1-ODF-2 | I148: 3
A149: LNK-00114 | B149: Z | C149: MH-DC-001-TOR-006 | D149: MH-DC-001-PC-00148 | E149: MH-DC-001-RACK-B-PP-F1 | F149: 14 | G149: MH-DC-001-RACK-B-TRK-1 | H149: MH-DC-001-RACK-S1-ODF-2 | I149: 4
... A1025: LNK-00552 | B1025: Z | C1025: MH-DC-001-TOR-009 | D1025: MH-DC-001-PC-01024 | E1025: MH-DC-001-RACK-B-PP-F19 | F1025: 20 | G1025: MH-DC-001-RACK-B-TRK-1 | H1025: MH-DC-001-RACK-S1-ODF-38 | I1025: 16
A1026: LNK-00553 | B1026: A | C1026: MH-DC-002-PE-T4-01 | D1026: MH-DC-002-PC-00001
A1027: LNK-00553 | B1027: Z | C1027: MH-DC-002-PE-T4-02 | D1027: MH-DC-002-PC-00002
A1028: LNK-00558 | B1028: A | C1028: MH-DC-002-PE-T4-01 | D1028: MH-DC-002-PC-00003
A1029: LNK-00558 | B1029: Z | C1029: MH-DC-002-PE-T4-03 | D1029: MH-DC-002-PC-00004
A1030: LNK-00563 | B1030: A | C1030: MH-DC-002-PE-T4-01 | D1030: MH-DC-002-PC-00005
A1031: LNK-00563 | B1031: Z | C1031: MH-DC-002-PE-T4-04 | D1031: MH-DC-002-PC-00006
A1032: LNK-00568 | B1032: A | C1032: MH-DC-002-PE-T4-02 | D1032: MH-DC-002-PC-00007
A1033: LNK-00568 | B1033: Z | C1033: MH-DC-002-PE-T4-03 | D1033: MH-DC-002-PC-00008
A1034: LNK-00573 | B1034: A | C1034: MH-DC-002-PE-T4-02 | D1034: MH-DC-002-PC-00009
A1035: LNK-00573 | B1035: Z | C1035: MH-DC-002-PE-T4-04 | D1035: MH-DC-002-PC-00010
A1036: LNK-00578 | B1036: A | C1036: MH-DC-002-PE-T4-03 | D1036: MH-DC-002-PC-00011
A1037: LNK-00578 | B1037: Z | C1037: MH-DC-002-PE-T4-04 | D1037: MH-DC-002-PC-00012
... A1061: LNK-00610 | B1061: Z | C1061: MH-DC-002-SPINE-02 | D1061: MH-DC-002-PC-00036
A1062: LNK-00611 | B1062: A | C1062: MH-DC-002-LEAF-01 | D1062: MH-DC-002-PC-00037 | E1062: MH-DC-002-RACK-B-PP-F1 | F1062: 1 | G1062: MH-DC-002-RACK-B-TRK-1 | H1062: MH-DC-002-RACK-W-ODF-1 | I1062: 1
A1063: LNK-00611 | B1063: Z | C1063: MH-DC-002-SPINE-01 | D1063: MH-DC-002-PC-00038 | E1063: MH-DC-002-RACK-A-PP-F1 | F1063: 1 | G1063: MH-DC-002-RACK-A-TRK-1 | H1063: MH-DC-002-RACK-W-ODF-1 | I1063: 2
A1064: LNK-00612 | B1064: A | C1064: MH-DC-002-LEAF-01 | D1064: MH-DC-002-PC-00039 | E1064: MH-DC-002-RACK-B-PP-F1 | F1064: 2 | G1064: MH-DC-002-RACK-B-TRK-2 | H1064: MH-DC-002-RACK-W-ODF-1 | I1064: 3
A1065: LNK-00612 | B1065: Z | C1065: MH-DC-002-SPINE-04 | D1065: MH-DC-002-PC-00040 | E1065: MH-DC-002-RACK-A-PP-F1 | F1065: 2 | G1065: MH-DC-002-RACK-A-TRK-1 | H1065: MH-DC-002-RACK-W-ODF-1 | I1065: 4
A1066: LNK-00613 | B1066: A | C1066: MH-DC-002-LEAF-02 | D1066: MH-DC-002-PC-00041 | E1066: MH-DC-002-RACK-B-PP-F1 | F1066: 3 | G1066: MH-DC-002-RACK-B-TRK-1 | H1066: MH-DC-002-RACK-W-ODF-1 | I1066: 5
A1067: LNK-00613 | B1067: Z | C1067: MH-DC-002-SPINE-02 | D1067: MH-DC-002-PC-00042 | E1067: MH-DC-002-RACK-A-PP-F1 | F1067: 3 | G1067: MH-DC-002-RACK-A-TRK-1 | H1067: MH-DC-002-RACK-W-ODF-1 | I1067: 6
A1068: LNK-00614 | B1068: A | C1068: MH-DC-002-LEAF-02 | D1068: MH-DC-002-PC-00043 | E1068: MH-DC-002-RACK-B-PP-F1 | F1068: 4 | G1068: MH-DC-002-RACK-B-TRK-2 | H1068: MH-DC-002-RACK-W-ODF-1 | I1068: 7
A1069: LNK-00614 | B1069: Z | C1069: MH-DC-002-SPINE-01 | D1069: MH-DC-002-PC-00044 | E1069: MH-DC-002-RACK-A-PP-F1 | F1069: 4 | G1069: MH-DC-002-RACK-A-TRK-2 | H1069: MH-DC-002-RACK-W-ODF-1 | I1069: 8
A1070: LNK-00615 | B1070: A | C1070: MH-DC-002-LEAF-03 | D1070: MH-DC-002-PC-00045 | E1070: MH-DC-002-RACK-B-PP-F1 | F1070: 5 | G1070: MH-DC-002-RACK-B-TRK-1 | H1070: MH-DC-002-RACK-W-ODF-1 | I1070: 9
A1071: LNK-00615 | B1071: Z | C1071: MH-DC-002-SPINE-03 | D1071: MH-DC-002-PC-00046 | E1071: MH-DC-002-RACK-A-PP-F1 | F1071: 5 | G1071: MH-DC-002-RACK-A-TRK-1 | H1071: MH-DC-002-RACK-W-ODF-1 | I1071: 10
A1072: LNK-00616 | B1072: A | C1072: MH-DC-002-LEAF-03 | D1072: MH-DC-002-PC-00047 | E1072: MH-DC-002-RACK-B-PP-F1 | F1072: 6 | G1072: MH-DC-002-RACK-B-TRK-2 | H1072: MH-DC-002-RACK-W-ODF-1 | I1072: 11
A1073: LNK-00616 | B1073: Z | C1073: MH-DC-002-SPINE-02 | D1073: MH-DC-002-PC-00048 | E1073: MH-DC-002-RACK-A-PP-F1 | F1073: 6 | G1073: MH-DC-002-RACK-A-TRK-2 | H1073: MH-DC-002-RACK-W-ODF-1 | I1073: 12
... A1077: LNK-00618 | B1077: Z | C1077: MH-DC-002-SPINE-03 | D1077: MH-DC-002-PC-00052 | E1077: MH-DC-002-RACK-A-PP-F1 | F1077: 8 | G1077: MH-DC-002-RACK-A-TRK-2 | H1077: MH-DC-002-RACK-W-ODF-1 | I1077: 16
A1078: LNK-00619 | B1078: A | C1078: MH-DC-002-TOR-001 | D1078: MH-DC-002-PC-00053
A1079: LNK-00619 | B1079: Z | C1079: MH-DC-002-LEAF-01 | D1079: MH-DC-002-PC-00054
...

Sheet Cooling_Coverage
A1: rack_id * | B1: primary_unit_id * | C1: cdu_id
A2: MH-DC-001-RACK-A | B2: MH-DC-001-CRAH-11
A3: MH-DC-001-RACK-B | B3: MH-DC-001-CRAH-11
A4: MH-DC-001-RACK-C | B4: MH-DC-001-CRAH-11
A5: MH-DC-001-RACK-D | B5: MH-DC-001-CRAH-11
A6: MH-DC-001-RACK-E | B6: MH-DC-001-CRAH-11
A7: MH-DC-001-RACK-F | B7: MH-DC-001-CRAH-11
A8: MH-DC-001-RACK-G | B8: MH-DC-001-CRAH-15
A9: MH-DC-001-RACK-H | B9: MH-DC-001-CRAH-15
A10: MH-DC-001-RACK-I | B10: MH-DC-001-CRAH-15
A11: MH-DC-001-RACK-J | B11: MH-DC-001-CRAH-15
A12: MH-DC-001-RACK-K | B12: MH-DC-001-CRAH-15
A13: MH-DC-001-RACK-L | B13: MH-DC-001-CRAH-15
... A69: MH-DC-002-RACK-W | B69: MH-DC-002-CRAH-18

Sheet GPU_Clusters
A1: cluster_id * | B1: site_id * | C1: room_id * | D1: name * | E1: scheduler * | F1: fabric * | G1: gpu_model * | H1: cooling * | I1: node_count (calc)
A2: MH-DC-002-POD-1 | B2: MH-DC-002 | C2: MH-DC-002-F0-R2 | D2: AI-POD-1 | E2: Kubernetes | F2: InfiniBand NDR 400G · 8 rails · 24 nodes | G2: H100 SXM 80 GB | H2: air | I2: =COUNTIF('GPU_Nodes'!$B$2:$B$4690,A2)

Sheet GPU_Nodes
A1: device_id * | B1: cluster_id * | C1: gpu_model * | D1: gpu_vendor * | E1: gpu_count * | F1: server_model * | G1: cooling * | H1: driver | I1: firmware
A2: MH-DC-002-GPU-001 | B2: MH-DC-002-POD-1 | C2: H100 SXM 80 GB | D2: NVIDIA | E2: 8 | F2: Supermicro SYS-821GE-TNHR (8×H100) | G2: air | H2: 550.127.05 | I2: VBIOS 96.00.89.00.01
A3: MH-DC-002-GPU-002 | B3: MH-DC-002-POD-1 | C3: H100 SXM 80 GB | D3: NVIDIA | E3: 8 | F3: Supermicro SYS-821GE-TNHR (8×H100) | G3: air | H3: 550.127.05 | I3: VBIOS 96.00.89.00.01
A4: MH-DC-002-GPU-003 | B4: MH-DC-002-POD-1 | C4: H100 SXM 80 GB | D4: NVIDIA | E4: 8 | F4: NVIDIA DGX H100 | G4: air | H4: 550.127.05 | I4: VBIOS 96.00.89.00.01
A5: MH-DC-002-GPU-004 | B5: MH-DC-002-POD-1 | C5: H100 SXM 80 GB | D5: NVIDIA | E5: 8 | F5: Supermicro SYS-821GE-TNHR (8×H100) | G5: air | H5: 550.127.05 | I5: VBIOS 96.00.89.00.01
A6: MH-DC-002-GPU-005 | B6: MH-DC-002-POD-1 | C6: H100 SXM 80 GB | D6: NVIDIA | E6: 8 | F6: Supermicro SYS-821GE-TNHR (8×H100) | G6: air | H6: 550.127.05 | I6: VBIOS 96.00.89.00.01
A7: MH-DC-002-GPU-006 | B7: MH-DC-002-POD-1 | C7: H100 SXM 80 GB | D7: NVIDIA | E7: 8 | F7: NVIDIA DGX H100 | G7: air | H7: 550.127.05 | I7: VBIOS 96.00.89.00.01
A8: MH-DC-002-GPU-007 | B8: MH-DC-002-POD-1 | C8: H100 SXM 80 GB | D8: NVIDIA | E8: 8 | F8: Supermicro SYS-821GE-TNHR (8×H100) | G8: air | H8: 550.127.05 | I8: VBIOS 96.00.89.00.01
A9: MH-DC-002-GPU-008 | B9: MH-DC-002-POD-1 | C9: H100 SXM 80 GB | D9: NVIDIA | E9: 8 | F9: NVIDIA DGX H100 | G9: air | H9: 550.127.05 | I9: VBIOS 96.00.89.00.01
A10: MH-DC-002-GPU-009 | B10: MH-DC-002-POD-1 | C10: H100 SXM 80 GB | D10: NVIDIA | E10: 8 | F10: Supermicro SYS-821GE-TNHR (8×H100) | G10: air | H10: 550.127.05 | I10: VBIOS 96.00.89.00.01
A11: MH-DC-002-GPU-010 | B11: MH-DC-002-POD-1 | C11: H100 SXM 80 GB | D11: NVIDIA | E11: 8 | F11: NVIDIA DGX H100 | G11: air | H11: 550.127.05 | I11: VBIOS 96.00.89.00.01
A12: MH-DC-002-GPU-011 | B12: MH-DC-002-POD-1 | C12: H100 SXM 80 GB | D12: NVIDIA | E12: 8 | F12: NVIDIA DGX H100 | G12: air | H12: 550.127.05 | I12: VBIOS 96.00.89.00.01
A13: MH-DC-002-GPU-012 | B13: MH-DC-002-POD-1 | C13: H100 SXM 80 GB | D13: NVIDIA | E13: 8 | F13: NVIDIA DGX H100 | G13: air | H13: 550.127.05 | I13: VBIOS 96.00.89.00.01
... A25: MH-DC-002-GPU-024 | B25: MH-DC-002-POD-1 | C25: H100 SXM 80 GB | D25: NVIDIA | E25: 8 | F25: NVIDIA DGX H100 | G25: air | H25: 550.127.05 | I25: VBIOS 96.00.89.00.01

Sheet Customers
A1: customer_id * | B1: name * | C1: segment * | D1: city * | E1: state * | F1: plan * | G1: premium * | H1: account_manager | I1: monthly_revenue (calc)
A2: CUST-1202 | B2: ShopSwift Commerce | C2: Retail | D2: Bengaluru | E2: Karnataka | F2: Enterprise support | G2: Y | H2: Neha Kapoor | I2: =SUMIF('Services'!$B$2:$B$4690,A2,'Services'!$M$2:$M$4690)
A3: CUST-9121 | B3: PayNow Fintech | C3: BFSI | D3: Mumbai | E3: Maharashtra | F3: Enterprise support | G3: Y | H3: Rohan Joshi | I3: =SUMIF('Services'!$B$2:$B$4690,A3,'Services'!$M$2:$M$4690)
A4: CUST-8240 | B4: Finance Group | C4: BFSI | D4: Mumbai | E4: Maharashtra | F4: Enterprise support | G4: Y | H4: Ananya Sen | I4: =SUMIF('Services'!$B$2:$B$4690,A4,'Services'!$M$2:$M$4690)
A5: CUST-7359 | B5: StreamBox Media | C5: Media | D5: Mumbai | E5: Maharashtra | F5: Business support | G5: Y | H5: Karthik Raman | I5: =SUMIF('Services'!$B$2:$B$4690,A5,'Services'!$M$2:$M$4690)
A6: CUST-6478 | B6: NexGen Gaming | C6: Gaming | D6: Hyderabad | E6: Telangana | F6: Business support | G6: N | H6: Pooja Verma | I6: =SUMIF('Services'!$B$2:$B$4690,A6,'Services'!$M$2:$M$4690)
A7: CUST-5597 | B7: EduVerse Learning | C7: EdTech | D7: Pune | E7: Maharashtra | F7: Business support | G7: N | H7: Neha Kapoor | I7: =SUMIF('Services'!$B$2:$B$4690,A7,'Services'!$M$2:$M$4690)
A8: CUST-4716 | B8: HealthCloud Analytics | C8: Healthcare | D8: New Delhi | E8: Delhi NCR | F8: Enterprise support | G8: Y | H8: Rohan Joshi | I8: =SUMIF('Services'!$B$2:$B$4690,A8,'Services'!$M$2:$M$4690)
A9: CUST-3835 | B9: AgriSense IoT | C9: IoT | D9: Jaipur | E9: Rajasthan | F9: Developer | G9: N | H9: Ananya Sen | I9: =SUMIF('Services'!$B$2:$B$4690,A9,'Services'!$M$2:$M$4690)
A10: CUST-2954 | B10: FleetTrack Logistics | C10: Logistics | D10: Hyderabad | E10: Telangana | F10: Business support | G10: N | H10: Karthik Raman | I10: =SUMIF('Services'!$B$2:$B$4690,A10,'Services'!$M$2:$M$4690)
A11: CUST-2073 | B11: CityGov Digital | C11: Government | D11: Lucknow | E11: Uttar Pradesh | F11: Enterprise support | G11: Y | H11: Pooja Verma | I11: =SUMIF('Services'!$B$2:$B$4690,A11,'Services'!$M$2:$M$4690)
A12: CUST-9992 | B12: QuantLedger AI | C12: AI / ML | D12: Bengaluru | E12: Karnataka | F12: Enterprise support | G12: Y | H12: Neha Kapoor | I12: =SUMIF('Services'!$B$2:$B$4690,A12,'Services'!$M$2:$M$4690)
A13: CUST-9111 | B13: VisionLabs ML | C13: AI / ML | D13: Chennai | E13: Tamil Nadu | F13: Business support | G13: N | H13: Rohan Joshi | I13: =SUMIF('Services'!$B$2:$B$4690,A13,'Services'!$M$2:$M$4690)
... A25: CUST-7339 | B25: Airport Operator | C25: Transport | D25: New Delhi | E25: Delhi NCR | F25: Enterprise support | G25: Y | H25: Karthik Raman | I25: =SUMIF('Services'!$B$2:$B$4690,A25,'Services'!$M$2:$M$4690)

Sheet Services
A1: service_id * | B1: customer_id * | C1: type * | D1: site_id * | E1: device_id | F1: if_name | G1: rack_ids | H1: gpu_node_ids | I1: qty * | J1: unit * | K1: bandwidth_mbps | L1: sla_target_pct * | M1: monthly_revenue * | N1: critical * | O1: start_date
A2: SVC-VM-1100 | B2: CUST-4706 | C2: VM | D2: MH-DC-001 | E2: MH-DC-001-CMP-0001 | F2: eth0 | I2: 8 | J2: vCPU | K2: 10000 | L2: 99.95 | M2: 14400 | N2: N
A3: SVC-K8-1101 | B3: CUST-9121 | C3: Kubernetes | D3: MH-DC-001 | E3: MH-DC-001-CMP-0005 | F3: eth0 | I3: 256 | J3: vCPU | K3: 10000 | L3: 99.99 | M3: 460800 | N3: Y
A4: SVC-K8-1102 | B4: CUST-8230 | C4: Kubernetes | D4: MH-DC-001 | E4: MH-DC-001-CMP-0009 | F4: eth0 | I4: 64 | J4: vCPU | K4: 10000 | L4: 99.95 | M4: 115200 | N4: N
A5: SVC-VM-1103 | B5: CUST-8220 | C5: VM | D5: MH-DC-001 | E5: MH-DC-001-CMP-0013 | F5: eth0 | I5: 64 | J5: vCPU | K5: 10000 | L5: 99.95 | M5: 115200 | N5: N
A6: SVC-VM-1104 | B6: CUST-4716 | C6: VM | D6: MH-DC-001 | E6: MH-DC-001-CMP-0017 | F6: eth0 | I6: 32 | J6: vCPU | K6: 10000 | L6: 99.99 | M6: 57600 | N6: Y
A7: SVC-K8-1105 | B7: CUST-8230 | C7: Kubernetes | D7: MH-DC-001 | E7: MH-DC-001-CMP-0017 | F7: eth0 | I7: 64 | J7: vCPU | K7: 10000 | L7: 99.95 | M7: 115200 | N7: N
A8: SVC-K8-1106 | B8: CUST-5597 | C8: Kubernetes | D8: MH-DC-001 | E8: MH-DC-001-CMP-0021 | F8: eth0 | I8: 128 | J8: vCPU | K8: 10000 | L8: 99.95 | M8: 230400 | N8: N
A9: SVC-VM-1107 | B9: CUST-5597 | C9: VM | D9: MH-DC-001 | E9: MH-DC-001-CMP-0025 | F9: eth0 | I9: 16 | J9: vCPU | K9: 10000 | L9: 99.95 | M9: 28800 | N9: N
A10: SVC-VM-1108 | B10: CUST-2073 | C10: VM | D10: MH-DC-001 | E10: MH-DC-001-CMP-0029 | F10: eth0 | I10: 32 | J10: vCPU | K10: 10000 | L10: 99.99 | M10: 57600 | N10: Y
A11: SVC-VM-1109 | B11: CUST-8240 | C11: VM | D11: MH-DC-001 | E11: MH-DC-001-CMP-0029 | F11: eth0 | I11: 128 | J11: vCPU | K11: 10000 | L11: 99.99 | M11: 230400 | N11: Y
A12: SVC-K8-1110 | B12: CUST-8230 | C12: Kubernetes | D12: MH-DC-001 | E12: MH-DC-001-CMP-0033 | F12: eth0 | I12: 256 | J12: vCPU | K12: 10000 | L12: 99.95 | M12: 460800 | N12: N
A13: SVC-VM-1111 | B13: CUST-9121 | C13: VM | D13: MH-DC-001 | E13: MH-DC-001-CMP-0037 | F13: eth0 | I13: 16 | J13: vCPU | K13: 10000 | L13: 99.99 | M13: 28800 | N13: Y
... A128: SVC-SV-1226 | B128: CUST-9101 | C128: Storage volume | D128: MH-DC-002 | E128: MH-DC-002-STO-036 | F128: eth0 | I128: 10 | J128: TB | K128: 10000 | L128: 99.99 | M128: 11000 | N128: Y
A129: SVC-GP-2819 | B129: CUST-8240 | C129: GPU cluster | D129: MH-DC-002 | E129: MH-DC-002-GPU-001 | F129: 13-node training job | H129: MH-DC-002-GPU-001;MH-DC-002-GPU-003;MH-DC-002-GPU-004;MH-DC-002-GPU-005;MH-DC-002-GPU-006;MH-DC-002-GPU-007;MH-DC-002-GPU-008;MH-DC-002-GPU-010;MH-DC-002-GPU-011;MH-DC-002-GPU-012;MH-DC-002-GPU-013;MH-DC-002-GPU-014;MH-DC-002-GPU-015 | I129: 104 | J129: GPU | K129: 400000 | L129: 99.99 | M129: 18200000 | N129: Y
A130: SVC-GP-2820 | B130: CUST-6468 | C130: GPU cluster | D130: MH-DC-002 | E130: MH-DC-002-GPU-016 | F130: 1-node inference job | H130: MH-DC-002-GPU-016 | I130: 8 | J130: GPU | K130: 400000 | L130: 99.95 | M130: 1400000 | N130: N
A131: SVC-GP-2821 | B131: CUST-2073 | C131: GPU cluster | D131: MH-DC-002 | E131: MH-DC-002-GPU-017 | F131: 2-node fine-tuning job | H131: MH-DC-002-GPU-017;MH-DC-002-GPU-018 | I131: 16 | J131: GPU | K131: 400000 | L131: 99.99 | M131: 2800000 | N131: Y
A132: SVC-GP-2822 | B132: CUST-8220 | C132: GPU cluster | D132: MH-DC-002 | E132: MH-DC-002-GPU-019 | F132: 4-node fine-tuning job | H132: MH-DC-002-GPU-019;MH-DC-002-GPU-020;MH-DC-002-GPU-021;MH-DC-002-GPU-022 | I132: 32 | J132: GPU | K132: 400000 | L132: 99.95 | M132: 5600000 | N132: N

Sheet Collectors
A1: collector_id * | B1: site_id * | C1: name * | D1: protocol * | E1: domain * | F1: host_ip | G1: covers
A2: COL-MH-DC-001-1 | B2: MH-DC-001 | C2: Collector Pune A | D2: gNMI | E2: Network
A3: COL-MH-DC-001-2 | B3: MH-DC-001 | C3: Collector Pune B | D3: gNMI | E3: Network
A4: COL-MH-DC-002-1 | B4: MH-DC-002 | C4: Collector Pune A | D4: gNMI | E4: Network
A5: COL-MH-DC-002-2 | B5: MH-DC-002 | C5: Collector Pune B | D5: gNMI | E5: Network

Sheet Fire_Systems
A1: zone_id * | B1: site_id * | C1: room_id * | D1: detection * | E1: suppression * | F1: release_mode * | G1: last_inspection * | H1: panel_point
A2: MH-DC-001-FZ-01 | B2: MH-DC-001 | C2: MH-DC-001-F0-R1 | D2: VESDA aspirating | E2: Novec 1230 gas | F2: Armed (auto) | G2: 46233
A3: MH-DC-001-FZ-02 | B3: MH-DC-001 | C3: MH-DC-001-F0-R2 | D3: VESDA aspirating | E3: Novec 1230 gas | F3: Armed (auto) | G3: 46281
A4: MH-DC-001-FZ-03 | B4: MH-DC-001 | C4: MH-DC-001-F1-R1 | D4: VESDA aspirating | E4: Inert gas (IG-541) | F4: Armed (auto) | G4: 46200
A5: MH-DC-001-FZ-04 | B5: MH-DC-001 | C5: MH-DC-001-F1-R2 | D5: VESDA aspirating | E5: Novec 1230 gas | F5: Armed (auto) | G5: 46242
A6: MH-DC-002-FZ-01 | B6: MH-DC-002 | C6: MH-DC-002-F0-R1 | D6: VESDA aspirating | E6: Novec 1230 gas | F6: Armed (auto) | G6: 46209
A7: MH-DC-002-FZ-02 | B7: MH-DC-002 | C7: MH-DC-002-F0-R2 | D7: VESDA aspirating | E7: Inert gas (IG-541) | F7: Armed (auto) | G7: 46227
A8: MH-DC-002-FZ-03 | B8: MH-DC-002 | C8: MH-DC-002-F1-R1 | D8: VESDA aspirating | E8: Novec 1230 gas | F8: Armed (auto) | G8: 46256
A9: MH-DC-002-FZ-04 | B9: MH-DC-002 | C9: MH-DC-002-F1-R2 | D9: VESDA aspirating | E9: Novec 1230 gas | F9: Armed (auto) | G9: 46241

Sheet Leak_Detection
A1: zone_id * | B1: site_id * | C1: room_id * | D1: guards * | E1: length_m | F1: last_test
A2: MH-DC-001-LK-01 | B2: MH-DC-001 | C2: MH-DC-001-F0-R1 | D2: Under CRAH-11, CRAH-15 | E2: 12 | F2: 46128
A3: MH-DC-001-LK-02 | B3: MH-DC-001 | C3: MH-DC-001-F0-R2 | D3: Under CRAH-12, CRAH-16 | E3: 16 | F3: 46208
A4: MH-DC-001-LK-03 | B4: MH-DC-001 | C4: MH-DC-001-F1-R1 | D4: Under CRAH-13, CRAH-17 | E4: 16 | F4: 46239
A5: MH-DC-001-LK-04 | B5: MH-DC-001 | C5: MH-DC-001-F1-R2 | D5: Under CRAH-14, CRAH-18 | E5: 12 | F5: 46146
A6: MH-DC-002-LK-01 | B6: MH-DC-002 | C6: MH-DC-002-F0-R1 | D6: Under CRAH-11, CRAH-15 | E6: 14 | F6: 46181
A7: MH-DC-002-LK-02 | B7: MH-DC-002 | C7: MH-DC-002-F0-R2 | D7: Under CRAH-12, CRAH-16 | E7: 18 | F7: 46266
A8: MH-DC-002-LK-03 | B8: MH-DC-002 | C8: MH-DC-002-F1-R1 | D8: Under CRAH-13, CRAH-17 | E8: 18 | F8: 46246
A9: MH-DC-002-LK-04 | B9: MH-DC-002 | C9: MH-DC-002-F1-R2 | D9: Under CRAH-14, CRAH-18 | E9: 16 | F9: 46217

Sheet Access_Points
A1: door_id * | B1: site_id * | C1: name * | D1: room_id | E1: kind * | F1: reader * | G1: tenant_customer_id
A2: MH-DC-001-DR-01 | B2: MH-DC-001 | C2: Main entrance · mantrap | E2: Building entry | F2: Card + biometric
A3: MH-DC-001-DR-02 | B3: MH-DC-001 | C3: Data hall 1 door | D3: MH-DC-001-F0-R1 | E3: Data hall door | F3: Card + biometric
A4: MH-DC-001-DR-03 | B4: MH-DC-001 | C4: Data hall 2 door | D4: MH-DC-001-F0-R2 | E4: Data hall door | F4: Card + biometric
A5: MH-DC-001-DR-04 | B5: MH-DC-001 | C5: Data hall 3 door | D5: MH-DC-001-F1-R1 | E5: Data hall door | F5: Card + biometric
A6: MH-DC-001-DR-05 | B6: MH-DC-001 | C6: GPU hall door | D6: MH-DC-001-F1-R2 | E6: Data hall door | F6: Card + biometric
A7: MH-DC-002-DR-01 | B7: MH-DC-002 | C7: Main entrance · mantrap | E7: Building entry | F7: Card + biometric
A8: MH-DC-002-DR-02 | B8: MH-DC-002 | C8: Data hall 1 door | D8: MH-DC-002-F0-R1 | E8: Data hall door | F8: Card + biometric
A9: MH-DC-002-DR-03 | B9: MH-DC-002 | C9: Data hall 2 door | D9: MH-DC-002-F0-R2 | E9: Data hall door | F9: Card + biometric
A10: MH-DC-002-DR-04 | B10: MH-DC-002 | C10: Data hall 3 door | D10: MH-DC-002-F1-R1 | E10: Data hall door | F10: Card + biometric
A11: MH-DC-002-DR-05 | B11: MH-DC-002 | C11: GPU hall door | D11: MH-DC-002-F1-R2 | E11: Data hall door | F11: Card + biometric

Sheet Support_Contracts
A1: contract_id * | B1: site_id * | C1: vendor * | D1: level * | E1: start | F1: expires *
A2: AMC-MH-94990 | B2: MH-DC-001 | C2: JUNIPER | D2: 24×7×4 | F2: 46788
A3: AMC-MH-43694 | B3: MH-DC-001 | C3: CISCO | D3: 24×7×4 | F3: 46390
A4: AMC-MH-45067 | B4: MH-DC-001 | C4: NOKIA | D4: 24×7×4 | F4: 46340
A5: AMC-MH-60459 | B5: MH-DC-001 | C5: CISCO | D5: 8×5 NBD | F5: 46810
A6: AMC-MH-71915 | B6: MH-DC-001 | C6: JUNIPER | D6: 8×5 NBD | F6: 46902
A7: AMC-MH-33776 | B7: MH-DC-001 | C7: ARISTA | D7: 8×5 NBD | F7: 46799
A8: AMC-MH-31357 | B8: MH-DC-001 | C8: DELL | D8: NBD | F8: 46410
A9: AMC-MH-94491 | B9: MH-DC-001 | C9: SUPERMICRO | D9: NBD | F9: 46428
A10: AMC-MH-91907 | B10: MH-DC-001 | C10: HPE | D10: NBD | F10: 46430
A11: AMC-MH-81693 | B11: MH-DC-001 | C11: PURE | D11: 24×7×4 | F11: 46505
A12: AMC-MH-24381 | B12: MH-DC-001 | C12: NETAPP | D12: 24×7×4 | F12: 46944
A13: AMC-MH-72444 | B13: MH-DC-001 | C13: DELL | D13: 24×7×4 | F13: 46834
... A31: AMC-MH-16977 | B31: MH-DC-002 | C31: NVIDIA | D31: 24×7×4 | F31: 46444

Sheet Asset_Lifecycle
A1: device_id * | B1: installed * | C1: warranty_end * | D1: contract_id
A2: MH-DC-001-PE-T4-01 | B2: 45497 | C2: 47322 | D2: AMC-MH-94990
A3: MH-DC-001-PE-T4-02 | B3: 45997 | C3: 47092 | D3: AMC-MH-94990
A4: MH-DC-001-PE-T4-03 | B4: 44164 | C4: 45989 | D4: AMC-MH-43694
A5: MH-DC-001-PE-T4-04 | B5: 43921 | C5: 45016 | D5: AMC-MH-43694
A6: MH-DC-001-FW-01 | B6: 44379 | C6: 46204
A7: MH-DC-001-FW-02 | B7: 44171 | C7: 45266
A8: MH-DC-001-OLA-01 | B8: 46061 | C8: 47156 | D8: AMC-MH-45067
A9: MH-DC-001-OLA-02 | B9: 46141 | C9: 47966 | D9: AMC-MH-45067
A10: MH-DC-001-SPINE-01 | B10: 46239 | C10: 47334 | D10: AMC-MH-43694
A11: MH-DC-001-SPINE-02 | B11: 46218 | C11: 48043 | D11: AMC-MH-43694
A12: MH-DC-001-SPINE-03 | B12: 45441 | C12: 46536 | D12: AMC-MH-43694
A13: MH-DC-001-SPINE-04 | B13: 46124 | C13: 47949 | D13: AMC-MH-43694
A14: MH-DC-001-LEAF-01 | B14: 44211 | C14: 45306
A15: MH-DC-001-LEAF-02 | B15: 43464 | C15: 44559
A16: MH-DC-001-LEAF-03 | B16: 45460 | C16: 47285 | D16: AMC-MH-60459
A17: MH-DC-001-LEAF-04 | B17: 46147 | C17: 47242 | D17: AMC-MH-71915
A18: MH-DC-001-TOR-001 | B18: 44265 | C18: 45360
A19: MH-DC-001-TOR-002 | B19: 43697 | C19: 44792
A20: MH-DC-001-TOR-003 | B20: 45098 | C20: 46923 | D20: AMC-MH-33776
A21: MH-DC-001-TOR-004 | B21: 44709 | C21: 46534 | D21: AMC-MH-33776
A22: MH-DC-001-TOR-005 | B22: 45018 | C22: 46113 | D22: AMC-MH-60459
A23: MH-DC-001-TOR-006 | B23: 46044 | C23: 47869 | D23: AMC-MH-33776
A24: MH-DC-001-TOR-007 | B24: 46043 | C24: 47138 | D24: AMC-MH-71915
A25: MH-DC-001-TOR-008 | B25: 46251 | C25: 47346 | D25: AMC-MH-60459
A26: MH-DC-001-TOR-009 | B26: 46089 | C26: 47184 | D26: AMC-MH-33776
A27: MH-DC-001-TOR-010 | B27: 46123 | C27: 47948 | D27: AMC-MH-33776
A28: MH-DC-001-TOR-011 | B28: 46048 | C28: 47873 | D28: AMC-MH-60459
A29: MH-DC-001-TOR-012 | B29: 46252 | C29: 47347 | D29: AMC-MH-33776
A30: MH-DC-001-TOR-013 | B30: 45129 | C30: 46224 | D30: AMC-MH-33776
A31: MH-DC-001-TOR-014 | B31: 46246 | C31: 47341 | D31: AMC-MH-60459
... A35: MH-DC-001-TOR-018 | B35: 46129 | C35: 47224 | D35: AMC-MH-71915
A36: MH-DC-001-CMP-0001 | B36: 44222 | C36: 45317
A37: MH-DC-001-CMP-0002 | B37: 44218 | C37: 45313
A38: MH-DC-001-CMP-0003 | B38: 44173 | C38: 45998 | D38: AMC-MH-31357
A39: MH-DC-001-CMP-0004 | B39: 44406 | C39: 46231
A40: MH-DC-001-CMP-0005 | B40: 44038 | C40: 45863
A41: MH-DC-001-CMP-0006 | B41: 43753 | C41: 44848 | D41: AMC-MH-94491
A42: MH-DC-001-CMP-0007 | B42: 43841 | C42: 44936
A43: MH-DC-001-CMP-0008 | B43: 43802 | C43: 44897
A44: MH-DC-001-CMP-0009 | B44: 44201 | C44: 46026 | D44: AMC-MH-94491
A45: MH-DC-001-CMP-0010 | B45: 43844 | C45: 44939
A46: MH-DC-001-CMP-0011 | B46: 43789 | C46: 44884
A47: MH-DC-001-CMP-0012 | B47: 43921 | C47: 45746 | D47: AMC-MH-94491
A48: MH-DC-001-CMP-0013 | B48: 44076 | C48: 45901 | D48: AMC-MH-31357
A49: MH-DC-001-CMP-0014 | B49: 43461 | C49: 45286 | D49: AMC-MH-94491
A50: MH-DC-001-CMP-0015 | B50: 43922 | C50: 45747 | D50: AMC-MH-94491
A51: MH-DC-001-CMP-0016 | B51: 44243 | C51: 45338
A52: MH-DC-001-CMP-0017 | B52: 43977 | C52: 45072
A53: MH-DC-001-CMP-0018 | B53: 44358 | C53: 45453
A54: MH-DC-001-CMP-0019 | B54: 44375 | C54: 45470 | D54: AMC-MH-94491
A55: MH-DC-001-CMP-0020 | B55: 43408 | C55: 44503 | D55: AMC-MH-94491
A56: MH-DC-001-CMP-0021 | B56: 43839 | C56: 45664 | D56: AMC-MH-91907
A57: MH-DC-001-CMP-0022 | B57: 43896 | C57: 45721 | D57: AMC-MH-94491
A58: MH-DC-001-CMP-0023 | B58: 43978 | C58: 45073
A59: MH-DC-001-CMP-0024 | B59: 43404 | C59: 44499
A60: MH-DC-001-CMP-0025 | B60: 44182 | C60: 46007
A61: MH-DC-001-CMP-0026 | B61: 43889 | C61: 44984
A62: MH-DC-001-CMP-0027 | B62: 44231 | C62: 45326 | D62: AMC-MH-91907
A63: MH-DC-001-CMP-0028 | B63: 43822 | C63: 45647 | D63: AMC-MH-91907
A64: MH-DC-001-CMP-0029 | B64: 44045 | C64: 45140 | D64: AMC-MH-94491
A65: MH-DC-001-CMP-0030 | B65: 44005 | C65: 45100
A66: MH-DC-001-CMP-0031 | B66: 44280 | C66: 45375
A67: MH-DC-001-CMP-0032 | B67: 43684 | C67: 45509 | D67: AMC-MH-31357
A68: MH-DC-001-CMP-0033 | B68: 43986 | C68: 45081 | D68: AMC-MH-31357
A69: MH-DC-001-CMP-0034 | B69: 43596 | C69: 45421 | D69: AMC-MH-91907
A70: MH-DC-001-CMP-0035 | B70: 44240 | C70: 45335 | D70: AMC-MH-31357
A71: MH-DC-001-CMP-0036 | B71: 44276 | C71: 46101
A72: MH-DC-001-CMP-0037 | B72: 43962 | C72: 45057
A73: MH-DC-001-CMP-0038 | B73: 44178 | C73: 45273
A74: MH-DC-001-CMP-0039 | B74: 44445 | C74: 45540
A75: MH-DC-001-CMP-0040 | B75: 43958 | C75: 45783
A76: MH-DC-001-CMP-0041 | B76: 43772 | C76: 44867
A77: MH-DC-001-CMP-0042 | B77: 43397 | C77: 44492
A78: MH-DC-001-CMP-0043 | B78: 44169 | C78: 45264
A79: MH-DC-001-CMP-0044 | B79: 43880 | C79: 44975 | D79: AMC-MH-91907
A80: MH-DC-001-CMP-0045 | B80: 43641 | C80: 45466 | D80: AMC-MH-91907
A81: MH-DC-001-CMP-0046 | B81: 44794 | C81: 45889 | D81: AMC-MH-91907
A82: MH-DC-001-CMP-0047 | B82: 45189 | C82: 47014 | D82: AMC-MH-31357
A83: MH-DC-001-CMP-0048 | B83: 46090 | C83: 47915 | D83: AMC-MH-91907
A84: MH-DC-001-CMP-0049 | B84: 46245 | C84: 48070 | D84: AMC-MH-94491
A85: MH-DC-001-CMP-0050 | B85: 46245 | C85: 47340 | D85: AMC-MH-94491
A86: MH-DC-001-CMP-0051 | B86: 46021 | C86: 47116 | D86: AMC-MH-91907
A87: MH-DC-001-CMP-0052 | B87: 45473 | C87: 47298 | D87: AMC-MH-94491
A88: MH-DC-001-CMP-0053 | B88: 46069 | C88: 47164 | D88: AMC-MH-94491
A89: MH-DC-001-CMP-0054 | B89: 45913 | C89: 47738 | D89: AMC-MH-31357
A90: MH-DC-001-CMP-0055 | B90: 46053 | C90: 47148 | D90: AMC-MH-94491
... A356: MH-DC-002-PE-T4-04 | B356: 43940 | C356: 45765 | D356: AMC-MH-96075
A357: MH-DC-002-FW-01 | B357: 43969 | C357: 45064
A358: MH-DC-002-OLA-01 | B358: 46218 | C358: 47313 | D358: AMC-MH-82686
A359: MH-DC-002-OLA-02 | B359: 45697 | C359: 47522 | D359: AMC-MH-36358
A360: MH-DC-002-SPINE-01 | B360: 45189 | C360: 46284 | D360: AMC-MH-69950
A361: MH-DC-002-SPINE-02 | B361: 45183 | C361: 47008 | D361: AMC-MH-69950
A362: MH-DC-002-SPINE-03 | B362: 45419 | C362: 46514 | D362: AMC-MH-69950
A363: MH-DC-002-SPINE-04 | B363: 45935 | C363: 47760 | D363: AMC-MH-69950
A364: MH-DC-002-LEAF-01 | B364: 44447 | C364: 46272
A365: MH-DC-002-LEAF-02 | B365: 45967 | C365: 47062 | D365: AMC-MH-56633
A366: MH-DC-002-LEAF-03 | B366: 46005 | C366: 47830 | D366: AMC-MH-19534
A367: MH-DC-002-LEAF-04 | B367: 45705 | C367: 47530 | D367: AMC-MH-98078
A368: MH-DC-002-TOR-001 | B368: 43519 | C368: 44614
...

Sheet Model_Lifecycle
A1: vendor * | B1: model * | C1: end_of_sale * | D1: end_of_support *
A2: JUNIPER | B2: MX204 | C2: 47669 | D2: 49494
A3: CISCO | B3: ASR 9006 | C3: 44796 | D3: 46621
A4: FORTINET | B4: FortiGate 3700F | C4: 44286 | D4: 46111
A5: NOKIA | B5: 1830 PSS-16II | C5: 47449 | D5: 49274
A6: CISCO | B6: Nexus 9364D | C6: 47343 | D6: 49168
A7: JUNIPER | B7: QFX5100-48S | C7: 44396 | D7: 46146
A8: CISCO | B8: Nexus 9372PX | C8: 43596 | D8: 45396
A9: CISCO | B9: Nexus 93180YC | C9: 47433 | D9: 49258
A10: JUNIPER | B10: QFX5120-48Y | C10: 47839 | D10: 49664
A11: CISCO | B11: Nexus 3172PQ | C11: 43896 | D11: 45726
A12: ARISTA | B12: 7050SX-64 | C12: 43796 | D12: 45596
A13: ARISTA | B13: 7050SX3-48YC | C13: 47774 | D13: 49599
... A30: SUPERMICRO | B30: SYS-821GE-TNHR (8×H100) | C30: 47431 | D30: 49256

Sheet Spares
A1: site_id * | B1: part * | C1: fits | D1: on_hand * | E1: min_level *
A2: MH-DC-001 | B2: NOKIA fan module | C2: NOKIA | D2: 0 | E2: 1
A3: MH-DC-001 | B3: HPE power supply | C3: HPE servers | D3: 5 | E3: 5
A4: MH-DC-001 | B4: NVMe 3.84 TB | C4: servers | D4: 24 | E4: 23
A5: MH-DC-001 | B5: SUPERMICRO power supply | C5: SUPERMICRO servers | D5: 6 | E5: 6
A6: MH-DC-001 | B6: ARISTA fan module | C6: ARISTA | D6: 3 | E6: 1
A7: MH-DC-001 | B7: ARISTA power supply | C7: ARISTA network | D7: 1 | E7: 1
A8: MH-DC-001 | B8: CISCO fan module | C8: CISCO | D8: 3 | E8: 1
A9: MH-DC-001 | B9: CISCO power supply | C9: CISCO network | D9: 2 | E9: 1
A10: MH-DC-001 | B10: DELL fan module | C10: DELL | D10: 4 | E10: 2
A11: MH-DC-001 | B11: DELL power supply | C11: DELL servers | D11: 9 | E11: 5
A12: MH-DC-001 | B12: FORTINET fan module | C12: FORTINET | D12: 4 | E12: 1
A13: MH-DC-001 | B13: FORTINET power supply | C13: FORTINET network | D13: 4 | E13: 1
... A51: MH-DC-002 | B51: SUPERMICRO power supply | C51: SUPERMICRO servers | D51: 4 | E51: 3

Sheet PM_Plan
A1: task_id * | B1: site_id * | C1: asset_id * | D1: kind * | E1: task * | F1: interval_days * | G1: last_done * | H1: owner
A2: MH-DC-001-PM-024 | B2: MH-DC-001 | C2: MH-DC-001-LV | D2: Electrical | E2: Annual thermography and ATS transfer test | F2: 365 | G2: 45832 | H2: Sarah Chen
A3: MH-DC-001-PM-001 | B3: MH-DC-001 | C3: MH-DC-001-UPS-1 | D3: UPS | E3: Quarterly inspection and thermal scan | F3: 91 | G3: 46183 | H3: Anil Kulkarni
A4: MH-DC-001-PM-009 | B4: MH-DC-001 | C4: MH-DC-001-DG | D4: Generator | E4: Monthly on-load run | F4: 30 | G4: 46257 | H4: Sarah Chen
A5: MH-DC-001-PM-022 | B5: MH-DC-001 | C5: MH-DC-001-FZ-03 | D5: Fire | E5: Gas suppression inspection | F5: 91 | G5: 46200 | H5: Mike Johnson
A6: MH-DC-001-PM-010 | B6: MH-DC-001 | C6: MH-DC-001-DG | D6: Generator | E6: DG load-bank test — 125 kVA set (booked in place of: annual load-bank test) | F6: 365 | G6: 46195 | H6: Anil Kulkarni
A7: MH-DC-001-PM-014 | B7: MH-DC-001 | C7: MH-DC-001-CRAH-13 | D7: Cooling | E7: Filter change and coil clean | F7: 91 | G7: 46218 | H7: Sarah Chen
A8: MH-DC-001-PM-007 | B8: MH-DC-001 | C8: MH-DC-001-UPS-4 | D8: UPS | E8: Quarterly inspection and thermal scan | F8: 91 | G8: 46220 | H8: David Kim
A9: MH-DC-001-PM-005 | B9: MH-DC-001 | C9: MH-DC-001-UPS-3 | D9: UPS | E9: Quarterly inspection and thermal scan | F9: 91 | G9: 46223 | H9: David Kim
A10: MH-DC-001-PM-012 | B10: MH-DC-001 | C10: MH-DC-001-CRAH-11 | D10: Cooling | E10: Filter change and coil clean | F10: 91 | G10: 46224 | H10: Anil Kulkarni
A11: MH-DC-001-PM-019 | B11: MH-DC-001 | C11: MH-DC-001-CRAH-18 | D11: Cooling | E11: Filter change and coil clean | F11: 91 | G11: 46233 | H11: Sneha Patil
A12: MH-DC-001-PM-020 | B12: MH-DC-001 | C12: MH-DC-001-FZ-01 | D12: Fire | E12: Gas suppression inspection | F12: 91 | G12: 46233 | H12: Vikram Singh
A13: MH-DC-001-PM-023 | B13: MH-DC-001 | C13: MH-DC-001-FZ-04 | D13: Fire | E13: Gas suppression inspection | F13: 91 | G13: 46242 | H13: Rahul Deshpande
... A51: MH-DC-002-PM-025 | B51: MH-DC-002 | C51: MH-DC-002-PDU | D51: Electrical | E51: Annual PDU thermography | F51: 365 | G51: 46212 | H51: Meera Iyer

Sheet On_Call
A1: region * | B1: role * | C1: name * | D1: tier * | E1: escalate_after_min * | F1: phone
A2: West | B2: NOC shift lead | C2: Sarah Chen | D2: 1 | E2: 15
A3: West | B3: Network engineer | C3: Meera Iyer | D3: 2 | E3: 30
A4: West | B4: Facility engineer | C4: Priya Nair | D4: 2 | E4: 30
A5: West | B5: Field technician | C5: David Kim | D5: 2 | E5: 60
A6: West | B6: Duty manager | C6: Vikram Singh | D6: 3 | E6: 60

Sheet Snapshot_Alerts
A1: alert_id | B1: site_id | C1: severity | D1: state | E1: title | F1: source | G1: category | H1: scope | I1: device_or_node | J1: if_name | K1: link_or_rack | L1: raised_at | M1: incident_id
A2: ALM-1930 | B2: MH-DC-001 | C2: critical | D2: active | E2: Interface Flapping Detected | F2: Interface | G2: Network | H2: edge | I2: MH-DC-001-PE-T4-01 | J2: xe-0/0/3 | L2: 2026-10-01 07:07 | M2: INC-0001
A3: ALM-1831 | B3: MH-DC-001 | C3: major | D3: active | E3: High CPU Utilization | F3: CPU | G3: Performance | H3: site | I3: MH-DC-001-PE-T4-01 | L3: 2026-10-01 06:52 | M3: INC-0001
A4: ALM-1774 | B4: MH-DC-001 | C4: major | D4: active | E4: Link Degradation | F4: Link | G4: Performance | H4: edge | I4: MH-DC-001-PE-T4-01 | J4: xe-0/0/3 | L4: 2026-10-01 04:52 | M4: INC-0001
A5: ALM-1702 | B5: MH-DC-001 | C5: minor | D5: active | E5: Optical Rx Power Low | F5: Interface | G5: Network | H5: edge | I5: MH-DC-001-PE-T4-01 | J5: xe-0/0/3 | L5: 2026-10-01 04:18 | M5: INC-0001
A6: ALM-1655 | B6: MH-DC-001 | C6: minor | D6: active | E6: BGP Peer Idle | F6: Protocol | G6: Network | H6: site | I6: MH-DC-001-PE-T4-01 | L6: 2026-10-01 02:45
A7: ALM-1610 | B7: MH-DC-001 | C7: minor | D7: active | E7: Temperature Warning | F7: Environment | G7: Device | H7: site | I7: MH-DC-001-PE-T4-01 | L7: 2026-09-30 05:32
A8: ALM-1598 | B8: MH-DC-001 | C8: minor | D8: active | E8: OSPF Neighbour in INIT | F8: Protocol | G8: Network | H8: site | I8: MH-DC-001-PE-T4-01 | L8: 2026-09-30 17:11
A9: ALM-1001 | B9: MH-DC-001 | C9: minor | D9: active | E9: OSPF Neighbour Down | F9: Protocol | G9: Network | H9: site | I9: MH-DC-001-PE-T4-02 | K9: LNK-00017 | L9: 2026-09-30 05:21
A10: ALM-1002 | B10: MH-DC-001 | C10: major | D10: acknowledged | E10: Link Down | F10: Link | G10: Network | H10: site | I10: MH-DC-001-CMP-0041 | J10: eth0 | K10: LNK-00185 | L10: 2026-09-30 19:20
A11: ALM-1003 | B11: MH-DC-002 | C11: major | D11: active | E11: Link Down | F11: Link | G11: Network | H11: site | I11: MH-DC-002-CMP-0003 | J11: eth0 | K11: LNK-00641 | L11: 2026-10-01 00:40 | M11: INC-0022
A12: ALM-1004 | B12: MH-DC-002 | C12: major | D12: acknowledged | E12: Link Down | F12: Link | G12: Network | H12: site | I12: MH-DC-002-STO-021 | J12: eth1 | K12: LNK-00960 | L12: 2026-10-01 01:33 | M12: INC-0022
A13: ALM-1057 | B13: MH-DC-002 | C13: minor | D13: active | E13: BGP Peer Idle | F13: Protocol | G13: Network | H13: edge | I13: MH-DC-002-PE-T4-03 | K13: LNK-12892 | L13: 2026-09-30 08:00
A14: ALM-1065 | B14: MH-DC-001 | C14: warning | D14: active | E14: Configuration Drift | F14: Discovery | G14: Device | H14: site | I14: MH-DC-001-LEAF-02 | L14: 2026-09-26 19:43
A15: ALM-1066 | B15: MH-DC-001 | C15: warning | D15: active | E15: Configuration Drift | F15: Discovery | G15: Device | H15: site | I15: MH-DC-001-TOR-003 | L15: 2026-09-30 07:18
A16: ALM-1067 | B16: MH-DC-001 | C16: warning | D16: active | E16: Configuration Drift | F16: Discovery | G16: Device | H16: site | I16: MH-DC-001-TOR-007 | L16: 2026-09-30 07:16
A17: ALM-1068 | B17: MH-DC-001 | C17: minor | D17: active | E17: Disk Failure Predicted | F17: Environment | G17: Device | H17: site | I17: MH-DC-001-CMP-0012 | L17: 2026-09-30 14:14
A18: ALM-1069 | B18: MH-DC-001 | C18: major | D18: active | E18: Power Supply Fault | F18: Power | G18: Device | H18: site | I18: MH-DC-001-CMP-0012 | L18: 2026-09-29 23:23
A19: ALM-1070 | B19: MH-DC-001 | C19: minor | D19: active | E19: Memory ECC Errors | F19: Environment | G19: Device | H19: site | I19: MH-DC-001-CMP-0013 | L19: 2026-10-01 06:21
A20: ALM-1071 | B20: MH-DC-001 | C20: warning | D20: active | E20: Configuration Drift | F20: Discovery | G20: Device | H20: site | I20: MH-DC-001-CMP-0036 | L20: 2026-09-26 15:03
A21: ALM-1072 | B21: MH-DC-001 | C21: minor | D21: active | E21: Disk Failure Predicted | F21: Environment | G21: Device | H21: site | I21: MH-DC-001-CMP-0041 | L21: 2026-09-30 20:09
A22: ALM-1073 | B22: MH-DC-001 | C22: warning | D22: active | E22: Configuration Drift | F22: Discovery | G22: Device | H22: site | I22: MH-DC-001-CMP-0041 | L22: 2026-09-26 18:28
A23: ALM-1074 | B23: MH-DC-001 | C23: minor | D23: active | E23: High Memory Utilization | F23: CPU | G23: Performance | H23: site | I23: MH-DC-001-CMP-0044 | L23: 2026-09-30 18:57
A24: ALM-1075 | B24: MH-DC-001 | C24: minor | D24: active | E24: Disk Failure Predicted | F24: Environment | G24: Device | H24: site | I24: MH-DC-001-CMP-0047 | L24: 2026-09-29 04:57
A25: ALM-1076 | B25: MH-DC-001 | C25: warning | D25: active | E25: Configuration Drift | F25: Discovery | G25: Device | H25: site | I25: MH-DC-001-CMP-0054 | L25: 2026-09-27 01:16
... A42: ALM-1093 | B42: MH-DC-001 | C42: warning | D42: active | E42: Configuration Drift | F42: Discovery | G42: Device | H42: site | I42: MH-DC-001-CMP-0136 | L42: 2026-09-26 21:41
A43: ALM-1094 | B43: MH-DC-001 | C43: critical | D43: active | E43: Device Unreachable | F43: Interface | G43: Network | H43: site | I43: MH-DC-001-CMP-0144 | L43: 2026-10-01 05:28 | M43: INC-0021
A44: ALM-1095 | B44: MH-DC-001 | C44: minor | D44: active | E44: Memory ECC Errors | F44: Environment | G44: Device | H44: site | I44: MH-DC-001-CMP-0144 | L44: 2026-09-30 20:25
A45: ALM-1096 | B45: MH-DC-001 | C45: major | D45: active | E45: Power Supply Fault | F45: Power | G45: Device | H45: site | I45: MH-DC-001-CMP-0146 | L45: 2026-10-01 00:02
A46: ALM-1097 | B46: MH-DC-001 | C46: minor | D46: active | E46: High Memory Utilization | F46: CPU | G46: Performance | H46: site | I46: MH-DC-001-CMP-0156 | L46: 2026-10-01 05:45
A47: ALM-1098 | B47: MH-DC-001 | C47: minor | D47: active | E47: Memory ECC Errors | F47: Environment | G47: Device | H47: site | I47: MH-DC-001-CMP-0158 | L47: 2026-09-29 11:00
A48: ALM-1099 | B48: MH-DC-001 | C48: warning | D48: active | E48: Configuration Drift | F48: Discovery | G48: Device | H48: site | I48: MH-DC-001-CMP-0159 | L48: 2026-09-28 02:31
A49: ALM-1100 | B49: MH-DC-001 | C49: minor | D49: active | E49: Memory ECC Errors | F49: Environment | G49: Device | H49: site | I49: MH-DC-001-CMP-0167 | L49: 2026-09-30 20:54
A50: ALM-1101 | B50: MH-DC-001 | C50: warning | D50: active | E50: Configuration Drift | F50: Discovery | G50: Device | H50: site | I50: MH-DC-001-CMP-0171 | L50: 2026-09-30 01:49
A51: ALM-1102 | B51: MH-DC-001 | C51: warning | D51: active | E51: NTP Offset Drift | F51: Protocol | G51: Network | H51: site | I51: MH-DC-001-CMP-0172 | L51: 2026-09-30 01:27
A52: ALM-1103 | B52: MH-DC-001 | C52: minor | D52: active | E52: Disk Failure Predicted | F52: Environment | G52: Device | H52: site | I52: MH-DC-001-CMP-0173 | L52: 2026-09-28 15:41
A53: ALM-1104 | B53: MH-DC-001 | C53: warning | D53: active | E53: Configuration Drift | F53: Discovery | G53: Device | H53: site | I53: MH-DC-001-CMP-0179 | L53: 2026-09-28 22:57
A54: ALM-1105 | B54: MH-DC-001 | C54: major | D54: active | E54: Power Supply Fault | F54: Power | G54: Device | H54: site | I54: MH-DC-001-CMP-0181 | L54: 2026-10-01 02:08
A55: ALM-1106 | B55: MH-DC-001 | C55: minor | D55: acknowledged | E55: High Memory Utilization | F55: CPU | G55: Performance | H55: site | I55: MH-DC-001-CMP-0188 | L55: 2026-09-29 22:57
... A72: ALM-1123 | B72: MH-DC-002 | C72: minor | D72: acknowledged | E72: High Memory Utilization | F72: CPU | G72: Performance | H72: site | I72: MH-DC-002-STO-017 | L72: 2026-09-30 15:19
A73: ALM-1503 | B73: MH-DC-001 | C73: major | D73: active | E73: Collector Stale | F73: Discovery | G73: Network | H73: dependency | L73: 2026-10-01 04:38
A74: ALM-1510 | B74: MH-DC-001 | C74: minor | D74: active | E74: High CPU Utilization | F74: CPU | G74: Performance | H74: downstream | I74: MH-POP-001-AGG-01 | L74: 2026-10-01 05:01
A75: ALM-1511 | B75: MH-DC-001 | C75: minor | D75: active | E75: High CPU Utilization | F75: CPU | G75: Performance | H75: downstream | I75: MH-POP-002-AGG-01 | L75: 2026-09-30 17:28
A76: ALM-1512 | B76: MH-DC-001 | C76: critical | D76: active | E76: Device Unreachable | F76: Interface | G76: Network | H76: downstream | I76: MH-POP-001-AGG-01 | L76: 2026-09-30 19:20
A77: ALM-1513 | B77: MH-DC-001 | C77: critical | D77: active | E77: Device Unreachable | F77: Interface | G77: Network | H77: downstream | I77: MH-ST-0001-CSR-01 | L77: 2026-09-30 19:20
A78: ALM-1514 | B78: MH-DC-001 | C78: critical | D78: active | E78: Device Unreachable | F78: Interface | G78: Network | H78: downstream | I78: MH-ST-0002-CSR-01 | L78: 2026-09-30 19:20
A79: ALM-1515 | B79: MH-DC-001 | C79: critical | D79: active | E79: Device Unreachable | F79: Interface | G79: Network | H79: downstream | I79: MH-ST-0003-CSR-01 | L79: 2026-09-30 19:20
A80: ALM-1516 | B80: MH-DC-002 | C80: critical | D80: active | E80: Mains Power Failure | F80: Power | G80: Facility | H80: downstream | I80: MH-POP-001-AGG-01 | L80: 2026-09-30 18:10
A81: ALM-1517 | B81: MH-DC-002 | C81: critical | D81: active | E81: Device Unreachable | F81: Interface | G81: Network | H81: downstream | I81: MH-POP-001-AGG-01 | L81: 2026-10-01 00:40
A82: ALM-1518 | B82: MH-DC-002 | C82: critical | D82: active | E82: Device Unreachable | F82: Interface | G82: Network | H82: downstream | I82: MH-ST-0001-CSR-01 | L82: 2026-10-01 00:40
A83: ALM-1519 | B83: MH-DC-002 | C83: critical | D83: active | E83: Device Unreachable | F83: Interface | G83: Network | H83: downstream | I83: MH-ST-0002-CSR-01 | L83: 2026-10-01 00:40
A84: ALM-1520 | B84: MH-DC-002 | C84: critical | D84: active | E84: Device Unreachable | F84: Interface | G84: Network | H84: downstream | I84: MH-ST-0003-CSR-01 | L84: 2026-10-01 00:40
A85: ALM-1628 | B85: MH-DC-001 | C85: major | D85: active | E85: Link Down | F85: Link | G85: Network | H85: edge | I85: MH-DC-001-SPINE-01 | J85: xe-0/0/15 | L85: 2026-10-01 06:15
A86: ALM-1629 | B86: MH-DC-001 | C86: minor | D86: active | E86: Secondary RADIUS Server Unreachable | F86: Security | G86: Network | H86: dependency | I86: AAA-SRV-02 (10.25.25.6) | L86: 2026-10-01 04:50
A87: ALM-1630 | B87: MH-DC-001 | C87: major | D87: active | E87: Shelf Midplane Fault | F87: Environment | G87: Device | H87: site | I87: MH-DC-001-CMP-0005 | L87: 2026-10-01 07:03
A88: ALM-1631 | B88: MH-DC-001 | C88: major | D88: active | E88: Shelf Midplane Fault | F88: Environment | G88: Device | H88: site | I88: MH-DC-001-CMP-0009 | L88: 2026-10-01 07:03
A89: ALM-1632 | B89: MH-DC-001 | C89: critical | D89: active | E89: Host Power Lost | F89: Power | G89: Device | H89: site | I89: MH-DC-001-CMP-0013 | L89: 2026-10-01 07:28
A90: ALM-1641 | B90: MH-DC-002 | C90: minor | D90: active | E90: GPU Temperature High | F90: Environment | G90: Device | H90: site | I90: MH-DC-002-GPU-015 | L90: 2026-10-01 03:17
A91: ALM-1642 | B91: MH-DC-002 | C91: minor | D91: active | E91: GPU Temperature High | F91: Environment | G91: Device | H91: site | I91: MH-DC-002-GPU-019 | L91: 2026-10-01 07:14
A92: ALM-1647 | B92: MH-DC-002 | C92: minor | D92: active | E92: Optical Rx Power Low | F92: Interface | G92: Network | H92: edge | I92: MH-DC-002-PE-T4-02 | J92: xe-0/0/2 | L92: 2026-10-01 01:50

Sheet Snapshot_Incidents
A1: incident_id | B1: site_id | C1: severity | D1: status | E1: type | F1: title | G1: owner | H1: detected_at | I1: resolved_at | J1: alarms | K1: services_hit | L1: customers_hit | M1: revenue_at_risk
A2: INC-0001 | B2: MH-DC-001 | C2: High | D2: Open | E2: Network | F2: Optical degradation on PE-T4-01 xe-0/0/3 — backhaul flapping | G2: Mike Johnson | H2: 2026-10-01 07:08 | J2: 4 | K2: 0 | L2: 0 | M2: 0
A3: INC-0021 | B3: MH-DC-001 | C3: Medium | D3: Open | E3: Network | F3: MH-DC-001-CMP-0144 unreachable | G3: Vikram Singh | H3: 2026-10-01 05:30 | J3: 1 | K3: 0 | L3: 0 | M3: 0
A4: INC-0022 | B4: MH-DC-002 | C4: High | D4: Open | E4: Network | F4: 2 physical links down in MH-DC-002 | G4: Sneha Patil | H4: 2026-10-01 00:41 | J4: 2 | K4: 0 | L4: 0 | M4: 0
A5: INC-0031 | B5: MH-DC-001 | C5: Medium | D5: Resolved | E5: Cooling | F5: GPU hall above 27°C — CRAH filter blocked — MH-DC-001 | G5: Arjun Mehta | H5: 2026-09-29 10:48 | I5: 2026-09-29 16:33 | J5: 0 | K5: 2 | L5: 2 | M5: 0
A6: INC-0035 | B6: MH-DC-002 | C6: Low | D6: Resolved | E6: Cooling | F6: GPU hall above 27°C — CRAH filter blocked — MH-DC-002 | G6: Vikram Singh | H6: 2026-09-19 22:46 | I6: 2026-09-21 23:29 | J6: 0 | K6: 6 | L6: 3 | M6: 0
A7: INC-0042 | B7: MH-DC-001 | C7: High | D7: Closed | E7: Cooling | F7: Chiller pump fault — MH-DC-001 | G7: Mike Johnson | H7: 2026-09-17 14:48 | I7: 2026-09-17 17:11 | J7: 0 | K7: 6 | L7: 1 | M7: 0

Sheet Snapshot_Changes
A1: change_id | B1: site_id | C1: kind | D1: title | E1: status | F1: risk | G1: window_start | H1: window_end | I1: requester | J1: approver | K1: scope
A2: CHG-2001 | B2: MH-DC-001 | C2: Change | D2: Re-patch ODF RACK-D core 7 to PE-T4-01 xe-0/0/3 (new backhaul span) | E2: Completed | F2: Medium | G2: 2026-09-30 16:30 | H2: 2026-09-30 17:30 | I2: Rahul Deshpande | J2: Priya Nair | K2: MH-DC-001-PE-T4-01
A3: CHG-2002 | B3: MH-DC-001 | C3: Change | D3: Junos upgrade 21.4R3-S5.5 → 22.2R3-S2 on MH-DC-001 PE pair | E3: Pending approval | F3: High | G3: 2026-10-03 17:50 | H3: 2026-10-03 21:50 | I3: Arjun Mehta | K3: MH-DC-001-PE-T4-01;MH-DC-001-PE-T4-02
A4: CHG-2003 | B4: MH-DC-001 | C4: Maintenance | D4: DG load-bank test — 125 kVA set | E4: Approved | F4: Low | G4: 2026-10-05 13:50 | H4: 2026-10-05 15:50 | I4: Anil Kulkarni | J4: Kavita Rao

Sheet Snapshot_RMA
A1: rma_id | B1: site_id | C1: device_id | D1: slot | E1: part | F1: vendor_case | G1: status | H1: opened | I1: spare_on_site
A2: RMA-20797 | B2: MH-DC-001 | C2: MH-DC-001-CMP-0012 | D2: PSU2 | E2: Power supply | F2: SUP-4829318 | G2: Part shipped | H2: 2026-09-30 09:50 | I2: Y
A3: RMA-57220 | B3: MH-DC-001 | C3: MH-DC-001-CMP-0012 | D3: DISK2 | E3: NVMe 3.84 TB | F3: SUP-7553402 | G3: Part shipped | H3: 2026-09-30 08:50 | I3: Y
A4: RMA-66643 | B4: MH-DC-001 | C4: MH-DC-001-CMP-0013 | D4: PSU1 | E4: Power supply | F4: DEL-9223955 | G4: Part shipped | H4: 2026-09-30 04:50 | I4: Y
A5: RMA-22006 | B5: MH-DC-001 | C5: MH-DC-001-CMP-0041 | D5: DISK0 | E5: NVMe 3.84 TB | F5: SUP-6124247 | G5: Part shipped | H5: 2026-09-30 09:50 | I5: Y
A6: RMA-34647 | B6: MH-DC-001 | C6: MH-DC-001-CMP-0047 | D6: DISK1 | E6: NVMe 3.84 TB | F6: DEL-1409272 | G6: Engineer booked | H6: 2026-09-29 18:50 | I6: Y
A7: RMA-46506 | B7: MH-DC-001 | C7: MH-DC-001-CMP-0079 | D7: PSU2 | E7: Power supply | F7: DEL-5083844 | G7: Engineer booked | H7: 2026-09-28 22:50 | I7: Y
A8: RMA-24347 | B8: MH-DC-001 | C8: MH-DC-001-CMP-0093 | D8: DISK0 | E8: NVMe 3.84 TB | F8: DEL-7399847 | G8: Engineer booked | H8: 2026-09-29 13:50 | I8: Y
A9: RMA-40755 | B9: MH-DC-001 | C9: MH-DC-001-CMP-0104 | D9: DISK3 | E9: NVMe 3.84 TB | F9: HPE-2968592 | G9: Opened | H9: 2026-10-01 01:50 | I9: Y
A10: RMA-24915 | B10: MH-DC-001 | C10: MH-DC-001-CMP-0109 | D10: PSU1 | E10: Power supply | F10: HPE-3712920 | G10: Part shipped | H10: 2026-09-30 07:50 | I10: Y
A11: RMA-26117 | B11: MH-DC-001 | C11: MH-DC-001-CMP-0114 | D11: PSU1 | E11: Power supply | F11: HPE-2922425 | G11: Engineer booked | H11: 2026-09-29 03:50 | I11: Y
A12: RMA-90444 | B12: MH-DC-001 | C12: MH-DC-001-CMP-0117 | D12: PSU1 | E12: Power supply | F12: SUP-4574989 | G12: Part shipped | H12: 2026-09-30 00:50 | I12: Y
... A23: RMA-38847 | B23: MH-DC-002 | C23: MH-DC-002-CMP-0085 | D23: PSU1 | E23: Power supply | F23: HPE-8364826 | G23: Engineer booked | H23: 2026-09-29 14:50 | I23: Y

Sheet Snapshot_Problems
A1: problem_id | B1: title | C1: type | D1: state | E1: incidents | F1: open | G1: sites | H1: workaround | I1: fix | J1: owner
A2: PRB-6505 | B2: Loss of power at the access rack (PDU breaker) | C2: Network | D2: Investigating | E2: INC-0006;INC-0008;INC-0009;INC-0011;INC-0012;INC-0013;INC-0014;INC-0015;INC-0017;INC-0018;INC-0021 | F2: 11 | G2: UP-DC-007;MH-DC-003;OD-DC-018;PB-DC-012;MH-DC-004;BR-DC-019;AP-DC-010;UP-DC-005;WB-DC-017;MH-DC-001 | H2: Reset the outlet / breaker after checking the cabinet load; the device rides on its other cord | I2: Re-balance the cabinet across phases and both sides; replace the PDU if trips recur | J2: Mike Johnson
A3: PRB-5147 | B3: Common cable tray / ODF fault | C3: Network | D3: Investigating | E3: INC-0005;INC-0007;INC-0019;INC-0022 | F3: 4 | G3: PB-DC-012;RJ-DC-015;WB-DC-016;MH-DC-002 | H3: Move circuits to the diverse route | I3: Repair or replace the trunk; add a second tray route | J3: Priya Nair
A4: PRB-4445 | B4: Optic degradation (SFP lot 22B) | C4: Network | D4: Investigating | E4: INC-0001;INC-0045 | F4: 1 | G4: MH-DC-001;TN-DC-022 | H4: Move traffic to the parallel span; swap the optic from a spare lot and clean the patch | I4: Replace every optic from the affected lot under a vendor field notice; inspect the ODF jumpers | J4: Sneha Patil
A5: PRB-6980 | B5: GPU hall above N°C | C5: Cooling | D5: Known error | E5: INC-0025;INC-0031;INC-0035;INC-0047 | F5: 0 | G5: UP-DC-006;MH-DC-001;MH-DC-002;BR-DC-019 | H5: Keep the spare unit running; portable cooling on standby | I5: Repair the unit and review the maintenance interval | J5: Sarah Chen
A6: PRB-4629 | B6: Chiller pump fault | C6: Cooling | D6: Known error | E6: INC-0033;INC-0042;INC-0049 | F6: 0 | G6: KA-DC-008;MH-DC-001;HR-DC-011 | H6: Keep the spare unit running; portable cooling on standby | I6: Repair the unit and review the maintenance interval | J6: James Wilson

Sheet Snapshot_Orders
A1: order_id | B1: kind | C1: site_id | D1: customer_id | E1: detail | F1: state | G1: opened | H1: due_or_minutes

Sheet Field_Dictionary
A1: Sheet | B1: Column | C1: Required | D1: Type | E1: Allowed values | F1: System field (types.ts) | G1: Description | H1: Example
A2: Sites | B2: site_id | C2: Required | D2: text | F2: Datacenter.id / Location.id | G2: Unique site code, format XX-DC-NNN (XX = state code). Every other sheet points to it. | H2: MH-DC-001
A3: Sites | B3: site_name | C3: Required | D3: text | F3: Datacenter.name | G3: Display name. | H3: MH-DC-001
A4: Sites | B4: operator | C4: Optional | D4: text | F4: (reference only) | G4: Owning company. Not shown in the tool today.
A5: Sites | B5: business_model | C5: Required | D5: list | E5: colocation, neocloud, cloud, enterprise, network | F5: Persona | G5: Sets vocabulary and rack contents: colocation, neocloud (GPU as a service), cloud, enterprise, network (telco). | H5: cloud
A6: Sites | B6: status | C6: Required | D6: list | E6: on-air, in-progress, planned, failed | F6: Datacenter.status | G6: on-air = live; in-progress = being built; planned; failed. | H6: in-progress
A7: Sites | B7: tier | C7: Required | D7: list | E7: Tier II, Tier III, Tier IV | F7: Datacenter.tier | G7: Uptime tier. | H7: Tier III
A8: Sites | B8: category | C8: Required | D8: list | E8: Central, Regional, Edge | F8: Datacenter.category | G8: Central / Regional / Edge. | H8: Central
A9: Sites | B9: region | C9: Required | D9: text | F9: Region.name / Datacenter.regionId | G9: For example West, South, North, East, Central. | H9: West
A10: Sites | B10: state | C10: Required | D10: text | F10: Datacenter.state | G10: State or province. | H10: Maharashtra
A11: Sites | B11: city | C11: Required | D11: text | F11: Datacenter.city | G11: City. | H11: Pune
A12: Sites | B12: address | C12: Required | D12: text | F12: Datacenter.address | G12: Postal address. | H12: Pune Data Park
A13: Sites | B13: latitude | C13: Required | D13: decimal | F13: Datacenter.lat | G13: Decimal degrees (WGS84). Places the pin on the estate map. | H13: 18.593
A14: Sites | B14: longitude | C14: Required | D14: decimal | F14: Datacenter.lng | G14: Decimal degrees (WGS84). | H14: 73.789
A15: Sites | B15: commissioned_on | C15: Optional | D15: date | F15: Datacenter.commissionedOn | G15: Date the site went live. | H15: 2025-05-13
A16: Sites | B16: it_capacity_kw | C16: Required | D16: decimal | F16: Datacenter.power.capacityKw | G16: Design IT load (kW) the site is built for. | H16: 1260
A17: Sites | B17: design_pue | C17: Optional | D17: decimal | F17: Datacenter.power.pue | G17: Design PUE. Live PUE comes from the BMS. | H17: 1.52
A18: Sites | B18: cooling_capacity_kw | C18: Required | D18: decimal | F18: Datacenter.cooling.capacityKw | G18: Total installed cooling capacity (kW). | H18: 990
A19: Sites | B19: cooling_redundancy | C19: Required | D19: list | E19: N, N+1, 2N | F19: Datacenter.cooling.redundancy | G19: N / N+1 / 2N. | H19: N+1
A20: Sites | B20: timezone | C20: Optional | D20: text | F20: (reference only) | G20: IANA timezone, for example Asia/Kolkata. | H20: Asia/Kolkata
A21: Floors | B21: site_id | C21: Required | D21: ref | E21: an ID from Sites | F21: Datacenter.id | G21: Must exist in Sites. | H21: MH-DC-001
A22: Floors | B22: floor_id | C22: Required | D22: text | F22: (key) | G22: Unique within the workbook, for example MP-DC-001-F0. | H22: MH-DC-001-F0
A23: Floors | B23: floor_name | C23: Required | D23: text | F23: Datacenter.floors[].name | G23: As staff call it: Ground, 1st floor… | H23: Ground
A24: Floors | B24: level | C24: Required | D24: integer | F24: (order in the 3D twin) | G24: 0 = ground, 1 = first floor…, −1 = basement. | H24: 0
A25: Rooms | B25: site_id | C25: Required | D25: ref | E25: an ID from Sites | F25: Datacenter.id | H25: MH-DC-001
A26: Rooms | B26: floor_id | C26: Required | D26: ref | E26: an ID from Floors | F26: (key) | G26: Must exist in Floors. | H26: MH-DC-001-F0
A27: Rooms | B27: room_id | C27: Required | D27: text | F27: (key) | G27: Unique within the workbook. | H27: MH-DC-001-F0-R1
A28: Rooms | B28: room_name | C28: Required | D28: text | F28: Datacenter.floors[].rooms[] / Rack.room | G28: Shown in the twin, the racks list and alarm locations. | H28: Data hall 1
A29: Rooms | B29: room_type | C29: Required | D29: list | E29: Data hall, AI hall, Meet-me room, Network room, Plant room, UPS room, Battery room, NOC | F29: (twin layout) | G29: Plant / UPS / battery rooms hold the power plant; halls hold racks. | H29: Data hall
A30: Rooms | B30: area_sqm | C30: Optional | D30: decimal | F30: (reference only) | G30: Floor area.
A31: Rooms | B31: rack_rows | C31: Optional | D31: integer | F31: (twin layout) | G31: Number of rack rows; racks face each other in pairs. | H31: 2
A32: Rooms | B32: containment | C32: Optional | D32: list | E32: Cold aisle, Hot aisle, None | F32: (twin layout) | G32: Aisle containment.
A33: Rooms | B33: cooling_method | C33: Optional | D33: list | E33: Air, Liquid, Hybrid | F33: Rack.liquid | G33: Air, Liquid or Hybrid. | H33: Air
A34: Racks | B34: rack_id | C34: Required | D34: text | F34: Rack.id | G34: Unique, for example MP-DC-001-A01. | H34: MH-DC-001-RACK-A
A35: Racks | B35: site_id | C35: Required | D35: ref | E35: an ID from Sites | F35: Rack.dcId | H35: MH-DC-001
A36: Racks | B36: room_id | C36: Required | D36: ref | E36: an ID from Rooms | F36: Rack.floor / Rack.room | G36: Floor and room come from the Rooms row. | H36: MH-DC-001-F0-R1
A37: Racks | B37: rack_name | C37: Required | D37: text | F37: Rack.name | G37: Label on the cabinet (shown on the 3D twin). | H37: RACK-A
A38: Racks | B38: row | C38: Optional | D38: text | F38: (twin layout) | G38: Row letter or number.
A39: Racks | B39: position | C39: Optional | D39: integer | F39: (twin layout) | G39: Position in the row, 1…n.
A40: Racks | B40: role | C40: Required | D40: list | E40: Core, Meet-me room, Network, Aggregation, Compute, Storage, GPU, Tenant, AI cage | F40: Rack.role | G40: What the cabinet is for. | H40: Core
A41: Racks | B41: height_u | C41: Required | D41: integer | F41: Rack.heightU | G41: Usable rack units (42, 45, 48…). | H41: 45
A42: Racks | B42: power_budget_kw | C42: Required | D42: decimal | F42: Rack.budgetKw | G42: Provisioned power (kW). Live draw comes from the PDUs. | H42: 16
A43: Racks | B43: owner | C43: Required | D43: list | E43: operator, tenant | F43: Rack.owner | G43: operator, or tenant (a leased cabinet: the operator sees power and environment only). | H43: operator
A44: Racks | B44: tenant_customer_id | C44: Conditional | D44: ref | E44: an ID from Customers | F44: Rack.tenantId | G44: Required when owner = tenant.
A45: Racks | B45: contracted_kw | C45: Conditional | D45: decimal | F45: Rack.contractedKw | G45: Required when owner = tenant: the power the tenant has bought.
A46: Racks | B46: density | C46: Optional | D46: list | E46: standard, ai | F46: Rack.density | G46: ai = high-density GPU rack or AI cage. | H46: standard
A47: Racks | B47: liquid_cooled | C47: Optional | D47: list | E47: Y, N | F47: Rack.liquid | G47: Y = direct liquid cooling. | H47: N
A48: Racks | B48: cdu_id | C48: Conditional | D48: ref | E48: an ID from CDUs | F48: AiCage.cduId / Cdu.racks | G48: Required when liquid_cooled = Y.
A49: Racks | B49: pdu_feed_a | C49: Optional | D49: ref | E49: an ID from Power_Feeds | F49: (power path) | G49: Feed powering the A-side PDU. | H49: MH-DC-001-AC-1
A50: Racks | B50: pdu_feed_b | C50: Optional | D50: ref | E50: an ID from Power_Feeds | F50: (power path) | G50: Feed powering the B-side PDU. | H50: MH-DC-001-AC-2
A51: Racks | B51: used_u (calc) | C51: Calculated | D51: formula | F51: Rack.usedU | G51: Calculated: the sum of u_size of the devices in this rack. Don't type it.
A52: Power_Feeds | B52: feed_id | C52: Required | D52: text | F52: PowerFeed.id | G52: Unique, for example MP-DC-001-AC-1. | H52: MH-DC-001-AC-1
A53: Power_Feeds | B53: site_id | C53: Required | D53: ref | E53: an ID from Sites | F53: Datacenter.id | H53: MH-DC-001
A54: Power_Feeds | B54: type | C54: Required | D54: list | E54: AC, DC | F54: PowerFeed.type | G54: AC or DC. | H54: AC
A55: Power_Feeds | B55: source | C55: Required | D55: text | F55: PowerFeed.source | G55: For example "Utility feed A", "Rectifier RECT-01". | H55: Utility feed A
A56: Power_Feeds | B56: rating | C56: Required | D56: text | F56: PowerFeed.rating | G56: For example "630 A · 415 V" or "48 V · 2400 A". | H56: 1227 A · 415 V
A57: Power_Feeds | B57: capacity_kw | C57: Required | D57: decimal | F57: PowerFeed.capacityKw | H57: 882
A58: Power_Feeds | B58: normal_role | C58: Optional | D58: list | E58: Active, Standby | F58: (ATS story) | G58: Active, or Standby (picked up by the ATS). | H58: Active
A59: Power_Feeds | B59: utility_account | C59: Optional | D59: text | F59: (reference only) | G59: Utility connection / account number.
A60: UPS | B60: ups_id | C60: Required | D60: text | F60: UpsUnit.id | H60: MH-DC-001-UPS-1
A61: UPS | B61: site_id | C61: Required | D61: ref | E61: an ID from Sites | F61: Datacenter.id | H61: MH-DC-001
A62: UPS | B62: room_id | C62: Optional | D62: ref | E62: an ID from Rooms | F62: (twin placement) | G62: Room the UPS stands in (shown and clickable in the realistic twin).
A63: UPS | B63: name | C63: Required | D63: text | F63: UpsUnit.name | G63: For example UPS-1. | H63: UPS-1
A64: UPS | B64: vendor | C64: Optional | D64: text | F64: (reference only)
A65: UPS | B65: model | C65: Optional | D65: text | F65: (reference only)
A66: UPS | B66: serial | C66: Optional | D66: text | F66: (reference only)
A67: UPS | B67: capacity_kw | C67: Required | D67: decimal | F67: UpsUnit.capacityKw | H67: 420
A68: UPS | B68: redundancy | C68: Required | D68: list | E68: N, N+1, 2N | F68: UpsUnit.redundancy | H68: N+1
A69: UPS | B69: battery_autonomy_min | C69: Required | D69: integer | F69: UpsUnit.batteryMin | G69: Design autonomy at full load (minutes). | H69: 13
A70: Generators | B70: dg_id | C70: Required | D70: text | F70: (key) | H70: MH-DC-001-DG-1
A71: Generators | B71: site_id | C71: Required | D71: ref | E71: an ID from Sites | F71: Datacenter.id | H71: MH-DC-001
A72: Generators | B72: name | C72: Required | D72: text | F72: (label) | H72: DG-1
A73: Generators | B73: kva | C73: Required | D73: decimal | F73: power.dg.kva | G73: Rating (kVA). | H73: 1575
A74: Generators | B74: fuel_tank_litres | C74: Optional | D74: decimal | F74: (fuel hours)
A75: Generators | B75: runtime_h_full_load | C75: Required | D75: decimal | F75: power.dg.runtimeH | G75: Hours on a full tank at full load. | H75: 11
A76: Generators | B76: last_test_date | C76: Optional | D76: date | F76: power.dg.lastTest | H76: 2026-08-23
A77: Generators | B77: last_test_result | C77: Optional | D77: list | E77: Pass, Fail | F77: power.dg.result | H77: Pass
A78: DC_Plant | B78: plant_id | C78: Required | D78: text | F78: (key) | H78: MH-DC-001-RECT-01
A79: DC_Plant | B79: site_id | C79: Required | D79: ref | E79: an ID from Sites | F79: Datacenter.id | H79: MH-DC-001
A80: DC_Plant | B80: room_id | C80: Optional | D80: ref | E80: an ID from Rooms | F80: (twin placement)
A81: DC_Plant | B81: kind | C81: Required | D81: list | E81: Rectifier, Battery bank | F81: (rectifier / battery) | H81: Rectifier
A82: DC_Plant | B82: name | C82: Required | D82: text | F82: (label) | G82: For example RECT-01, BATT-01. | H82: RECT-01
A83: DC_Plant | B83: volts | C83: Conditional | D83: decimal | F83: power.battery.volts | G83: Battery banks: nominal voltage. | H83: 48
A84: DC_Plant | B84: ah | C84: Conditional | D84: decimal | F84: power.battery.ah | G84: Battery banks: capacity (Ah). | H84: 7600
A85: DC_Plant | B85: rated_output | C85: Conditional | D85: text | F85: PowerFeed.rating (DC) | G85: Rectifiers: for example "48 V · 2400 A". | H85: 48 V · 7880 A
A86: DC_Plant | B86: capacity_kw | C86: Conditional | D86: decimal | F86: PowerFeed.capacityKw (DC) | G86: Rectifiers: DC output (kW). | H86: 378
A87: DC_Plant | B87: autonomy_h | C87: Conditional | D87: decimal | F87: power.battery.runtimeH | G87: Battery banks: design autonomy (hours). | H87: 2.9
A88: DC_Plant | B88: last_test_date | C88: Optional | D88: date | F88: power.battery.lastTest | H88: 2026-07-08
A89: Cooling_Units | B89: unit_id | C89: Required | D89: text | F89: CoolingUnit.id | H89: MH-DC-001-CRAH-11
A90: Cooling_Units | B90: site_id | C90: Required | D90: ref | E90: an ID from Sites | F90: Datacenter.id | H90: MH-DC-001
A91: Cooling_Units | B91: room_id | C91: Required | D91: ref | E91: an ID from Rooms | F91: CoolingUnit.zone | G91: The zone is "<floor> · <room>". | H91: MH-DC-001-F0-R1
A92: Cooling_Units | B92: name | C92: Required | D92: text | F92: CoolingUnit.name | G92: For example CRAH-11. | H92: CRAH-11
A93: Cooling_Units | B93: type | C93: Required | D93: list | E93: CRAH, CRAC, CDU | F93: CoolingUnit.type | H93: CRAH
A94: Cooling_Units | B94: vendor | C94: Optional | D94: text | F94: (reference only)
A95: Cooling_Units | B95: model | C95: Optional | D95: text | F95: (reference only)
A96: Cooling_Units | B96: capacity_kw | C96: Required | D96: decimal | F96: CoolingUnit.capacityKw | G96: Rated cooling capacity. | H96: 124
A97: Cooling_Units | B97: design_supply_c | C97: Optional | D97: decimal | F97: CoolingUnit.supplyC (setpoint) | G97: Supply air / coolant setpoint. | H97: 19
A98: CDUs | B98: cdu_id | C98: Required | D98: text | F98: Cdu.id
A99: CDUs | B99: site_id | C99: Required | D99: ref | E99: an ID from Sites | F99: Cdu.dcId
A100: CDUs | B100: room_id | C100: Required | D100: ref | E100: an ID from Rooms | F100: Cdu.room
...

Sheet Lookups
A1: business_model | B1: site_status | C1: tier | D1: site_category | E1: redundancy | F1: room_type | G1: containment | H1: cooling_method | I1: rack_role | J1: owner | K1: density | L1: yes_no | M1: feed_type | N1: feed_role | O1: plant_kind | P1: test_result | Q1: cooling_type | R1: sensor_kind | S1: device_role | T1: layer | U1: lifecycle | V1: if_admin | W1: link_role | X1: protocol | Y1: gpu_model | Z1: gpu_vendor | AA1: scheduler | AB1: air_liquid | AC1: service_type | AD1: service_unit | AE1: collector_protocol | AF1: collector_domain | AG1: pdu_side | AH1: pdu_kind | AI1: panel_kind | AJ1: panel_role | AK1: link_end | AL1: tray_route | AM1: detection | AN1: suppression | AO1: release_mode | AP1: door_kind | AQ1: reader | AR1: support_level | AS1: pm_kind | AT1: oncall_role
A2: colocation | B2: on-air | C2: Tier II | D2: Central | E2: N | F2: Data hall | G2: Cold aisle | H2: Air | I2: Core | J2: operator | K2: standard | L2: Y | M2: AC | N2: Active | O2: Rectifier | P2: Pass | Q2: CRAH | R2: Temperature + humidity | S2: Router | T2: core | U2: Ready | V2: up | W2: Fabric | X2: LLDP | Y2: B200 SXM 192 GB | Z2: NVIDIA | AA2: Kubernetes | AB2: air | AC2: Cabinet lease | AD2: cabinets | AE2: SNMP | AF2: Network | AG2: A | AH2: AC | AI2: LC duplex | AJ2: rack | AK2: A | AL2: Tray route 1 | AM2: VESDA aspirating | AN2: Novec 1230 gas | AO2: Armed (auto) | AP2: Building entry | AQ2: Card + biometric | AR2: 24×7×4 | AS2: UPS | AT2: NOC shift lead
A3: neocloud | B3: in-progress | C3: Tier III | D3: Regional | E3: N+1 | F3: AI hall | G3: Hot aisle | H3: Liquid | I3: Meet-me room | J3: tenant | K3: ai | L3: N | M3: DC | N3: Standby | O3: Battery bank | P3: Fail | Q3: CRAC | R3: Leak | S3: Switch | T3: spine | U3: Planned | V3: admin-down | W3: Uplink | X3: OSPF | Y3: H200 SXM 141 GB | Z3: Intel | AA3: Slurm | AB3: liquid | AC3: Power circuit | AD3: kW | AE3: gNMI | AF3: Facility | AG3: B | AH3: DC | AI3: MPO | AJ3: odf | AK3: Z | AL3: Tray route 2 | AM3: Point smoke + heat | AN3: Inert gas (IG-541) | AO3: Manual only | AP3: Data hall door | AQ3: Card + PIN | AR3: NBD | AS3: Battery | AT3: Network engineer
A4: cloud | B4: planned | C4: Tier IV | D4: Edge | E4: 2N | F4: Meet-me room | G4: None | H4: Hybrid | I4: Network | Q4: CDU | R4: Smoke | S4: DWDM | T4: leaf | U4: Maintenance | V4: reserved | W4: Backhaul | X4: BGP | Y4: H100 SXM 80 GB | AC4: Cross-connect | AD4: Mbps | AE4: Redfish | AF4: Compute | AI4: RJ45 | AN4: Pre-action sprinkler | AO4: Isolated | AP4: Cage door | AQ4: Card | AR4: 8×5 NBD | AS4: Generator | AT4: Facility engineer
A5: enterprise | B5: failed | F5: Network room | I5: Aggregation | S5: Firewall | T5: access | U5: Decommissioning | W5: Peering | X5: ISIS | Y5: A100 SXM 80 GB | AC5: Remote hands | AD5: hours | AE5: DCGM exporter | AF5: GPU | AP5: Plant room door | AR5: None | AS5: Cooling | AT5: Field technician
A6: network | F6: Plant room | I6: Compute | S6: Access | W6: Access | X6: LSP | Y6: L40S PCIe 48 GB | AC6: Reserved cluster | AD6: GPU | AE6: Modbus TCP | AP6: Meet-me room door | AS6: CDU | AT6: Duty manager
F7: UPS room | I7: Storage | S7: Server | Y7: T4 PCIe 16 GB | AC7: On-demand GPUs | AD7: vCPU | AE7: BACnet | AS7: Fire | AT7: AI infrastructure engineer
F8: Battery room | I8: GPU | S8: Storage | Y8: Gaudi 3 OAM 128 GB | AC8: CPU instances | AD8: TB | AE8: Syslog | AS8: Electrical
F9: NOC | I9: Tenant | S9: GPU | Y9: Max 1550 OAM 128 GB | AC9: VM | AD9: users
I10: AI cage | S10: Tenant gear | AC10: Storage volume
AC11: Managed DB
AC12: GPU cluster
AC13: Kubernetes
AC14: IRV
AC15: Leased Line
AC16: L2VPN
AC17: L3VPN
AC18: Core application
AC19: Database
AC20: Collaboration
AC21: Analytics
AC22: Backup & DR
... AC24: Other
