Workbook
Name L_business_model: Lookups!$A$2:$A$6
Name L_site_status: Lookups!$B$2:$B$5
Name L_tier: Lookups!$C$2:$C$4
Name L_site_category: Lookups!$D$2:$D$4
Name L_redundancy: Lookups!$E$2:$E$4
Name L_room_type: Lookups!$F$2:$F$9
Name L_containment: Lookups!$G$2:$G$4
Name L_cooling_method: Lookups!$H$2:$H$4
Name L_rack_role: Lookups!$I$2:$I$10
Name L_owner: Lookups!$J$2:$J$3
Name L_density: Lookups!$K$2:$K$3
Name L_yes_no: Lookups!$L$2:$L$3
Name L_feed_type: Lookups!$M$2:$M$3
Name L_feed_role: Lookups!$N$2:$N$3
Name L_plant_kind: Lookups!$O$2:$O$3
Name L_test_result: Lookups!$P$2:$P$3
Name L_cooling_type: Lookups!$Q$2:$Q$4
Name L_sensor_kind: Lookups!$R$2:$R$4
Name L_device_role: Lookups!$S$2:$S$10
Name L_layer: Lookups!$T$2:$T$5
Name L_lifecycle: Lookups!$U$2:$U$5
Name L_if_admin: Lookups!$V$2:$V$4
Name L_link_role: Lookups!$W$2:$W$6
Name L_protocol: Lookups!$X$2:$X$6
Name L_gpu_model: Lookups!$Y$2:$Y$9
Name L_gpu_vendor: Lookups!$Z$2:$Z$3
Name L_scheduler: Lookups!$AA$2:$AA$3
Name L_air_liquid: Lookups!$AB$2:$AB$3
Name L_service_type: Lookups!$AC$2:$AC$24
Name L_service_unit: Lookups!$AD$2:$AD$9
Name L_collector_protocol: Lookups!$AE$2:$AE$8
Name L_collector_domain: Lookups!$AF$2:$AF$5
Name L_pdu_side: Lookups!$AG$2:$AG$3
Name L_pdu_kind: Lookups!$AH$2:$AH$3
Name L_panel_kind: Lookups!$AI$2:$AI$4
Name L_panel_role: Lookups!$AJ$2:$AJ$3
Name L_link_end: Lookups!$AK$2:$AK$3
Name L_tray_route: Lookups!$AL$2:$AL$3
Name L_detection: Lookups!$AM$2:$AM$3
Name L_suppression: Lookups!$AN$2:$AN$4
Name L_release_mode: Lookups!$AO$2:$AO$4
Name L_door_kind: Lookups!$AP$2:$AP$6
Name L_reader: Lookups!$AQ$2:$AQ$4
Name L_support_level: Lookups!$AR$2:$AR$5
Name L_pm_kind: Lookups!$AS$2:$AS$8
Name L_oncall_role: Lookups!$AT$2:$AT$7

Sheet README
A1: SynapseDC · Sample data for two datacenters · Colocation · India · MH-DC-001, MH-DC-002
A2: A complete, end-to-end export of MH-DC-001, MH-DC-002 as the platform holds them (data clock 2026-10-01 07:50 UTC): the two sites, their floors, rooms, racks, power and cooling plant, every device with its ports, the cables between them, GPU clusters, the customers served there and their services, plus the physical, safety, lifecycle and maintenance records. Only links whose two ends are in these sites and only customers who buy something there are included. Use it as the worked example for the import template: every sheet is filled exactly the way the customer should fill it for their own datacenters, the Summary sheet shows what the platform will then display. Snapshot_* sheets keep the alarms, incidents and changes of that moment for the record; they are not imported.
A3: Version 1.0 · 12-Oct-2026 · matches the DCO data model (app/src/api/types.ts)
A5: What this workbook is for
A6: Use it to collect everything the DCO platform needs to know about a customer's datacenters BEFORE monitoring is switched on: sites, floors, rooms, racks, power and cooling plant, sensors, every racked device, its ports and cables, GPU clusters, customers and the services they buy, and the monitoring sources.
A8: How to fill it
A9: 1. Fill the sheets in tab order. A sheet can only point at IDs that exist in the sheets before it (Sites → Floors → Rooms → Racks → … → Services).
A10: 2. Row 1 holds the import keys. Don't rename, reorder or delete columns. Hover over a header for its meaning; the Field_Dictionary sheet lists every field.
A11: 3. Header colours: dark blue = required · amber = required in some cases (see the note) · grey = optional · green = calculated by a formula (don't type it).
A12: 4. Columns with a fixed set of values have a dropdown (from the Lookups sheet). Dates use YYYY-MM-DD. Numbers are plain, with no units in the cell. Lists inside a cell use ";".
A13: 5. IDs must be unique and stable: the system keys every alarm, incident and revenue figure on them. Recommended: site XX-DC-NNN, then <site>-<object> (MP-DC-001-A01).
A14: 6. Check the Summary sheet when you finish. Every count must match what the customer expects, and the checks column must say OK.
... A24: Sheet order and the system object each one fills
A25: Sheet | B25: System object | C25: What goes in it | D25: Example rows
A26: Sites | B26: Datacenter + Location | C26: One row per datacenter. | D26: 2
A27: Floors | B27: Datacenter.floors[] | C27: One row per floor. | D27: 4
A28: Rooms | B28: Datacenter.floors[].rooms[] | C28: One row per room / hall. | D28: 8
A29: Racks | B29: Rack | C29: One row per cabinet, including tenant cabinets and AI cages. | D29: 32
A30: Power_Feeds | B30: Datacenter.power.feeds[] (PowerFeed) | C30: Utility, DG and DC-plant feeds. | D30: 6
A31: UPS | B31: Datacenter.power.ups[] (UpsUnit) | C31: One row per UPS module or system. | D31: 8
A32: Generators | B32: Datacenter.power.dg | C32: Diesel generator sets. | D32: 2
A33: DC_Plant | B33: Datacenter.power.battery + rectifier | C33: 48 V DC plant: rectifiers and battery banks. | D33: 4
A34: Cooling_Units | B34: Datacenter.cooling.units[] (CoolingUnit) | C34: CRAH, CRAC and CDU units. | D34: 17
A35: CDUs | B35: Cdu | C35: Liquid-cooling loops (only for liquid-cooled racks). | D35: 1
A36: Sensors | B36: Datacenter.cooling.sensors[] (EnvSensor) | C36: Environment sensors. | D36: 8
A37: Devices | B37: NetworkElement | C37: Every racked device: network, servers, storage, GPU nodes, and opaque tenant gear blocks. | D37: 183
... A66: Snapshot_Orders | B66: CrossConnectOrder + RemoteHandsTicket (snapshot) | C66: Colocation cross-connect orders and remote-hands tickets. | D66: 41
A67: Summary | B67: — | C67: Counts per site and the reconciliation checks (formulas).
A68: Field_Dictionary | B68: — | C68: Every column: required, type, allowed values, the system field it maps to.
A69: Lookups | B69: — | C69: Allowed values behind the dropdowns.

Sheet Summary
A1: Summary and reconciliation checks
A2: Every figure is a formula over the data sheets. Check it with the customer: these are the numbers the platform will show.
A4: Measure | B4: =IF('Sites'!A2="","(site 1)",'Sites'!A2) | C4: =IF('Sites'!A3="","(site 2)",'Sites'!A3) | D4: =IF('Sites'!A4="","(site 3)",'Sites'!A4) | E4: =IF('Sites'!A5="","(site 4)",'Sites'!A5) | F4: =IF('Sites'!A6="","(site 5)",'Sites'!A6) | G4: =IF('Sites'!A7="","(site 6)",'Sites'!A7) | H4: Total
A5: Floors | B5: =IF('Sites'!$A$2="","",COUNTIF('Floors'!$A$2:$A$2000,B$4)) | C5: =IF('Sites'!$A$3="","",COUNTIF('Floors'!$A$2:$A$2000,C$4)) | D5: =IF('Sites'!$A$4="","",COUNTIF('Floors'!$A$2:$A$2000,D$4)) | E5: =IF('Sites'!$A$5="","",COUNTIF('Floors'!$A$2:$A$2000,E$4)) | F5: =IF('Sites'!$A$6="","",COUNTIF('Floors'!$A$2:$A$2000,F$4)) | G5: =IF('Sites'!$A$7="","",COUNTIF('Floors'!$A$2:$A$2000,G$4)) | H5: =SUM(B5:G5)
A6: Rooms | B6: =IF('Sites'!$A$2="","",COUNTIF('Rooms'!$A$2:$A$2000,B$4)) | C6: =IF('Sites'!$A$3="","",COUNTIF('Rooms'!$A$2:$A$2000,C$4)) | D6: =IF('Sites'!$A$4="","",COUNTIF('Rooms'!$A$2:$A$2000,D$4)) | E6: =IF('Sites'!$A$5="","",COUNTIF('Rooms'!$A$2:$A$2000,E$4)) | F6: =IF('Sites'!$A$6="","",COUNTIF('Rooms'!$A$2:$A$2000,F$4)) | G6: =IF('Sites'!$A$7="","",COUNTIF('Rooms'!$A$2:$A$2000,G$4)) | H6: =SUM(B6:G6)
A7: Racks | B7: =IF('Sites'!$A$2="","",COUNTIF('Racks'!$B$2:$B$2000,B$4)) | C7: =IF('Sites'!$A$3="","",COUNTIF('Racks'!$B$2:$B$2000,C$4)) | D7: =IF('Sites'!$A$4="","",COUNTIF('Racks'!$B$2:$B$2000,D$4)) | E7: =IF('Sites'!$A$5="","",COUNTIF('Racks'!$B$2:$B$2000,E$4)) | F7: =IF('Sites'!$A$6="","",COUNTIF('Racks'!$B$2:$B$2000,F$4)) | G7: =IF('Sites'!$A$7="","",COUNTIF('Racks'!$B$2:$B$2000,G$4)) | H7: =SUM(B7:G7)
A8: of which tenant cabinets | B8: =IF('Sites'!$A$2="","",COUNTIFS('Racks'!$B$2:$B$2000,B$4,'Racks'!$J$2:$J$2000,"tenant")) | C8: =IF('Sites'!$A$3="","",COUNTIFS('Racks'!$B$2:$B$2000,C$4,'Racks'!$J$2:$J$2000,"tenant")) | D8: =IF('Sites'!$A$4="","",COUNTIFS('Racks'!$B$2:$B$2000,D$4,'Racks'!$J$2:$J$2000,"tenant")) | E8: =IF('Sites'!$A$5="","",COUNTIFS('Racks'!$B$2:$B$2000,E$4,'Racks'!$J$2:$J$2000,"tenant")) | F8: =IF('Sites'!$A$6="","",COUNTIFS('Racks'!$B$2:$B$2000,F$4,'Racks'!$J$2:$J$2000,"tenant")) | G8: =IF('Sites'!$A$7="","",COUNTIFS('Racks'!$B$2:$B$2000,G$4,'Racks'!$J$2:$J$2000,"tenant")) | H8: =SUM(B8:G8)
A9: of which AI / high-density | B9: =IF('Sites'!$A$2="","",COUNTIFS('Racks'!$B$2:$B$2000,B$4,'Racks'!$M$2:$M$2000,"ai")) | C9: =IF('Sites'!$A$3="","",COUNTIFS('Racks'!$B$2:$B$2000,C$4,'Racks'!$M$2:$M$2000,"ai")) | D9: =IF('Sites'!$A$4="","",COUNTIFS('Racks'!$B$2:$B$2000,D$4,'Racks'!$M$2:$M$2000,"ai")) | E9: =IF('Sites'!$A$5="","",COUNTIFS('Racks'!$B$2:$B$2000,E$4,'Racks'!$M$2:$M$2000,"ai")) | F9: =IF('Sites'!$A$6="","",COUNTIFS('Racks'!$B$2:$B$2000,F$4,'Racks'!$M$2:$M$2000,"ai")) | G9: =IF('Sites'!$A$7="","",COUNTIFS('Racks'!$B$2:$B$2000,G$4,'Racks'!$M$2:$M$2000,"ai")) | H9: =SUM(B9:G9)
A10: Rack power budget (kW) | B10: =IF('Sites'!$A$2="","",SUMIF('Racks'!$B$2:$B$2000,B$4,'Racks'!$I$2:$I$2000)) | C10: =IF('Sites'!$A$3="","",SUMIF('Racks'!$B$2:$B$2000,C$4,'Racks'!$I$2:$I$2000)) | D10: =IF('Sites'!$A$4="","",SUMIF('Racks'!$B$2:$B$2000,D$4,'Racks'!$I$2:$I$2000)) | E10: =IF('Sites'!$A$5="","",SUMIF('Racks'!$B$2:$B$2000,E$4,'Racks'!$I$2:$I$2000)) | F10: =IF('Sites'!$A$6="","",SUMIF('Racks'!$B$2:$B$2000,F$4,'Racks'!$I$2:$I$2000)) | G10: =IF('Sites'!$A$7="","",SUMIF('Racks'!$B$2:$B$2000,G$4,'Racks'!$I$2:$I$2000)) | H10: =SUM(B10:G10)
A11: Site IT capacity (kW) | B11: =IF('Sites'!$A$2="","",SUMIF('Sites'!$A$2:$A$2000,B$4,'Sites'!$O$2:$O$2000)) | C11: =IF('Sites'!$A$3="","",SUMIF('Sites'!$A$2:$A$2000,C$4,'Sites'!$O$2:$O$2000)) | D11: =IF('Sites'!$A$4="","",SUMIF('Sites'!$A$2:$A$2000,D$4,'Sites'!$O$2:$O$2000)) | E11: =IF('Sites'!$A$5="","",SUMIF('Sites'!$A$2:$A$2000,E$4,'Sites'!$O$2:$O$2000)) | F11: =IF('Sites'!$A$6="","",SUMIF('Sites'!$A$2:$A$2000,F$4,'Sites'!$O$2:$O$2000)) | G11: =IF('Sites'!$A$7="","",SUMIF('Sites'!$A$2:$A$2000,G$4,'Sites'!$O$2:$O$2000)) | H11: =SUM(B11:G11)
A12: Devices (all) | B12: =IF('Sites'!$A$2="","",COUNTIFS('Devices'!$B$2:$B$2000,B$4)) | C12: =IF('Sites'!$A$3="","",COUNTIFS('Devices'!$B$2:$B$2000,C$4)) | D12: =IF('Sites'!$A$4="","",COUNTIFS('Devices'!$B$2:$B$2000,D$4)) | E12: =IF('Sites'!$A$5="","",COUNTIFS('Devices'!$B$2:$B$2000,E$4)) | F12: =IF('Sites'!$A$6="","",COUNTIFS('Devices'!$B$2:$B$2000,F$4)) | G12: =IF('Sites'!$A$7="","",COUNTIFS('Devices'!$B$2:$B$2000,G$4)) | H12: =SUM(B12:G12)
A13: operator devices | B13: =IF('Sites'!$A$2="","",COUNTIFS('Devices'!$B$2:$B$2000,B$4,'Devices'!$P$2:$P$2000,"operator")) | C13: =IF('Sites'!$A$3="","",COUNTIFS('Devices'!$B$2:$B$2000,C$4,'Devices'!$P$2:$P$2000,"operator")) | D13: =IF('Sites'!$A$4="","",COUNTIFS('Devices'!$B$2:$B$2000,D$4,'Devices'!$P$2:$P$2000,"operator")) | E13: =IF('Sites'!$A$5="","",COUNTIFS('Devices'!$B$2:$B$2000,E$4,'Devices'!$P$2:$P$2000,"operator")) | F13: =IF('Sites'!$A$6="","",COUNTIFS('Devices'!$B$2:$B$2000,F$4,'Devices'!$P$2:$P$2000,"operator")) | G13: =IF('Sites'!$A$7="","",COUNTIFS('Devices'!$B$2:$B$2000,G$4,'Devices'!$P$2:$P$2000,"operator")) | H13: =SUM(B13:G13)
A14: tenant gear blocks | B14: =IF('Sites'!$A$2="","",COUNTIFS('Devices'!$B$2:$B$2000,B$4,'Devices'!$P$2:$P$2000,"tenant")) | C14: =IF('Sites'!$A$3="","",COUNTIFS('Devices'!$B$2:$B$2000,C$4,'Devices'!$P$2:$P$2000,"tenant")) | D14: =IF('Sites'!$A$4="","",COUNTIFS('Devices'!$B$2:$B$2000,D$4,'Devices'!$P$2:$P$2000,"tenant")) | E14: =IF('Sites'!$A$5="","",COUNTIFS('Devices'!$B$2:$B$2000,E$4,'Devices'!$P$2:$P$2000,"tenant")) | F14: =IF('Sites'!$A$6="","",COUNTIFS('Devices'!$B$2:$B$2000,F$4,'Devices'!$P$2:$P$2000,"tenant")) | G14: =IF('Sites'!$A$7="","",COUNTIFS('Devices'!$B$2:$B$2000,G$4,'Devices'!$P$2:$P$2000,"tenant")) | H14: =SUM(B14:G14)
A15: GPU nodes | B15: =IF('Sites'!$A$2="","",COUNTIFS('Devices'!$B$2:$B$2000,B$4,'Devices'!$D$2:$D$2000,"GPU")) | C15: =IF('Sites'!$A$3="","",COUNTIFS('Devices'!$B$2:$B$2000,C$4,'Devices'!$D$2:$D$2000,"GPU")) | D15: =IF('Sites'!$A$4="","",COUNTIFS('Devices'!$B$2:$B$2000,D$4,'Devices'!$D$2:$D$2000,"GPU")) | E15: =IF('Sites'!$A$5="","",COUNTIFS('Devices'!$B$2:$B$2000,E$4,'Devices'!$D$2:$D$2000,"GPU")) | F15: =IF('Sites'!$A$6="","",COUNTIFS('Devices'!$B$2:$B$2000,F$4,'Devices'!$D$2:$D$2000,"GPU")) | G15: =IF('Sites'!$A$7="","",COUNTIFS('Devices'!$B$2:$B$2000,G$4,'Devices'!$D$2:$D$2000,"GPU")) | H15: =SUM(B15:G15)
A16: network (routers, firewalls, switches) | B16: =IF('Sites'!$A$2="","",COUNTIFS('Devices'!$B$2:$B$2000,B$4,'Devices'!$D$2:$D$2000,"Router")+COUNTIFS('Devices'!$B$2:$B$2000,B$4,'Devices'!$D$2:$D$2000,"Firewall")+COUNTIFS('Devices'!$B$2:$B$2000,B$4,'Devices'!$D$2:$D$2000,"Switch")) | C16: =IF('Sites'!$A$3="","",COUNTIFS('Devices'!$B$2:$B$2000,C$4,'Devices'!$D$2:$D$2000,"Router")+COUNTIFS('Devices'!$B$2:$B$2000,C$4,'Devices'!$D$2:$D$2000,"Firewall")+COUNTIFS('Devices'!$B$2:$B$2000,C$4,'Devices'!$D$2:$D$2000,"Switch")) | D16: =IF('Sites'!$A$4="","",COUNTIFS('Devices'!$B$2:$B$2000,D$4,'Devices'!$D$2:$D$2000,"Router")+COUNTIFS('Devices'!$B$2:$B$2000,D$4,'Devices'!$D$2:$D$2000,"Firewall")+COUNTIFS('Devices'!$B$2:$B$2000,D$4,'Devices'!$D$2:$D$2000,"Switch")) | E16: =IF('Sites'!$A$5="","",COUNTIFS('Devices'!$B$2:$B$2000,E$4,'Devices'!$D$2:$D$2000,"Router")+COUNTIFS('Devices'!$B$2:$B$2000,E$4,'Devices'!$D$2:$D$2000,"Firewall")+COUNTIFS('Devices'!$B$2:$B$2000,E$4,'Devices'!$D$2:$D$2000,"Switch")) | F16: =IF('Sites'!$A$6="","",COUNTIFS('Devices'!$B$2:$B$2000,F$4,'Devices'!$D$2:$D$2000,"Router")+COUNTIFS('Devices'!$B$2:$B$2000,F$4,'Devices'!$D$2:$D$2000,"Firewall")+COUNTIFS('Devices'!$B$2:$B$2000,F$4,'Devices'!$D$2:$D$2000,"Switch")) | G16: =IF('Sites'!$A$7="","",COUNTIFS('Devices'!$B$2:$B$2000,G$4,'Devices'!$D$2:$D$2000,"Router")+COUNTIFS('Devices'!$B$2:$B$2000,G$4,'Devices'!$D$2:$D$2000,"Firewall")+COUNTIFS('Devices'!$B$2:$B$2000,G$4,'Devices'!$D$2:$D$2000,"Switch")) | H16: =SUM(B16:G16)
A17: UPS units | B17: =IF('Sites'!$A$2="","",COUNTIF('UPS'!$B$2:$B$2000,B$4)) | C17: =IF('Sites'!$A$3="","",COUNTIF('UPS'!$B$2:$B$2000,C$4)) | D17: =IF('Sites'!$A$4="","",COUNTIF('UPS'!$B$2:$B$2000,D$4)) | E17: =IF('Sites'!$A$5="","",COUNTIF('UPS'!$B$2:$B$2000,E$4)) | F17: =IF('Sites'!$A$6="","",COUNTIF('UPS'!$B$2:$B$2000,F$4)) | G17: =IF('Sites'!$A$7="","",COUNTIF('UPS'!$B$2:$B$2000,G$4)) | H17: =SUM(B17:G17)
A18: UPS capacity (kW) | B18: =IF('Sites'!$A$2="","",SUMIF('UPS'!$B$2:$B$2000,B$4,'UPS'!$H$2:$H$2000)) | C18: =IF('Sites'!$A$3="","",SUMIF('UPS'!$B$2:$B$2000,C$4,'UPS'!$H$2:$H$2000)) | D18: =IF('Sites'!$A$4="","",SUMIF('UPS'!$B$2:$B$2000,D$4,'UPS'!$H$2:$H$2000)) | E18: =IF('Sites'!$A$5="","",SUMIF('UPS'!$B$2:$B$2000,E$4,'UPS'!$H$2:$H$2000)) | F18: =IF('Sites'!$A$6="","",SUMIF('UPS'!$B$2:$B$2000,F$4,'UPS'!$H$2:$H$2000)) | G18: =IF('Sites'!$A$7="","",SUMIF('UPS'!$B$2:$B$2000,G$4,'UPS'!$H$2:$H$2000)) | H18: =SUM(B18:G18)
A19: Generators | B19: =IF('Sites'!$A$2="","",COUNTIF('Generators'!$B$2:$B$2000,B$4)) | C19: =IF('Sites'!$A$3="","",COUNTIF('Generators'!$B$2:$B$2000,C$4)) | D19: =IF('Sites'!$A$4="","",COUNTIF('Generators'!$B$2:$B$2000,D$4)) | E19: =IF('Sites'!$A$5="","",COUNTIF('Generators'!$B$2:$B$2000,E$4)) | F19: =IF('Sites'!$A$6="","",COUNTIF('Generators'!$B$2:$B$2000,F$4)) | G19: =IF('Sites'!$A$7="","",COUNTIF('Generators'!$B$2:$B$2000,G$4)) | H19: =SUM(B19:G19)
A20: Cooling units | B20: =IF('Sites'!$A$2="","",COUNTIF('Cooling_Units'!$B$2:$B$2000,B$4)) | C20: =IF('Sites'!$A$3="","",COUNTIF('Cooling_Units'!$B$2:$B$2000,C$4)) | D20: =IF('Sites'!$A$4="","",COUNTIF('Cooling_Units'!$B$2:$B$2000,D$4)) | E20: =IF('Sites'!$A$5="","",COUNTIF('Cooling_Units'!$B$2:$B$2000,E$4)) | F20: =IF('Sites'!$A$6="","",COUNTIF('Cooling_Units'!$B$2:$B$2000,F$4)) | G20: =IF('Sites'!$A$7="","",COUNTIF('Cooling_Units'!$B$2:$B$2000,G$4)) | H20: =SUM(B20:G20)
A21: Cooling unit capacity (kW) | B21: =IF('Sites'!$A$2="","",SUMIF('Cooling_Units'!$B$2:$B$2000,B$4,'Cooling_Units'!$H$2:$H$2000)) | C21: =IF('Sites'!$A$3="","",SUMIF('Cooling_Units'!$B$2:$B$2000,C$4,'Cooling_Units'!$H$2:$H$2000)) | D21: =IF('Sites'!$A$4="","",SUMIF('Cooling_Units'!$B$2:$B$2000,D$4,'Cooling_Units'!$H$2:$H$2000)) | E21: =IF('Sites'!$A$5="","",SUMIF('Cooling_Units'!$B$2:$B$2000,E$4,'Cooling_Units'!$H$2:$H$2000)) | F21: =IF('Sites'!$A$6="","",SUMIF('Cooling_Units'!$B$2:$B$2000,F$4,'Cooling_Units'!$H$2:$H$2000)) | G21: =IF('Sites'!$A$7="","",SUMIF('Cooling_Units'!$B$2:$B$2000,G$4,'Cooling_Units'!$H$2:$H$2000)) | H21: =SUM(B21:G21)
A22: Sensors | B22: =IF('Sites'!$A$2="","",COUNTIF('Sensors'!$B$2:$B$2000,B$4)) | C22: =IF('Sites'!$A$3="","",COUNTIF('Sensors'!$B$2:$B$2000,C$4)) | D22: =IF('Sites'!$A$4="","",COUNTIF('Sensors'!$B$2:$B$2000,D$4)) | E22: =IF('Sites'!$A$5="","",COUNTIF('Sensors'!$B$2:$B$2000,E$4)) | F22: =IF('Sites'!$A$6="","",COUNTIF('Sensors'!$B$2:$B$2000,F$4)) | G22: =IF('Sites'!$A$7="","",COUNTIF('Sensors'!$B$2:$B$2000,G$4)) | H22: =SUM(B22:G22)
A23: Collectors | B23: =IF('Sites'!$A$2="","",COUNTIF('Collectors'!$B$2:$B$2000,B$4)) | C23: =IF('Sites'!$A$3="","",COUNTIF('Collectors'!$B$2:$B$2000,C$4)) | D23: =IF('Sites'!$A$4="","",COUNTIF('Collectors'!$B$2:$B$2000,D$4)) | E23: =IF('Sites'!$A$5="","",COUNTIF('Collectors'!$B$2:$B$2000,E$4)) | F23: =IF('Sites'!$A$6="","",COUNTIF('Collectors'!$B$2:$B$2000,F$4)) | G23: =IF('Sites'!$A$7="","",COUNTIF('Collectors'!$B$2:$B$2000,G$4)) | H23: =SUM(B23:G23)
A24: Services | B24: =IF('Sites'!$A$2="","",COUNTIF('Services'!$D$2:$D$2000,B$4)) | C24: =IF('Sites'!$A$3="","",COUNTIF('Services'!$D$2:$D$2000,C$4)) | D24: =IF('Sites'!$A$4="","",COUNTIF('Services'!$D$2:$D$2000,D$4)) | E24: =IF('Sites'!$A$5="","",COUNTIF('Services'!$D$2:$D$2000,E$4)) | F24: =IF('Sites'!$A$6="","",COUNTIF('Services'!$D$2:$D$2000,F$4)) | G24: =IF('Sites'!$A$7="","",COUNTIF('Services'!$D$2:$D$2000,G$4)) | H24: =SUM(B24:G24)
A25: Services monthly revenue (₹) | B25: =IF('Sites'!$A$2="","",SUMIF('Services'!$D$2:$D$2000,B$4,'Services'!$M$2:$M$2000)) | C25: =IF('Sites'!$A$3="","",SUMIF('Services'!$D$2:$D$2000,C$4,'Services'!$M$2:$M$2000)) | D25: =IF('Sites'!$A$4="","",SUMIF('Services'!$D$2:$D$2000,D$4,'Services'!$M$2:$M$2000)) | E25: =IF('Sites'!$A$5="","",SUMIF('Services'!$D$2:$D$2000,E$4,'Services'!$M$2:$M$2000)) | F25: =IF('Sites'!$A$6="","",SUMIF('Services'!$D$2:$D$2000,F$4,'Services'!$M$2:$M$2000)) | G25: =IF('Sites'!$A$7="","",SUMIF('Services'!$D$2:$D$2000,G$4,'Services'!$M$2:$M$2000)) | H25: =SUM(B25:G25)
A28: Checks
A29: Check | B29: Result | C29: Why it matters
A30: Every device sits in a rack that exists | B30: =IF(SUMPRODUCT(--(COUNTIF('Racks'!$A$2:$A$2000,'Devices'!$L$2:$L$184)=0))=0,"OK","FIX: unknown rack_id") | C30: The twin and rack views place devices by rack_id.
A31: No rack is over-filled (used U ≤ height U) | B31: =IF(SUMPRODUCT(--('Racks'!$R$2:$R$33>'Racks'!$H$2:$H$33))=0,"OK","FIX: rack over capacity") | C31: used_u is calculated from Devices.
A32: Device IDs are unique | B32: =IF(SUMPRODUCT(--(COUNTIF('Devices'!$A$2:$A$184,'Devices'!$A$2:$A$184)>1))=0,"OK","FIX: duplicate device_id") | C32: Alarms and incidents key on the device ID.
A33: Operator serial numbers are unique | B33: =IF(SUMPRODUCT(('Devices'!$I$2:$I$184<>"")*(COUNTIF('Devices'!$I$2:$I$184,'Devices'!$I$2:$I$184)>1))=0,"OK","FIX: duplicate serial") | C33: Discovery matches the polled serial against this one.
A34: Tenant racks name a tenant and contracted kW | B34: =IF(COUNTIFS('Racks'!$J$2:$J$33,"tenant",'Racks'!$K$2:$K$33,"")+COUNTIFS('Racks'!$J$2:$J$33,"tenant",'Racks'!$L$2:$L$33,"")=0,"OK","FIX: tenant rack missing data") | C34: Colocation power-over-contract is measured against it.
A35: Liquid racks name a CDU | B35: =IF(COUNTIFS('Racks'!$N$2:$N$33,"Y",'Racks'!$O$2:$O$33,"")=0,"OK","FIX: liquid rack without CDU") | C35: A CDU fault is traced to the racks it feeds.
A36: Rack budget fits site IT capacity | B36: =IF(SUMPRODUCT(--(B10:G10>B11:G11))=0,"OK","CHECK: racks exceed IT capacity") | C36: Power and space views compare the two.
A37: GPU nodes = GPU devices in service | B37: =IF(COUNTA('GPU_Nodes'!$A$2:$A$2000)=COUNTIFS('Devices'!$D$2:$D$2000,"GPU",'Devices'!$R$2:$R$2000,"Y"),"OK","FIX: GPU_Nodes and Devices differ") | C37: Each GPU node in service needs a rack position and a telemetry record; hosts not yet commissioned into a cluster have none.
A38: Every installed device has a power connection | B38: =IF(SUMPRODUCT(('Devices'!$O$2:$O$184<>"Planned")*('Devices'!$A$2:$A$184<>"")*(COUNTIF('Power_Connections'!$A$2:$A$2000,'Devices'!$A$2:$A$184)=0))=0,"OK","FIX: device without a power cord") | C38: Without it the power path, single-fed devices and UPS / PDU what-ifs cannot be traced.
A39: Power cords point at a known PDU | B39: =IF(SUMPRODUCT(('Power_Connections'!$C$2:$C$2000<>"")*(COUNTIF('Rack_PDUs'!$A$2:$A$2000,'Power_Connections'!$C$2:$C$2000)=0))=0,"OK","FIX: unknown pdu_id") | C39: The outlet map and failover check group cords by PDU.
A40: Every rack has an A and a B PDU | B40: =IF(SUMPRODUCT(('Racks'!$A$2:$A$33<>"")*((COUNTIFS('Rack_PDUs'!$C$2:$C$2000,'Racks'!$A$2:$A$33,'Rack_PDUs'!$D$2:$D$2000,"A")=0)+(COUNTIFS('Rack_PDUs'!$C$2:$C$2000,'Racks'!$A$2:$A$33,'Rack_PDUs'!$D$2:$D$2000,"B")=0)))=0,"OK","CHECK: rack with one power side") | C40: A cabinet with one side is a single point of failure for everything in it.
A41: Cable paths name a known link | B41: =IF(SUMPRODUCT(('Cable_Paths'!$A$2:$A$2000<>"")*(COUNTIF('Links'!$A$2:$A$2000,'Cable_Paths'!$A$2:$A$2000)=0))=0,"OK","FIX: unknown link_id") | C41: Each cable path belongs to one link end.
A42: Every operator device has warranty / support data | B42: =IF(SUMPRODUCT(('Devices'!$P$2:$P$184="operator")*('Devices'!$O$2:$O$184<>"Planned")*(COUNTIF('Asset_Lifecycle'!$A$2:$A$2000,'Devices'!$A$2:$A$184)=0))=0,"OK","CHECK: device without lifecycle row") | C42: Warranty, contract and end-of-support flags need it.
A43: Every room has a fire system | B43: =IF(SUMPRODUCT(('Rooms'!$C$2:$C$9<>"")*(COUNTIF('Fire_Systems'!$C$2:$C$2000,'Rooms'!$C$2:$C$9)=0))=0,"OK","CHECK: room without fire protection") | C43: Fire detection / suppression and its inspection plan are tracked per room.
A44: Customer revenue = sum of services | B44: =IF(ROUND(SUM('Customers'!$I$2:$I$2000)-SUM('Services'!$M$2:$M$2000),0)=0,"OK","FIX: a service names an unknown customer") | C44: Revenue impact adds up only if every service has a customer.

Sheet Sites
A1: site_id * | B1: site_name * | C1: operator | D1: business_model * | E1: status * | F1: tier * | G1: category * | H1: region * | I1: state * | J1: city * | K1: address * | L1: latitude * | M1: longitude * | N1: commissioned_on | O1: it_capacity_kw * | P1: design_pue | Q1: cooling_capacity_kw * | R1: cooling_redundancy * | S1: timezone
A2: MH-DC-001 | B2: MH-DC-001 | D2: colocation | E2: in-progress | F2: Tier III | G2: Central | H2: West | I2: Maharashtra | J2: Pune | K2: Pune Data Park | L2: 18.593 | M2: 73.789 | O2: 390 | P2: 1.52 | Q2: 240 | R2: N+1 | S2: Asia/Kolkata
A3: MH-DC-002 | B3: MH-DC-002 | D3: colocation | E3: on-air | F3: Tier III | G3: Central | H3: West | I3: Maharashtra | J3: Pune | K3: Pune Data Park | L3: 18.601 | M3: 73.762 | N3: 45000 | O3: 330 | P3: 1.59 | Q3: 190 | R3: N+1 | S3: Asia/Kolkata

Sheet Floors
A1: site_id * | B1: floor_id * | C1: floor_name * | D1: level *
A2: MH-DC-001 | B2: MH-DC-001-F0 | C2: Ground | D2: 0
A3: MH-DC-001 | B3: MH-DC-001-F1 | C3: 1st floor | D3: 1
A4: MH-DC-002 | B4: MH-DC-002-F0 | C4: Ground | D4: 0
A5: MH-DC-002 | B5: MH-DC-002-F1 | C5: 1st floor | D5: 1

Sheet Rooms
A1: site_id * | B1: floor_id * | C1: room_id * | D1: room_name * | E1: room_type * | F1: area_sqm | G1: rack_rows | H1: containment | I1: cooling_method
A2: MH-DC-001 | B2: MH-DC-001-F0 | C2: MH-DC-001-F0-R1 | D2: Meet-me room | E2: Meet-me room | G2: 1 | I2: Air
A3: MH-DC-001 | B3: MH-DC-001-F0 | C3: MH-DC-001-F0-R2 | D3: Hall A | E3: Data hall | G3: 1 | I3: Air
A4: MH-DC-001 | B4: MH-DC-001-F1 | C4: MH-DC-001-F1-R1 | D4: Hall B | E4: Data hall | G4: 1 | I4: Air
A5: MH-DC-001 | B5: MH-DC-001-F1 | C5: MH-DC-001-F1-R2 | D5: Hall C | E5: Data hall | G5: 1 | I5: Air
A6: MH-DC-002 | B6: MH-DC-002-F0 | C6: MH-DC-002-F0-R1 | D6: Meet-me room | E6: Meet-me room | G6: 1 | I6: Hybrid
A7: MH-DC-002 | B7: MH-DC-002-F0 | C7: MH-DC-002-F0-R2 | D7: Hall A | E7: Data hall | G7: 1 | I7: Air
A8: MH-DC-002 | B8: MH-DC-002-F1 | C8: MH-DC-002-F1-R1 | D8: Hall B | E8: Data hall | G8: 1 | I8: Hybrid
A9: MH-DC-002 | B9: MH-DC-002-F1 | C9: MH-DC-002-F1-R2 | D9: Hall C | E9: Data hall | G9: 1 | I9: Air

Sheet Racks
A1: rack_id * | B1: site_id * | C1: room_id * | D1: rack_name * | E1: row | F1: position | G1: role * | H1: height_u * | I1: power_budget_kw * | J1: owner * | K1: tenant_customer_id | L1: contracted_kw | M1: density | N1: liquid_cooled | O1: cdu_id | P1: pdu_feed_a | Q1: pdu_feed_b | R1: used_u (calc)
A2: MH-DC-001-RACK-A | B2: MH-DC-001 | C2: MH-DC-001-F0-R1 | D2: RACK-A | G2: Core | H2: 45 | I2: 15 | J2: operator | M2: standard | N2: N | P2: MH-DC-001-AC-1 | Q2: MH-DC-001-AC-2 | R2: =SUMIF('Devices'!$L$2:$L$2000,A2,'Devices'!$N$2:$N$2000)
A3: MH-DC-001-RACK-B | B3: MH-DC-001 | C3: MH-DC-001-F0-R1 | D3: RACK-B | G3: Meet-me room | H3: 42 | I3: 16 | J3: operator | M3: standard | N3: N | P3: MH-DC-001-AC-1 | Q3: MH-DC-001-AC-2 | R3: =SUMIF('Devices'!$L$2:$L$2000,A3,'Devices'!$N$2:$N$2000)
A4: MH-DC-001-RACK-C | B4: MH-DC-001 | C4: MH-DC-001-F0-R1 | D4: RACK-C | G4: Tenant cabinet | H4: 45 | I4: 19 | J4: tenant | K4: CUST-7349 | L4: 19 | M4: standard | N4: N | P4: MH-DC-001-AC-1 | Q4: MH-DC-001-AC-2 | R4: =SUMIF('Devices'!$L$2:$L$2000,A4,'Devices'!$N$2:$N$2000)
A5: MH-DC-001-RACK-D | B5: MH-DC-001 | C5: MH-DC-001-F0-R1 | D5: RACK-D | G5: Tenant cabinet | H5: 45 | I5: 15 | J5: tenant | K5: CUST-2954 | L5: 15 | M5: standard | N5: N | P5: MH-DC-001-AC-1 | Q5: MH-DC-001-AC-2 | R5: =SUMIF('Devices'!$L$2:$L$2000,A5,'Devices'!$N$2:$N$2000)
A6: MH-DC-001-RACK-E | B6: MH-DC-001 | C6: MH-DC-001-F0-R1 | D6: RACK-E | G6: Tenant cabinet | H6: 42 | I6: 19 | J6: tenant | K6: CUST-2954 | L6: 19 | M6: standard | N6: N | P6: MH-DC-001-AC-1 | Q6: MH-DC-001-AC-2 | R6: =SUMIF('Devices'!$L$2:$L$2000,A6,'Devices'!$N$2:$N$2000)
A7: MH-DC-001-RACK-F | B7: MH-DC-001 | C7: MH-DC-001-F0-R2 | D7: RACK-F | G7: Tenant cabinet | H7: 45 | I7: 20 | J7: tenant | K7: CUST-9111 | L7: 20 | M7: standard | N7: N | P7: MH-DC-001-AC-1 | Q7: MH-DC-001-AC-2 | R7: =SUMIF('Devices'!$L$2:$L$2000,A7,'Devices'!$N$2:$N$2000)
A8: MH-DC-001-RACK-G | B8: MH-DC-001 | C8: MH-DC-001-F0-R2 | D8: RACK-G | G8: Tenant cabinet | H8: 45 | I8: 18 | J8: tenant | K8: CUST-9111 | L8: 18 | M8: standard | N8: N | P8: MH-DC-001-AC-1 | Q8: MH-DC-001-AC-2 | R8: =SUMIF('Devices'!$L$2:$L$2000,A8,'Devices'!$N$2:$N$2000)
A9: MH-DC-001-RACK-H | B9: MH-DC-001 | C9: MH-DC-001-F0-R2 | D9: RACK-H | G9: Tenant cabinet | H9: 42 | I9: 11 | J9: tenant | K9: CUST-6478 | L9: 11 | M9: standard | N9: N | P9: MH-DC-001-AC-1 | Q9: MH-DC-001-AC-2 | R9: =SUMIF('Devices'!$L$2:$L$2000,A9,'Devices'!$N$2:$N$2000)
A10: MH-DC-001-RACK-I | B10: MH-DC-001 | C10: MH-DC-001-F0-R2 | D10: RACK-I | G10: Tenant cabinet | H10: 45 | I10: 12 | J10: tenant | K10: CUST-2063 | L10: 12 | M10: standard | N10: N | P10: MH-DC-001-AC-1 | Q10: MH-DC-001-AC-2 | R10: =SUMIF('Devices'!$L$2:$L$2000,A10,'Devices'!$N$2:$N$2000)
A11: MH-DC-001-RACK-J | B11: MH-DC-001 | C11: MH-DC-001-F0-R2 | D11: RACK-J | G11: Tenant cabinet | H11: 45 | I11: 8 | J11: tenant | K11: CUST-8230 | L11: 8 | M11: standard | N11: N | P11: MH-DC-001-AC-1 | Q11: MH-DC-001-AC-2 | R11: =SUMIF('Devices'!$L$2:$L$2000,A11,'Devices'!$N$2:$N$2000)
A12: MH-DC-001-RACK-K | B12: MH-DC-001 | C12: MH-DC-001-F1-R1 | D12: RACK-K | G12: Tenant cabinet | H12: 42 | I12: 11 | J12: tenant | K12: CUST-8230 | L12: 11 | M12: standard | N12: N | P12: MH-DC-001-AC-1 | Q12: MH-DC-001-AC-2 | R12: =SUMIF('Devices'!$L$2:$L$2000,A12,'Devices'!$N$2:$N$2000)
A13: MH-DC-001-RACK-L | B13: MH-DC-001 | C13: MH-DC-001-F1-R1 | D13: RACK-L | G13: Tenant cabinet | H13: 45 | I13: 8 | J13: tenant | K13: CUST-8230 | L13: 8 | M13: standard | N13: N | P13: MH-DC-001-AC-1 | Q13: MH-DC-001-AC-2 | R13: =SUMIF('Devices'!$L$2:$L$2000,A13,'Devices'!$N$2:$N$2000)
A14: MH-DC-001-RACK-M | B14: MH-DC-001 | C14: MH-DC-001-F1-R1 | D14: RACK-M | G14: Tenant cabinet | H14: 45 | I14: 8 | J14: tenant | K14: CUST-6468 | L14: 8 | M14: standard | N14: N | P14: MH-DC-001-AC-1 | Q14: MH-DC-001-AC-2 | R14: =SUMIF('Devices'!$L$2:$L$2000,A14,'Devices'!$N$2:$N$2000)
A15: MH-DC-001-RACK-N | B15: MH-DC-001 | C15: MH-DC-001-F1-R1 | D15: RACK-N | G15: Tenant cabinet | H15: 42 | I15: 8 | J15: tenant | K15: CUST-6468 | L15: 8 | M15: standard | N15: N | P15: MH-DC-001-AC-1 | Q15: MH-DC-001-AC-2 | R15: =SUMIF('Devices'!$L$2:$L$2000,A15,'Devices'!$N$2:$N$2000)
... A17: MH-DC-001-RACK-P | B17: MH-DC-001 | C17: MH-DC-001-F1-R2 | D17: RACK-P | G17: Tenant cabinet | H17: 45 | I17: 8 | J17: tenant | K17: CUST-1202 | L17: 8 | M17: standard | N17: N | P17: MH-DC-001-AC-1 | Q17: MH-DC-001-AC-2 | R17: =SUMIF('Devices'!$L$2:$L$2000,A17,'Devices'!$N$2:$N$2000)
A18: MH-DC-001-RACK-Q | B18: MH-DC-001 | C18: MH-DC-001-F1-R2 | D18: RACK-Q | G18: Access | H18: 42 | I18: 8 | J18: operator | M18: standard | N18: N | P18: MH-DC-001-AC-1 | Q18: MH-DC-001-AC-2 | R18: =SUMIF('Devices'!$L$2:$L$2000,A18,'Devices'!$N$2:$N$2000)
A19: MH-DC-001-RACK-R | B19: MH-DC-001 | C19: MH-DC-001-F1-R2 | D19: RACK-R | G19: Access | H19: 45 | I19: 8 | J19: operator | M19: standard | N19: N | P19: MH-DC-001-AC-1 | Q19: MH-DC-001-AC-2 | R19: =SUMIF('Devices'!$L$2:$L$2000,A19,'Devices'!$N$2:$N$2000)
A20: MH-DC-001-RACK-S | B20: MH-DC-001 | C20: MH-DC-001-F1-R2 | D20: RACK-S | G20: Access | H20: 45 | I20: 8 | J20: operator | M20: standard | N20: N | P20: MH-DC-001-AC-1 | Q20: MH-DC-001-AC-2 | R20: =SUMIF('Devices'!$L$2:$L$2000,A20,'Devices'!$N$2:$N$2000)
A21: MH-DC-001-RACK-T | B21: MH-DC-001 | C21: MH-DC-001-F1-R2 | D21: RACK-T | G21: ODF / patching | H21: 42 | I21: 8 | J21: operator | M21: standard | N21: N | P21: MH-DC-001-AC-1 | Q21: MH-DC-001-AC-2 | R21: =SUMIF('Devices'!$L$2:$L$2000,A21,'Devices'!$N$2:$N$2000)
A22: MH-DC-001-RACK-U | B22: MH-DC-001 | C22: MH-DC-001-F0-R1 | D22: RACK-U | G22: Operator servers | H22: 42 | I22: 9 | J22: operator | M22: standard | N22: N | P22: MH-DC-001-AC-1 | Q22: MH-DC-001-AC-2 | R22: =SUMIF('Devices'!$L$2:$L$2000,A22,'Devices'!$N$2:$N$2000)
A23: MH-DC-002-RACK-A | B23: MH-DC-002 | C23: MH-DC-002-F0-R1 | D23: RACK-A | G23: Core | H23: 45 | I23: 15 | J23: operator | M23: standard | N23: N | P23: MH-DC-002-AC-1 | Q23: MH-DC-002-AC-2 | R23: =SUMIF('Devices'!$L$2:$L$2000,A23,'Devices'!$N$2:$N$2000)
A24: MH-DC-002-RACK-B | B24: MH-DC-002 | C24: MH-DC-002-F0-R1 | D24: RACK-B | G24: AI cage | H24: 42 | I24: 40 | J24: tenant | K24: CUST-7349 | L24: 40 | M24: ai | N24: Y | O24: MH-DC-002-CDU-1 | P24: MH-DC-002-AC-1 | Q24: MH-DC-002-AC-2 | R24: =SUMIF('Devices'!$L$2:$L$2000,A24,'Devices'!$N$2:$N$2000)
A25: MH-DC-002-RACK-C | B25: MH-DC-002 | C25: MH-DC-002-F0-R1 | D25: RACK-C | G25: AI cage | H25: 45 | I25: 40 | J25: tenant | K25: CUST-7349 | L25: 40 | M25: ai | N25: Y | O25: MH-DC-002-CDU-1 | P25: MH-DC-002-AC-1 | Q25: MH-DC-002-AC-2 | R25: =SUMIF('Devices'!$L$2:$L$2000,A25,'Devices'!$N$2:$N$2000)
A26: MH-DC-002-RACK-D | B26: MH-DC-002 | C26: MH-DC-002-F0-R2 | D26: RACK-D | G26: Tenant cabinet | H26: 45 | I26: 17 | J26: tenant | K26: CUST-8220 | L26: 17 | M26: standard | N26: N | P26: MH-DC-002-AC-1 | Q26: MH-DC-002-AC-2 | R26: =SUMIF('Devices'!$L$2:$L$2000,A26,'Devices'!$N$2:$N$2000)
A27: MH-DC-002-RACK-E | B27: MH-DC-002 | C27: MH-DC-002-F0-R2 | D27: RACK-E | G27: Tenant cabinet | H27: 42 | I27: 20 | J27: tenant | K27: CUST-4716 | L27: 20 | M27: standard | N27: N | P27: MH-DC-002-AC-1 | Q27: MH-DC-002-AC-2 | R27: =SUMIF('Devices'!$L$2:$L$2000,A27,'Devices'!$N$2:$N$2000)
A28: MH-DC-002-RACK-F | B28: MH-DC-002 | C28: MH-DC-002-F1-R1 | D28: RACK-F | G28: Tenant cabinet | H28: 45 | I28: 17 | J28: tenant | K28: CUST-2954 | L28: 17 | M28: standard | N28: N | P28: MH-DC-002-AC-1 | Q28: MH-DC-002-AC-2 | R28: =SUMIF('Devices'!$L$2:$L$2000,A28,'Devices'!$N$2:$N$2000)
A29: MH-DC-002-RACK-G | B29: MH-DC-002 | C29: MH-DC-002-F1-R1 | D29: RACK-G | G29: Tenant cabinet | H29: 45 | I29: 17 | J29: tenant | K29: CUST-2954 | L29: 17 | M29: standard | N29: N | P29: MH-DC-002-AC-1 | Q29: MH-DC-002-AC-2 | R29: =SUMIF('Devices'!$L$2:$L$2000,A29,'Devices'!$N$2:$N$2000)
A30: MH-DC-002-RACK-H | B30: MH-DC-002 | C30: MH-DC-002-F1-R1 | D30: RACK-H | G30: AI cage | H30: 42 | I30: 40 | J30: tenant | K30: CUST-1202 | L30: 40 | M30: ai | N30: Y | O30: MH-DC-002-CDU-1 | P30: MH-DC-002-AC-1 | Q30: MH-DC-002-AC-2 | R30: =SUMIF('Devices'!$L$2:$L$2000,A30,'Devices'!$N$2:$N$2000)
A31: MH-DC-002-RACK-I | B31: MH-DC-002 | C31: MH-DC-002-F1-R2 | D31: RACK-I | G31: Tenant cabinet | H31: 45 | I31: 8 | J31: tenant | K31: CUST-1202 | L31: 8 | M31: standard | N31: N | P31: MH-DC-002-AC-1 | Q31: MH-DC-002-AC-2 | R31: =SUMIF('Devices'!$L$2:$L$2000,A31,'Devices'!$N$2:$N$2000)
A32: MH-DC-002-RACK-J | B32: MH-DC-002 | C32: MH-DC-002-F1-R2 | D32: RACK-J | G32: ODF / patching | H32: 45 | I32: 8 | J32: operator | M32: standard | N32: N | P32: MH-DC-002-AC-1 | Q32: MH-DC-002-AC-2 | R32: =SUMIF('Devices'!$L$2:$L$2000,A32,'Devices'!$N$2:$N$2000)
A33: MH-DC-002-RACK-K | B33: MH-DC-002 | C33: MH-DC-002-F0-R1 | D33: RACK-K | G33: Operator servers | H33: 42 | I33: 8 | J33: operator | M33: standard | N33: N | P33: MH-DC-002-AC-1 | Q33: MH-DC-002-AC-2 | R33: =SUMIF('Devices'!$L$2:$L$2000,A33,'Devices'!$N$2:$N$2000)

Sheet Power_Feeds
A1: feed_id * | B1: site_id * | C1: type * | D1: source * | E1: rating * | F1: capacity_kw * | G1: normal_role | H1: utility_account
A2: MH-DC-001-AC-1 | B2: MH-DC-001 | C2: AC | D2: Utility feed A | E2: 380 A · 415 V | F2: 273 | G2: Active
A3: MH-DC-001-AC-2 | B3: MH-DC-001 | C3: AC | D3: Utility feed B | E3: 380 A · 415 V | F3: 273 | G3: Standby
A4: MH-DC-001-DC-1 | B4: MH-DC-001 | C4: DC | D4: Rectifier RECT-01 | E4: 48 V · 2440 A | F4: 117 | G4: Active
A5: MH-DC-002-AC-1 | B5: MH-DC-002 | C5: AC | D5: Utility feed A | E5: 321 A · 415 V | F5: 231 | G5: Active
A6: MH-DC-002-AC-2 | B6: MH-DC-002 | C6: AC | D6: Utility feed B | E6: 321 A · 415 V | F6: 231 | G6: Standby
A7: MH-DC-002-DC-1 | B7: MH-DC-002 | C7: DC | D7: Rectifier RECT-01 | E7: 48 V · 2060 A | F7: 99 | G7: Active

Sheet UPS
A1: ups_id * | B1: site_id * | C1: room_id | D1: name * | E1: vendor | F1: model | G1: serial | H1: capacity_kw * | I1: redundancy * | J1: battery_autonomy_min *
A2: MH-DC-001-UPS-1 | B2: MH-DC-001 | D2: UPS-1 | H2: 130 | I2: N+1 | J2: 15
A3: MH-DC-001-UPS-2 | B3: MH-DC-001 | D3: UPS-2 | H3: 130 | I3: N+1 | J3: 16
A4: MH-DC-001-UPS-3 | B4: MH-DC-001 | D4: UPS-3 | H4: 130 | I4: N+1 | J4: 23
A5: MH-DC-001-UPS-4 | B5: MH-DC-001 | D5: UPS-4 | H5: 130 | I5: N+1 | J5: 18
A6: MH-DC-002-UPS-1 | B6: MH-DC-002 | D6: UPS-1 | H6: 110 | I6: N+1 | J6: 26
A7: MH-DC-002-UPS-2 | B7: MH-DC-002 | D7: UPS-2 | H7: 110 | I7: N+1 | J7: 26
A8: MH-DC-002-UPS-3 | B8: MH-DC-002 | D8: UPS-3 | H8: 110 | I8: N+1 | J8: 15
A9: MH-DC-002-UPS-4 | B9: MH-DC-002 | D9: UPS-4 | H9: 110 | I9: N+1 | J9: 16

Sheet Generators
A1: dg_id * | B1: site_id * | C1: name * | D1: kva * | E1: fuel_tank_litres | F1: runtime_h_full_load * | G1: last_test_date | H1: last_test_result
A2: MH-DC-001-DG-1 | B2: MH-DC-001 | C2: DG-1 | D2: 500 | F2: 10 | G2: 46261 | H2: Pass
A3: MH-DC-002-DG-1 | B3: MH-DC-002 | C3: DG-1 | D3: 425 | F3: 12 | G3: 46282 | H3: Pass

Sheet DC_Plant
A1: plant_id * | B1: site_id * | C1: room_id | D1: kind * | E1: name * | F1: volts | G1: ah | H1: rated_output | I1: capacity_kw | J1: autonomy_h | K1: last_test_date
A2: MH-DC-001-RECT-01 | B2: MH-DC-001 | D2: Rectifier | E2: RECT-01 | H2: 48 V · 2440 A | I2: 117
A3: MH-DC-001-BATT-01 | B3: MH-DC-001 | D3: Battery bank | E3: BATT-01 | F3: 48 | G3: 2400 | J3: 3.4 | K3: 46256
A4: MH-DC-002-RECT-01 | B4: MH-DC-002 | D4: Rectifier | E4: RECT-01 | H4: 48 V · 2060 A | I4: 99
A5: MH-DC-002-BATT-01 | B5: MH-DC-002 | D5: Battery bank | E5: BATT-01 | F5: 48 | G5: 2000 | J5: 3.8 | K5: 46229

Sheet Cooling_Units
A1: unit_id * | B1: site_id * | C1: room_id * | D1: name * | E1: type * | F1: vendor | G1: model | H1: capacity_kw * | I1: design_supply_c
A2: MH-DC-001-CRAH-11 | B2: MH-DC-001 | C2: MH-DC-001-F0-R1 | D2: CRAH-11 | E2: CRAH | H2: 30 | I2: 18
A3: MH-DC-001-CRAH-12 | B3: MH-DC-001 | C3: MH-DC-001-F0-R2 | D3: CRAH-12 | E3: CRAH | H3: 30 | I3: 18
A4: MH-DC-001-CRAH-13 | B4: MH-DC-001 | C4: MH-DC-001-F1-R1 | D4: CRAH-13 | E4: CRAH | H4: 30 | I4: 17
A5: MH-DC-001-CRAH-14 | B5: MH-DC-001 | C5: MH-DC-001-F1-R2 | D5: CRAH-14 | E5: CRAH | H5: 30 | I5: 20
A6: MH-DC-001-CRAH-15 | B6: MH-DC-001 | C6: MH-DC-001-F0-R1 | D6: CRAH-15 | E6: CRAC | H6: 30 | I6: 20
A7: MH-DC-001-CRAH-16 | B7: MH-DC-001 | C7: MH-DC-001-F0-R2 | D7: CRAH-16 | E7: CRAH | H7: 30 | I7: 18
A8: MH-DC-001-CRAH-17 | B8: MH-DC-001 | C8: MH-DC-001-F1-R1 | D8: CRAH-17 | E8: CRAH | H8: 30 | I8: 18
A9: MH-DC-001-CRAH-18 | B9: MH-DC-001 | C9: MH-DC-001-F1-R2 | D9: CRAH-18 | E9: CRAH | H9: 30 | I9: 19
A10: MH-DC-002-CRAH-11 | B10: MH-DC-002 | C10: MH-DC-002-F0-R1 | D10: CRAH-11 | E10: CRAH | H10: 24 | I10: 20
A11: MH-DC-002-CRAH-12 | B11: MH-DC-002 | C11: MH-DC-002-F0-R2 | D11: CRAH-12 | E11: CRAH | H11: 24 | I11: 18
A12: MH-DC-002-CRAH-13 | B12: MH-DC-002 | C12: MH-DC-002-F1-R1 | D12: CRAH-13 | E12: CRAH | H12: 24 | I12: 20
A13: MH-DC-002-CRAH-14 | B13: MH-DC-002 | C13: MH-DC-002-F1-R2 | D13: CRAH-14 | E13: CRAH | H13: 24 | I13: 19
... A18: MH-DC-002-CDU-1 | B18: MH-DC-002 | C18: MH-DC-002-F0-R1 | D18: CDU-1 | E18: CDU | H18: 150 | I18: 26.8

Sheet CDUs
A1: cdu_id * | B1: site_id * | C1: room_id * | D1: name * | E1: capacity_kw * | F1: nominal_flow_lpm * | G1: design_supply_c | H1: racks_served (calc)
A2: MH-DC-002-CDU-1 | B2: MH-DC-002 | C2: MH-DC-002-F0-R1 | D2: CDU-1 | E2: 150 | F2: 220 | G2: 26.8 | H2: =COUNTIF('Racks'!$O$2:$O$2000,A2)

Sheet Sensors
A1: sensor_id * | B1: site_id * | C1: room_id * | D1: kind * | E1: position | F1: bms_point
A2: MH-DC-001-ENV-1 | B2: MH-DC-001 | C2: MH-DC-001-F0-R1 | D2: Temperature + humidity
A3: MH-DC-001-ENV-2 | B3: MH-DC-001 | C3: MH-DC-001-F0-R2 | D3: Temperature + humidity
A4: MH-DC-001-ENV-3 | B4: MH-DC-001 | C4: MH-DC-001-F1-R1 | D4: Temperature + humidity
A5: MH-DC-001-ENV-4 | B5: MH-DC-001 | C5: MH-DC-001-F1-R2 | D5: Temperature + humidity
A6: MH-DC-002-ENV-1 | B6: MH-DC-002 | C6: MH-DC-002-F0-R1 | D6: Temperature + humidity
A7: MH-DC-002-ENV-2 | B7: MH-DC-002 | C7: MH-DC-002-F0-R2 | D7: Temperature + humidity
A8: MH-DC-002-ENV-3 | B8: MH-DC-002 | C8: MH-DC-002-F1-R1 | D8: Temperature + humidity
A9: MH-DC-002-ENV-4 | B9: MH-DC-002 | C9: MH-DC-002-F1-R2 | D9: Temperature + humidity

Sheet Devices
A1: device_id * | B1: site_id * | C1: hostname * | D1: role * | E1: layer * | F1: vendor * | G1: model * | H1: os_version | I1: serial | J1: mgmt_ip | K1: mac | L1: rack_id * | M1: u_position * | N1: u_size * | O1: lifecycle * | P1: owner * | Q1: tenant_customer_id | R1: monitored * | S1: collector_id | T1: wan_edge
A2: MH-DC-001-PE-T4-01 | B2: MH-DC-001 | C2: MH-DC-001-PE-T4-01 | D2: Router | E2: core | F2: JUNIPER | G2: MX204 | H2: 21.4R3-S5.5 | I2: JU0011000 | J2: 172.31.40.20 | K2: A4:5E:60:16:8F:48 | L2: MH-DC-001-RACK-A | M2: 2 | N2: 1 | O2: Ready | P2: operator | R2: Y | S2: COL-MH-DC-001-2 | T2: Y
A3: MH-DC-001-PE-T4-02 | B3: MH-DC-001 | C3: MH-DC-001-PE-T4-02 | D3: Router | E3: core | F3: JUNIPER | G3: MX204 | H3: 21.4R3-S5.5 | I3: JU0011012 | J3: 172.16.40.21 | K3: A4:5E:60:E4:96:7C | L3: MH-DC-001-RACK-A | M3: 3 | N3: 1 | O3: Ready | P3: operator | R3: Y | S3: COL-MH-DC-001-1 | T3: Y
A4: MH-DC-001-PE-T4-03 | B4: MH-DC-001 | C4: MH-DC-001-PE-T4-03 | D4: Router | E4: core | F4: CISCO | G4: ASR 9006 | H4: IOS XR 7.9.2 | I4: CS0011018 | J4: 172.16.40.22 | K4: A4:5E:60:03:E2:69 | L4: MH-DC-001-RACK-A | M4: 4 | N4: 1 | O4: Ready | P4: operator | R4: Y | S4: COL-MH-DC-001-2 | T4: Y
A5: MH-DC-001-PE-T4-04 | B5: MH-DC-001 | C5: MH-DC-001-PE-T4-04 | D5: Router | E5: core | F5: CISCO | G5: ASR 9006 | H5: IOS XR 7.9.2 | I5: CS0011027 | J5: 172.16.40.23 | K5: A4:5E:60:71:F5:F9 | L5: MH-DC-001-RACK-A | M5: 5 | N5: 1 | O5: Ready | P5: operator | R5: Y | S5: COL-MH-DC-001-1 | T5: Y
A6: MH-DC-001-FW-01 | B6: MH-DC-001 | C6: MH-DC-001-FW-01 | D6: Firewall | E6: core | F6: FORTINET | G6: FortiGate 3700F | H6: FortiOS 7.4.3 | I6: FG0011031 | J6: 172.16.40.24 | K6: A4:5E:60:B1:E8:37 | L6: MH-DC-001-RACK-A | M6: 6 | N6: 3 | O6: Ready | P6: operator | R6: Y | S6: COL-MH-DC-001-1 | T6: N
A7: MH-DC-001-FW-02 | B7: MH-DC-001 | C7: MH-DC-001-FW-02 | D7: Firewall | E7: core | F7: FORTINET | G7: FortiGate 3700F | H7: FortiOS 7.4.3 | I7: FG0011035 | J7: 172.16.40.25 | K7: A4:5E:60:FA:5F:B0 | L7: MH-DC-001-RACK-A | M7: 9 | N7: 3 | O7: Ready | P7: operator | R7: Y | S7: COL-MH-DC-001-2 | T7: N
A8: MH-DC-001-OLA-01 | B8: MH-DC-001 | C8: MH-DC-001-OLA-01 | D8: DWDM | E8: core | F8: NOKIA | G8: 1830 PSS-16II | H8: R23.6 | I8: NK0011042 | J8: 172.16.40.26 | K8: A4:5E:60:95:3C:15 | L8: MH-DC-001-RACK-A | M8: 12 | N8: 6 | O8: Ready | P8: operator | R8: Y | S8: COL-MH-DC-001-2 | T8: N
A9: MH-DC-001-OLA-02 | B9: MH-DC-001 | C9: MH-DC-001-OLA-02 | D9: DWDM | E9: core | F9: NOKIA | G9: 1830 PSS-16II | H9: R23.6 | I9: NK0011055 | J9: 172.16.40.27 | K9: A4:5E:60:B4:0B:73 | L9: MH-DC-001-RACK-A | M9: 18 | N9: 6 | O9: Ready | P9: operator | R9: Y | S9: COL-MH-DC-001-1 | T9: N
A10: MH-DC-001-AGG-R01 | B10: MH-DC-001 | C10: MH-DC-001-AGG-R01 | D10: Router | E10: spine | F10: JUNIPER | G10: MX480 | H10: 22.2R3-S2 | I10: JU0011062 | J10: 172.16.40.28 | K10: A4:5E:60:33:FB:48 | L10: MH-DC-001-RACK-A | M10: 24 | N10: 4 | O10: Ready | P10: operator | R10: Y | S10: COL-MH-DC-001-1 | T10: N
A11: MH-DC-001-AGG-R02 | B11: MH-DC-001 | C11: MH-DC-001-AGG-R02 | D11: Router | E11: spine | F11: JUNIPER | G11: MX480 | H11: 22.2R3-S2 | I11: JU0011065 | J11: 172.16.40.29 | K11: A4:5E:60:9F:2F:3B | L11: MH-DC-001-RACK-A | M11: 28 | N11: 4 | O11: Ready | P11: operator | R11: Y | S11: COL-MH-DC-001-2 | T11: N
A12: MH-DC-001-AGG-R03 | B12: MH-DC-001 | C12: MH-DC-001-AGG-R03 | D12: Router | E12: spine | F12: JUNIPER | G12: MX480 | H12: 22.2R3-S2 | I12: JU0011071 | J12: 172.16.40.30 | K12: A4:5E:60:EF:F0:A5 | L12: MH-DC-001-RACK-A | M12: 32 | N12: 4 | O12: Ready | P12: operator | R12: Y | S12: COL-MH-DC-001-1 | T12: N
A13: MH-DC-001-MMR-SW-01 | B13: MH-DC-001 | C13: MH-DC-001-MMR-SW-01 | D13: Switch | E13: leaf | F13: JUNIPER | G13: QFX5100-48S | H13: Junos 21.4R3-S6 | I13: JU0011080 | J13: 172.16.40.31 | K13: A4:5E:60:C0:C8:FC | L13: MH-DC-001-RACK-A | M13: 36 | N13: 1 | O13: Ready | P13: operator | R13: Y | S13: COL-MH-DC-001-1 | T13: N
... A27: MH-DC-001-TOR-006 | B27: MH-DC-001 | C27: MH-DC-001-TOR-006 | D27: Switch | E27: access | F27: ARISTA | G27: 7050SX3-48YC | H27: EOS 4.31.1F | I27: AR0011180 | J27: 172.16.40.45 | K27: A4:5E:60:F6:66:F8 | L27: MH-DC-001-RACK-B | M27: 15 | N27: 1 | O27: Ready | P27: operator | R27: Y | S27: COL-MH-DC-001-2 | T27: N
A28: MH-DC-001-TN-001 | B28: MH-DC-001 | C28: MH-DC-001-TN-001 | D28: Tenant gear | E28: access | F28: Tenant-owned | G28: Mixed equipment | H28: — | L28: MH-DC-001-RACK-B | M28: 16 | N28: 6 | O28: Ready | P28: tenant | R28: N | T28: N
A29: MH-DC-001-TN-002 | B29: MH-DC-001 | C29: MH-DC-001-TN-002 | D29: Tenant gear | E29: access | F29: Tenant-owned | G29: Network stack | H29: — | L29: MH-DC-001-RACK-B | M29: 22 | N29: 6 | O29: Ready | P29: tenant | R29: N | T29: N
A30: MH-DC-001-TN-003 | B30: MH-DC-001 | C30: MH-DC-001-TN-003 | D30: Tenant gear | E30: access | F30: Tenant-owned | G30: Network stack | H30: — | L30: MH-DC-001-RACK-C | M30: 2 | N30: 8 | O30: Ready | P30: tenant | Q30: CUST-7349 | R30: N | T30: N
A31: MH-DC-001-TN-004 | B31: MH-DC-001 | C31: MH-DC-001-TN-004 | D31: Tenant gear | E31: access | F31: Tenant-owned | G31: Network stack | H31: — | L31: MH-DC-001-RACK-C | M31: 10 | N31: 4 | O31: Ready | P31: tenant | Q31: CUST-7349 | R31: N | T31: N
A32: MH-DC-001-TN-005 | B32: MH-DC-001 | C32: MH-DC-001-TN-005 | D32: Tenant gear | E32: access | F32: Tenant-owned | G32: Storage array | H32: — | L32: MH-DC-001-RACK-C | M32: 14 | N32: 4 | O32: Ready | P32: tenant | Q32: CUST-7349 | R32: N | T32: N
A33: MH-DC-001-TN-006 | B33: MH-DC-001 | C33: MH-DC-001-TN-006 | D33: Tenant gear | E33: access | F33: Tenant-owned | G33: HPC nodes | H33: — | L33: MH-DC-001-RACK-C | M33: 18 | N33: 2 | O33: Ready | P33: tenant | Q33: CUST-7349 | R33: N | T33: N
A34: MH-DC-001-TN-007 | B34: MH-DC-001 | C34: MH-DC-001-TN-007 | D34: Tenant gear | E34: access | F34: Tenant-owned | G34: Blade chassis | H34: — | L34: MH-DC-001-RACK-C | M34: 20 | N34: 8 | O34: Ready | P34: tenant | Q34: CUST-7349 | R34: N | T34: N
A35: MH-DC-001-TN-008 | B35: MH-DC-001 | C35: MH-DC-001-TN-008 | D35: Tenant gear | E35: access | F35: Tenant-owned | G35: Mixed equipment | H35: — | L35: MH-DC-001-RACK-C | M35: 28 | N35: 4 | O35: Ready | P35: tenant | Q35: CUST-7349 | R35: N | T35: N
A36: MH-DC-001-TN-009 | B36: MH-DC-001 | C36: MH-DC-001-TN-009 | D36: Tenant gear | E36: access | F36: Tenant-owned | G36: Blade chassis | H36: — | L36: MH-DC-001-RACK-C | M36: 32 | N36: 4 | O36: Ready | P36: tenant | Q36: CUST-7349 | R36: N | T36: N
A37: MH-DC-001-TN-010 | B37: MH-DC-001 | C37: MH-DC-001-TN-010 | D37: Tenant gear | E37: access | F37: Tenant-owned | G37: Mixed equipment | H37: — | L37: MH-DC-001-RACK-D | M37: 2 | N37: 10 | O37: Ready | P37: tenant | Q37: CUST-2954 | R37: N | T37: N
A38: MH-DC-001-TN-011 | B38: MH-DC-001 | C38: MH-DC-001-TN-011 | D38: Tenant gear | E38: access | F38: Tenant-owned | G38: Network stack | H38: — | L38: MH-DC-001-RACK-D | M38: 12 | N38: 2 | O38: Ready | P38: tenant | Q38: CUST-2954 | R38: N | T38: N
A39: MH-DC-001-TN-012 | B39: MH-DC-001 | C39: MH-DC-001-TN-012 | D39: Tenant gear | E39: access | F39: Tenant-owned | G39: Network stack | H39: — | L39: MH-DC-001-RACK-D | M39: 14 | N39: 10 | O39: Ready | P39: tenant | Q39: CUST-2954 | R39: N | T39: N
A40: MH-DC-001-TN-013 | B40: MH-DC-001 | C40: MH-DC-001-TN-013 | D40: Tenant gear | E40: access | F40: Tenant-owned | G40: Network stack | H40: — | L40: MH-DC-001-RACK-D | M40: 24 | N40: 2 | O40: Ready | P40: tenant | Q40: CUST-2954 | R40: N | T40: N
A41: MH-DC-001-TN-014 | B41: MH-DC-001 | C41: MH-DC-001-TN-014 | D41: Tenant gear | E41: access | F41: Tenant-owned | G41: Storage array | H41: — | L41: MH-DC-001-RACK-D | M41: 26 | N41: 10 | O41: Ready | P41: tenant | Q41: CUST-2954 | R41: N | T41: N
... A108: MH-DC-001-TN-081 | B108: MH-DC-001 | C108: MH-DC-001-TN-081 | D108: Tenant gear | E108: access | F108: Tenant-owned | G108: Blade chassis | H108: — | L108: MH-DC-001-RACK-P | M108: 12 | N108: 6 | O108: Ready | P108: tenant | Q108: CUST-1202 | R108: N | T108: N
A109: MH-DC-001-BMS-01 | B109: MH-DC-001 | C109: MH-DC-001-BMS-01 | D109: Server | E109: access | F109: DELL | G109: PowerEdge R640 | H109: ESXi 7.0u3 | I109: DL0011754 | J109: 172.16.40.127 | K109: A4:5E:60:F6:F0:87 | L109: MH-DC-001-RACK-U | M109: 2 | N109: 1 | O109: Ready | P109: operator | R109: Y | S109: COL-MH-DC-001-2 | T109: N
A110: MH-DC-001-BMS-02 | B110: MH-DC-001 | C110: MH-DC-001-BMS-02 | D110: Server | E110: access | F110: DELL | G110: PowerEdge R640 | H110: ESXi 7.0u3 | I110: DL0011762 | J110: 172.16.40.128 | K110: A4:5E:60:5C:CC:A7 | L110: MH-DC-001-RACK-U | M110: 3 | N110: 1 | O110: Ready | P110: operator | R110: Y | S110: COL-MH-DC-001-1 | T110: N
A111: MH-DC-001-ACS-01 | B111: MH-DC-001 | C111: MH-DC-001-ACS-01 | D111: Server | E111: access | F111: SUPERMICRO | G111: SYS-121H | H111: Ubuntu 22.04 | I111: SM0011765 | J111: 172.16.40.129 | K111: A4:5E:60:75:E5:C9 | L111: MH-DC-001-RACK-U | M111: 4 | N111: 1 | O111: Ready | P111: operator | R111: Y | S111: COL-MH-DC-001-1 | T111: N
A112: MH-DC-001-NVR-01 | B112: MH-DC-001 | C112: MH-DC-001-NVR-01 | D112: Server | E112: access | F112: HPE | G112: ProLiant DL380 Gen11 | H112: RHEL 9.3 | I112: HP0011772 | J112: 172.16.40.130 | K112: A4:5E:60:13:C5:EA | L112: MH-DC-001-RACK-U | M112: 5 | N112: 2 | O112: Ready | P112: operator | R112: Y | S112: COL-MH-DC-001-2 | T112: N
A113: MH-DC-001-NVR-02 | B113: MH-DC-001 | C113: MH-DC-001-NVR-02 | D113: Server | E113: access | F113: SUPERMICRO | G113: SYS-121H | H113: Ubuntu 22.04 | I113: SM0011779 | J113: 172.16.40.131 | K113: A4:5E:60:8D:93:D8 | L113: MH-DC-001-RACK-U | M113: 7 | N113: 2 | O113: Ready | P113: operator | R113: Y | S113: COL-MH-DC-001-1 | T113: N
A114: MH-DC-001-JMP-01 | B114: MH-DC-001 | C114: MH-DC-001-JMP-01 | D114: Server | E114: access | F114: SUPERMICRO | G114: SYS-121H | H114: Ubuntu 22.04 | I114: SM0011787 | J114: 172.16.40.132 | K114: A4:5E:60:0A:CB:A4 | L114: MH-DC-001-RACK-U | M114: 9 | N114: 1 | O114: Ready | P114: operator | R114: Y | S114: COL-MH-DC-001-1 | T114: N
A115: MH-DC-001-JMP-02 | B115: MH-DC-001 | C115: MH-DC-001-JMP-02 | D115: Server | E115: access | F115: HPE | G115: ProLiant DL380 Gen11 | H115: RHEL 9.3 | I115: HP0011793 | J115: 172.16.40.133 | K115: A4:5E:60:B6:CB:A6 | L115: MH-DC-001-RACK-U | M115: 10 | N115: 1 | O115: Ready | P115: operator | R115: Y | S115: COL-MH-DC-001-2 | T115: N
A116: MH-DC-001-BKP-01 | B116: MH-DC-001 | C116: MH-DC-001-BKP-01 | D116: Server | E116: access | F116: DELL | G116: PowerEdge R760 | H116: ESXi 8.0u2 | I116: DL0011804 | J116: 172.16.40.134 | K116: A4:5E:60:4C:E0:FB | L116: MH-DC-001-RACK-U | M116: 11 | N116: 2 | O116: Ready | P116: operator | R116: Y | S116: COL-MH-DC-001-1 | T116: N
A117: MH-DC-001-DCIM-01 | B117: MH-DC-001 | C117: MH-DC-001-DCIM-01 | D117: Server | E117: access | F117: SUPERMICRO | G117: SYS-121H | H117: Ubuntu 22.04 | I117: SM0011811 | J117: 172.16.40.135 | K117: A4:5E:60:08:99:7B | L117: MH-DC-001-RACK-U | M117: 13 | N117: 1 | O117: Ready | P117: operator | R117: Y | S117: COL-MH-DC-001-1 | T117: N
A118: MH-DC-001-DCIM-02 | B118: MH-DC-001 | C118: MH-DC-001-DCIM-02 | D118: Server | E118: access | F118: SUPERMICRO | G118: SYS-121H | H118: Ubuntu 22.04 | I118: SM0011812 | J118: 172.16.40.136 | K118: A4:5E:60:AB:75:74 | L118: MH-DC-001-RACK-U | M118: 14 | N118: 1 | O118: Ready | P118: operator | R118: Y | S118: COL-MH-DC-001-2 | T118: N
A119: MH-DC-001-MON-01 | B119: MH-DC-001 | C119: MH-DC-001-MON-01 | D119: Server | E119: access | F119: HPE | G119: ProLiant DL380 Gen11 | H119: RHEL 9.3 | I119: HP0011825 | J119: 172.16.40.137 | K119: A4:5E:60:3A:44:87 | L119: MH-DC-001-RACK-U | M119: 15 | N119: 1 | O119: Ready | P119: operator | R119: Y | S119: COL-MH-DC-001-2 | T119: N
A120: MH-DC-001-MON-02 | B120: MH-DC-001 | C120: MH-DC-001-MON-02 | D120: Server | E120: access | F120: DELL | G120: PowerEdge R760 | H120: ESXi 8.0u2 | I120: DL0011829 | J120: 172.16.40.138 | K120: A4:5E:60:72:5C:E6 | L120: MH-DC-001-RACK-U | M120: 16 | N120: 1 | O120: Ready | P120: operator | R120: Y | S120: COL-MH-DC-001-1 | T120: N
... A135: MH-DC-002-TOR-003 | B135: MH-DC-002 | C135: MH-DC-002-TOR-003 | D135: Switch | E135: access | F135: CISCO | G135: Nexus 93180YC | H135: NX-OS 10.3(4a) | I135: CS0011101 | J135: 172.25.40.34 | K135: A4:5E:60:0A:23:80 | L135: MH-DC-002-RACK-A | M135: 29 | N135: 1 | O135: Ready | P135: operator | R135: Y | S135: COL-MH-DC-002-2 | T135: N
A136: MH-DC-002-TN-001 | B136: MH-DC-002 | C136: MH-DC-002-TN-001 | D136: Tenant gear | E136: access | F136: Tenant-owned | G136: Storage array | H136: — | L136: MH-DC-002-RACK-B | M136: 2 | N136: 10 | O136: Ready | P136: tenant | Q136: CUST-7349 | R136: N | T136: N
A137: MH-DC-002-TN-002 | B137: MH-DC-002 | C137: MH-DC-002-TN-002 | D137: Tenant gear | E137: access | F137: Tenant-owned | G137: Network stack | H137: — | L137: MH-DC-002-RACK-B | M137: 12 | N137: 2 | O137: Ready | P137: tenant | Q137: CUST-7349 | R137: N | T137: N
A138: MH-DC-002-TN-003 | B138: MH-DC-002 | C138: MH-DC-002-TN-003 | D138: Tenant gear | E138: access | F138: Tenant-owned | G138: Rack servers | H138: — | L138: MH-DC-002-RACK-B | M138: 14 | N138: 4 | O138: Ready | P138: tenant | Q138: CUST-7349 | R138: N | T138: N
A139: MH-DC-002-TN-004 | B139: MH-DC-002 | C139: MH-DC-002-TN-004 | D139: Tenant gear | E139: access | F139: Tenant-owned | G139: Storage array | H139: — | L139: MH-DC-002-RACK-B | M139: 18 | N139: 6 | O139: Ready | P139: tenant | Q139: CUST-7349 | R139: N | T139: N
A140: MH-DC-002-TN-005 | B140: MH-DC-002 | C140: MH-DC-002-TN-005 | D140: Tenant gear | E140: access | F140: Tenant-owned | G140: Blade chassis | H140: — | L140: MH-DC-002-RACK-B | M140: 24 | N140: 6 | O140: Ready | P140: tenant | Q140: CUST-7349 | R140: N | T140: N
A141: MH-DC-002-TN-006 | B141: MH-DC-002 | C141: MH-DC-002-TN-006 | D141: Tenant gear | E141: access | F141: Tenant-owned | G141: Blade chassis | H141: — | L141: MH-DC-002-RACK-B | M141: 30 | N141: 2 | O141: Ready | P141: tenant | Q141: CUST-7349 | R141: N | T141: N
A142: MH-DC-002-TN-007 | B142: MH-DC-002 | C142: MH-DC-002-TN-007 | D142: Tenant gear | E142: access | F142: Tenant-owned | G142: Rack servers | H142: — | L142: MH-DC-002-RACK-C | M142: 2 | N142: 4 | O142: Ready | P142: tenant | Q142: CUST-7349 | R142: N | T142: N
A143: MH-DC-002-TN-008 | B143: MH-DC-002 | C143: MH-DC-002-TN-008 | D143: Tenant gear | E143: access | F143: Tenant-owned | G143: HPC nodes | H143: — | L143: MH-DC-002-RACK-C | M143: 6 | N143: 4 | O143: Ready | P143: tenant | Q143: CUST-7349 | R143: N | T143: N
A144: MH-DC-002-TN-009 | B144: MH-DC-002 | C144: MH-DC-002-TN-009 | D144: Tenant gear | E144: access | F144: Tenant-owned | G144: Storage array | H144: — | L144: MH-DC-002-RACK-C | M144: 10 | N144: 6 | O144: Ready | P144: tenant | Q144: CUST-7349 | R144: N | T144: N
A145: MH-DC-002-TN-010 | B145: MH-DC-002 | C145: MH-DC-002-TN-010 | D145: Tenant gear | E145: access | F145: Tenant-owned | G145: Blade chassis | H145: — | L145: MH-DC-002-RACK-C | M145: 16 | N145: 6 | O145: Ready | P145: tenant | Q145: CUST-7349 | R145: N | T145: N
A146: MH-DC-002-TN-011 | B146: MH-DC-002 | C146: MH-DC-002-TN-011 | D146: Tenant gear | E146: access | F146: Tenant-owned | G146: Network stack | H146: — | L146: MH-DC-002-RACK-C | M146: 22 | N146: 10 | O146: Ready | P146: tenant | Q146: CUST-7349 | R146: N | T146: N
A147: MH-DC-002-TN-012 | B147: MH-DC-002 | C147: MH-DC-002-TN-012 | D147: Tenant gear | E147: access | F147: Tenant-owned | G147: Mixed equipment | H147: — | L147: MH-DC-002-RACK-D | M147: 2 | N147: 8 | O147: Ready | P147: tenant | Q147: CUST-8220 | R147: N | T147: N
... A174: MH-DC-002-TN-039 | B174: MH-DC-002 | C174: MH-DC-002-TN-039 | D174: Tenant gear | E174: access | F174: Tenant-owned | G174: Storage array | H174: — | L174: MH-DC-002-RACK-I | M174: 2 | N174: 4 | O174: Ready | P174: tenant | Q174: CUST-1202 | R174: N | T174: N
A175: MH-DC-002-BMS-01 | B175: MH-DC-002 | C175: MH-DC-002-BMS-01 | D175: Server | E175: access | F175: SUPERMICRO | G175: SYS-120U-TNR | H175: Ubuntu 20.04 | I175: SM0011380 | J175: 172.25.40.74 | K175: A4:5E:60:94:BE:74 | L175: MH-DC-002-RACK-K | M175: 2 | N175: 1 | O175: Ready | P175: operator | R175: Y | S175: COL-MH-DC-002-1 | T175: N
A176: MH-DC-002-BMS-02 | B176: MH-DC-002 | C176: MH-DC-002-BMS-02 | D176: Server | E176: access | F176: SUPERMICRO | G176: SYS-120U-TNR | H176: Ubuntu 20.04 | I176: SM0011389 | J176: 172.25.40.75 | K176: A4:5E:60:66:82:17 | L176: MH-DC-002-RACK-K | M176: 3 | N176: 1 | O176: Ready | P176: operator | R176: Y | S176: COL-MH-DC-002-2 | T176: N
A177: MH-DC-002-ACS-01 | B177: MH-DC-002 | C177: MH-DC-002-ACS-01 | D177: Server | E177: access | F177: SUPERMICRO | G177: SYS-120U-TNR | H177: Ubuntu 20.04 | I177: SM0011397 | J177: 172.25.40.76 | K177: A4:5E:60:8A:08:08 | L177: MH-DC-002-RACK-K | M177: 4 | N177: 1 | O177: Ready | P177: operator | R177: Y | S177: COL-MH-DC-002-2 | T177: N
A178: MH-DC-002-NVR-01 | B178: MH-DC-002 | C178: MH-DC-002-NVR-01 | D178: Server | E178: access | F178: DELL | G178: PowerEdge R760 | H178: ESXi 8.0u2 | I178: DL0011403 | J178: 172.25.40.77 | K178: A4:5E:60:4D:49:3D | L178: MH-DC-002-RACK-K | M178: 5 | N178: 2 | O178: Ready | P178: operator | R178: Y | S178: COL-MH-DC-002-1 | T178: N
A179: MH-DC-002-JMP-01 | B179: MH-DC-002 | C179: MH-DC-002-JMP-01 | D179: Server | E179: access | F179: HPE | G179: ProLiant DL380 Gen11 | H179: RHEL 9.3 | I179: HP0011412 | J179: 172.25.40.78 | K179: A4:5E:60:69:32:87 | L179: MH-DC-002-RACK-K | M179: 7 | N179: 1 | O179: Ready | P179: operator | R179: Y | S179: COL-MH-DC-002-2 | T179: N
A180: MH-DC-002-BKP-01 | B180: MH-DC-002 | C180: MH-DC-002-BKP-01 | D180: Server | E180: access | F180: HPE | G180: ProLiant DL380 Gen11 | H180: RHEL 9.3 | I180: HP0011414 | J180: 172.25.40.79 | K180: A4:5E:60:B3:E9:22 | L180: MH-DC-002-RACK-K | M180: 8 | N180: 2 | O180: Ready | P180: operator | R180: Y | S180: COL-MH-DC-002-2 | T180: N
A181: MH-DC-002-DCIM-01 | B181: MH-DC-002 | C181: MH-DC-002-DCIM-01 | D181: Server | E181: access | F181: HPE | G181: ProLiant DL380 Gen11 | H181: RHEL 9.3 | I181: HP0011421 | J181: 172.25.40.80 | K181: A4:5E:60:E1:15:4B | L181: MH-DC-002-RACK-K | M181: 10 | N181: 1 | O181: Ready | P181: operator | R181: Y | S181: COL-MH-DC-002-2 | T181: N
A182: MH-DC-002-DCIM-02 | B182: MH-DC-002 | C182: MH-DC-002-DCIM-02 | D182: Server | E182: access | F182: SUPERMICRO | G182: SYS-121H | H182: Ubuntu 22.04 | I182: SM0011433 | J182: 172.25.40.81 | K182: A4:5E:60:2B:DA:2C | L182: MH-DC-002-RACK-K | M182: 11 | N182: 1 | O182: Ready | P182: operator | R182: Y | S182: COL-MH-DC-002-1 | T182: N
A183: MH-DC-002-MON-01 | B183: MH-DC-002 | C183: MH-DC-002-MON-01 | D183: Server | E183: access | F183: SUPERMICRO | G183: SYS-121H | H183: Ubuntu 22.04 | I183: SM0011438 | J183: 172.25.40.82 | K183: A4:5E:60:F9:7D:B9 | L183: MH-DC-002-RACK-K | M183: 12 | N183: 1 | O183: Ready | P183: operator | R183: Y | S183: COL-MH-DC-002-1 | T183: N
A184: MH-DC-002-MON-02 | B184: MH-DC-002 | C184: MH-DC-002-MON-02 | D184: Server | E184: access | F184: DELL | G184: PowerEdge R760 | H184: ESXi 8.0u2 | I184: DL0011443 | J184: 172.25.40.83 | K184: A4:5E:60:EF:A9:35 | L184: MH-DC-002-RACK-K | M184: 13 | N184: 1 | O184: Ready | P184: operator | R184: Y | S184: COL-MH-DC-002-2 | T184: N

Sheet Modules
A1: device_id * | B1: slot * | C1: name * | D1: serial
A2: MH-DC-001-PE-T4-01 | B2: RE0 | C2: Routing Engine | D2: JU0011000-RE0
A3: MH-DC-001-PE-T4-01 | B3: FPC0 | C3: MPC (fixed) | D3: JU0011000-F0
A4: MH-DC-001-PE-T4-01 | B4: PEM0 | C4: Power supply AC | D4: JU0011000-P0
A5: MH-DC-001-PE-T4-01 | B5: PEM1 | C5: Power supply AC | D5: JU0011000-P1
A6: MH-DC-001-PE-T4-01 | B6: FAN0 | C6: Fan tray | D6: JU0011000-FT
A7: MH-DC-001-PE-T4-02 | B7: RE0 | C7: Routing Engine | D7: JU0011012-RE0
A8: MH-DC-001-PE-T4-02 | B8: FPC0 | C8: MPC (fixed) | D8: JU0011012-F0
A9: MH-DC-001-PE-T4-02 | B9: PEM0 | C9: Power supply AC | D9: JU0011012-P0
A10: MH-DC-001-PE-T4-02 | B10: PEM1 | C10: Power supply AC | D10: JU0011012-P1
A11: MH-DC-001-PE-T4-02 | B11: FAN0 | C11: Fan tray | D11: JU0011012-FT
A12: MH-DC-001-PE-T4-03 | B12: RE0 | C12: Routing Engine | D12: CS0011018-RE0
... A304: MH-DC-002-MON-02 | B304: DISK3 | C304: NVMe 3.84 TB | D304: DL0011443-D3

Sheet Interfaces
A1: device_id * | B1: if_name * | C1: type * | D1: speed_mbps * | E1: admin_state * | F1: description | G1: optic_model
A2: MH-DC-001-PE-T4-01 | B2: xe-0/0/0 | C2: 10G SFP+ | D2: 10000 | E2: admin-down
A3: MH-DC-001-PE-T4-01 | B3: xe-0/0/1 | C3: 10G SFP+ | D3: 10000 | E3: up | F3: Backhaul to UP-DC-006 | G3: SFP-10G-LR
A4: MH-DC-001-PE-T4-01 | B4: xe-0/0/2 | C4: 10G SFP+ | D4: 10000 | E4: up | F4: Backhaul to KA-DC-021 | G4: SFP-10G-LR
A5: MH-DC-001-PE-T4-01 | B5: xe-0/0/3 | C5: 10G SFP+ | D5: 10000 | E5: up | F5: Backhaul to TS-DC-023 | G5: SFP-10G-LR
A6: MH-DC-001-PE-T4-01 | B6: xe-0/0/4 | C6: 10G SFP+ | D6: 10000 | E6: up | F6: Backhaul to BR-DC-019 | G6: SFP-10G-LR
A7: MH-DC-001-PE-T4-01 | B7: xe-0/0/5 | C7: 10G SFP+ | D7: 10000 | E7: up | F7: Backhaul to PB-DC-012 | G7: SFP-10G-LR
A8: MH-DC-001-PE-T4-01 | B8: xe-0/0/6 | C8: 10G SFP+ | D8: 10000 | E8: up | F8: Uplink to MH-DC-001-AGG-R01 | G8: SFP-10G-LR
A9: MH-DC-001-PE-T4-01 | B9: xe-0/0/7 | C9: 10G SFP+ | D9: 10000 | E9: admin-down
A10: MH-DC-001-PE-T4-01 | B10: xe-0/0/8 | C10: 10G SFP+ | D10: 10000 | E10: admin-down
A11: MH-DC-001-PE-T4-01 | B11: xe-0/0/9 | C11: 10G SFP+ | D11: 10000 | E11: admin-down
A12: MH-DC-001-PE-T4-01 | B12: xe-0/0/10 | C12: 10G SFP+ | D12: 10000 | E12: admin-down
A13: MH-DC-001-PE-T4-01 | B13: xe-0/0/11 | C13: 10G SFP+ | D13: 10000 | E13: admin-down
A14: MH-DC-001-PE-T4-01 | B14: et-0/1/0 | C14: 100G QSFP28 | D14: 100000 | E14: up | F14: Fabric to MH-DC-001-PE-T4-02 | G14: QSFP28-100G-LR4
A15: MH-DC-001-PE-T4-01 | B15: et-0/1/1 | C15: 100G QSFP28 | D15: 100000 | E15: up | F15: Fabric to MH-DC-001-PE-T4-03 | G15: QSFP28-100G-LR4
A16: MH-DC-001-PE-T4-01 | B16: et-0/1/2 | C16: 100G QSFP28 | D16: 100000 | E16: up | F16: Fabric to MH-DC-001-PE-T4-04 | G16: QSFP28-100G-LR4
A17: MH-DC-001-PE-T4-01 | B17: et-0/1/3 | C17: 100G QSFP28 | D17: 100000 | E17: reserved
A18: MH-DC-001-PE-T4-01 | B18: ge-0/2/0 | C18: 1G copper | D18: 1000 | E18: reserved
A19: MH-DC-001-PE-T4-01 | B19: ge-0/2/1 | C19: 1G copper | D19: 1000 | E19: admin-down
A20: MH-DC-001-PE-T4-01 | B20: ge-0/2/2 | C20: 1G copper | D20: 1000 | E20: admin-down
A21: MH-DC-001-PE-T4-01 | B21: ge-0/2/3 | C21: 1G copper | D21: 1000 | E21: admin-down
A22: MH-DC-001-PE-T4-01 | B22: ge-0/2/4 | C22: 1G copper | D22: 1000 | E22: admin-down
A23: MH-DC-001-PE-T4-01 | B23: ge-0/2/5 | C23: 1G copper | D23: 1000 | E23: admin-down
A24: MH-DC-001-PE-T4-01 | B24: ge-0/2/6 | C24: 1G copper | D24: 1000 | E24: admin-down
A25: MH-DC-001-PE-T4-01 | B25: ge-0/2/7 | C25: 1G copper | D25: 1000 | E25: admin-down
A26: MH-DC-001-PE-T4-01 | B26: ge-0/2/8 | C26: 1G copper | D26: 1000 | E26: admin-down
A27: MH-DC-001-PE-T4-01 | B27: ge-0/2/9 | C27: 1G copper | D27: 1000 | E27: admin-down
A28: MH-DC-001-PE-T4-01 | B28: ge-0/2/10 | C28: 1G copper | D28: 1000 | E28: admin-down
... A34: MH-DC-001-PE-T4-02 | B34: xe-0/0/0 | C34: 10G SFP+ | D34: 10000 | E34: admin-down
A35: MH-DC-001-PE-T4-02 | B35: xe-0/0/1 | C35: 10G SFP+ | D35: 10000 | E35: up | F35: Backhaul to HR-DC-011 | G35: SFP-10G-LR
A36: MH-DC-001-PE-T4-02 | B36: xe-0/0/2 | C36: 10G SFP+ | D36: 10000 | E36: up | F36: Backhaul to DL-DC-009 | G36: SFP-10G-LR
A37: MH-DC-001-PE-T4-02 | B37: xe-0/0/3 | C37: 10G SFP+ | D37: 10000 | E37: up | F37: Backhaul to UP-DC-006 | G37: SFP-10G-LR
A38: MH-DC-001-PE-T4-02 | B38: xe-0/0/4 | C38: 10G SFP+ | D38: 10000 | E38: up | F38: Backhaul to BR-DC-019 | G38: SFP-10G-LR
A39: MH-DC-001-PE-T4-02 | B39: xe-0/0/5 | C39: 10G SFP+ | D39: 10000 | E39: up | F39: Backhaul to TS-DC-023 | G39: SFP-10G-LR
A40: MH-DC-001-PE-T4-02 | B40: xe-0/0/6 | C40: 10G SFP+ | D40: 10000 | E40: up | F40: Uplink to MH-DC-001-AGG-R01 | G40: SFP-10G-LR
A41: MH-DC-001-PE-T4-02 | B41: xe-0/0/7 | C41: 10G SFP+ | D41: 10000 | E41: up | F41: Uplink to MH-DC-001-AGG-R02 | G41: SFP-10G-LR
A42: MH-DC-001-PE-T4-02 | B42: xe-0/0/8 | C42: 10G SFP+ | D42: 10000 | E42: admin-down
A43: MH-DC-001-PE-T4-02 | B43: xe-0/0/9 | C43: 10G SFP+ | D43: 10000 | E43: admin-down
A44: MH-DC-001-PE-T4-02 | B44: xe-0/0/10 | C44: 10G SFP+ | D44: 10000 | E44: admin-down
A45: MH-DC-001-PE-T4-02 | B45: xe-0/0/11 | C45: 10G SFP+ | D45: 10000 | E45: admin-down
A46: MH-DC-001-PE-T4-02 | B46: et-0/1/0 | C46: 100G QSFP28 | D46: 100000 | E46: up | F46: Fabric to MH-DC-001-PE-T4-01 | G46: QSFP28-100G-LR4
A47: MH-DC-001-PE-T4-02 | B47: et-0/1/1 | C47: 100G QSFP28 | D47: 100000 | E47: up | F47: Fabric to MH-DC-001-PE-T4-03 | G47: QSFP28-100G-LR4
A48: MH-DC-001-PE-T4-02 | B48: et-0/1/2 | C48: 100G QSFP28 | D48: 100000 | E48: up | F48: Fabric to MH-DC-001-PE-T4-04 | G48: QSFP28-100G-LR4
A49: MH-DC-001-PE-T4-02 | B49: et-0/1/3 | C49: 100G QSFP28 | D49: 100000 | E49: admin-down
A50: MH-DC-001-PE-T4-02 | B50: ge-0/2/0 | C50: 1G copper | D50: 1000 | E50: admin-down
A51: MH-DC-001-PE-T4-02 | B51: ge-0/2/1 | C51: 1G copper | D51: 1000 | E51: admin-down
A52: MH-DC-001-PE-T4-02 | B52: ge-0/2/2 | C52: 1G copper | D52: 1000 | E52: admin-down
A53: MH-DC-001-PE-T4-02 | B53: ge-0/2/3 | C53: 1G copper | D53: 1000 | E53: reserved
A54: MH-DC-001-PE-T4-02 | B54: ge-0/2/4 | C54: 1G copper | D54: 1000 | E54: admin-down
A55: MH-DC-001-PE-T4-02 | B55: ge-0/2/5 | C55: 1G copper | D55: 1000 | E55: admin-down
A56: MH-DC-001-PE-T4-02 | B56: ge-0/2/6 | C56: 1G copper | D56: 1000 | E56: admin-down
A57: MH-DC-001-PE-T4-02 | B57: ge-0/2/7 | C57: 1G copper | D57: 1000 | E57: admin-down
A58: MH-DC-001-PE-T4-02 | B58: ge-0/2/8 | C58: 1G copper | D58: 1000 | E58: admin-down
A59: MH-DC-001-PE-T4-02 | B59: ge-0/2/9 | C59: 1G copper | D59: 1000 | E59: admin-down
A60: MH-DC-001-PE-T4-02 | B60: ge-0/2/10 | C60: 1G copper | D60: 1000 | E60: admin-down
... A66: MH-DC-001-PE-T4-03 | B66: Te0/0/0/0 | C66: 10G SFP+ | D66: 10000 | E66: admin-down
A67: MH-DC-001-PE-T4-03 | B67: Te0/0/0/1 | C67: 10G SFP+ | D67: 10000 | E67: up | F67: Backhaul to BR-DC-019 | G67: SFP-10G-LR
A68: MH-DC-001-PE-T4-03 | B68: Te0/0/0/2 | C68: 10G SFP+ | D68: 10000 | E68: up | F68: Backhaul to WB-DC-016 | G68: SFP-10G-LR
A69: MH-DC-001-PE-T4-03 | B69: Te0/0/0/3 | C69: 10G SFP+ | D69: 10000 | E69: up | F69: Backhaul to TN-DC-022 | G69: SFP-10G-LR
A70: MH-DC-001-PE-T4-03 | B70: Te0/0/0/4 | C70: 10G SFP+ | D70: 10000 | E70: up | F70: Backhaul to RJ-DC-015 | G70: SFP-10G-LR
A71: MH-DC-001-PE-T4-03 | B71: Te0/0/0/5 | C71: 10G SFP+ | D71: 10000 | E71: up | F71: Backhaul to HR-DC-011 | G71: SFP-10G-LR
A72: MH-DC-001-PE-T4-03 | B72: Te0/0/0/6 | C72: 10G SFP+ | D72: 10000 | E72: up | F72: Uplink to MH-DC-001-AGG-R02 | G72: SFP-10G-LR
A73: MH-DC-001-PE-T4-03 | B73: Te0/0/0/7 | C73: 10G SFP+ | D73: 10000 | E73: up | F73: Uplink to MH-DC-001-AGG-R03 | G73: SFP-10G-LR
A74: MH-DC-001-PE-T4-03 | B74: Te0/0/0/8 | C74: 10G SFP+ | D74: 10000 | E74: admin-down
A75: MH-DC-001-PE-T4-03 | B75: Te0/0/0/9 | C75: 10G SFP+ | D75: 10000 | E75: admin-down
A76: MH-DC-001-PE-T4-03 | B76: Te0/0/0/10 | C76: 10G SFP+ | D76: 10000 | E76: admin-down
A77: MH-DC-001-PE-T4-03 | B77: Te0/0/0/11 | C77: 10G SFP+ | D77: 10000 | E77: admin-down
A78: MH-DC-001-PE-T4-03 | B78: Hu0/0/1/0 | C78: 100G QSFP28 | D78: 100000 | E78: up | F78: Fabric to MH-DC-001-PE-T4-01 | G78: QSFP28-100G-LR4
A79: MH-DC-001-PE-T4-03 | B79: Hu0/0/1/1 | C79: 100G QSFP28 | D79: 100000 | E79: up | F79: Fabric to MH-DC-001-PE-T4-02 | G79: QSFP28-100G-LR4
A80: MH-DC-001-PE-T4-03 | B80: Hu0/0/1/2 | C80: 100G QSFP28 | D80: 100000 | E80: up | F80: Fabric to MH-DC-001-PE-T4-04 | G80: QSFP28-100G-LR4
A81: MH-DC-001-PE-T4-03 | B81: Hu0/0/1/3 | C81: 100G QSFP28 | D81: 100000 | E81: reserved
A82: MH-DC-001-PE-T4-03 | B82: Gi0/0/2/0 | C82: 1G copper | D82: 1000 | E82: admin-down
A83: MH-DC-001-PE-T4-03 | B83: Gi0/0/2/1 | C83: 1G copper | D83: 1000 | E83: admin-down
A84: MH-DC-001-PE-T4-03 | B84: Gi0/0/2/2 | C84: 1G copper | D84: 1000 | E84: admin-down
A85: MH-DC-001-PE-T4-03 | B85: Gi0/0/2/3 | C85: 1G copper | D85: 1000 | E85: admin-down
A86: MH-DC-001-PE-T4-03 | B86: Gi0/0/2/4 | C86: 1G copper | D86: 1000 | E86: admin-down
A87: MH-DC-001-PE-T4-03 | B87: Gi0/0/2/5 | C87: 1G copper | D87: 1000 | E87: admin-down
A88: MH-DC-001-PE-T4-03 | B88: Gi0/0/2/6 | C88: 1G copper | D88: 1000 | E88: admin-down
A89: MH-DC-001-PE-T4-03 | B89: Gi0/0/2/7 | C89: 1G copper | D89: 1000 | E89: admin-down
A90: MH-DC-001-PE-T4-03 | B90: Gi0/0/2/8 | C90: 1G copper | D90: 1000 | E90: admin-down
A91: MH-DC-001-PE-T4-03 | B91: Gi0/0/2/9 | C91: 1G copper | D91: 1000 | E91: admin-down
A92: MH-DC-001-PE-T4-03 | B92: Gi0/0/2/10 | C92: 1G copper | D92: 1000 | E92: admin-down
... A98: MH-DC-001-PE-T4-04 | B98: Te0/0/0/0 | C98: 10G SFP+ | D98: 10000 | E98: admin-down
A99: MH-DC-001-PE-T4-04 | B99: Te0/0/0/1 | C99: 10G SFP+ | D99: 10000 | E99: up | F99: Backhaul to MP-DC-014 | G99: SFP-10G-LR
A100: MH-DC-001-PE-T4-04 | B100: Te0/0/0/2 | C100: 10G SFP+ | D100: 10000 | E100: up | F100: Backhaul to MH-DC-004 | G100: SFP-10G-LR
A101: MH-DC-001-PE-T4-04 | B101: Te0/0/0/3 | C101: 10G SFP+ | D101: 10000 | E101: up | F101: Backhaul to KL-DC-024 | G101: SFP-10G-LR
A102: MH-DC-001-PE-T4-04 | B102: Te0/0/0/4 | C102: 10G SFP+ | D102: 10000 | E102: up | F102: Backhaul to KA-DC-021 | G102: SFP-10G-LR
A103: MH-DC-001-PE-T4-04 | B103: Te0/0/0/5 | C103: 10G SFP+ | D103: 10000 | E103: up | F103: Backhaul to TS-DC-023 | G103: SFP-10G-LR
A104: MH-DC-001-PE-T4-04 | B104: Te0/0/0/6 | C104: 10G SFP+ | D104: 10000 | E104: up | F104: Uplink to MH-DC-001-AGG-R03 | G104: SFP-10G-LR
A105: MH-DC-001-PE-T4-04 | B105: Te0/0/0/7 | C105: 10G SFP+ | D105: 10000 | E105: admin-down
A106: MH-DC-001-PE-T4-04 | B106: Te0/0/0/8 | C106: 10G SFP+ | D106: 10000 | E106: admin-down
A107: MH-DC-001-PE-T4-04 | B107: Te0/0/0/9 | C107: 10G SFP+ | D107: 10000 | E107: admin-down
A108: MH-DC-001-PE-T4-04 | B108: Te0/0/0/10 | C108: 10G SFP+ | D108: 10000 | E108: admin-down
A109: MH-DC-001-PE-T4-04 | B109: Te0/0/0/11 | C109: 10G SFP+ | D109: 10000 | E109: admin-down
A110: MH-DC-001-PE-T4-04 | B110: Hu0/0/1/0 | C110: 100G QSFP28 | D110: 100000 | E110: up | F110: Fabric to MH-DC-001-PE-T4-01 | G110: QSFP28-100G-LR4
A111: MH-DC-001-PE-T4-04 | B111: Hu0/0/1/1 | C111: 100G QSFP28 | D111: 100000 | E111: up | F111: Fabric to MH-DC-001-PE-T4-02 | G111: QSFP28-100G-LR4
A112: MH-DC-001-PE-T4-04 | B112: Hu0/0/1/2 | C112: 100G QSFP28 | D112: 100000 | E112: up | F112: Fabric to MH-DC-001-PE-T4-03 | G112: QSFP28-100G-LR4
A113: MH-DC-001-PE-T4-04 | B113: Hu0/0/1/3 | C113: 100G QSFP28 | D113: 100000 | E113: admin-down
A114: MH-DC-001-PE-T4-04 | B114: Gi0/0/2/0 | C114: 1G copper | D114: 1000 | E114: admin-down
A115: MH-DC-001-PE-T4-04 | B115: Gi0/0/2/1 | C115: 1G copper | D115: 1000 | E115: admin-down
...

Sheet Links
A1: link_id * | B1: a_device_id * | C1: a_if_name * | D1: z_device_id * | E1: z_if_name * | F1: role * | G1: protocol | H1: capacity_mbps * | I1: cable_id | J1: strand | K1: a_patch_port | L1: z_patch_port | M1: carrier_circuit_id
A2: LNK-00001 | B2: MH-DC-001-PE-T4-01 | C2: et-0/1/0 | D2: MH-DC-001-PE-T4-02 | E2: et-0/1/0 | F2: Fabric | G2: LLDP | H2: 100000 | I2: MH-DC-001-CBL-0001 | J2: Red | K2: ODF-2/P24 | L2: ODF-2/P15
A3: LNK-00002 | B3: MH-DC-001-PE-T4-01 | C3: et-0/1/0 | D3: MH-DC-001-PE-T4-02 | E3: et-0/1/0 | F3: Fabric | G3: OSPF | H3: 100000
A4: LNK-00003 | B4: MH-DC-001-PE-T4-01 | C4: et-0/1/0 | D4: MH-DC-001-PE-T4-02 | E4: et-0/1/0 | F4: Fabric | G4: ISIS | H4: 100000
A5: LNK-00004 | B5: MH-DC-001-PE-T4-01 | C5: et-0/1/0 | D5: MH-DC-001-PE-T4-02 | E5: et-0/1/0 | F5: Fabric | G5: BGP | H5: 100000
A6: LNK-00005 | B6: MH-DC-001-PE-T4-01 | C6: et-0/1/0 | D6: MH-DC-001-PE-T4-02 | E6: et-0/1/0 | F6: Fabric | G6: LSP | H6: 100000
A7: LNK-00006 | B7: MH-DC-001-PE-T4-01 | C7: et-0/1/1 | D7: MH-DC-001-PE-T4-03 | E7: Hu0/0/1/0 | F7: Fabric | G7: LLDP | H7: 100000 | I7: MH-DC-001-CBL-0002 | J7: Yellow | K7: ODF-4/P13 | L7: ODF-2/P12
A8: LNK-00007 | B8: MH-DC-001-PE-T4-01 | C8: et-0/1/1 | D8: MH-DC-001-PE-T4-03 | E8: Hu0/0/1/0 | F8: Fabric | G8: OSPF | H8: 100000
A9: LNK-00008 | B9: MH-DC-001-PE-T4-01 | C9: et-0/1/1 | D9: MH-DC-001-PE-T4-03 | E9: Hu0/0/1/0 | F9: Fabric | G9: ISIS | H9: 100000
A10: LNK-00009 | B10: MH-DC-001-PE-T4-01 | C10: et-0/1/1 | D10: MH-DC-001-PE-T4-03 | E10: Hu0/0/1/0 | F10: Fabric | G10: BGP | H10: 100000
A11: LNK-00010 | B11: MH-DC-001-PE-T4-01 | C11: et-0/1/1 | D11: MH-DC-001-PE-T4-03 | E11: Hu0/0/1/0 | F11: Fabric | G11: LSP | H11: 100000
A12: LNK-00011 | B12: MH-DC-001-PE-T4-01 | C12: et-0/1/2 | D12: MH-DC-001-PE-T4-04 | E12: Hu0/0/1/0 | F12: Fabric | G12: LLDP | H12: 100000 | I12: MH-DC-001-CBL-0003 | J12: Rose | K12: ODF-2/P17 | L12: ODF-2/P19
A13: LNK-00012 | B13: MH-DC-001-PE-T4-01 | C13: et-0/1/2 | D13: MH-DC-001-PE-T4-04 | E13: Hu0/0/1/0 | F13: Fabric | G13: OSPF | H13: 100000
A14: LNK-00013 | B14: MH-DC-001-PE-T4-01 | C14: et-0/1/2 | D14: MH-DC-001-PE-T4-04 | E14: Hu0/0/1/0 | F14: Fabric | G14: ISIS | H14: 100000
A15: LNK-00014 | B15: MH-DC-001-PE-T4-01 | C15: et-0/1/2 | D15: MH-DC-001-PE-T4-04 | E15: Hu0/0/1/0 | F15: Fabric | G15: BGP | H15: 100000
A16: LNK-00015 | B16: MH-DC-001-PE-T4-01 | C16: et-0/1/2 | D16: MH-DC-001-PE-T4-04 | E16: Hu0/0/1/0 | F16: Fabric | G16: LSP | H16: 100000
A17: LNK-00016 | B17: MH-DC-001-PE-T4-02 | C17: et-0/1/1 | D17: MH-DC-001-PE-T4-03 | E17: Hu0/0/1/1 | F17: Fabric | G17: LLDP | H17: 100000 | I17: MH-DC-001-CBL-0004 | J17: Brown | K17: ODF-3/P24 | L17: ODF-2/P20
A18: LNK-00017 | B18: MH-DC-001-PE-T4-02 | C18: et-0/1/1 | D18: MH-DC-001-PE-T4-03 | E18: Hu0/0/1/1 | F18: Fabric | G18: OSPF | H18: 100000
A19: LNK-00018 | B19: MH-DC-001-PE-T4-02 | C19: et-0/1/1 | D19: MH-DC-001-PE-T4-03 | E19: Hu0/0/1/1 | F19: Fabric | G19: ISIS | H19: 100000
A20: LNK-00019 | B20: MH-DC-001-PE-T4-02 | C20: et-0/1/1 | D20: MH-DC-001-PE-T4-03 | E20: Hu0/0/1/1 | F20: Fabric | G20: BGP | H20: 100000
A21: LNK-00020 | B21: MH-DC-001-PE-T4-02 | C21: et-0/1/1 | D21: MH-DC-001-PE-T4-03 | E21: Hu0/0/1/1 | F21: Fabric | G21: LSP | H21: 100000
A22: LNK-00021 | B22: MH-DC-001-PE-T4-02 | C22: et-0/1/2 | D22: MH-DC-001-PE-T4-04 | E22: Hu0/0/1/1 | F22: Fabric | G22: LLDP | H22: 100000 | I22: MH-DC-001-CBL-0005 | J22: Black | K22: ODF-3/P2 | L22: ODF-3/P12
A23: LNK-00022 | B23: MH-DC-001-PE-T4-02 | C23: et-0/1/2 | D23: MH-DC-001-PE-T4-04 | E23: Hu0/0/1/1 | F23: Fabric | G23: OSPF | H23: 100000
A24: LNK-00023 | B24: MH-DC-001-PE-T4-02 | C24: et-0/1/2 | D24: MH-DC-001-PE-T4-04 | E24: Hu0/0/1/1 | F24: Fabric | G24: ISIS | H24: 100000
A25: LNK-00024 | B25: MH-DC-001-PE-T4-02 | C25: et-0/1/2 | D25: MH-DC-001-PE-T4-04 | E25: Hu0/0/1/1 | F25: Fabric | G25: BGP | H25: 100000
A26: LNK-00025 | B26: MH-DC-001-PE-T4-02 | C26: et-0/1/2 | D26: MH-DC-001-PE-T4-04 | E26: Hu0/0/1/1 | F26: Fabric | G26: LSP | H26: 100000
A27: LNK-00026 | B27: MH-DC-001-PE-T4-03 | C27: Hu0/0/1/2 | D27: MH-DC-001-PE-T4-04 | E27: Hu0/0/1/2 | F27: Fabric | G27: LLDP | H27: 100000 | I27: MH-DC-001-CBL-0006 | J27: Black | K27: ODF-3/P6 | L27: ODF-4/P2
A28: LNK-00027 | B28: MH-DC-001-PE-T4-03 | C28: Hu0/0/1/2 | D28: MH-DC-001-PE-T4-04 | E28: Hu0/0/1/2 | F28: Fabric | G28: OSPF | H28: 100000
A29: LNK-00028 | B29: MH-DC-001-PE-T4-03 | C29: Hu0/0/1/2 | D29: MH-DC-001-PE-T4-04 | E29: Hu0/0/1/2 | F29: Fabric | G29: ISIS | H29: 100000
A30: LNK-00029 | B30: MH-DC-001-PE-T4-03 | C30: Hu0/0/1/2 | D30: MH-DC-001-PE-T4-04 | E30: Hu0/0/1/2 | F30: Fabric | G30: BGP | H30: 100000
A31: LNK-00030 | B31: MH-DC-001-PE-T4-03 | C31: Hu0/0/1/2 | D31: MH-DC-001-PE-T4-04 | E31: Hu0/0/1/2 | F31: Fabric | G31: LSP | H31: 100000
A32: LNK-00031 | B32: MH-DC-001-AGG-R01 | C32: et-0/1/0 | D32: MH-DC-001-PE-T4-01 | E32: xe-0/0/6 | F32: Uplink | G32: LLDP | H32: 10000 | I32: MH-DC-001-CBL-0007 | J32: Green | K32: ODF-3/P22 | L32: ODF-4/P23
A33: LNK-00032 | B33: MH-DC-001-AGG-R01 | C33: et-0/1/0 | D33: MH-DC-001-PE-T4-01 | E33: xe-0/0/6 | F33: Uplink | G33: OSPF | H33: 10000
A34: LNK-00033 | B34: MH-DC-001-AGG-R01 | C34: et-0/1/0 | D34: MH-DC-001-PE-T4-01 | E34: xe-0/0/6 | F34: Uplink | G34: ISIS | H34: 10000
A35: LNK-00034 | B35: MH-DC-001-AGG-R01 | C35: et-0/1/1 | D35: MH-DC-001-PE-T4-02 | E35: xe-0/0/6 | F35: Uplink | G35: LLDP | H35: 10000 | I35: MH-DC-001-CBL-0008 | J35: Green | K35: ODF-2/P2 | L35: ODF-2/P12
A36: LNK-00035 | B36: MH-DC-001-AGG-R01 | C36: et-0/1/1 | D36: MH-DC-001-PE-T4-02 | E36: xe-0/0/6 | F36: Uplink | G36: OSPF | H36: 10000
A37: LNK-00036 | B37: MH-DC-001-AGG-R01 | C37: et-0/1/1 | D37: MH-DC-001-PE-T4-02 | E37: xe-0/0/6 | F37: Uplink | G37: ISIS | H37: 10000
A38: LNK-00037 | B38: MH-DC-001-AGG-R02 | C38: et-0/1/0 | D38: MH-DC-001-PE-T4-02 | E38: xe-0/0/7 | F38: Uplink | G38: LLDP | H38: 10000 | I38: MH-DC-001-CBL-0009 | J38: Yellow | K38: ODF-1/P13 | L38: ODF-1/P16
A39: LNK-00038 | B39: MH-DC-001-AGG-R02 | C39: et-0/1/0 | D39: MH-DC-001-PE-T4-02 | E39: xe-0/0/7 | F39: Uplink | G39: OSPF | H39: 10000
A40: LNK-00039 | B40: MH-DC-001-AGG-R02 | C40: et-0/1/0 | D40: MH-DC-001-PE-T4-02 | E40: xe-0/0/7 | F40: Uplink | G40: ISIS | H40: 10000
A41: LNK-00040 | B41: MH-DC-001-AGG-R02 | C41: et-0/1/1 | D41: MH-DC-001-PE-T4-03 | E41: Te0/0/0/6 | F41: Uplink | G41: LLDP | H41: 10000 | I41: MH-DC-001-CBL-0010 | J41: Yellow | K41: ODF-2/P16 | L41: ODF-1/P3
A42: LNK-00041 | B42: MH-DC-001-AGG-R02 | C42: et-0/1/1 | D42: MH-DC-001-PE-T4-03 | E42: Te0/0/0/6 | F42: Uplink | G42: OSPF | H42: 10000
A43: LNK-00042 | B43: MH-DC-001-AGG-R02 | C43: et-0/1/1 | D43: MH-DC-001-PE-T4-03 | E43: Te0/0/0/6 | F43: Uplink | G43: ISIS | H43: 10000
A44: LNK-00043 | B44: MH-DC-001-AGG-R03 | C44: et-0/1/0 | D44: MH-DC-001-PE-T4-03 | E44: Te0/0/0/7 | F44: Uplink | G44: LLDP | H44: 10000 | I44: MH-DC-001-CBL-0011 | J44: Orange | K44: ODF-1/P24 | L44: ODF-3/P4
A45: LNK-00044 | B45: MH-DC-001-AGG-R03 | C45: et-0/1/0 | D45: MH-DC-001-PE-T4-03 | E45: Te0/0/0/7 | F45: Uplink | G45: OSPF | H45: 10000
A46: LNK-00045 | B46: MH-DC-001-AGG-R03 | C46: et-0/1/0 | D46: MH-DC-001-PE-T4-03 | E46: Te0/0/0/7 | F46: Uplink | G46: ISIS | H46: 10000
A47: LNK-00046 | B47: MH-DC-001-AGG-R03 | C47: et-0/1/1 | D47: MH-DC-001-PE-T4-04 | E47: Te0/0/0/6 | F47: Uplink | G47: LLDP | H47: 10000 | I47: MH-DC-001-CBL-0012 | J47: Red | K47: ODF-4/P5 | L47: ODF-2/P1
A48: LNK-00047 | B48: MH-DC-001-AGG-R03 | C48: et-0/1/1 | D48: MH-DC-001-PE-T4-04 | E48: Te0/0/0/6 | F48: Uplink | G48: OSPF | H48: 10000
A49: LNK-00048 | B49: MH-DC-001-AGG-R03 | C49: et-0/1/1 | D49: MH-DC-001-PE-T4-04 | E49: Te0/0/0/6 | F49: Uplink | G49: ISIS | H49: 10000
A50: LNK-00049 | B50: MH-DC-001-OLA-01 | C50: 1/2/c1 | D50: MH-DC-001-AGG-R01 | E50: et-0/1/2 | F50: Uplink | G50: LLDP | H50: 100000 | I50: MH-DC-001-CBL-0013 | J50: Slate | K50: ODF-2/P12 | L50: ODF-2/P11
A51: LNK-00050 | B51: MH-DC-001-OLA-02 | C51: 1/2/c1 | D51: MH-DC-001-AGG-R02 | E51: et-0/1/2 | F51: Uplink | G51: LLDP | H51: 100000 | I51: MH-DC-001-CBL-0014 | J51: Aqua | K51: ODF-2/P20 | L51: ODF-4/P23
A52: LNK-00051 | B52: MH-DC-001-FW-01 | C52: port1 | D52: MH-DC-001-AGG-R01 | E52: xe-0/0/0 | F52: Uplink | G52: LLDP | H52: 10000 | I52: MH-DC-001-CBL-0015 | J52: Green | K52: ODF-3/P2 | L52: ODF-2/P15
A53: LNK-00052 | B53: MH-DC-001-FW-01 | C53: port2 | D53: MH-DC-001-AGG-R02 | E53: xe-0/0/0 | F53: Uplink | G53: LLDP | H53: 10000 | I53: MH-DC-001-CBL-0016 | J53: Yellow | K53: ODF-4/P6 | L53: ODF-1/P13
A54: LNK-00053 | B54: MH-DC-001-FW-02 | C54: port1 | D54: MH-DC-001-AGG-R02 | E54: xe-0/0/1 | F54: Uplink | G54: LLDP | H54: 10000 | I54: MH-DC-001-CBL-0017 | J54: Green | K54: ODF-1/P14 | L54: ODF-3/P8
A55: LNK-00054 | B55: MH-DC-001-FW-02 | C55: port2 | D55: MH-DC-001-AGG-R03 | E55: xe-0/0/0 | F55: Uplink | G55: LLDP | H55: 10000 | I55: MH-DC-001-CBL-0018 | J55: Slate | K55: ODF-1/P16 | L55: ODF-2/P15
A56: LNK-00055 | B56: MH-DC-001-MMR-SW-01 | C56: et-0/1/0 | D56: MH-DC-001-AGG-R01 | E56: xe-0/0/1 | F56: Uplink | G56: LLDP | H56: 10000 | I56: MH-DC-001-CBL-0019 | J56: Rose | K56: ODF-2/P22 | L56: ODF-4/P7
A57: LNK-00056 | B57: MH-DC-001-MMR-SW-01 | C57: et-0/1/1 | D57: MH-DC-001-AGG-R01 | E57: xe-0/0/2 | F57: Uplink | G57: LLDP | H57: 10000 | I57: MH-DC-001-CBL-0020 | J57: Blue | K57: ODF-3/P19 | L57: ODF-4/P21
A58: LNK-00057 | B58: MH-DC-001-MMR-SW-02 | C58: Hu0/0/1/0 | D58: MH-DC-001-AGG-R02 | E58: xe-0/0/2 | F58: Uplink | G58: LLDP | H58: 10000 | I58: MH-DC-001-CBL-0021 | J58: Black | K58: ODF-3/P17 | L58: ODF-4/P13
A59: LNK-00058 | B59: MH-DC-001-MMR-SW-02 | C59: Hu0/0/1/1 | D59: MH-DC-001-AGG-R02 | E59: xe-0/0/3 | F59: Uplink | G59: LLDP | H59: 10000 | I59: MH-DC-001-CBL-0022 | J59: Violet | K59: ODF-1/P15 | L59: ODF-1/P23
A60: LNK-00059 | B60: MH-DC-001-MMR-SW-03 | C60: Hu0/0/1/0 | D60: MH-DC-001-AGG-R03 | E60: xe-0/0/1 | F60: Uplink | G60: LLDP | H60: 10000 | I60: MH-DC-001-CBL-0023 | J60: Green | K60: ODF-3/P12 | L60: ODF-2/P6
A61: LNK-00060 | B61: MH-DC-001-MMR-SW-03 | C61: Hu0/0/1/1 | D61: MH-DC-001-AGG-R03 | E61: xe-0/0/2 | F61: Uplink | G61: LLDP | H61: 10000 | I61: MH-DC-001-CBL-0024 | J61: White | K61: ODF-4/P4 | L61: ODF-4/P21
... A86: LNK-00085 | B86: MH-DC-002-PE-T4-01 | C86: et-0/1/0 | D86: MH-DC-002-PE-T4-02 | E86: et-0/1/0 | F86: Fabric | G86: LLDP | H86: 100000 | I86: MH-DC-002-CBL-0049 | J86: Aqua | K86: ODF-4/P10 | L86: ODF-4/P4
A87: LNK-00086 | B87: MH-DC-002-PE-T4-01 | C87: et-0/1/0 | D87: MH-DC-002-PE-T4-02 | E87: et-0/1/0 | F87: Fabric | G87: OSPF | H87: 100000
A88: LNK-00087 | B88: MH-DC-002-PE-T4-01 | C88: et-0/1/0 | D88: MH-DC-002-PE-T4-02 | E88: et-0/1/0 | F88: Fabric | G88: ISIS | H88: 100000
A89: LNK-00088 | B89: MH-DC-002-PE-T4-01 | C89: et-0/1/0 | D89: MH-DC-002-PE-T4-02 | E89: et-0/1/0 | F89: Fabric | G89: BGP | H89: 100000
A90: LNK-00089 | B90: MH-DC-002-PE-T4-01 | C90: et-0/1/0 | D90: MH-DC-002-PE-T4-02 | E90: et-0/1/0 | F90: Fabric | G90: LSP | H90: 100000
A91: LNK-00090 | B91: MH-DC-002-PE-T4-01 | C91: et-0/1/1 | D91: MH-DC-002-PE-T4-03 | E91: Hu0/0/1/0 | F91: Fabric | G91: LLDP | H91: 100000 | I91: MH-DC-002-CBL-0050 | J91: Red | K91: ODF-3/P20 | L91: ODF-3/P16
A92: LNK-00091 | B92: MH-DC-002-PE-T4-01 | C92: et-0/1/1 | D92: MH-DC-002-PE-T4-03 | E92: Hu0/0/1/0 | F92: Fabric | G92: OSPF | H92: 100000
A93: LNK-00092 | B93: MH-DC-002-PE-T4-01 | C93: et-0/1/1 | D93: MH-DC-002-PE-T4-03 | E93: Hu0/0/1/0 | F93: Fabric | G93: ISIS | H93: 100000
A94: LNK-00093 | B94: MH-DC-002-PE-T4-01 | C94: et-0/1/1 | D94: MH-DC-002-PE-T4-03 | E94: Hu0/0/1/0 | F94: Fabric | G94: BGP | H94: 100000
A95: LNK-00094 | B95: MH-DC-002-PE-T4-01 | C95: et-0/1/1 | D95: MH-DC-002-PE-T4-03 | E95: Hu0/0/1/0 | F95: Fabric | G95: LSP | H95: 100000
A96: LNK-00095 | B96: MH-DC-002-PE-T4-01 | C96: et-0/1/2 | D96: MH-DC-002-PE-T4-04 | E96: Hu0/0/1/0 | F96: Fabric | G96: LLDP | H96: 100000 | I96: MH-DC-002-CBL-0051 | J96: Yellow | K96: ODF-3/P22 | L96: ODF-3/P12
A97: LNK-00096 | B97: MH-DC-002-PE-T4-01 | C97: et-0/1/2 | D97: MH-DC-002-PE-T4-04 | E97: Hu0/0/1/0 | F97: Fabric | G97: OSPF | H97: 100000
A98: LNK-00097 | B98: MH-DC-002-PE-T4-01 | C98: et-0/1/2 | D98: MH-DC-002-PE-T4-04 | E98: Hu0/0/1/0 | F98: Fabric | G98: ISIS | H98: 100000
A99: LNK-00098 | B99: MH-DC-002-PE-T4-01 | C99: et-0/1/2 | D99: MH-DC-002-PE-T4-04 | E99: Hu0/0/1/0 | F99: Fabric | G99: BGP | H99: 100000
A100: LNK-00099 | B100: MH-DC-002-PE-T4-01 | C100: et-0/1/2 | D100: MH-DC-002-PE-T4-04 | E100: Hu0/0/1/0 | F100: Fabric | G100: LSP | H100: 100000
A101: LNK-00100 | B101: MH-DC-002-PE-T4-02 | C101: et-0/1/1 | D101: MH-DC-002-PE-T4-03 | E101: Hu0/0/1/1 | F101: Fabric | G101: LLDP | H101: 100000 | I101: MH-DC-002-CBL-0052 | J101: Brown | K101: ODF-3/P17 | L101: ODF-4/P18
A102: LNK-00101 | B102: MH-DC-002-PE-T4-02 | C102: et-0/1/1 | D102: MH-DC-002-PE-T4-03 | E102: Hu0/0/1/1 | F102: Fabric | G102: OSPF | H102: 100000
A103: LNK-00102 | B103: MH-DC-002-PE-T4-02 | C103: et-0/1/1 | D103: MH-DC-002-PE-T4-03 | E103: Hu0/0/1/1 | F103: Fabric | G103: ISIS | H103: 100000
A104: LNK-00103 | B104: MH-DC-002-PE-T4-02 | C104: et-0/1/1 | D104: MH-DC-002-PE-T4-03 | E104: Hu0/0/1/1 | F104: Fabric | G104: BGP | H104: 100000
A105: LNK-00104 | B105: MH-DC-002-PE-T4-02 | C105: et-0/1/1 | D105: MH-DC-002-PE-T4-03 | E105: Hu0/0/1/1 | F105: Fabric | G105: LSP | H105: 100000
A106: LNK-00105 | B106: MH-DC-002-PE-T4-02 | C106: et-0/1/2 | D106: MH-DC-002-PE-T4-04 | E106: Hu0/0/1/1 | F106: Fabric | G106: LLDP | H106: 100000 | I106: MH-DC-002-CBL-0053 | J106: Red | K106: ODF-4/P1 | L106: ODF-1/P10
A107: LNK-00106 | B107: MH-DC-002-PE-T4-02 | C107: et-0/1/2 | D107: MH-DC-002-PE-T4-04 | E107: Hu0/0/1/1 | F107: Fabric | G107: OSPF | H107: 100000
A108: LNK-00107 | B108: MH-DC-002-PE-T4-02 | C108: et-0/1/2 | D108: MH-DC-002-PE-T4-04 | E108: Hu0/0/1/1 | F108: Fabric | G108: ISIS | H108: 100000
A109: LNK-00108 | B109: MH-DC-002-PE-T4-02 | C109: et-0/1/2 | D109: MH-DC-002-PE-T4-04 | E109: Hu0/0/1/1 | F109: Fabric | G109: BGP | H109: 100000
A110: LNK-00109 | B110: MH-DC-002-PE-T4-02 | C110: et-0/1/2 | D110: MH-DC-002-PE-T4-04 | E110: Hu0/0/1/1 | F110: Fabric | G110: LSP | H110: 100000
A111: LNK-00110 | B111: MH-DC-002-PE-T4-03 | C111: Hu0/0/1/2 | D111: MH-DC-002-PE-T4-04 | E111: Hu0/0/1/2 | F111: Fabric | G111: LLDP | H111: 100000 | I111: MH-DC-002-CBL-0054 | J111: Yellow | K111: ODF-2/P20 | L111: ODF-2/P7
A112: LNK-00111 | B112: MH-DC-002-PE-T4-03 | C112: Hu0/0/1/2 | D112: MH-DC-002-PE-T4-04 | E112: Hu0/0/1/2 | F112: Fabric | G112: OSPF | H112: 100000
A113: LNK-00112 | B113: MH-DC-002-PE-T4-03 | C113: Hu0/0/1/2 | D113: MH-DC-002-PE-T4-04 | E113: Hu0/0/1/2 | F113: Fabric | G113: ISIS | H113: 100000
A114: LNK-00113 | B114: MH-DC-002-PE-T4-03 | C114: Hu0/0/1/2 | D114: MH-DC-002-PE-T4-04 | E114: Hu0/0/1/2 | F114: Fabric | G114: BGP | H114: 100000
A115: LNK-00114 | B115: MH-DC-002-PE-T4-03 | C115: Hu0/0/1/2 | D115: MH-DC-002-PE-T4-04 | E115: Hu0/0/1/2 | F115: Fabric | G115: LSP | H115: 100000
A116: LNK-00115 | B116: MH-DC-002-AGG-R01 | C116: et-0/1/0 | D116: MH-DC-002-PE-T4-01 | E116: xe-0/0/6 | F116: Uplink | G116: LLDP | H116: 10000 | I116: MH-DC-002-CBL-0055 | J116: Orange | K116: ODF-1/P12 | L116: ODF-2/P15
A117: LNK-00116 | B117: MH-DC-002-AGG-R01 | C117: et-0/1/0 | D117: MH-DC-002-PE-T4-01 | E117: xe-0/0/6 | F117: Uplink | G117: OSPF | H117: 10000
A118: LNK-00117 | B118: MH-DC-002-AGG-R01 | C118: et-0/1/0 | D118: MH-DC-002-PE-T4-01 | E118: xe-0/0/6 | F118: Uplink | G118: ISIS | H118: 10000
A119: LNK-00118 | B119: MH-DC-002-AGG-R01 | C119: et-0/1/1 | D119: MH-DC-002-PE-T4-02 | E119: xe-0/0/6 | F119: Uplink | G119: LLDP | H119: 10000 | I119: MH-DC-002-CBL-0056 | J119: Yellow | K119: ODF-4/P22 | L119: ODF-3/P19
A120: LNK-00119 | B120: MH-DC-002-AGG-R01 | C120: et-0/1/1 | D120: MH-DC-002-PE-T4-02 | E120: xe-0/0/6 | F120: Uplink | G120: OSPF | H120: 10000
A121: LNK-00120 | B121: MH-DC-002-AGG-R01 | C121: et-0/1/1 | D121: MH-DC-002-PE-T4-02 | E121: xe-0/0/6 | F121: Uplink | G121: ISIS | H121: 10000
A122: LNK-00121 | B122: MH-DC-002-AGG-R02 | C122: et-0/1/0 | D122: MH-DC-002-PE-T4-02 | E122: xe-0/0/7 | F122: Uplink | G122: LLDP | H122: 10000 | I122: MH-DC-002-CBL-0057 | J122: Aqua | K122: ODF-2/P17 | L122: ODF-1/P6
A123: LNK-00122 | B123: MH-DC-002-AGG-R02 | C123: et-0/1/0 | D123: MH-DC-002-PE-T4-02 | E123: xe-0/0/7 | F123: Uplink | G123: OSPF | H123: 10000
A124: LNK-00123 | B124: MH-DC-002-AGG-R02 | C124: et-0/1/0 | D124: MH-DC-002-PE-T4-02 | E124: xe-0/0/7 | F124: Uplink | G124: ISIS | H124: 10000
...

Sheet Rack_PDUs
A1: pdu_id * | B1: site_id * | C1: rack_id * | D1: side * | E1: kind * | F1: model | G1: volts * | H1: phases * | I1: rating_a * | J1: capacity_kw * | K1: outlets * | L1: upstream_id * | M1: feed_id *
A2: MH-DC-001-RACK-A-PDU-A | B2: MH-DC-001 | C2: MH-DC-001-RACK-A | D2: A | E2: AC | F2: Switched rack PDU · 3-ph 32 A · 400 V | G2: 400 | H2: 3 | I2: 32 | J2: 15 | K2: 36 | L2: MH-DC-001-UPS-2 | M2: MH-DC-001-AC-1
A3: MH-DC-001-RACK-A-PDU-B | B3: MH-DC-001 | C3: MH-DC-001-RACK-A | D3: B | E3: AC | F3: Switched rack PDU · 3-ph 32 A · 400 V | G3: 400 | H3: 3 | I3: 32 | J3: 15 | K3: 36 | L3: MH-DC-001-UPS-1 | M3: MH-DC-001-AC-2
A4: MH-DC-001-RACK-B-PDU-A | B4: MH-DC-001 | C4: MH-DC-001-RACK-B | D4: A | E4: AC | F4: Switched rack PDU · 3-ph 32 A · 400 V | G4: 400 | H4: 3 | I4: 32 | J4: 16 | K4: 36 | L4: MH-DC-001-UPS-2 | M4: MH-DC-001-AC-1
A5: MH-DC-001-RACK-B-PDU-B | B5: MH-DC-001 | C5: MH-DC-001-RACK-B | D5: B | E5: AC | F5: Switched rack PDU · 3-ph 32 A · 400 V | G5: 400 | H5: 3 | I5: 32 | J5: 16 | K5: 36 | L5: MH-DC-001-UPS-1 | M5: MH-DC-001-AC-2
A6: MH-DC-001-RACK-C-PDU-A | B6: MH-DC-001 | C6: MH-DC-001-RACK-C | D6: A | E6: AC | F6: Switched rack PDU · 3-ph 32 A · 400 V | G6: 400 | H6: 3 | I6: 32 | J6: 19 | K6: 36 | L6: MH-DC-001-UPS-2 | M6: MH-DC-001-AC-1
A7: MH-DC-001-RACK-C-PDU-B | B7: MH-DC-001 | C7: MH-DC-001-RACK-C | D7: B | E7: AC | F7: Switched rack PDU · 3-ph 32 A · 400 V | G7: 400 | H7: 3 | I7: 32 | J7: 19 | K7: 36 | L7: MH-DC-001-UPS-1 | M7: MH-DC-001-AC-2
A8: MH-DC-001-RACK-D-PDU-A | B8: MH-DC-001 | C8: MH-DC-001-RACK-D | D8: A | E8: AC | F8: Switched rack PDU · 3-ph 32 A · 400 V | G8: 400 | H8: 3 | I8: 32 | J8: 15 | K8: 36 | L8: MH-DC-001-UPS-2 | M8: MH-DC-001-AC-1
A9: MH-DC-001-RACK-D-PDU-B | B9: MH-DC-001 | C9: MH-DC-001-RACK-D | D9: B | E9: AC | F9: Switched rack PDU · 3-ph 32 A · 400 V | G9: 400 | H9: 3 | I9: 32 | J9: 15 | K9: 36 | L9: MH-DC-001-UPS-1 | M9: MH-DC-001-AC-2
A10: MH-DC-001-RACK-E-PDU-A | B10: MH-DC-001 | C10: MH-DC-001-RACK-E | D10: A | E10: AC | F10: Switched rack PDU · 3-ph 32 A · 400 V | G10: 400 | H10: 3 | I10: 32 | J10: 19 | K10: 36 | L10: MH-DC-001-UPS-2 | M10: MH-DC-001-AC-1
A11: MH-DC-001-RACK-E-PDU-B | B11: MH-DC-001 | C11: MH-DC-001-RACK-E | D11: B | E11: AC | F11: Switched rack PDU · 3-ph 32 A · 400 V | G11: 400 | H11: 3 | I11: 32 | J11: 19 | K11: 36 | L11: MH-DC-001-UPS-1 | M11: MH-DC-001-AC-2
A12: MH-DC-001-RACK-F-PDU-A | B12: MH-DC-001 | C12: MH-DC-001-RACK-F | D12: A | E12: AC | F12: Switched rack PDU · 3-ph 32 A · 400 V | G12: 400 | H12: 3 | I12: 32 | J12: 20 | K12: 36 | L12: MH-DC-001-UPS-4 | M12: MH-DC-001-AC-1
A13: MH-DC-001-RACK-F-PDU-B | B13: MH-DC-001 | C13: MH-DC-001-RACK-F | D13: B | E13: AC | F13: Switched rack PDU · 3-ph 32 A · 400 V | G13: 400 | H13: 3 | I13: 32 | J13: 20 | K13: 36 | L13: MH-DC-001-UPS-3 | M13: MH-DC-001-AC-2
... A65: MH-DC-002-RACK-K-PDU-B | B65: MH-DC-002 | C65: MH-DC-002-RACK-K | D65: B | E65: AC | F65: Switched rack PDU · 3-ph 16 A · 400 V | G65: 400 | H65: 3 | I65: 16 | J65: 8 | K65: 24 | L65: MH-DC-002-UPS-1 | M65: MH-DC-002-AC-2

Sheet Power_Connections
A1: device_id * | B1: psu_slot * | C1: pdu_id * | D1: outlet * | E1: breaker_bank | F1: psu_rated_w
A2: MH-DC-001-PE-T4-01 | B2: PEM0 | C2: MH-DC-001-RACK-A-PDU-A | D2: 1 | E2: L1
A3: MH-DC-001-PE-T4-01 | B3: PEM1 | C3: MH-DC-001-RACK-A-PDU-B | D3: 1 | E3: L1
A4: MH-DC-001-PE-T4-02 | B4: PEM0 | C4: MH-DC-001-RACK-A-PDU-A | D4: 13 | E4: L2
A5: MH-DC-001-PE-T4-02 | B5: PEM1 | C5: MH-DC-001-RACK-A-PDU-B | D5: 13 | E5: L2
A6: MH-DC-001-PE-T4-03 | B6: PEM0 | C6: MH-DC-001-RACK-A-PDU-A | D6: 25 | E6: L3
A7: MH-DC-001-PE-T4-03 | B7: PEM1 | C7: MH-DC-001-RACK-A-PDU-B | D7: 25 | E7: L3
A8: MH-DC-001-PE-T4-04 | B8: PEM0 | C8: MH-DC-001-RACK-A-PDU-A | D8: 2 | E8: L1
A9: MH-DC-001-PE-T4-04 | B9: PEM1 | C9: MH-DC-001-RACK-A-PDU-B | D9: 2 | E9: L1
A10: MH-DC-001-FW-01 | B10: PSU1 | C10: MH-DC-001-RACK-A-PDU-A | D10: 14 | E10: L2
A11: MH-DC-001-FW-01 | B11: PSU2 | C11: MH-DC-001-RACK-A-PDU-B | D11: 14 | E11: L2
A12: MH-DC-001-FW-02 | B12: PSU1 | C12: MH-DC-001-RACK-A-PDU-A | D12: 26 | E12: L3
A13: MH-DC-001-FW-02 | B13: PSU2 | C13: MH-DC-001-RACK-A-PDU-B | D13: 26 | E13: L3
... A313: MH-DC-002-MON-02 | B313: PSU2 | C313: MH-DC-002-RACK-K-PDU-B | D313: 4 | E313: L1

Sheet Patch_Panels
A1: panel_id * | B1: site_id * | C1: rack_id * | D1: name * | E1: kind * | F1: role * | G1: ports *
A2: MH-DC-001-RACK-B-PP-F1 | B2: MH-DC-001 | C2: MH-DC-001-RACK-B | D2: PP-F1 | E2: LC duplex | F2: rack | G2: 24
A3: MH-DC-001-RACK-B-PP-F2 | B3: MH-DC-001 | C3: MH-DC-001-RACK-B | D3: PP-F2 | E3: LC duplex | F3: rack | G3: 24
A4: MH-DC-001-RACK-A-PP-F1 | B4: MH-DC-001 | C4: MH-DC-001-RACK-A | D4: PP-F1 | E4: LC duplex | F4: rack | G4: 24
A5: MH-DC-001-RACK-A-PP-F2 | B5: MH-DC-001 | C5: MH-DC-001-RACK-A | D5: PP-F2 | E5: LC duplex | F5: rack | G5: 24
A6: MH-DC-001-RACK-U-PP-F1 | B6: MH-DC-001 | C6: MH-DC-001-RACK-U | D6: PP-F1 | E6: LC duplex | F6: rack | G6: 24
A7: MH-DC-001-RACK-T-ODF-1 | B7: MH-DC-001 | C7: MH-DC-001-RACK-T | D7: ODF-1 | E7: LC duplex | F7: odf | G7: 24
A8: MH-DC-001-RACK-T-ODF-2 | B8: MH-DC-001 | C8: MH-DC-001-RACK-T | D8: ODF-2 | E8: LC duplex | F8: odf | G8: 24
A9: MH-DC-001-RACK-T-ODF-3 | B9: MH-DC-001 | C9: MH-DC-001-RACK-T | D9: ODF-3 | E9: LC duplex | F9: odf | G9: 24
A10: MH-DC-001-RACK-T-ODF-4 | B10: MH-DC-001 | C10: MH-DC-001-RACK-T | D10: ODF-4 | E10: LC duplex | F10: odf | G10: 24
A11: MH-DC-001-RACK-T-ODF-5 | B11: MH-DC-001 | C11: MH-DC-001-RACK-T | D11: ODF-5 | E11: LC duplex | F11: odf | G11: 24
A12: MH-DC-002-RACK-A-PP-F1 | B12: MH-DC-002 | C12: MH-DC-002-RACK-A | D12: PP-F1 | E12: LC duplex | F12: rack | G12: 24
A13: MH-DC-002-RACK-A-PP-F2 | B13: MH-DC-002 | C13: MH-DC-002-RACK-A | D13: PP-F2 | E13: LC duplex | F13: rack | G13: 24
... A17: MH-DC-002-RACK-J-ODF-3 | B17: MH-DC-002 | C17: MH-DC-002-RACK-J | D17: ODF-3 | E17: LC duplex | F17: odf | G17: 24

Sheet Trunk_Cables
A1: trunk_id * | B1: site_id * | C1: a_panel_id * | D1: z_panel_id * | E1: kind * | F1: pairs * | G1: route * | H1: length_m
A2: MH-DC-001-RACK-B-TRK-1 | B2: MH-DC-001 | C2: MH-DC-001-RACK-B-PP-F1 | D2: MH-DC-001-RACK-T-ODF-1 | E2: MPO-24 OM4 trunk × 2 | F2: 24 | G2: Tray route 1 | H2: 50
A3: MH-DC-001-RACK-A-TRK-2 | B3: MH-DC-001 | C3: MH-DC-001-RACK-A-PP-F1 | D3: MH-DC-001-RACK-T-ODF-1 | E3: MPO-24 OM4 trunk × 2 | F3: 24 | G3: Tray route 2 | H3: 56
A4: MH-DC-001-RACK-B-TRK-2 | B4: MH-DC-001 | C4: MH-DC-001-RACK-B-PP-F1 | D4: MH-DC-001-RACK-T-ODF-1 | E4: MPO-24 OM4 trunk × 2 | F4: 24 | G4: Tray route 2 | H4: 58
A5: MH-DC-001-RACK-A-TRK-1 | B5: MH-DC-001 | C5: MH-DC-001-RACK-A-PP-F1 | D5: MH-DC-001-RACK-T-ODF-1 | E5: MPO-24 OM4 trunk × 2 | F5: 24 | G5: Tray route 1 | H5: 56
A6: MH-DC-001-RACK-U-TRK-1 | B6: MH-DC-001 | C6: MH-DC-001-RACK-U-PP-F1 | D6: MH-DC-001-RACK-T-ODF-1 | E6: MPO-24 OM4 trunk × 1 | F6: 12 | G6: Tray route 1 | H6: 48
A7: MH-DC-001-RACK-U-TRK-2 | B7: MH-DC-001 | C7: MH-DC-001-RACK-U-PP-F1 | D7: MH-DC-001-RACK-T-ODF-1 | E7: MPO-24 OM4 trunk × 1 | F7: 12 | G7: Tray route 2 | H7: 52
A8: MH-DC-002-RACK-A-TRK-1 | B8: MH-DC-002 | C8: MH-DC-002-RACK-A-PP-F1 | D8: MH-DC-002-RACK-J-ODF-1 | E8: MPO-24 OM4 trunk × 2 | F8: 24 | G8: Tray route 1 | H8: 41
A9: MH-DC-002-RACK-A-TRK-2 | B9: MH-DC-002 | C9: MH-DC-002-RACK-A-PP-F1 | D9: MH-DC-002-RACK-J-ODF-1 | E9: MPO-24 OM4 trunk × 2 | F9: 24 | G9: Tray route 2 | H9: 42
A10: MH-DC-002-RACK-K-TRK-1 | B10: MH-DC-002 | C10: MH-DC-002-RACK-K-PP-F1 | D10: MH-DC-002-RACK-J-ODF-1 | E10: MPO-24 OM4 trunk × 1 | F10: 12 | G10: Tray route 1 | H10: 77
A11: MH-DC-002-RACK-K-TRK-2 | B11: MH-DC-002 | C11: MH-DC-002-RACK-K-PP-F1 | D11: MH-DC-002-RACK-J-ODF-1 | E11: MPO-24 OM4 trunk × 1 | F11: 12 | G11: Tray route 2 | H11: 53

Sheet Cable_Paths
A1: link_id * | B1: end * | C1: device_id * | D1: patch_cord_id | E1: panel_id | F1: panel_port | G1: trunk_id | H1: odf_panel_id | I1: odf_port | J1: osp_core
A2: LNK-00001 | B2: A | C2: MH-DC-001-PE-T4-01 | D2: MH-DC-001-PC-00001
A3: LNK-00001 | B3: Z | C3: MH-DC-001-PE-T4-02 | D3: MH-DC-001-PC-00002
A4: LNK-00006 | B4: A | C4: MH-DC-001-PE-T4-01 | D4: MH-DC-001-PC-00003
A5: LNK-00006 | B5: Z | C5: MH-DC-001-PE-T4-03 | D5: MH-DC-001-PC-00004
A6: LNK-00011 | B6: A | C6: MH-DC-001-PE-T4-01 | D6: MH-DC-001-PC-00005
A7: LNK-00011 | B7: Z | C7: MH-DC-001-PE-T4-04 | D7: MH-DC-001-PC-00006
A8: LNK-00016 | B8: A | C8: MH-DC-001-PE-T4-02 | D8: MH-DC-001-PC-00007
A9: LNK-00016 | B9: Z | C9: MH-DC-001-PE-T4-03 | D9: MH-DC-001-PC-00008
A10: LNK-00021 | B10: A | C10: MH-DC-001-PE-T4-02 | D10: MH-DC-001-PC-00009
A11: LNK-00021 | B11: Z | C11: MH-DC-001-PE-T4-04 | D11: MH-DC-001-PC-00010
A12: LNK-00026 | B12: A | C12: MH-DC-001-PE-T4-03 | D12: MH-DC-001-PC-00011
A13: LNK-00026 | B13: Z | C13: MH-DC-001-PE-T4-04 | D13: MH-DC-001-PC-00012
... A41: LNK-00056 | B41: Z | C41: MH-DC-001-AGG-R01 | D41: MH-DC-001-PC-00040
A42: LNK-00057 | B42: A | C42: MH-DC-001-MMR-SW-02 | D42: MH-DC-001-PC-00041 | E42: MH-DC-001-RACK-B-PP-F1 | F42: 1 | G42: MH-DC-001-RACK-B-TRK-1 | H42: MH-DC-001-RACK-T-ODF-1 | I42: 1
A43: LNK-00057 | B43: Z | C43: MH-DC-001-AGG-R02 | D43: MH-DC-001-PC-00042 | E43: MH-DC-001-RACK-A-PP-F1 | F43: 1 | G43: MH-DC-001-RACK-A-TRK-2 | H43: MH-DC-001-RACK-T-ODF-1 | I43: 2
A44: LNK-00058 | B44: A | C44: MH-DC-001-MMR-SW-02 | D44: MH-DC-001-PC-00043 | E44: MH-DC-001-RACK-B-PP-F1 | F44: 2 | G44: MH-DC-001-RACK-B-TRK-2 | H44: MH-DC-001-RACK-T-ODF-1 | I44: 3
A45: LNK-00058 | B45: Z | C45: MH-DC-001-AGG-R02 | D45: MH-DC-001-PC-00044 | E45: MH-DC-001-RACK-A-PP-F1 | F45: 2 | G45: MH-DC-001-RACK-A-TRK-1 | H45: MH-DC-001-RACK-T-ODF-1 | I45: 4
A46: LNK-00059 | B46: A | C46: MH-DC-001-MMR-SW-03 | D46: MH-DC-001-PC-00045 | E46: MH-DC-001-RACK-B-PP-F1 | F46: 3 | G46: MH-DC-001-RACK-B-TRK-1 | H46: MH-DC-001-RACK-T-ODF-1 | I46: 5
A47: LNK-00059 | B47: Z | C47: MH-DC-001-AGG-R03 | D47: MH-DC-001-PC-00046 | E47: MH-DC-001-RACK-A-PP-F1 | F47: 3 | G47: MH-DC-001-RACK-A-TRK-2 | H47: MH-DC-001-RACK-T-ODF-1 | I47: 6
A48: LNK-00060 | B48: A | C48: MH-DC-001-MMR-SW-03 | D48: MH-DC-001-PC-00047 | E48: MH-DC-001-RACK-B-PP-F1 | F48: 4 | G48: MH-DC-001-RACK-B-TRK-2 | H48: MH-DC-001-RACK-T-ODF-1 | I48: 7
A49: LNK-00060 | B49: Z | C49: MH-DC-001-AGG-R03 | D49: MH-DC-001-PC-00048 | E49: MH-DC-001-RACK-A-PP-F1 | F49: 4 | G49: MH-DC-001-RACK-A-TRK-1 | H49: MH-DC-001-RACK-T-ODF-1 | I49: 8
A50: LNK-00061 | B50: A | C50: MH-DC-001-MMR-SW-04 | D50: MH-DC-001-PC-00049 | E50: MH-DC-001-RACK-B-PP-F1 | F50: 5 | G50: MH-DC-001-RACK-B-TRK-1 | H50: MH-DC-001-RACK-T-ODF-1 | I50: 9
A51: LNK-00061 | B51: Z | C51: MH-DC-001-AGG-R01 | D51: MH-DC-001-PC-00050 | E51: MH-DC-001-RACK-A-PP-F1 | F51: 5 | G51: MH-DC-001-RACK-A-TRK-1 | H51: MH-DC-001-RACK-T-ODF-1 | I51: 10
A52: LNK-00062 | B52: A | C52: MH-DC-001-MMR-SW-04 | D52: MH-DC-001-PC-00051 | E52: MH-DC-001-RACK-B-PP-F1 | F52: 6 | G52: MH-DC-001-RACK-B-TRK-2 | H52: MH-DC-001-RACK-T-ODF-1 | I52: 11
A53: LNK-00062 | B53: Z | C53: MH-DC-001-AGG-R01 | D53: MH-DC-001-PC-00052 | E53: MH-DC-001-RACK-A-PP-F1 | F53: 6 | G53: MH-DC-001-RACK-A-TRK-2 | H53: MH-DC-001-RACK-T-ODF-1 | I53: 12
... A75: LNK-00073 | B75: Z | C75: MH-DC-001-MMR-SW-01 | D75: MH-DC-001-PC-00074 | E75: MH-DC-001-RACK-A-PP-F1 | F75: 17 | G75: MH-DC-001-RACK-A-TRK-1 | H75: MH-DC-001-RACK-T-ODF-2 | I75: 10
A76: LNK-00074 | B76: A | C76: MH-DC-001-TOR-001 | D76: MH-DC-001-PC-00075
A77: LNK-00074 | B77: Z | C77: MH-DC-001-MMR-SW-02 | D77: MH-DC-001-PC-00076
A78: LNK-00075 | B78: A | C78: MH-DC-001-TOR-002 | D78: MH-DC-001-PC-00077
A79: LNK-00075 | B79: Z | C79: MH-DC-001-MMR-SW-02 | D79: MH-DC-001-PC-00078
A80: LNK-00076 | B80: A | C80: MH-DC-001-TOR-002 | D80: MH-DC-001-PC-00079
A81: LNK-00076 | B81: Z | C81: MH-DC-001-MMR-SW-03 | D81: MH-DC-001-PC-00080
A82: LNK-00077 | B82: A | C82: MH-DC-001-TOR-003 | D82: MH-DC-001-PC-00081
A83: LNK-00077 | B83: Z | C83: MH-DC-001-MMR-SW-03 | D83: MH-DC-001-PC-00082
A84: LNK-00078 | B84: A | C84: MH-DC-001-TOR-003 | D84: MH-DC-001-PC-00083
A85: LNK-00078 | B85: Z | C85: MH-DC-001-MMR-SW-04 | D85: MH-DC-001-PC-00084
A86: LNK-00079 | B86: A | C86: MH-DC-001-TOR-004 | D86: MH-DC-001-PC-00085
A87: LNK-00079 | B87: Z | C87: MH-DC-001-MMR-SW-04 | D87: MH-DC-001-PC-00086
... A97: LNK-00084 | B97: Z | C97: MH-DC-001-MMR-SW-07 | D97: MH-DC-001-PC-00096
A98: LNK-02113 | B98: A | C98: MH-DC-001-BMS-01 | D98: MH-DC-001-PC-00117 | E98: MH-DC-001-RACK-U-PP-F1 | F98: 1 | G98: MH-DC-001-RACK-U-TRK-1 | H98: MH-DC-001-RACK-T-ODF-3 | I98: 7
A99: LNK-02113 | B99: Z | C99: MH-DC-001-TOR-001 | D99: MH-DC-001-PC-00118 | E99: MH-DC-001-RACK-B-PP-F1 | F99: 18 | G99: MH-DC-001-RACK-B-TRK-1 | H99: MH-DC-001-RACK-T-ODF-3 | I99: 8
A100: LNK-02114 | B100: A | C100: MH-DC-001-BMS-01 | D100: MH-DC-001-PC-00119 | E100: MH-DC-001-RACK-U-PP-F1 | F100: 2 | G100: MH-DC-001-RACK-U-TRK-2 | H100: MH-DC-001-RACK-T-ODF-3 | I100: 9
A101: LNK-02114 | B101: Z | C101: MH-DC-001-TOR-002 | D101: MH-DC-001-PC-00120 | E101: MH-DC-001-RACK-B-PP-F1 | F101: 19 | G101: MH-DC-001-RACK-B-TRK-1 | H101: MH-DC-001-RACK-T-ODF-3 | I101: 10
A102: LNK-02115 | B102: A | C102: MH-DC-001-BMS-02 | D102: MH-DC-001-PC-00121 | E102: MH-DC-001-RACK-U-PP-F1 | F102: 3 | G102: MH-DC-001-RACK-U-TRK-1 | H102: MH-DC-001-RACK-T-ODF-3 | I102: 11
A103: LNK-02115 | B103: Z | C103: MH-DC-001-TOR-001 | D103: MH-DC-001-PC-00122 | E103: MH-DC-001-RACK-B-PP-F1 | F103: 20 | G103: MH-DC-001-RACK-B-TRK-2 | H103: MH-DC-001-RACK-T-ODF-3 | I103: 12
A104: LNK-02116 | B104: A | C104: MH-DC-001-BMS-02 | D104: MH-DC-001-PC-00123 | E104: MH-DC-001-RACK-U-PP-F1 | F104: 4 | G104: MH-DC-001-RACK-U-TRK-2 | H104: MH-DC-001-RACK-T-ODF-3 | I104: 13
A105: LNK-02116 | B105: Z | C105: MH-DC-001-TOR-002 | D105: MH-DC-001-PC-00124 | E105: MH-DC-001-RACK-B-PP-F1 | F105: 21 | G105: MH-DC-001-RACK-B-TRK-2 | H105: MH-DC-001-RACK-T-ODF-3 | I105: 14
A106: LNK-02117 | B106: A | C106: MH-DC-001-ACS-01 | D106: MH-DC-001-PC-00125 | E106: MH-DC-001-RACK-U-PP-F1 | F106: 5 | G106: MH-DC-001-RACK-U-TRK-1 | H106: MH-DC-001-RACK-T-ODF-3 | I106: 15
A107: LNK-02117 | B107: Z | C107: MH-DC-001-TOR-001 | D107: MH-DC-001-PC-00126 | E107: MH-DC-001-RACK-B-PP-F1 | F107: 22 | G107: MH-DC-001-RACK-B-TRK-1 | H107: MH-DC-001-RACK-T-ODF-3 | I107: 16
A108: LNK-02118 | B108: A | C108: MH-DC-001-ACS-01 | D108: MH-DC-001-PC-00127 | E108: MH-DC-001-RACK-U-PP-F1 | F108: 6 | G108: MH-DC-001-RACK-U-TRK-2 | H108: MH-DC-001-RACK-T-ODF-3 | I108: 17
A109: LNK-02118 | B109: Z | C109: MH-DC-001-TOR-002 | D109: MH-DC-001-PC-00128 | E109: MH-DC-001-RACK-B-PP-F1 | F109: 23 | G109: MH-DC-001-RACK-B-TRK-1 | H109: MH-DC-001-RACK-T-ODF-3 | I109: 18
... A145: LNK-02136 | B145: Z | C145: MH-DC-001-TOR-004 | D145: MH-DC-001-PC-00164 | E145: MH-DC-001-RACK-B-PP-F2 | F145: 17 | G145: MH-DC-001-RACK-B-TRK-1 | H145: MH-DC-001-RACK-T-ODF-5 | I145: 6
A146: LNK-00085 | B146: A | C146: MH-DC-002-PE-T4-01 | D146: MH-DC-002-PC-00001
A147: LNK-00085 | B147: Z | C147: MH-DC-002-PE-T4-02 | D147: MH-DC-002-PC-00002
A148: LNK-00090 | B148: A | C148: MH-DC-002-PE-T4-01 | D148: MH-DC-002-PC-00003
A149: LNK-00090 | B149: Z | C149: MH-DC-002-PE-T4-03 | D149: MH-DC-002-PC-00004
A150: LNK-00095 | B150: A | C150: MH-DC-002-PE-T4-01 | D150: MH-DC-002-PC-00005
A151: LNK-00095 | B151: Z | C151: MH-DC-002-PE-T4-04 | D151: MH-DC-002-PC-00006
A152: LNK-00100 | B152: A | C152: MH-DC-002-PE-T4-02 | D152: MH-DC-002-PC-00007
A153: LNK-00100 | B153: Z | C153: MH-DC-002-PE-T4-03 | D153: MH-DC-002-PC-00008
A154: LNK-00105 | B154: A | C154: MH-DC-002-PE-T4-02 | D154: MH-DC-002-PC-00009
A155: LNK-00105 | B155: Z | C155: MH-DC-002-PE-T4-04 | D155: MH-DC-002-PC-00010
A156: LNK-00110 | B156: A | C156: MH-DC-002-PE-T4-03 | D156: MH-DC-002-PC-00011
A157: LNK-00110 | B157: Z | C157: MH-DC-002-PE-T4-04 | D157: MH-DC-002-PC-00012
... A199: LNK-00143 | B199: Z | C199: MH-DC-002-MMR-SW-04 | D199: MH-DC-002-PC-00054
A200: LNK-02137 | B200: A | C200: MH-DC-002-BMS-01 | D200: MH-DC-002-PC-00075 | E200: MH-DC-002-RACK-K-PP-F1 | F200: 1 | G200: MH-DC-002-RACK-K-TRK-1 | H200: MH-DC-002-RACK-J-ODF-1 | I200: 21
A201: LNK-02137 | B201: Z | C201: MH-DC-002-TOR-001 | D201: MH-DC-002-PC-00076 | E201: MH-DC-002-RACK-A-PP-F1 | F201: 21 | G201: MH-DC-002-RACK-A-TRK-1 | H201: MH-DC-002-RACK-J-ODF-1 | I201: 22
A202: LNK-02138 | B202: A | C202: MH-DC-002-BMS-01 | D202: MH-DC-002-PC-00077 | E202: MH-DC-002-RACK-K-PP-F1 | F202: 2 | G202: MH-DC-002-RACK-K-TRK-2 | H202: MH-DC-002-RACK-J-ODF-1 | I202: 23
A203: LNK-02138 | B203: Z | C203: MH-DC-002-TOR-002 | D203: MH-DC-002-PC-00078 | E203: MH-DC-002-RACK-A-PP-F1 | F203: 22 | G203: MH-DC-002-RACK-A-TRK-1 | H203: MH-DC-002-RACK-J-ODF-1 | I203: 24
A204: LNK-02139 | B204: A | C204: MH-DC-002-BMS-02 | D204: MH-DC-002-PC-00079 | E204: MH-DC-002-RACK-K-PP-F1 | F204: 3 | G204: MH-DC-002-RACK-K-TRK-1 | H204: MH-DC-002-RACK-J-ODF-2 | I204: 1
A205: LNK-02139 | B205: Z | C205: MH-DC-002-TOR-001 | D205: MH-DC-002-PC-00080 | E205: MH-DC-002-RACK-A-PP-F1 | F205: 23 | G205: MH-DC-002-RACK-A-TRK-2 | H205: MH-DC-002-RACK-J-ODF-2 | I205: 2
A206: LNK-02140 | B206: A | C206: MH-DC-002-BMS-02 | D206: MH-DC-002-PC-00081 | E206: MH-DC-002-RACK-K-PP-F1 | F206: 4 | G206: MH-DC-002-RACK-K-TRK-2 | H206: MH-DC-002-RACK-J-ODF-2 | I206: 3
A207: LNK-02140 | B207: Z | C207: MH-DC-002-TOR-002 | D207: MH-DC-002-PC-00082 | E207: MH-DC-002-RACK-A-PP-F1 | F207: 24 | G207: MH-DC-002-RACK-A-TRK-2 | H207: MH-DC-002-RACK-J-ODF-2 | I207: 4
A208: LNK-02141 | B208: A | C208: MH-DC-002-ACS-01 | D208: MH-DC-002-PC-00083 | E208: MH-DC-002-RACK-K-PP-F1 | F208: 5 | G208: MH-DC-002-RACK-K-TRK-1 | H208: MH-DC-002-RACK-J-ODF-2 | I208: 5
A209: LNK-02141 | B209: Z | C209: MH-DC-002-TOR-001 | D209: MH-DC-002-PC-00084 | E209: MH-DC-002-RACK-A-PP-F2 | F209: 1 | G209: MH-DC-002-RACK-A-TRK-1 | H209: MH-DC-002-RACK-J-ODF-2 | I209: 6
A210: LNK-02142 | B210: A | C210: MH-DC-002-ACS-01 | D210: MH-DC-002-PC-00085 | E210: MH-DC-002-RACK-K-PP-F1 | F210: 6 | G210: MH-DC-002-RACK-K-TRK-2 | H210: MH-DC-002-RACK-J-ODF-2 | I210: 7
A211: LNK-02142 | B211: Z | C211: MH-DC-002-TOR-002 | D211: MH-DC-002-PC-00086 | E211: MH-DC-002-RACK-A-PP-F2 | F211: 2 | G211: MH-DC-002-RACK-A-TRK-1 | H211: MH-DC-002-RACK-J-ODF-2 | I211: 8
... A239: LNK-02156 | B239: Z | C239: MH-DC-002-MMR-SW-02 | D239: MH-DC-002-PC-00114 | E239: MH-DC-002-RACK-A-PP-F2 | F239: 16 | G239: MH-DC-002-RACK-A-TRK-1 | H239: MH-DC-002-RACK-J-ODF-3 | I239: 12

Sheet Cooling_Coverage
A1: rack_id * | B1: primary_unit_id * | C1: cdu_id
A2: MH-DC-001-RACK-A | B2: MH-DC-001-CRAH-11
A3: MH-DC-001-RACK-B | B3: MH-DC-001-CRAH-11
A4: MH-DC-001-RACK-C | B4: MH-DC-001-CRAH-11
A5: MH-DC-001-RACK-D | B5: MH-DC-001-CRAH-15
A6: MH-DC-001-RACK-E | B6: MH-DC-001-CRAH-15
A7: MH-DC-001-RACK-U | B7: MH-DC-001-CRAH-15
A8: MH-DC-001-RACK-F | B8: MH-DC-001-CRAH-12
A9: MH-DC-001-RACK-G | B9: MH-DC-001-CRAH-12
A10: MH-DC-001-RACK-H | B10: MH-DC-001-CRAH-12
A11: MH-DC-001-RACK-I | B11: MH-DC-001-CRAH-16
A12: MH-DC-001-RACK-J | B12: MH-DC-001-CRAH-16
A13: MH-DC-001-RACK-K | B13: MH-DC-001-CRAH-13
... A23: MH-DC-002-RACK-A | B23: MH-DC-002-CRAH-11
A24: MH-DC-002-RACK-B | B24: MH-DC-002-CRAH-11 | C24: MH-DC-002-CDU-1
A25: MH-DC-002-RACK-C | B25: MH-DC-002-CRAH-15 | C25: MH-DC-002-CDU-1
A26: MH-DC-002-RACK-K | B26: MH-DC-002-CRAH-15
A27: MH-DC-002-RACK-D | B27: MH-DC-002-CRAH-12
A28: MH-DC-002-RACK-E | B28: MH-DC-002-CRAH-16
A29: MH-DC-002-RACK-F | B29: MH-DC-002-CRAH-13
A30: MH-DC-002-RACK-G | B30: MH-DC-002-CRAH-13
A31: MH-DC-002-RACK-H | B31: MH-DC-002-CRAH-17 | C31: MH-DC-002-CDU-1
A32: MH-DC-002-RACK-I | B32: MH-DC-002-CRAH-14
A33: MH-DC-002-RACK-J | B33: MH-DC-002-CRAH-18

Sheet GPU_Clusters
A1: cluster_id * | B1: site_id * | C1: room_id * | D1: name * | E1: scheduler * | F1: fabric * | G1: gpu_model * | H1: cooling * | I1: node_count (calc)

Sheet GPU_Nodes
A1: device_id * | B1: cluster_id * | C1: gpu_model * | D1: gpu_vendor * | E1: gpu_count * | F1: server_model * | G1: cooling * | H1: driver | I1: firmware

Sheet Customers
A1: customer_id * | B1: name * | C1: segment * | D1: city * | E1: state * | F1: plan * | G1: premium * | H1: account_manager | I1: monthly_revenue (calc)
A2: CUST-1202 | B2: Hyperscale Cloud East | C2: Hyperscaler | D2: Mumbai | E2: Maharashtra | F2: Private cage · 2N | G2: Y | H2: Neha Kapoor | I2: =SUMIF('Services'!$B$2:$B$2000,A2,'Services'!$M$2:$M$2000)
A3: CUST-6478 | B3: Payments Gateway | C3: BFSI | D3: Mumbai | E3: Maharashtra | F3: Cabinets · 8 kW | G3: Y | H3: Pooja Verma | I3: =SUMIF('Services'!$B$2:$B$2000,A3,'Services'!$M$2:$M$2000)
A4: CUST-4716 | B4: Telecom Provider | C4: Carrier | D4: Chennai | E4: Tamil Nadu | F4: MMR cabinets | G4: Y | H4: Rohan Joshi | I4: =SUMIF('Services'!$B$2:$B$2000,A4,'Services'!$M$2:$M$2000)
A5: CUST-2954 | B5: Cloud Exchange | C5: Carrier | D5: Bengaluru | E5: Karnataka | F5: MMR cabinets | G5: Y | H5: Karthik Raman | I5: =SUMIF('Services'!$B$2:$B$2000,A5,'Services'!$M$2:$M$2000)
A6: CUST-9111 | B6: Gaming Studio | C6: Media | D6: Hyderabad | E6: Telangana | F6: Cabinets · 8 kW | G6: N | H6: Rohan Joshi | I6: =SUMIF('Services'!$B$2:$B$2000,A6,'Services'!$M$2:$M$2000)
A7: CUST-8230 | B7: E-commerce Marketplace | C7: Enterprise | D7: Bengaluru | E7: Karnataka | F7: Suite · 20 kW | G7: Y | H7: Ananya Sen | I7: =SUMIF('Services'!$B$2:$B$2000,A7,'Services'!$M$2:$M$2000)
A8: CUST-7349 | B8: Logistics Partners | C8: Enterprise | D8: Hyderabad | E8: Telangana | F8: Cabinets · 6 kW | G8: N | H8: Karthik Raman | I8: =SUMIF('Services'!$B$2:$B$2000,A8,'Services'!$M$2:$M$2000)
A9: CUST-6468 | B9: Pharma Manufacturing | C9: Enterprise | D9: Ahmedabad | E9: Gujarat | F9: Cabinets · 4 kW | G9: N | H9: Pooja Verma | I9: =SUMIF('Services'!$B$2:$B$2000,A9,'Services'!$M$2:$M$2000)
A10: CUST-2063 | B10: Smart City Mission | C10: Government | D10: Indore | E10: Madhya Pradesh | F10: Cabinets · 6 kW | G10: N | H10: Pooja Verma | I10: =SUMIF('Services'!$B$2:$B$2000,A10,'Services'!$M$2:$M$2000)
A11: CUST-9982 | B11: Health Network | C11: Healthcare | D11: New Delhi | E11: Delhi NCR | F11: Cabinets · 8 kW | G11: Y | H11: Neha Kapoor | I11: =SUMIF('Services'!$B$2:$B$2000,A11,'Services'!$M$2:$M$2000)
A12: CUST-8220 | B12: Research Institute | C12: Government | D12: Bengaluru | E12: Karnataka | F12: HPC cabinets · 12 kW | G12: N | H12: Ananya Sen | I12: =SUMIF('Services'!$B$2:$B$2000,A12,'Services'!$M$2:$M$2000)

Sheet Services
A1: service_id * | B1: customer_id * | C1: type * | D1: site_id * | E1: device_id | F1: if_name | G1: rack_ids | H1: gpu_node_ids | I1: qty * | J1: unit * | K1: bandwidth_mbps | L1: sla_target_pct * | M1: monthly_revenue * | N1: critical * | O1: start_date
A2: SVC-CB-1100 | B2: CUST-7349 | C2: Cabinet lease | D2: MH-DC-001 | E2: MH-DC-001-TN-003 | F2: RACK-C | I2: 1 | J2: cabinets | K2: 10000 | L2: 99.99 | M2: 120000 | N2: N
A3: SVC-PW-1101 | B3: CUST-7349 | C3: Power circuit | D3: MH-DC-001 | E3: MH-DC-001-TN-003 | F3: RACK-C · PDU A+B | I3: 19 | J3: kW | K3: 10000 | L3: 99.99 | M3: 171000 | N3: N
A4: SVC-XC-1102 | B4: CUST-7349 | C4: Cross-connect | D4: MH-DC-001 | E4: MH-DC-001-MMR-SW-01 | F4: MMR panel 1 · P34 | I4: 100000 | J4: Mbps | K4: 100000 | L4: 99.99 | M4: 400000 | N4: N
A5: SVC-XC-1103 | B5: CUST-7349 | C5: Cross-connect | D5: MH-DC-001 | E5: MH-DC-001-MMR-SW-02 | F5: MMR panel 8 · P26 | I5: 1000 | J5: Mbps | K5: 1000 | L5: 99.99 | M5: 4000 | N5: N
A6: SVC-CB-1104 | B6: CUST-2954 | C6: Cabinet lease | D6: MH-DC-001 | E6: MH-DC-001-TN-010 | F6: RACK-D, RACK-E | I6: 2 | J6: cabinets | K6: 10000 | L6: 99.999 | M6: 240000 | N6: Y
A7: SVC-PW-1105 | B7: CUST-2954 | C7: Power circuit | D7: MH-DC-001 | E7: MH-DC-001-TN-010 | F7: RACK-D · PDU A+B | I7: 15 | J7: kW | K7: 10000 | L7: 99.999 | M7: 135000 | N7: Y
A8: SVC-PW-1106 | B8: CUST-2954 | C8: Power circuit | D8: MH-DC-001 | E8: MH-DC-001-TN-015 | F8: RACK-E · PDU A+B | I8: 19 | J8: kW | K8: 10000 | L8: 99.999 | M8: 171000 | N8: Y
A9: SVC-XC-1107 | B9: CUST-2954 | C9: Cross-connect | D9: MH-DC-001 | E9: MH-DC-001-MMR-SW-06 | F9: MMR panel 11 · P20 | I9: 10000 | J9: Mbps | K9: 10000 | L9: 99.999 | M9: 40000 | N9: Y
A10: SVC-CB-1108 | B10: CUST-9111 | C10: Cabinet lease | D10: MH-DC-001 | E10: MH-DC-001-TN-020 | F10: RACK-F, RACK-G | I10: 2 | J10: cabinets | K10: 10000 | L10: 99.99 | M10: 240000 | N10: N
A11: SVC-PW-1109 | B11: CUST-9111 | C11: Power circuit | D11: MH-DC-001 | E11: MH-DC-001-TN-020 | F11: RACK-F · PDU A+B | I11: 20 | J11: kW | K11: 10000 | L11: 99.99 | M11: 180000 | N11: N
A12: SVC-PW-1110 | B12: CUST-9111 | C12: Power circuit | D12: MH-DC-001 | E12: MH-DC-001-TN-026 | F12: RACK-G · PDU A+B | I12: 18 | J12: kW | K12: 10000 | L12: 99.99 | M12: 162000 | N12: N
A13: SVC-XC-1111 | B13: CUST-9111 | C13: Cross-connect | D13: MH-DC-001 | E13: MH-DC-001-MMR-SW-09 | F13: MMR panel 7 · P10 | I13: 100000 | J13: Mbps | K13: 100000 | L13: 99.99 | M13: 400000 | N13: N
... A63: SVC-XC-1161 | B63: CUST-1202 | C63: Cross-connect | D63: MH-DC-002 | E63: MH-DC-002-MMR-SW-02 | F63: MMR panel 10 · P21 | I63: 10000 | J63: Mbps | K63: 10000 | L63: 99.999 | M63: 40000 | N63: Y

Sheet Collectors
A1: collector_id * | B1: site_id * | C1: name * | D1: protocol * | E1: domain * | F1: host_ip | G1: covers
A2: COL-MH-DC-001-1 | B2: MH-DC-001 | C2: Collector Pune A | D2: gNMI | E2: Network
A3: COL-MH-DC-001-2 | B3: MH-DC-001 | C3: Collector Pune B | D3: gNMI | E3: Network
A4: COL-MH-DC-002-1 | B4: MH-DC-002 | C4: Collector Pune A | D4: gNMI | E4: Network
A5: COL-MH-DC-002-2 | B5: MH-DC-002 | C5: Collector Pune B | D5: gNMI | E5: Network

Sheet Fire_Systems
A1: zone_id * | B1: site_id * | C1: room_id * | D1: detection * | E1: suppression * | F1: release_mode * | G1: last_inspection * | H1: panel_point
A2: MH-DC-001-FZ-01 | B2: MH-DC-001 | C2: MH-DC-001-F0-R1 | D2: VESDA aspirating | E2: Inert gas (IG-541) | F2: Armed (auto) | G2: 46232
A3: MH-DC-001-FZ-02 | B3: MH-DC-001 | C3: MH-DC-001-F0-R2 | D3: VESDA aspirating | E3: Novec 1230 gas | F3: Armed (auto) | G3: 46258
A4: MH-DC-001-FZ-03 | B4: MH-DC-001 | C4: MH-DC-001-F1-R1 | D4: VESDA aspirating | E4: Inert gas (IG-541) | F4: Armed (auto) | G4: 46235
A5: MH-DC-001-FZ-04 | B5: MH-DC-001 | C5: MH-DC-001-F1-R2 | D5: VESDA aspirating | E5: Novec 1230 gas | F5: Armed (auto) | G5: 46203
A6: MH-DC-002-FZ-01 | B6: MH-DC-002 | C6: MH-DC-002-F0-R1 | D6: VESDA aspirating | E6: Inert gas (IG-541) | F6: Armed (auto) | G6: 46283
A7: MH-DC-002-FZ-02 | B7: MH-DC-002 | C7: MH-DC-002-F0-R2 | D7: VESDA aspirating | E7: Inert gas (IG-541) | F7: Armed (auto) | G7: 46241
A8: MH-DC-002-FZ-03 | B8: MH-DC-002 | C8: MH-DC-002-F1-R1 | D8: VESDA aspirating | E8: Novec 1230 gas | F8: Armed (auto) | G8: 46259
A9: MH-DC-002-FZ-04 | B9: MH-DC-002 | C9: MH-DC-002-F1-R2 | D9: VESDA aspirating | E9: Novec 1230 gas | F9: Armed (auto) | G9: 46216

Sheet Leak_Detection
A1: zone_id * | B1: site_id * | C1: room_id * | D1: guards * | E1: length_m | F1: last_test
A2: MH-DC-001-LK-01 | B2: MH-DC-001 | C2: MH-DC-001-F0-R1 | D2: Under CRAH-11, CRAH-15 | E2: 14 | F2: 46259
A3: MH-DC-001-LK-02 | B3: MH-DC-001 | C3: MH-DC-001-F0-R2 | D3: Under CRAH-12, CRAH-16 | E3: 14 | F3: 46264
A4: MH-DC-001-LK-03 | B4: MH-DC-001 | C4: MH-DC-001-F1-R1 | D4: Under CRAH-13, CRAH-17 | E4: 14 | F4: 46142
A5: MH-DC-001-LK-04 | B5: MH-DC-001 | C5: MH-DC-001-F1-R2 | D5: Under CRAH-14, CRAH-18 | E5: 16 | F5: 46151
A6: MH-DC-002-LK-01 | B6: MH-DC-002 | C6: MH-DC-002-F0-R1 | D6: Under CRAH-11, CRAH-15 | E6: 16 | F6: 46167
A7: MH-DC-002-LK-02 | B7: MH-DC-002 | C7: MH-DC-002-F0-R1 | D7: CDU-1 manifold · 2 liquid racks | E7: 10 | F7: 46259
A8: MH-DC-002-LK-03 | B8: MH-DC-002 | C8: MH-DC-002-F0-R2 | D8: Under CRAH-12, CRAH-16 | E8: 18 | F8: 46159
A9: MH-DC-002-LK-04 | B9: MH-DC-002 | C9: MH-DC-002-F1-R1 | D9: Under CRAH-13, CRAH-17 | E9: 20 | F9: 46217
A10: MH-DC-002-LK-05 | B10: MH-DC-002 | C10: MH-DC-002-F1-R1 | D10: 1 liquid rack | E10: 7 | F10: 46224
A11: MH-DC-002-LK-06 | B11: MH-DC-002 | C11: MH-DC-002-F1-R2 | D11: Under CRAH-14, CRAH-18 | E11: 18 | F11: 46143

Sheet Access_Points
A1: door_id * | B1: site_id * | C1: name * | D1: room_id | E1: kind * | F1: reader * | G1: tenant_customer_id
A2: MH-DC-001-DR-01 | B2: MH-DC-001 | C2: Main entrance · mantrap | E2: Building entry | F2: Card + biometric
A3: MH-DC-001-DR-02 | B3: MH-DC-001 | C3: Meet-me room door | D3: MH-DC-001-F0-R1 | E3: Meet-me room door | F3: Card + biometric
A4: MH-DC-001-DR-03 | B4: MH-DC-001 | C4: Hall A door | D4: MH-DC-001-F0-R2 | E4: Data hall door | F4: Card + biometric
A5: MH-DC-001-DR-04 | B5: MH-DC-001 | C5: Hall B door | D5: MH-DC-001-F1-R1 | E5: Data hall door | F5: Card + biometric
A6: MH-DC-001-DR-05 | B6: MH-DC-001 | C6: Hall C door | D6: MH-DC-001-F1-R2 | E6: Data hall door | F6: Card + biometric
A7: MH-DC-001-DR-06 | B7: MH-DC-001 | C7: Cage · Logistics Partners | D7: MH-DC-001-F0-R1 | E7: Cage door | F7: Card + PIN | G7: CUST-7349
A8: MH-DC-001-DR-07 | B8: MH-DC-001 | C8: Cage · Cloud Exchange | D8: MH-DC-001-F0-R1 | E8: Cage door | F8: Card + PIN | G8: CUST-2954
A9: MH-DC-001-DR-08 | B9: MH-DC-001 | C9: Cage · Gaming Studio | D9: MH-DC-001-F0-R2 | E9: Cage door | F9: Card + PIN | G9: CUST-9111
A10: MH-DC-001-DR-09 | B10: MH-DC-001 | C10: Cage · Payments Gateway | D10: MH-DC-001-F0-R2 | E10: Cage door | F10: Card + PIN | G10: CUST-6478
A11: MH-DC-001-DR-10 | B11: MH-DC-001 | C11: Cage · Smart City Mission | D11: MH-DC-001-F0-R2 | E11: Cage door | F11: Card + PIN | G11: CUST-2063
A12: MH-DC-001-DR-11 | B12: MH-DC-001 | C12: Cage · E-commerce Marketplace | D12: MH-DC-001-F0-R2 | E12: Cage door | F12: Card + PIN | G12: CUST-8230
A13: MH-DC-001-DR-12 | B13: MH-DC-001 | C13: Cage · Pharma Manufacturing | D13: MH-DC-001-F1-R1 | E13: Cage door | F13: Card + PIN | G13: CUST-6468
A14: MH-DC-001-DR-13 | B14: MH-DC-001 | C14: Cage · Health Network | D14: MH-DC-001-F1-R1 | E14: Cage door | F14: Card + PIN | G14: CUST-9982
A15: MH-DC-001-DR-14 | B15: MH-DC-001 | C15: Cage · Hyperscale Cloud East | D15: MH-DC-001-F1-R2 | E15: Cage door | F15: Card + PIN | G15: CUST-1202
A16: MH-DC-002-DR-01 | B16: MH-DC-002 | C16: Main entrance · mantrap | E16: Building entry | F16: Card + biometric
A17: MH-DC-002-DR-02 | B17: MH-DC-002 | C17: Meet-me room door | D17: MH-DC-002-F0-R1 | E17: Meet-me room door | F17: Card + biometric
A18: MH-DC-002-DR-03 | B18: MH-DC-002 | C18: Hall A door | D18: MH-DC-002-F0-R2 | E18: Data hall door | F18: Card + biometric
A19: MH-DC-002-DR-04 | B19: MH-DC-002 | C19: Hall B door | D19: MH-DC-002-F1-R1 | E19: Data hall door | F19: Card + biometric
A20: MH-DC-002-DR-05 | B20: MH-DC-002 | C20: Hall C door | D20: MH-DC-002-F1-R2 | E20: Data hall door | F20: Card + biometric
A21: MH-DC-002-DR-06 | B21: MH-DC-002 | C21: Cage · Logistics Partners | D21: MH-DC-002-F0-R1 | E21: Cage door | F21: Card + PIN | G21: CUST-7349
A22: MH-DC-002-DR-07 | B22: MH-DC-002 | C22: Cage · Research Institute | D22: MH-DC-002-F0-R2 | E22: Cage door | F22: Card + PIN | G22: CUST-8220
A23: MH-DC-002-DR-08 | B23: MH-DC-002 | C23: Cage · Telecom Provider | D23: MH-DC-002-F0-R2 | E23: Cage door | F23: Card + PIN | G23: CUST-4716
A24: MH-DC-002-DR-09 | B24: MH-DC-002 | C24: Cage · Cloud Exchange | D24: MH-DC-002-F1-R1 | E24: Cage door | F24: Card + PIN | G24: CUST-2954
A25: MH-DC-002-DR-10 | B25: MH-DC-002 | C25: Cage · Hyperscale Cloud East | D25: MH-DC-002-F1-R1 | E25: Cage door | F25: Card + PIN | G25: CUST-1202

Sheet Support_Contracts
A1: contract_id * | B1: site_id * | C1: vendor * | D1: level * | E1: start | F1: expires *
A2: AMC-MH-94990 | B2: MH-DC-001 | C2: JUNIPER | D2: 24×7×4 | F2: 46788
A3: AMC-MH-43694 | B3: MH-DC-001 | C3: CISCO | D3: 24×7×4 | F3: 46390
A4: AMC-MH-45067 | B4: MH-DC-001 | C4: NOKIA | D4: 24×7×4 | F4: 46340
A5: AMC-MH-60459 | B5: MH-DC-001 | C5: CISCO | D5: 8×5 NBD | F5: 46810
A6: AMC-MH-71915 | B6: MH-DC-001 | C6: JUNIPER | D6: 8×5 NBD | F6: 46902
A7: AMC-MH-33776 | B7: MH-DC-001 | C7: ARISTA | D7: 8×5 NBD | F7: 46799
A8: AMC-MH-31357 | B8: MH-DC-001 | C8: DELL | D8: NBD | F8: 46410
A9: AMC-MH-94491 | B9: MH-DC-001 | C9: SUPERMICRO | D9: NBD | F9: 46428
A10: AMC-MH-91907 | B10: MH-DC-001 | C10: HPE | D10: NBD | F10: 46430
A11: AMC-MH-57371 | B11: MH-DC-002 | C11: JUNIPER | D11: 24×7×4 | F11: 46456
A12: AMC-MH-96075 | B12: MH-DC-002 | C12: CISCO | D12: 24×7×4 | F12: 46565
A13: AMC-MH-82686 | B13: MH-DC-002 | C13: NOKIA | D13: 24×7×4 | F13: 46894
... A18: AMC-MH-39526 | B18: MH-DC-002 | C18: HPE | D18: NBD | F18: 46347

Sheet Asset_Lifecycle
A1: device_id * | B1: installed * | C1: warranty_end * | D1: contract_id
A2: MH-DC-001-PE-T4-01 | B2: 45497 | C2: 47322 | D2: AMC-MH-94990
A3: MH-DC-001-PE-T4-02 | B3: 45997 | C3: 47092 | D3: AMC-MH-94990
A4: MH-DC-001-PE-T4-03 | B4: 44164 | C4: 45989 | D4: AMC-MH-43694
A5: MH-DC-001-PE-T4-04 | B5: 43921 | C5: 45016 | D5: AMC-MH-43694
A6: MH-DC-001-FW-01 | B6: 44379 | C6: 46204
A7: MH-DC-001-FW-02 | B7: 44171 | C7: 45266
A8: MH-DC-001-OLA-01 | B8: 46061 | C8: 47156 | D8: AMC-MH-45067
A9: MH-DC-001-OLA-02 | B9: 46141 | C9: 47966 | D9: AMC-MH-45067
A10: MH-DC-001-AGG-R01 | B10: 46093 | C10: 47188 | D10: AMC-MH-94990
A11: MH-DC-001-AGG-R02 | B11: 46186 | C11: 48011 | D11: AMC-MH-94990
A12: MH-DC-001-AGG-R03 | B12: 46244 | C12: 47339 | D12: AMC-MH-94990
A13: MH-DC-001-MMR-SW-01 | B13: 43719 | C13: 44814
A14: MH-DC-001-MMR-SW-02 | B14: 45757 | C14: 46852 | D14: AMC-MH-60459
A15: MH-DC-001-MMR-SW-03 | B15: 46187 | C15: 47282 | D15: AMC-MH-60459
A16: MH-DC-001-MMR-SW-04 | B16: 46095 | C16: 47190 | D16: AMC-MH-60459
A17: MH-DC-001-MMR-SW-05 | B17: 46109 | C17: 47934 | D17: AMC-MH-71915
A18: MH-DC-001-MMR-SW-06 | B18: 46250 | C18: 47345 | D18: AMC-MH-60459
A19: MH-DC-001-MMR-SW-07 | B19: 46095 | C19: 47190 | D19: AMC-MH-60459
A20: MH-DC-001-MMR-SW-08 | B20: 46151 | C20: 47246 | D20: AMC-MH-60459
A21: MH-DC-001-MMR-SW-09 | B21: 46025 | C21: 47120 | D21: AMC-MH-33776
A22: MH-DC-001-TOR-001 | B22: 44265 | C22: 45360
A23: MH-DC-001-TOR-002 | B23: 46205 | C23: 47300 | D23: AMC-MH-60459
A24: MH-DC-001-TOR-003 | B24: 45098 | C24: 46923 | D24: AMC-MH-71915
A25: MH-DC-001-TOR-004 | B25: 44709 | C25: 46534 | D25: AMC-MH-60459
A26: MH-DC-001-TOR-005 | B26: 45018 | C26: 46113 | D26: AMC-MH-71915
A27: MH-DC-001-TOR-006 | B27: 46044 | C27: 47869 | D27: AMC-MH-33776
A28: MH-DC-001-BMS-01 | B28: 44060 | C28: 45155 | D28: AMC-MH-31357
A29: MH-DC-001-BMS-02 | B29: 44225 | C29: 45320
A30: MH-DC-001-ACS-01 | B30: 46024 | C30: 47849 | D30: AMC-MH-94491
A31: MH-DC-001-NVR-01 | B31: 46118 | C31: 47213 | D31: AMC-MH-91907
A32: MH-DC-001-NVR-02 | B32: 46223 | C32: 47318 | D32: AMC-MH-94491
A33: MH-DC-001-JMP-01 | B33: 46205 | C33: 48030 | D33: AMC-MH-94491
A34: MH-DC-001-JMP-02 | B34: 45108 | C34: 46203 | D34: AMC-MH-91907
A35: MH-DC-001-BKP-01 | B35: 46262 | C35: 47357 | D35: AMC-MH-31357
A36: MH-DC-001-DCIM-01 | B36: 46074 | C36: 47169 | D36: AMC-MH-94491
A37: MH-DC-001-DCIM-02 | B37: 46190 | C37: 48015 | D37: AMC-MH-94491
A38: MH-DC-001-MON-01 | B38: 46151 | C38: 47246 | D38: AMC-MH-91907
A39: MH-DC-001-MON-02 | B39: 46056 | C39: 47881 | D39: AMC-MH-31357
A40: MH-DC-002-PE-T4-01 | B40: 46097 | C40: 47192 | D40: AMC-MH-57371
A41: MH-DC-002-PE-T4-02 | B41: 45489 | C41: 47314 | D41: AMC-MH-57371
... A43: MH-DC-002-PE-T4-04 | B43: 43940 | C43: 45765 | D43: AMC-MH-96075
A44: MH-DC-002-FW-01 | B44: 43969 | C44: 45064
A45: MH-DC-002-OLA-01 | B45: 46139 | C45: 47234 | D45: AMC-MH-82686
A46: MH-DC-002-AGG-R01 | B46: 45351 | C46: 46446 | D46: AMC-MH-57371
A47: MH-DC-002-AGG-R02 | B47: 45875 | C47: 46970 | D47: AMC-MH-57371
A48: MH-DC-002-MMR-SW-01 | B48: 44271 | C48: 45366
A49: MH-DC-002-MMR-SW-02 | B49: 44959 | C49: 46054 | D49: AMC-MH-19534
A50: MH-DC-002-MMR-SW-03 | B50: 44724 | C50: 45819 | D50: AMC-MH-98078
A51: MH-DC-002-MMR-SW-04 | B51: 45076 | C51: 46171 | D51: AMC-MH-98078
A52: MH-DC-002-TOR-001 | B52: 45706 | C52: 46801 | D52: AMC-MH-19534
A53: MH-DC-002-TOR-002 | B53: 45640 | C53: 46735 | D53: AMC-MH-19534
A54: MH-DC-002-TOR-003 | B54: 44940 | C54: 46035 | D54: AMC-MH-98078
A55: MH-DC-002-BMS-01 | B55: 44427 | C55: 45522 | D55: AMC-MH-42110
A56: MH-DC-002-BMS-02 | B56: 44318 | C56: 45413
A57: MH-DC-002-ACS-01 | B57: 44153 | C57: 45248 | D57: AMC-MH-42110
A58: MH-DC-002-NVR-01 | B58: 46262 | C58: 47357 | D58: AMC-MH-98500
A59: MH-DC-002-JMP-01 | B59: 46240 | C59: 47335 | D59: AMC-MH-39526
A60: MH-DC-002-BKP-01 | B60: 44809 | C60: 45904 | D60: AMC-MH-39526
A61: MH-DC-002-DCIM-01 | B61: 45350 | C61: 46445 | D61: AMC-MH-39526
A62: MH-DC-002-DCIM-02 | B62: 45417 | C62: 46512 | D62: AMC-MH-42110
A63: MH-DC-002-MON-01 | B63: 46136 | C63: 47961 | D63: AMC-MH-42110
A64: MH-DC-002-MON-02 | B64: 44718 | C64: 46543 | D64: AMC-MH-98500

Sheet Model_Lifecycle
A1: vendor * | B1: model * | C1: end_of_sale * | D1: end_of_support *
A2: JUNIPER | B2: MX204 | C2: 47669 | D2: 49494
A3: CISCO | B3: ASR 9006 | C3: 44796 | D3: 46621
A4: FORTINET | B4: FortiGate 3700F | C4: 44286 | D4: 46111
A5: NOKIA | B5: 1830 PSS-16II | C5: 47449 | D5: 49274
A6: JUNIPER | B6: MX480 | C6: 47493 | D6: 49318
A7: JUNIPER | B7: QFX5100-48S | C7: 44396 | D7: 46146
A8: CISCO | B8: Nexus 93180YC | C8: 47433 | D8: 49258
A9: JUNIPER | B9: QFX5120-48Y | C9: 47839 | D9: 49664
A10: ARISTA | B10: 7050SX3-48YC | C10: 47774 | D10: 49599
A11: CISCO | B11: Nexus 3172PQ | C11: 43896 | D11: 45726
A12: DELL | B12: PowerEdge R640 | C12: 45196 | D12: 46996
A13: SUPERMICRO | B13: SYS-121H | C13: 47660 | D13: 49485
... A17: SUPERMICRO | B17: SYS-120U-TNR | C17: 45696 | D17: 47316

Sheet Spares
A1: site_id * | B1: part * | C1: fits | D1: on_hand * | E1: min_level *
A2: MH-DC-001 | B2: NOKIA fan module | C2: NOKIA | D2: 0 | E2: 1
A3: MH-DC-001 | B3: ARISTA fan module | C3: ARISTA | D3: 3 | E3: 1
A4: MH-DC-001 | B4: ARISTA power supply | C4: ARISTA network | D4: 1 | E4: 1
A5: MH-DC-001 | B5: CISCO fan module | C5: CISCO | D5: 3 | E5: 1
A6: MH-DC-001 | B6: CISCO power supply | C6: CISCO network | D6: 2 | E6: 1
A7: MH-DC-001 | B7: DELL fan module | C7: DELL | D7: 3 | E7: 1
A8: MH-DC-001 | B8: DELL power supply | C8: DELL servers | D8: 5 | E8: 1
A9: MH-DC-001 | B9: FORTINET fan module | C9: FORTINET | D9: 4 | E9: 1
A10: MH-DC-001 | B10: FORTINET power supply | C10: FORTINET network | D10: 4 | E10: 1
A11: MH-DC-001 | B11: HPE fan module | C11: HPE | D11: 2 | E11: 1
A12: MH-DC-001 | B12: HPE power supply | C12: HPE servers | D12: 1 | E12: 1
A13: MH-DC-001 | B13: JUNIPER fan module | C13: JUNIPER | D13: 2 | E13: 1
... A39: MH-DC-002 | B39: SUPERMICRO power supply | C39: SUPERMICRO servers | D39: 2 | E39: 1

Sheet PM_Plan
A1: task_id * | B1: site_id * | C1: asset_id * | D1: kind * | E1: task * | F1: interval_days * | G1: last_done * | H1: owner
A2: MH-DC-001-PM-024 | B2: MH-DC-001 | C2: MH-DC-001-LV | D2: Electrical | E2: Annual thermography and ATS transfer test | F2: 365 | G2: 45832 | H2: Sarah Chen
A3: MH-DC-001-PM-001 | B3: MH-DC-001 | C3: MH-DC-001-UPS-1 | D3: UPS | E3: Quarterly inspection and thermal scan | F3: 91 | G3: 46183 | H3: Anil Kulkarni
A4: MH-DC-001-PM-009 | B4: MH-DC-001 | C4: MH-DC-001-DG | D4: Generator | E4: Monthly on-load run | F4: 30 | G4: 46261 | H4: Sarah Chen
A5: MH-DC-001-PM-023 | B5: MH-DC-001 | C5: MH-DC-001-FZ-04 | D5: Fire | E5: Gas suppression inspection | F5: 91 | G5: 46203 | H5: Rahul Deshpande
A6: MH-DC-001-PM-010 | B6: MH-DC-001 | C6: MH-DC-001-DG | D6: Generator | E6: DG load-bank test — 125 kVA set (booked in place of: annual load-bank test) | F6: 365 | G6: 46195 | H6: Anil Kulkarni
A7: MH-DC-001-PM-014 | B7: MH-DC-001 | C7: MH-DC-001-CRAH-13 | D7: Cooling | E7: Filter change and coil clean | F7: 91 | G7: 46218 | H7: Sarah Chen
A8: MH-DC-001-PM-007 | B8: MH-DC-001 | C8: MH-DC-001-UPS-4 | D8: UPS | E8: Quarterly inspection and thermal scan | F8: 91 | G8: 46220 | H8: David Kim
A9: MH-DC-001-PM-005 | B9: MH-DC-001 | C9: MH-DC-001-UPS-3 | D9: UPS | E9: Quarterly inspection and thermal scan | F9: 91 | G9: 46223 | H9: David Kim
A10: MH-DC-001-PM-012 | B10: MH-DC-001 | C10: MH-DC-001-CRAH-11 | D10: Cooling | E10: Filter change and coil clean | F10: 91 | G10: 46224 | H10: Anil Kulkarni
A11: MH-DC-001-PM-020 | B11: MH-DC-001 | C11: MH-DC-001-FZ-01 | D11: Fire | E11: Gas suppression inspection | F11: 91 | G11: 46232 | H11: Vikram Singh
A12: MH-DC-001-PM-019 | B12: MH-DC-001 | C12: MH-DC-001-CRAH-18 | D12: Cooling | E12: Filter change and coil clean | F12: 91 | G12: 46233 | H12: Sneha Patil
A13: MH-DC-001-PM-022 | B13: MH-DC-001 | C13: MH-DC-001-FZ-03 | D13: Fire | E13: Gas suppression inspection | F13: 91 | G13: 46235 | H13: Mike Johnson
... A52: MH-DC-002-PM-026 | B52: MH-DC-002 | C52: MH-DC-002-PDU | D52: Electrical | E52: Annual PDU thermography | F52: 365 | G52: 46212 | H52: Meera Iyer

Sheet On_Call
A1: region * | B1: role * | C1: name * | D1: tier * | E1: escalate_after_min * | F1: phone
A2: West | B2: NOC shift lead | C2: Sarah Chen | D2: 1 | E2: 15
A3: West | B3: Network engineer | C3: Meera Iyer | D3: 2 | E3: 30
A4: West | B4: Facility engineer | C4: Priya Nair | D4: 2 | E4: 30
A5: West | B5: Field technician | C5: David Kim | D5: 2 | E5: 60
A6: West | B6: Duty manager | C6: Vikram Singh | D6: 3 | E6: 60

Sheet Snapshot_Alerts
A1: alert_id | B1: site_id | C1: severity | D1: state | E1: title | F1: source | G1: category | H1: scope | I1: device_or_node | J1: if_name | K1: link_or_rack | L1: raised_at | M1: incident_id
A2: ALM-1930 | B2: MH-DC-001 | C2: critical | D2: active | E2: Interface Flapping Detected | F2: Interface | G2: Network | H2: edge | I2: MH-DC-001-PE-T4-01 | J2: xe-0/0/3 | L2: 2026-10-01 07:07 | M2: INC-0001
A3: ALM-1831 | B3: MH-DC-001 | C3: major | D3: active | E3: High CPU Utilization | F3: CPU | G3: Performance | H3: site | I3: MH-DC-001-PE-T4-01 | L3: 2026-10-01 06:52 | M3: INC-0001
A4: ALM-1774 | B4: MH-DC-001 | C4: major | D4: active | E4: Link Degradation | F4: Link | G4: Performance | H4: edge | I4: MH-DC-001-PE-T4-01 | J4: xe-0/0/3 | L4: 2026-10-01 04:52 | M4: INC-0001
A5: ALM-1702 | B5: MH-DC-001 | C5: minor | D5: active | E5: Optical Rx Power Low | F5: Interface | G5: Network | H5: edge | I5: MH-DC-001-PE-T4-01 | J5: xe-0/0/3 | L5: 2026-10-01 04:18 | M5: INC-0001
A6: ALM-1655 | B6: MH-DC-001 | C6: minor | D6: active | E6: BGP Peer Idle | F6: Protocol | G6: Network | H6: site | I6: MH-DC-001-PE-T4-01 | L6: 2026-10-01 02:45
A7: ALM-1610 | B7: MH-DC-001 | C7: minor | D7: active | E7: Temperature Warning | F7: Environment | G7: Device | H7: site | I7: MH-DC-001-PE-T4-01 | L7: 2026-09-30 05:32
A8: ALM-1598 | B8: MH-DC-001 | C8: minor | D8: active | E8: OSPF Neighbour in INIT | F8: Protocol | G8: Network | H8: site | I8: MH-DC-001-PE-T4-01 | L8: 2026-09-30 17:11
A9: ALM-1001 | B9: MH-DC-001 | C9: minor | D9: active | E9: OSPF Neighbour Down | F9: Protocol | G9: Network | H9: site | I9: MH-DC-001-PE-T4-02 | K9: LNK-00017 | L9: 2026-09-30 05:21
A10: ALM-1021 | B10: MH-DC-001 | C10: minor | D10: acknowledged | E10: High Memory Utilization | F10: CPU | G10: Performance | H10: site | I10: MH-DC-001-AGG-R02 | L10: 2026-09-30 15:56
A11: ALM-1022 | B11: MH-DC-001 | C11: warning | D11: active | E11: Configuration Drift | F11: Discovery | G11: Device | H11: site | I11: MH-DC-001-AGG-R03 | L11: 2026-09-28 14:51
A12: ALM-1042 | B12: MH-DC-001 | C12: major | D12: active | E12: Collector Stale | F12: Discovery | G12: Network | H12: dependency | L12: 2026-10-01 04:38 | M12: INC-0010
A13: ALM-1049 | B13: MH-DC-001 | C13: minor | D13: active | E13: High CPU Utilization | F13: CPU | G13: Performance | H13: downstream | I13: MH-POP-001-AGG-01 | L13: 2026-10-01 05:01
A14: ALM-1050 | B14: MH-DC-001 | C14: minor | D14: active | E14: High CPU Utilization | F14: CPU | G14: Performance | H14: downstream | I14: MH-POP-002-AGG-01 | L14: 2026-09-30 17:28
A15: ALM-1051 | B15: MH-DC-002 | C15: critical | D15: active | E15: Mains Power Failure | F15: Power | G15: Facility | H15: downstream | I15: MH-POP-001-AGG-01 | L15: 2026-09-30 18:10
A16: ALM-1091 | B16: MH-DC-001 | C16: major | D16: active | E16: Link Down | F16: Link | G16: Network | H16: edge | I16: MH-DC-001-AGG-R01 | J16: xe-0/0/15 | L16: 2026-10-01 06:15
A17: ALM-1092 | B17: MH-DC-001 | C17: minor | D17: active | E17: Secondary RADIUS Server Unreachable | F17: Security | G17: Network | H17: dependency | I17: AAA-SRV-02 (10.25.25.6) | L17: 2026-10-01 04:50
A18: ALM-1093 | B18: MH-DC-001 | C18: major | D18: active | E18: Cabinet PDU-A Breaker Trip | F18: Power | G18: Facility | H18: site | K18: MH-DC-001-RACK-C | L18: 2026-10-01 07:12
A19: ALM-1094 | B19: MH-DC-001 | C19: critical | D19: active | E19: Cross-connect Loss of Signal | F19: Interface | G19: Network | H19: site | I19: MH-DC-001-MMR-SW-06 | J19: MMR panel 11 · P20 | L19: 2026-10-01 06:46
A20: ALM-1095 | B20: MH-DC-001 | C20: minor | D20: active | E20: Cabinet Inlet Temperature High | F20: Environment | G20: Facility | H20: site | K20: MH-DC-001-RACK-F | L20: 2026-10-01 05:50
A21: ALM-1097 | B21: MH-DC-002 | C21: minor | D21: active | E21: Optical Rx Power Low | F21: Interface | G21: Network | H21: edge | I21: MH-DC-002-PE-T4-02 | J21: xe-0/0/2 | L21: 2026-10-01 01:50
A22: ALM-1101 | B22: MH-DC-001 | C22: major | D22: active | E22: Power Supply Fault | F22: Power | G22: Device | H22: site | I22: MH-DC-001-BMS-01 | L22: 2026-09-30 23:50
A23: ALM-1102 | B23: MH-DC-002 | C23: major | D23: active | E23: Power Supply Fault | F23: Power | G23: Device | H23: site | I23: MH-DC-002-BMS-02 | L23: 2026-10-01 00:55

Sheet Snapshot_Incidents
A1: incident_id | B1: site_id | C1: severity | D1: status | E1: type | F1: title | G1: owner | H1: detected_at | I1: resolved_at | J1: alarms | K1: services_hit | L1: customers_hit | M1: revenue_at_risk
A2: INC-0001 | B2: MH-DC-001 | C2: High | D2: Open | E2: Network | F2: Optical degradation on PE-T4-01 xe-0/0/3 — backhaul flapping | G2: Mike Johnson | H2: 2026-10-01 07:08 | J2: 4 | K2: 0 | L2: 0 | M2: 0
A3: INC-0010 | B3: MH-DC-001 | C3: Low | D3: Open | E3: Network | F3: Discovery collector stale — MH-DC-001 | G3: Arjun Mehta | H3: 2026-10-01 04:53 | J3: 1 | K3: 0 | L3: 0 | M3: 0
A4: INC-0012 | B4: MH-DC-001 | C4: Low | D4: Closed | E4: Capacity | F4: Cross-connect panel ports exhausted — MH-DC-001 | G4: Kavita Rao | H4: 2026-09-14 23:28 | I4: 2026-09-15 18:58 | J4: 0 | K4: 0 | L4: 4 | M4: 0
A5: INC-0017 | B5: MH-DC-002 | C5: Low | D5: Closed | E5: Rack | F5: Tenant cabinet over contracted power — MH-DC-002 | G5: Sneha Patil | H5: 2026-09-09 19:09 | I5: 2026-09-10 18:26 | J5: 0 | K5: 0 | L5: 2 | M5: 0
A6: INC-0028 | B6: MH-DC-001 | C6: Low | D6: Closed | E6: Security | F6: Cage access alarm — badge mismatch — MH-DC-001 | G6: Rahul Deshpande | H6: 2026-09-11 23:24 | I6: 2026-09-12 19:37 | J6: 0 | K6: 5 | L6: 5 | M6: 0
A7: INC-0029 | B7: MH-DC-002 | C7: Medium | D7: Closed | E7: Cooling | F7: Chiller pump fault — MH-DC-002 | G7: Anil Kulkarni | H7: 2026-09-21 14:41 | I7: 2026-09-23 00:35 | J7: 0 | K7: 6 | L7: 3 | M7: 0

Sheet Snapshot_Changes
A1: change_id | B1: site_id | C1: kind | D1: title | E1: status | F1: risk | G1: window_start | H1: window_end | I1: requester | J1: approver | K1: scope
A2: CHG-2001 | B2: MH-DC-001 | C2: Change | D2: Re-patch ODF RACK-D core 7 to PE-T4-01 xe-0/0/3 (new backhaul span) | E2: Completed | F2: Medium | G2: 2026-09-30 16:30 | H2: 2026-09-30 17:30 | I2: Rahul Deshpande | J2: Priya Nair | K2: MH-DC-001-PE-T4-01
A3: CHG-2002 | B3: MH-DC-001 | C3: Change | D3: Junos upgrade 21.4R3-S5.5 → 22.2R3-S2 on MH-DC-001 PE pair | E3: Pending approval | F3: High | G3: 2026-10-03 17:50 | H3: 2026-10-03 21:50 | I3: Arjun Mehta | K3: MH-DC-001-PE-T4-01;MH-DC-001-PE-T4-02
A4: CHG-2003 | B4: MH-DC-001 | C4: Maintenance | D4: DG load-bank test — 125 kVA set | E4: Approved | F4: Low | G4: 2026-10-05 13:50 | H4: 2026-10-05 15:50 | I4: Anil Kulkarni | J4: Kavita Rao

Sheet Snapshot_RMA
A1: rma_id | B1: site_id | C1: device_id | D1: slot | E1: part | F1: vendor_case | G1: status | H1: opened | I1: spare_on_site
A2: RMA-48287 | B2: MH-DC-001 | C2: MH-DC-001-BMS-01 | D2: PSU2 | E2: Power supply | F2: DEL-8205146 | G2: Opened | H2: 2026-09-30 23:50 | I2: Y
A3: RMA-78333 | B3: MH-DC-002 | C3: MH-DC-002-BMS-02 | D3: PSU2 | E3: Power supply | F3: SUP-5808864 | G3: Opened | H3: 2026-09-30 17:50 | I3: Y

Sheet Snapshot_Problems
A1: problem_id | B1: title | C1: type | D1: state | E1: incidents | F1: open | G1: sites | H1: workaround | I1: fix | J1: owner
A2: PRB-4445 | B2: Optic degradation (SFP lot 22B) | C2: Network | D2: Investigating | E2: INC-0001;INC-0024;INC-0034 | F2: 1 | G2: MH-DC-001;MH-DC-004;WB-DC-017 | H2: Move traffic to the parallel span; swap the optic from a spare lot and clean the patch | I2: Replace every optic from the affected lot under a vendor field notice; inspect the ODF jumpers | J2: Sneha Patil
A3: PRB-7148 | B3: Cage access alarm | C3: Security | D3: Known error | E3: INC-0027;INC-0028;INC-0033;INC-0038;INC-0042;INC-0043;INC-0044;INC-0046 | F3: 0 | G3: WB-DC-017;MH-DC-001;MH-DC-003;UP-DC-005;KA-DC-008;BR-DC-019;DL-DC-009 | H3: Follow the runbook for this alarm type | I3: Root cause and permanent fix to be confirmed | J3: James Wilson
A4: PRB-4629 | B4: Chiller pump fault | C4: Cooling | D4: Known error | E4: INC-0011;INC-0022;INC-0029;INC-0035;INC-0045 | F4: 0 | G4: MP-DC-014;KA-DC-020;MH-DC-002;RJ-DC-015;KL-DC-024 | H4: Keep the spare unit running; portable cooling on standby | I4: Repair the unit and review the maintenance interval | J4: James Wilson
A5: PRB-3034 | B5: Tenant cabinet over contracted power | C5: Rack | D5: Known error | E5: INC-0016;INC-0017;INC-0020;INC-0026;INC-0048 | F5: 0 | G5: WB-DC-017;MH-DC-002;UP-DC-005;BR-DC-019;RJ-DC-015 | H5: Follow the runbook for this alarm type | I5: Root cause and permanent fix to be confirmed | J5: Anil Kulkarni
A6: PRB-6635 | B6: Cross-connect panel ports exhausted | C6: Capacity | D6: Known error | E6: INC-0012;INC-0013 | F6: 0 | G6: MH-DC-001;AP-DC-010 | H6: Re-balance traffic onto parallel spans or free ports | I6: Add capacity (upgrade or new span / leaf) before the forecast threshold | J6: Sneha Patil

Sheet Snapshot_Orders
A1: order_id | B1: kind | C1: site_id | D1: customer_id | E1: detail | F1: state | G1: opened | H1: due_or_minutes
A2: XC-76071 | B2: Cross-connect | C2: MH-DC-001 | D2: CUST-8230 | E2: RACK-J (tenant cabinet) → Carrier POP · MMR panel 3 | F2: Approved | G2: 2026-09-24 07:50 | H2: 46294
A3: XC-85767 | B3: Cross-connect | C3: MH-DC-002 | D3: CUST-4716 | E3: RACK-E (tenant cabinet) → Carrier POP · MMR panel 3 | F3: Approved | G3: 2026-09-23 07:50 | H3: 46293
A4: XC-97323 | B4: Cross-connect | C4: MH-DC-001 | D4: CUST-2063 | E4: RACK-I (tenant cabinet) → Peering fabric · MMR panel 2 | F4: Patched | G4: 2026-09-30 07:50 | H4: 46300
A5: XC-80289 | B5: Cross-connect | C5: MH-DC-002 | D5: CUST-2954 | E5: RACK-F (tenant cabinet) → Other tenant · cage cross-connect | F5: Patched | G5: 2026-09-30 07:50 | H5: 46300
A6: XC-26347 | B6: Cross-connect | C6: MH-DC-001 | D6: CUST-1202 | E6: RACK-P (tenant cabinet) → Cloud on-ramp · MMR panel 7 | F6: Patched | G6: 2026-09-24 07:50 | H6: 46294
A7: XC-90401 | B7: Cross-connect | C7: MH-DC-002 | D7: CUST-2954 | E7: RACK-F (tenant cabinet) → MMR-SW-03 MMR panel 7 · P16 | F7: Handed over | G7: 2026-08-27 07:50 | H7: 46266
A8: XC-42282 | B8: Cross-connect | C8: MH-DC-001 | D8: CUST-9982 | E8: RACK-O (tenant cabinet) → MMR-SW-04 MMR panel 4 · P19 | F8: Handed over | G8: 2026-08-09 07:50 | H8: 46248
A9: XC-25211 | B9: Cross-connect | C9: MH-DC-002 | D9: CUST-7349 | E9: RACK-B (tenant cabinet) → MMR-SW-01 MMR panel 3 · P16 | F9: Handed over | G9: 2026-07-15 07:50 | H9: 46223
A10: XC-18848 | B10: Cross-connect | C10: MH-DC-001 | D10: CUST-9111 | E10: RACK-F (tenant cabinet) → MMR-SW-09 MMR panel 7 · P10 | F10: Handed over | G10: 2026-06-21 07:50 | H10: 46199
A11: XC-64562 | B11: Cross-connect | C11: MH-DC-001 | D11: CUST-6478 | E11: RACK-H (tenant cabinet) → MMR-SW-05 MMR panel 4 · P37 | F11: Handed over | G11: 2026-06-21 07:50 | H11: 46199
A12: XC-33306 | B12: Cross-connect | C12: MH-DC-002 | D12: CUST-7349 | E12: RACK-B (tenant cabinet) → MMR-SW-02 MMR panel 6 · P3 | F12: Handed over | G12: 2026-05-30 07:50 | H12: 46177
A13: XC-75639 | B13: Cross-connect | C13: MH-DC-002 | D13: CUST-4716 | E13: RACK-E (tenant cabinet) → MMR-SW-04 MMR panel 7 · P26 | F13: Handed over | G13: 2026-05-11 07:50 | H13: 46158
... A42: RH-98566 | B42: Remote hands | C42: MH-DC-001 | D42: CUST-7349 | E42: Re-seat a transceiver and check light | F42: Done | G42: 2026-09-25 14:50 | H42: 16

Sheet Field_Dictionary
A1: Sheet | B1: Column | C1: Required | D1: Type | E1: Allowed values | F1: System field (types.ts) | G1: Description | H1: Example
A2: Sites | B2: site_id | C2: Required | D2: text | F2: Datacenter.id / Location.id | G2: Unique site code, format XX-DC-NNN (XX = state code). Every other sheet points to it. | H2: MH-DC-001
A3: Sites | B3: site_name | C3: Required | D3: text | F3: Datacenter.name | G3: Display name. | H3: MH-DC-001
A4: Sites | B4: operator | C4: Optional | D4: text | F4: (reference only) | G4: Owning company. Not shown in the tool today.
A5: Sites | B5: business_model | C5: Required | D5: list | E5: colocation, neocloud, cloud, enterprise, network | F5: Persona | G5: Sets vocabulary and rack contents: colocation, neocloud (GPU as a service), cloud, enterprise, network (telco). | H5: colocation
A6: Sites | B6: status | C6: Required | D6: list | E6: on-air, in-progress, planned, failed | F6: Datacenter.status | G6: on-air = live; in-progress = being built; planned; failed. | H6: in-progress
A7: Sites | B7: tier | C7: Required | D7: list | E7: Tier II, Tier III, Tier IV | F7: Datacenter.tier | G7: Uptime tier. | H7: Tier III
A8: Sites | B8: category | C8: Required | D8: list | E8: Central, Regional, Edge | F8: Datacenter.category | G8: Central / Regional / Edge. | H8: Central
A9: Sites | B9: region | C9: Required | D9: text | F9: Region.name / Datacenter.regionId | G9: For example West, South, North, East, Central. | H9: West
A10: Sites | B10: state | C10: Required | D10: text | F10: Datacenter.state | G10: State or province. | H10: Maharashtra
A11: Sites | B11: city | C11: Required | D11: text | F11: Datacenter.city | G11: City. | H11: Pune
A12: Sites | B12: address | C12: Required | D12: text | F12: Datacenter.address | G12: Postal address. | H12: Pune Data Park
A13: Sites | B13: latitude | C13: Required | D13: decimal | F13: Datacenter.lat | G13: Decimal degrees (WGS84). Places the pin on the estate map. | H13: 18.593
A14: Sites | B14: longitude | C14: Required | D14: decimal | F14: Datacenter.lng | G14: Decimal degrees (WGS84). | H14: 73.789
A15: Sites | B15: commissioned_on | C15: Optional | D15: date | F15: Datacenter.commissionedOn | G15: Date the site went live. | H15: 2023-03-15
A16: Sites | B16: it_capacity_kw | C16: Required | D16: decimal | F16: Datacenter.power.capacityKw | G16: Design IT load (kW) the site is built for. | H16: 390
A17: Sites | B17: design_pue | C17: Optional | D17: decimal | F17: Datacenter.power.pue | G17: Design PUE. Live PUE comes from the BMS. | H17: 1.52
A18: Sites | B18: cooling_capacity_kw | C18: Required | D18: decimal | F18: Datacenter.cooling.capacityKw | G18: Total installed cooling capacity (kW). | H18: 240
A19: Sites | B19: cooling_redundancy | C19: Required | D19: list | E19: N, N+1, 2N | F19: Datacenter.cooling.redundancy | G19: N / N+1 / 2N. | H19: N+1
A20: Sites | B20: timezone | C20: Optional | D20: text | F20: (reference only) | G20: IANA timezone, for example Asia/Kolkata. | H20: Asia/Kolkata
A21: Floors | B21: site_id | C21: Required | D21: ref | E21: an ID from Sites | F21: Datacenter.id | G21: Must exist in Sites. | H21: MH-DC-001
A22: Floors | B22: floor_id | C22: Required | D22: text | F22: (key) | G22: Unique within the workbook, for example MP-DC-001-F0. | H22: MH-DC-001-F0
A23: Floors | B23: floor_name | C23: Required | D23: text | F23: Datacenter.floors[].name | G23: As staff call it: Ground, 1st floor… | H23: Ground
A24: Floors | B24: level | C24: Required | D24: integer | F24: (order in the 3D twin) | G24: 0 = ground, 1 = first floor…, −1 = basement. | H24: 0
A25: Rooms | B25: site_id | C25: Required | D25: ref | E25: an ID from Sites | F25: Datacenter.id | H25: MH-DC-001
A26: Rooms | B26: floor_id | C26: Required | D26: ref | E26: an ID from Floors | F26: (key) | G26: Must exist in Floors. | H26: MH-DC-001-F0
A27: Rooms | B27: room_id | C27: Required | D27: text | F27: (key) | G27: Unique within the workbook. | H27: MH-DC-001-F0-R1
A28: Rooms | B28: room_name | C28: Required | D28: text | F28: Datacenter.floors[].rooms[] / Rack.room | G28: Shown in the twin, the racks list and alarm locations. | H28: Meet-me room
A29: Rooms | B29: room_type | C29: Required | D29: list | E29: Data hall, AI hall, Meet-me room, Network room, Plant room, UPS room, Battery room, NOC | F29: (twin layout) | G29: Plant / UPS / battery rooms hold the power plant; halls hold racks. | H29: Meet-me room
A30: Rooms | B30: area_sqm | C30: Optional | D30: decimal | F30: (reference only) | G30: Floor area.
A31: Rooms | B31: rack_rows | C31: Optional | D31: integer | F31: (twin layout) | G31: Number of rack rows; racks face each other in pairs. | H31: 1
A32: Rooms | B32: containment | C32: Optional | D32: list | E32: Cold aisle, Hot aisle, None | F32: (twin layout) | G32: Aisle containment.
A33: Rooms | B33: cooling_method | C33: Optional | D33: list | E33: Air, Liquid, Hybrid | F33: Rack.liquid | G33: Air, Liquid or Hybrid. | H33: Air
A34: Racks | B34: rack_id | C34: Required | D34: text | F34: Rack.id | G34: Unique, for example MP-DC-001-A01. | H34: MH-DC-001-RACK-A
A35: Racks | B35: site_id | C35: Required | D35: ref | E35: an ID from Sites | F35: Rack.dcId | H35: MH-DC-001
A36: Racks | B36: room_id | C36: Required | D36: ref | E36: an ID from Rooms | F36: Rack.floor / Rack.room | G36: Floor and room come from the Rooms row. | H36: MH-DC-001-F0-R1
A37: Racks | B37: rack_name | C37: Required | D37: text | F37: Rack.name | G37: Label on the cabinet (shown on the 3D twin). | H37: RACK-A
A38: Racks | B38: row | C38: Optional | D38: text | F38: (twin layout) | G38: Row letter or number.
A39: Racks | B39: position | C39: Optional | D39: integer | F39: (twin layout) | G39: Position in the row, 1…n.
A40: Racks | B40: role | C40: Required | D40: list | E40: Core, Meet-me room, Network, Aggregation, Compute, Storage, GPU, Tenant, AI cage | F40: Rack.role | G40: What the cabinet is for. | H40: Core
A41: Racks | B41: height_u | C41: Required | D41: integer | F41: Rack.heightU | G41: Usable rack units (42, 45, 48…). | H41: 45
A42: Racks | B42: power_budget_kw | C42: Required | D42: decimal | F42: Rack.budgetKw | G42: Provisioned power (kW). Live draw comes from the PDUs. | H42: 15
A43: Racks | B43: owner | C43: Required | D43: list | E43: operator, tenant | F43: Rack.owner | G43: operator, or tenant (a leased cabinet: the operator sees power and environment only). | H43: operator
A44: Racks | B44: tenant_customer_id | C44: Conditional | D44: ref | E44: an ID from Customers | F44: Rack.tenantId | G44: Required when owner = tenant. | H44: CUST-7349
A45: Racks | B45: contracted_kw | C45: Conditional | D45: decimal | F45: Rack.contractedKw | G45: Required when owner = tenant: the power the tenant has bought. | H45: 19
A46: Racks | B46: density | C46: Optional | D46: list | E46: standard, ai | F46: Rack.density | G46: ai = high-density GPU rack or AI cage. | H46: standard
A47: Racks | B47: liquid_cooled | C47: Optional | D47: list | E47: Y, N | F47: Rack.liquid | G47: Y = direct liquid cooling. | H47: N
A48: Racks | B48: cdu_id | C48: Conditional | D48: ref | E48: an ID from CDUs | F48: AiCage.cduId / Cdu.racks | G48: Required when liquid_cooled = Y. | H48: MH-DC-002-CDU-1
A49: Racks | B49: pdu_feed_a | C49: Optional | D49: ref | E49: an ID from Power_Feeds | F49: (power path) | G49: Feed powering the A-side PDU. | H49: MH-DC-001-AC-1
A50: Racks | B50: pdu_feed_b | C50: Optional | D50: ref | E50: an ID from Power_Feeds | F50: (power path) | G50: Feed powering the B-side PDU. | H50: MH-DC-001-AC-2
A51: Racks | B51: used_u (calc) | C51: Calculated | D51: formula | F51: Rack.usedU | G51: Calculated: the sum of u_size of the devices in this rack. Don't type it.
A52: Power_Feeds | B52: feed_id | C52: Required | D52: text | F52: PowerFeed.id | G52: Unique, for example MP-DC-001-AC-1. | H52: MH-DC-001-AC-1
A53: Power_Feeds | B53: site_id | C53: Required | D53: ref | E53: an ID from Sites | F53: Datacenter.id | H53: MH-DC-001
A54: Power_Feeds | B54: type | C54: Required | D54: list | E54: AC, DC | F54: PowerFeed.type | G54: AC or DC. | H54: AC
A55: Power_Feeds | B55: source | C55: Required | D55: text | F55: PowerFeed.source | G55: For example "Utility feed A", "Rectifier RECT-01". | H55: Utility feed A
A56: Power_Feeds | B56: rating | C56: Required | D56: text | F56: PowerFeed.rating | G56: For example "630 A · 415 V" or "48 V · 2400 A". | H56: 380 A · 415 V
A57: Power_Feeds | B57: capacity_kw | C57: Required | D57: decimal | F57: PowerFeed.capacityKw | H57: 273
A58: Power_Feeds | B58: normal_role | C58: Optional | D58: list | E58: Active, Standby | F58: (ATS story) | G58: Active, or Standby (picked up by the ATS). | H58: Active
A59: Power_Feeds | B59: utility_account | C59: Optional | D59: text | F59: (reference only) | G59: Utility connection / account number.
A60: UPS | B60: ups_id | C60: Required | D60: text | F60: UpsUnit.id | H60: MH-DC-001-UPS-1
A61: UPS | B61: site_id | C61: Required | D61: ref | E61: an ID from Sites | F61: Datacenter.id | H61: MH-DC-001
A62: UPS | B62: room_id | C62: Optional | D62: ref | E62: an ID from Rooms | F62: (twin placement) | G62: Room the UPS stands in (shown and clickable in the realistic twin).
A63: UPS | B63: name | C63: Required | D63: text | F63: UpsUnit.name | G63: For example UPS-1. | H63: UPS-1
A64: UPS | B64: vendor | C64: Optional | D64: text | F64: (reference only)
A65: UPS | B65: model | C65: Optional | D65: text | F65: (reference only)
A66: UPS | B66: serial | C66: Optional | D66: text | F66: (reference only)
A67: UPS | B67: capacity_kw | C67: Required | D67: decimal | F67: UpsUnit.capacityKw | H67: 130
A68: UPS | B68: redundancy | C68: Required | D68: list | E68: N, N+1, 2N | F68: UpsUnit.redundancy | H68: N+1
A69: UPS | B69: battery_autonomy_min | C69: Required | D69: integer | F69: UpsUnit.batteryMin | G69: Design autonomy at full load (minutes). | H69: 15
A70: Generators | B70: dg_id | C70: Required | D70: text | F70: (key) | H70: MH-DC-001-DG-1
A71: Generators | B71: site_id | C71: Required | D71: ref | E71: an ID from Sites | F71: Datacenter.id | H71: MH-DC-001
A72: Generators | B72: name | C72: Required | D72: text | F72: (label) | H72: DG-1
A73: Generators | B73: kva | C73: Required | D73: decimal | F73: power.dg.kva | G73: Rating (kVA). | H73: 500
A74: Generators | B74: fuel_tank_litres | C74: Optional | D74: decimal | F74: (fuel hours)
A75: Generators | B75: runtime_h_full_load | C75: Required | D75: decimal | F75: power.dg.runtimeH | G75: Hours on a full tank at full load. | H75: 10
A76: Generators | B76: last_test_date | C76: Optional | D76: date | F76: power.dg.lastTest | H76: 2026-08-27
A77: Generators | B77: last_test_result | C77: Optional | D77: list | E77: Pass, Fail | F77: power.dg.result | H77: Pass
A78: DC_Plant | B78: plant_id | C78: Required | D78: text | F78: (key) | H78: MH-DC-001-RECT-01
A79: DC_Plant | B79: site_id | C79: Required | D79: ref | E79: an ID from Sites | F79: Datacenter.id | H79: MH-DC-001
A80: DC_Plant | B80: room_id | C80: Optional | D80: ref | E80: an ID from Rooms | F80: (twin placement)
A81: DC_Plant | B81: kind | C81: Required | D81: list | E81: Rectifier, Battery bank | F81: (rectifier / battery) | H81: Rectifier
A82: DC_Plant | B82: name | C82: Required | D82: text | F82: (label) | G82: For example RECT-01, BATT-01. | H82: RECT-01
A83: DC_Plant | B83: volts | C83: Conditional | D83: decimal | F83: power.battery.volts | G83: Battery banks: nominal voltage. | H83: 48
A84: DC_Plant | B84: ah | C84: Conditional | D84: decimal | F84: power.battery.ah | G84: Battery banks: capacity (Ah). | H84: 2400
A85: DC_Plant | B85: rated_output | C85: Conditional | D85: text | F85: PowerFeed.rating (DC) | G85: Rectifiers: for example "48 V · 2400 A". | H85: 48 V · 2440 A
A86: DC_Plant | B86: capacity_kw | C86: Conditional | D86: decimal | F86: PowerFeed.capacityKw (DC) | G86: Rectifiers: DC output (kW). | H86: 117
A87: DC_Plant | B87: autonomy_h | C87: Conditional | D87: decimal | F87: power.battery.runtimeH | G87: Battery banks: design autonomy (hours). | H87: 3.4
A88: DC_Plant | B88: last_test_date | C88: Optional | D88: date | F88: power.battery.lastTest | H88: 2026-08-22
A89: Cooling_Units | B89: unit_id | C89: Required | D89: text | F89: CoolingUnit.id | H89: MH-DC-001-CRAH-11
A90: Cooling_Units | B90: site_id | C90: Required | D90: ref | E90: an ID from Sites | F90: Datacenter.id | H90: MH-DC-001
A91: Cooling_Units | B91: room_id | C91: Required | D91: ref | E91: an ID from Rooms | F91: CoolingUnit.zone | G91: The zone is "<floor> · <room>". | H91: MH-DC-001-F0-R1
A92: Cooling_Units | B92: name | C92: Required | D92: text | F92: CoolingUnit.name | G92: For example CRAH-11. | H92: CRAH-11
A93: Cooling_Units | B93: type | C93: Required | D93: list | E93: CRAH, CRAC, CDU | F93: CoolingUnit.type | H93: CRAH
A94: Cooling_Units | B94: vendor | C94: Optional | D94: text | F94: (reference only)
A95: Cooling_Units | B95: model | C95: Optional | D95: text | F95: (reference only)
A96: Cooling_Units | B96: capacity_kw | C96: Required | D96: decimal | F96: CoolingUnit.capacityKw | G96: Rated cooling capacity. | H96: 30
A97: Cooling_Units | B97: design_supply_c | C97: Optional | D97: decimal | F97: CoolingUnit.supplyC (setpoint) | G97: Supply air / coolant setpoint. | H97: 18
A98: CDUs | B98: cdu_id | C98: Required | D98: text | F98: Cdu.id | H98: MH-DC-002-CDU-1
A99: CDUs | B99: site_id | C99: Required | D99: ref | E99: an ID from Sites | F99: Cdu.dcId | H99: MH-DC-002
A100: CDUs | B100: room_id | C100: Required | D100: ref | E100: an ID from Rooms | F100: Cdu.room | H100: MH-DC-002-F0-R1
...

Sheet Lookups
A1: business_model | B1: site_status | C1: tier | D1: site_category | E1: redundancy | F1: room_type | G1: containment | H1: cooling_method | I1: rack_role | J1: owner | K1: density | L1: yes_no | M1: feed_type | N1: feed_role | O1: plant_kind | P1: test_result | Q1: cooling_type | R1: sensor_kind | S1: device_role | T1: layer | U1: lifecycle | V1: if_admin | W1: link_role | X1: protocol | Y1: gpu_model | Z1: gpu_vendor | AA1: scheduler | AB1: air_liquid | AC1: service_type | AD1: service_unit | AE1: collector_protocol | AF1: collector_domain | AG1: pdu_side | AH1: pdu_kind | AI1: panel_kind | AJ1: panel_role | AK1: link_end | AL1: tray_route | AM1: detection | AN1: suppression | AO1: release_mode | AP1: door_kind | AQ1: reader | AR1: support_level | AS1: pm_kind | AT1: oncall_role
A2: colocation | B2: on-air | C2: Tier II | D2: Central | E2: N | F2: Data hall | G2: Cold aisle | H2: Air | I2: Core | J2: operator | K2: standard | L2: Y | M2: AC | N2: Active | O2: Rectifier | P2: Pass | Q2: CRAH | R2: Temperature + humidity | S2: Router | T2: core | U2: Ready | V2: up | W2: Fabric | X2: LLDP | Y2: B200 SXM 192 GB | Z2: NVIDIA | AA2: Kubernetes | AB2: air | AC2: Cabinet lease | AD2: cabinets | AE2: SNMP | AF2: Network | AG2: A | AH2: AC | AI2: LC duplex | AJ2: rack | AK2: A | AL2: Tray route 1 | AM2: VESDA aspirating | AN2: Novec 1230 gas | AO2: Armed (auto) | AP2: Building entry | AQ2: Card + biometric | AR2: 24×7×4 | AS2: UPS | AT2: NOC shift lead
A3: neocloud | B3: in-progress | C3: Tier III | D3: Regional | E3: N+1 | F3: AI hall | G3: Hot aisle | H3: Liquid | I3: Meet-me room | J3: tenant | K3: ai | L3: N | M3: DC | N3: Standby | O3: Battery bank | P3: Fail | Q3: CRAC | R3: Leak | S3: Switch | T3: spine | U3: Planned | V3: admin-down | W3: Uplink | X3: OSPF | Y3: H200 SXM 141 GB | Z3: Intel | AA3: Slurm | AB3: liquid | AC3: Power circuit | AD3: kW | AE3: gNMI | AF3: Facility | AG3: B | AH3: DC | AI3: MPO | AJ3: odf | AK3: Z | AL3: Tray route 2 | AM3: Point smoke + heat | AN3: Inert gas (IG-541) | AO3: Manual only | AP3: Data hall door | AQ3: Card + PIN | AR3: NBD | AS3: Battery | AT3: Network engineer
A4: cloud | B4: planned | C4: Tier IV | D4: Edge | E4: 2N | F4: Meet-me room | G4: None | H4: Hybrid | I4: Network | Q4: CDU | R4: Smoke | S4: DWDM | T4: leaf | U4: Maintenance | V4: reserved | W4: Backhaul | X4: BGP | Y4: H100 SXM 80 GB | AC4: Cross-connect | AD4: Mbps | AE4: Redfish | AF4: Compute | AI4: RJ45 | AN4: Pre-action sprinkler | AO4: Isolated | AP4: Cage door | AQ4: Card | AR4: 8×5 NBD | AS4: Generator | AT4: Facility engineer
A5: enterprise | B5: failed | F5: Network room | I5: Aggregation | S5: Firewall | T5: access | U5: Decommissioning | W5: Peering | X5: ISIS | Y5: A100 SXM 80 GB | AC5: Remote hands | AD5: hours | AE5: DCGM exporter | AF5: GPU | AP5: Plant room door | AR5: None | AS5: Cooling | AT5: Field technician
A6: network | F6: Plant room | I6: Compute | S6: Access | W6: Access | X6: LSP | Y6: L40S PCIe 48 GB | AC6: Reserved cluster | AD6: GPU | AE6: Modbus TCP | AP6: Meet-me room door | AS6: CDU | AT6: Duty manager
F7: UPS room | I7: Storage | S7: Server | Y7: T4 PCIe 16 GB | AC7: On-demand GPUs | AD7: vCPU | AE7: BACnet | AS7: Fire | AT7: AI infrastructure engineer
F8: Battery room | I8: GPU | S8: Storage | Y8: Gaudi 3 OAM 128 GB | AC8: CPU instances | AD8: TB | AE8: Syslog | AS8: Electrical
F9: NOC | I9: Tenant | S9: GPU | Y9: Max 1550 OAM 128 GB | AC9: VM | AD9: users
I10: AI cage | S10: Tenant gear | AC10: Storage volume
AC11: Managed DB
AC12: GPU cluster
AC13: Kubernetes
AC14: IRV
AC15: Leased Line
AC16: L2VPN
AC17: L3VPN
AC18: Core application
AC19: Database
AC20: Collaboration
AC21: Analytics
AC22: Backup & DR
... AC24: Other
